package org.netlib.lapack;

import java.lang.reflect.InvocationTargetException;
import java.lang.reflect.Method;

public final class Dggesx
{
  /* Error */
  public static void dggesx(String paramString1, String paramString2, String paramString3, Object paramObject, String paramString4, int paramInt1, double[] paramArrayOfDouble1, int paramInt2, int paramInt3, double[] paramArrayOfDouble2, int paramInt4, int paramInt5, org.netlib.util.intW paramintW1, double[] paramArrayOfDouble3, int paramInt6, double[] paramArrayOfDouble4, int paramInt7, double[] paramArrayOfDouble5, int paramInt8, double[] paramArrayOfDouble6, int paramInt9, int paramInt10, double[] paramArrayOfDouble7, int paramInt11, int paramInt12, double[] paramArrayOfDouble8, int paramInt13, double[] paramArrayOfDouble9, int paramInt14, double[] paramArrayOfDouble10, int paramInt15, int paramInt16, int[] paramArrayOfInt, int paramInt17, int paramInt18, boolean[] paramArrayOfBoolean, int paramInt19, org.netlib.util.intW paramintW2)
  {
    // Byte code:
    //   0: iconst_0
    //   1: istore 42
    //   3: iconst_0
    //   4: istore 43
    //   6: iconst_0
    //   7: istore 44
    //   9: iconst_0
    //   10: istore 45
    //   12: iconst_0
    //   13: istore 46
    //   15: iconst_0
    //   16: istore 47
    //   18: iconst_0
    //   19: istore 48
    //   21: iconst_0
    //   22: istore 49
    //   24: iconst_0
    //   25: istore 50
    //   27: iconst_0
    //   28: istore 51
    //   30: iconst_0
    //   31: istore 52
    //   33: iconst_0
    //   34: istore 53
    //   36: iconst_0
    //   37: istore 54
    //   39: iconst_0
    //   40: istore 55
    //   42: iconst_0
    //   43: istore 56
    //   45: new 16	org/netlib/util/intW
    //   48: dup
    //   49: iconst_0
    //   50: invokespecial 19	org/netlib/util/intW:<init>	(I)V
    //   53: astore 57
    //   55: new 16	org/netlib/util/intW
    //   58: dup
    //   59: iconst_0
    //   60: invokespecial 19	org/netlib/util/intW:<init>	(I)V
    //   63: astore 58
    //   65: iconst_0
    //   66: istore 59
    //   68: iconst_0
    //   69: istore 60
    //   71: iconst_0
    //   72: istore 61
    //   74: iconst_0
    //   75: istore 62
    //   77: new 16	org/netlib/util/intW
    //   80: dup
    //   81: iconst_0
    //   82: invokespecial 19	org/netlib/util/intW:<init>	(I)V
    //   85: astore 63
    //   87: iconst_0
    //   88: istore 64
    //   90: iconst_0
    //   91: istore 65
    //   93: iconst_0
    //   94: istore 66
    //   96: iconst_0
    //   97: istore 67
    //   99: iconst_0
    //   100: istore 68
    //   102: iconst_0
    //   103: istore 69
    //   105: iconst_0
    //   106: istore 70
    //   108: iconst_0
    //   109: istore 71
    //   111: iconst_0
    //   112: istore 72
    //   114: dconst_0
    //   115: dstore 73
    //   117: dconst_0
    //   118: dstore 75
    //   120: dconst_0
    //   121: dstore 77
    //   123: dconst_0
    //   124: dstore 79
    //   126: dconst_0
    //   127: dstore 81
    //   129: dconst_0
    //   130: dstore 83
    //   132: new 21	org/netlib/util/doubleW
    //   135: dup
    //   136: dconst_0
    //   137: invokespecial 24	org/netlib/util/doubleW:<init>	(D)V
    //   140: astore 85
    //   142: new 21	org/netlib/util/doubleW
    //   145: dup
    //   146: dconst_0
    //   147: invokespecial 24	org/netlib/util/doubleW:<init>	(D)V
    //   150: astore 87
    //   152: new 21	org/netlib/util/doubleW
    //   155: dup
    //   156: dconst_0
    //   157: invokespecial 24	org/netlib/util/doubleW:<init>	(D)V
    //   160: astore 89
    //   162: new 21	org/netlib/util/doubleW
    //   165: dup
    //   166: dconst_0
    //   167: invokespecial 24	org/netlib/util/doubleW:<init>	(D)V
    //   170: astore 91
    //   172: dconst_0
    //   173: dstore 93
    //   175: iconst_2
    //   176: newarray <illegal type>
    //   178: astore 95
    //   180: aload_3
    //   181: invokevirtual 28	java/lang/Object:getClass	()Ljava/lang/Class;
    //   184: invokevirtual 34	java/lang/Class:getDeclaredMethods	()[Ljava/lang/reflect/Method;
    //   187: iconst_0
    //   188: aaload
    //   189: astore 97
    //   191: aload_0
    //   192: ldc 36
    //   194: invokestatic 42	org/netlib/lapack/Lsame:lsame	(Ljava/lang/String;Ljava/lang/String;)Z
    //   197: ifeq +12 -> 209
    //   200: iconst_1
    //   201: istore 60
    //   203: iconst_0
    //   204: istore 45
    //   206: goto +27 -> 233
    //   209: aload_0
    //   210: ldc 44
    //   212: invokestatic 42	org/netlib/lapack/Lsame:lsame	(Ljava/lang/String;Ljava/lang/String;)Z
    //   215: ifeq +12 -> 227
    //   218: iconst_2
    //   219: istore 60
    //   221: iconst_1
    //   222: istore 45
    //   224: goto +9 -> 233
    //   227: iconst_m1
    //   228: istore 60
    //   230: iconst_0
    //   231: istore 45
    //   233: aload_1
    //   234: ldc 36
    //   236: invokestatic 42	org/netlib/lapack/Lsame:lsame	(Ljava/lang/String;Ljava/lang/String;)Z
    //   239: ifeq +12 -> 251
    //   242: iconst_1
    //   243: istore 61
    //   245: iconst_0
    //   246: istore 46
    //   248: goto +27 -> 275
    //   251: aload_1
    //   252: ldc 44
    //   254: invokestatic 42	org/netlib/lapack/Lsame:lsame	(Ljava/lang/String;Ljava/lang/String;)Z
    //   257: ifeq +12 -> 269
    //   260: iconst_2
    //   261: istore 61
    //   263: iconst_1
    //   264: istore 46
    //   266: goto +9 -> 275
    //   269: iconst_m1
    //   270: istore 61
    //   272: iconst_0
    //   273: istore 46
    //   275: aload_2
    //   276: ldc 46
    //   278: invokestatic 42	org/netlib/lapack/Lsame:lsame	(Ljava/lang/String;Ljava/lang/String;)Z
    //   281: istore 53
    //   283: aload 4
    //   285: ldc 36
    //   287: invokestatic 42	org/netlib/lapack/Lsame:lsame	(Ljava/lang/String;Ljava/lang/String;)Z
    //   290: istore 52
    //   292: aload 4
    //   294: ldc 48
    //   296: invokestatic 42	org/netlib/lapack/Lsame:lsame	(Ljava/lang/String;Ljava/lang/String;)Z
    //   299: istore 51
    //   301: aload 4
    //   303: ldc 44
    //   305: invokestatic 42	org/netlib/lapack/Lsame:lsame	(Ljava/lang/String;Ljava/lang/String;)Z
    //   308: istore 54
    //   310: aload 4
    //   312: ldc 50
    //   314: invokestatic 42	org/netlib/lapack/Lsame:lsame	(Ljava/lang/String;Ljava/lang/String;)Z
    //   317: istore 50
    //   319: iload 31
    //   321: iconst_m1
    //   322: if_icmpeq +7 -> 329
    //   325: iconst_0
    //   326: goto +4 -> 330
    //   329: iconst_1
    //   330: ifne +21 -> 351
    //   333: iload 34
    //   335: iconst_m1
    //   336: if_icmpeq +7 -> 343
    //   339: iconst_0
    //   340: goto +4 -> 344
    //   343: iconst_1
    //   344: ifne +7 -> 351
    //   347: iconst_0
    //   348: goto +4 -> 352
    //   351: iconst_1
    //   352: istore 48
    //   354: iload 52
    //   356: ifeq +9 -> 365
    //   359: iconst_0
    //   360: istore 59
    //   362: goto +36 -> 398
    //   365: iload 51
    //   367: ifeq +9 -> 376
    //   370: iconst_1
    //   371: istore 59
    //   373: goto +25 -> 398
    //   376: iload 54
    //   378: ifeq +9 -> 387
    //   381: iconst_2
    //   382: istore 59
    //   384: goto +14 -> 398
    //   387: iload 50
    //   389: ifeq +9 -> 398
    //   392: iconst_4
    //   393: istore 59
    //   395: goto +3 -> 398
    //   398: aload 37
    //   400: iconst_0
    //   401: putfield 54	org/netlib/util/intW:val	I
    //   404: iload 60
    //   406: iconst_0
    //   407: if_icmple +7 -> 414
    //   410: iconst_0
    //   411: goto +4 -> 415
    //   414: iconst_1
    //   415: ifeq +12 -> 427
    //   418: aload 37
    //   420: iconst_m1
    //   421: putfield 54	org/netlib/util/intW:val	I
    //   424: goto +351 -> 775
    //   427: iload 61
    //   429: iconst_0
    //   430: if_icmple +7 -> 437
    //   433: iconst_0
    //   434: goto +4 -> 438
    //   437: iconst_1
    //   438: ifeq +13 -> 451
    //   441: aload 37
    //   443: bipush -2
    //   445: putfield 54	org/netlib/util/intW:val	I
    //   448: goto +327 -> 775
    //   451: iload 53
    //   453: iconst_1
    //   454: ixor
    //   455: ifeq +18 -> 473
    //   458: aload_2
    //   459: ldc 36
    //   461: invokestatic 42	org/netlib/lapack/Lsame:lsame	(Ljava/lang/String;Ljava/lang/String;)Z
    //   464: iconst_1
    //   465: ixor
    //   466: ifeq +7 -> 473
    //   469: iconst_1
    //   470: goto +4 -> 474
    //   473: iconst_0
    //   474: ifeq +13 -> 487
    //   477: aload 37
    //   479: bipush -3
    //   481: putfield 54	org/netlib/util/intW:val	I
    //   484: goto +291 -> 775
    //   487: iload 52
    //   489: ifne +12 -> 501
    //   492: iload 51
    //   494: ifne +7 -> 501
    //   497: iconst_0
    //   498: goto +4 -> 502
    //   501: iconst_1
    //   502: ifne +12 -> 514
    //   505: iload 54
    //   507: ifne +7 -> 514
    //   510: iconst_0
    //   511: goto +4 -> 515
    //   514: iconst_1
    //   515: ifne +12 -> 527
    //   518: iload 50
    //   520: ifne +7 -> 527
    //   523: iconst_0
    //   524: goto +4 -> 528
    //   527: iconst_1
    //   528: iconst_1
    //   529: ixor
    //   530: ifne +29 -> 559
    //   533: iload 53
    //   535: iconst_1
    //   536: ixor
    //   537: ifeq +14 -> 551
    //   540: iload 52
    //   542: iconst_1
    //   543: ixor
    //   544: ifeq +7 -> 551
    //   547: iconst_1
    //   548: goto +4 -> 552
    //   551: iconst_0
    //   552: ifne +7 -> 559
    //   555: iconst_0
    //   556: goto +4 -> 560
    //   559: iconst_1
    //   560: ifeq +13 -> 573
    //   563: aload 37
    //   565: bipush -5
    //   567: putfield 54	org/netlib/util/intW:val	I
    //   570: goto +205 -> 775
    //   573: iload 5
    //   575: iconst_0
    //   576: if_icmplt +7 -> 583
    //   579: iconst_0
    //   580: goto +4 -> 584
    //   583: iconst_1
    //   584: ifeq +13 -> 597
    //   587: aload 37
    //   589: bipush -6
    //   591: putfield 54	org/netlib/util/intW:val	I
    //   594: goto +181 -> 775
    //   597: iload 8
    //   599: iconst_1
    //   600: iload 5
    //   602: invokestatic 60	java/lang/Math:max	(II)I
    //   605: if_icmplt +7 -> 612
    //   608: iconst_0
    //   609: goto +4 -> 613
    //   612: iconst_1
    //   613: ifeq +13 -> 626
    //   616: aload 37
    //   618: bipush -8
    //   620: putfield 54	org/netlib/util/intW:val	I
    //   623: goto +152 -> 775
    //   626: iload 11
    //   628: iconst_1
    //   629: iload 5
    //   631: invokestatic 60	java/lang/Math:max	(II)I
    //   634: if_icmplt +7 -> 641
    //   637: iconst_0
    //   638: goto +4 -> 642
    //   641: iconst_1
    //   642: ifeq +13 -> 655
    //   645: aload 37
    //   647: bipush -10
    //   649: putfield 54	org/netlib/util/intW:val	I
    //   652: goto +123 -> 775
    //   655: iload 21
    //   657: iconst_1
    //   658: if_icmplt +7 -> 665
    //   661: iconst_0
    //   662: goto +4 -> 666
    //   665: iconst_1
    //   666: ifne +35 -> 701
    //   669: iload 45
    //   671: ifeq +22 -> 693
    //   674: iload 21
    //   676: iload 5
    //   678: if_icmplt +7 -> 685
    //   681: iconst_0
    //   682: goto +4 -> 686
    //   685: iconst_1
    //   686: ifeq +7 -> 693
    //   689: iconst_1
    //   690: goto +4 -> 694
    //   693: iconst_0
    //   694: ifne +7 -> 701
    //   697: iconst_0
    //   698: goto +4 -> 702
    //   701: iconst_1
    //   702: ifeq +13 -> 715
    //   705: aload 37
    //   707: bipush -16
    //   709: putfield 54	org/netlib/util/intW:val	I
    //   712: goto +63 -> 775
    //   715: iload 24
    //   717: iconst_1
    //   718: if_icmplt +7 -> 725
    //   721: iconst_0
    //   722: goto +4 -> 726
    //   725: iconst_1
    //   726: ifne +35 -> 761
    //   729: iload 46
    //   731: ifeq +22 -> 753
    //   734: iload 24
    //   736: iload 5
    //   738: if_icmplt +7 -> 745
    //   741: iconst_0
    //   742: goto +4 -> 746
    //   745: iconst_1
    //   746: ifeq +7 -> 753
    //   749: iconst_1
    //   750: goto +4 -> 754
    //   753: iconst_0
    //   754: ifne +7 -> 761
    //   757: iconst_0
    //   758: goto +4 -> 762
    //   761: iconst_1
    //   762: ifeq +13 -> 775
    //   765: aload 37
    //   767: bipush -18
    //   769: putfield 54	org/netlib/util/intW:val	I
    //   772: goto +3 -> 775
    //   775: aload 37
    //   777: getfield 54	org/netlib/util/intW:val	I
    //   780: iconst_0
    //   781: if_icmpeq +7 -> 788
    //   784: iconst_0
    //   785: goto +4 -> 789
    //   788: iconst_1
    //   789: ifeq +312 -> 1101
    //   792: iload 5
    //   794: iconst_0
    //   795: if_icmpgt +7 -> 802
    //   798: iconst_0
    //   799: goto +4 -> 803
    //   802: iconst_1
    //   803: ifeq +146 -> 949
    //   806: bipush 8
    //   808: iload 5
    //   810: imul
    //   811: bipush 6
    //   813: iload 5
    //   815: imul
    //   816: bipush 16
    //   818: iadd
    //   819: invokestatic 60	java/lang/Math:max	(II)I
    //   822: istore 72
    //   824: iload 72
    //   826: iload 5
    //   828: isub
    //   829: iload 5
    //   831: iconst_1
    //   832: ldc 62
    //   834: ldc 64
    //   836: iload 5
    //   838: iconst_1
    //   839: iload 5
    //   841: iconst_0
    //   842: invokestatic 70	org/netlib/lapack/Ilaenv:ilaenv	(ILjava/lang/String;Ljava/lang/String;IIII)I
    //   845: imul
    //   846: iadd
    //   847: istore 71
    //   849: iload 71
    //   851: iload 72
    //   853: iload 5
    //   855: isub
    //   856: iload 5
    //   858: iconst_1
    //   859: ldc 72
    //   861: ldc 64
    //   863: iload 5
    //   865: iconst_1
    //   866: iload 5
    //   868: iconst_m1
    //   869: invokestatic 70	org/netlib/lapack/Ilaenv:ilaenv	(ILjava/lang/String;Ljava/lang/String;IIII)I
    //   872: imul
    //   873: iadd
    //   874: invokestatic 60	java/lang/Math:max	(II)I
    //   877: istore 71
    //   879: iload 45
    //   881: ifeq +33 -> 914
    //   884: iload 71
    //   886: iload 72
    //   888: iload 5
    //   890: isub
    //   891: iload 5
    //   893: iconst_1
    //   894: ldc 74
    //   896: ldc 64
    //   898: iload 5
    //   900: iconst_1
    //   901: iload 5
    //   903: iconst_m1
    //   904: invokestatic 70	org/netlib/lapack/Ilaenv:ilaenv	(ILjava/lang/String;Ljava/lang/String;IIII)I
    //   907: imul
    //   908: iadd
    //   909: invokestatic 60	java/lang/Math:max	(II)I
    //   912: istore 71
    //   914: iload 71
    //   916: istore 70
    //   918: iload 59
    //   920: iconst_1
    //   921: if_icmpge +7 -> 928
    //   924: iconst_0
    //   925: goto +4 -> 929
    //   928: iconst_1
    //   929: ifeq +17 -> 946
    //   932: iload 70
    //   934: iload 5
    //   936: iload 5
    //   938: imul
    //   939: iconst_2
    //   940: idiv
    //   941: invokestatic 60	java/lang/Math:max	(II)I
    //   944: istore 70
    //   946: goto +12 -> 958
    //   949: iconst_1
    //   950: istore 72
    //   952: iconst_1
    //   953: istore 71
    //   955: iconst_1
    //   956: istore 70
    //   958: aload 29
    //   960: iconst_1
    //   961: iconst_1
    //   962: isub
    //   963: iload 30
    //   965: iadd
    //   966: iload 70
    //   968: i2d
    //   969: dastore
    //   970: iload 52
    //   972: ifne +21 -> 993
    //   975: iload 5
    //   977: iconst_0
    //   978: if_icmpeq +7 -> 985
    //   981: iconst_0
    //   982: goto +4 -> 986
    //   985: iconst_1
    //   986: ifne +7 -> 993
    //   989: iconst_0
    //   990: goto +4 -> 994
    //   993: iconst_1
    //   994: ifeq +9 -> 1003
    //   997: iconst_1
    //   998: istore 69
    //   1000: goto +10 -> 1010
    //   1003: iload 5
    //   1005: bipush 6
    //   1007: iadd
    //   1008: istore 69
    //   1010: aload 32
    //   1012: iconst_1
    //   1013: iconst_1
    //   1014: isub
    //   1015: iload 33
    //   1017: iadd
    //   1018: iload 69
    //   1020: iastore
    //   1021: iload 31
    //   1023: iload 72
    //   1025: if_icmplt +7 -> 1032
    //   1028: iconst_0
    //   1029: goto +4 -> 1033
    //   1032: iconst_1
    //   1033: ifeq +14 -> 1047
    //   1036: iload 48
    //   1038: iconst_1
    //   1039: ixor
    //   1040: ifeq +7 -> 1047
    //   1043: iconst_1
    //   1044: goto +4 -> 1048
    //   1047: iconst_0
    //   1048: ifeq +13 -> 1061
    //   1051: aload 37
    //   1053: bipush -22
    //   1055: putfield 54	org/netlib/util/intW:val	I
    //   1058: goto +43 -> 1101
    //   1061: iload 34
    //   1063: iload 69
    //   1065: if_icmplt +7 -> 1072
    //   1068: iconst_0
    //   1069: goto +4 -> 1073
    //   1072: iconst_1
    //   1073: ifeq +14 -> 1087
    //   1076: iload 48
    //   1078: iconst_1
    //   1079: ixor
    //   1080: ifeq +7 -> 1087
    //   1083: iconst_1
    //   1084: goto +4 -> 1088
    //   1087: iconst_0
    //   1088: ifeq +13 -> 1101
    //   1091: aload 37
    //   1093: bipush -24
    //   1095: putfield 54	org/netlib/util/intW:val	I
    //   1098: goto +3 -> 1101
    //   1101: aload 37
    //   1103: getfield 54	org/netlib/util/intW:val	I
    //   1106: iconst_0
    //   1107: if_icmpne +7 -> 1114
    //   1110: iconst_0
    //   1111: goto +4 -> 1115
    //   1114: iconst_1
    //   1115: ifeq +18 -> 1133
    //   1118: ldc 76
    //   1120: aload 37
    //   1122: getfield 54	org/netlib/util/intW:val	I
    //   1125: ineg
    //   1126: invokestatic 82	org/netlib/err/Xerbla:xerbla	(Ljava/lang/String;I)V
    //   1129: return
    //   1130: goto +0 -> 1130
    //   1133: iload 48
    //   1135: ifeq +7 -> 1142
    //   1138: return
    //   1139: goto +0 -> 1139
    //   1142: iload 5
    //   1144: iconst_0
    //   1145: if_icmpeq +7 -> 1152
    //   1148: iconst_0
    //   1149: goto +4 -> 1153
    //   1152: iconst_1
    //   1153: ifeq +10 -> 1163
    //   1156: aload 12
    //   1158: iconst_0
    //   1159: putfield 54	org/netlib/util/intW:val	I
    //   1162: return
    //   1163: ldc 84
    //   1165: invokestatic 90	org/netlib/lapack/Dlamch:dlamch	(Ljava/lang/String;)D
    //   1168: dstore 83
    //   1170: aload 91
    //   1172: ldc 46
    //   1174: invokestatic 90	org/netlib/lapack/Dlamch:dlamch	(Ljava/lang/String;)D
    //   1177: putfield 93	org/netlib/util/doubleW:val	D
    //   1180: aload 89
    //   1182: dconst_1
    //   1183: aload 91
    //   1185: getfield 93	org/netlib/util/doubleW:val	D
    //   1188: ddiv
    //   1189: putfield 93	org/netlib/util/doubleW:val	D
    //   1192: aload 91
    //   1194: aload 89
    //   1196: invokestatic 99	org/netlib/lapack/Dlabad:dlabad	(Lorg/netlib/util/doubleW;Lorg/netlib/util/doubleW;)V
    //   1199: aload 91
    //   1201: getfield 93	org/netlib/util/doubleW:val	D
    //   1204: invokestatic 103	java/lang/Math:sqrt	(D)D
    //   1207: dload 83
    //   1209: ddiv
    //   1210: dstore 93
    //   1212: dconst_1
    //   1213: dload 93
    //   1215: ddiv
    //   1216: dstore 77
    //   1218: ldc 105
    //   1220: iload 5
    //   1222: iload 5
    //   1224: aload 6
    //   1226: iload 7
    //   1228: iload 8
    //   1230: aload 29
    //   1232: iload 30
    //   1234: invokestatic 111	org/netlib/lapack/Dlange:dlange	(Ljava/lang/String;II[DII[DI)D
    //   1237: dstore 73
    //   1239: iconst_0
    //   1240: istore 43
    //   1242: dload 73
    //   1244: dconst_0
    //   1245: dcmpl
    //   1246: ifgt +7 -> 1253
    //   1249: iconst_0
    //   1250: goto +4 -> 1254
    //   1253: iconst_1
    //   1254: ifeq +23 -> 1277
    //   1257: dload 73
    //   1259: dload 93
    //   1261: dcmpg
    //   1262: iflt +7 -> 1269
    //   1265: iconst_0
    //   1266: goto +4 -> 1270
    //   1269: iconst_1
    //   1270: ifeq +7 -> 1277
    //   1273: iconst_1
    //   1274: goto +4 -> 1278
    //   1277: iconst_0
    //   1278: ifeq +13 -> 1291
    //   1281: dload 93
    //   1283: dstore 75
    //   1285: iconst_1
    //   1286: istore 43
    //   1288: goto +29 -> 1317
    //   1291: dload 73
    //   1293: dload 77
    //   1295: dcmpl
    //   1296: ifgt +7 -> 1303
    //   1299: iconst_0
    //   1300: goto +4 -> 1304
    //   1303: iconst_1
    //   1304: ifeq +13 -> 1317
    //   1307: dload 77
    //   1309: dstore 75
    //   1311: iconst_1
    //   1312: istore 43
    //   1314: goto +3 -> 1317
    //   1317: iload 43
    //   1319: ifeq +26 -> 1345
    //   1322: ldc 113
    //   1324: iconst_0
    //   1325: iconst_0
    //   1326: dload 73
    //   1328: dload 75
    //   1330: iload 5
    //   1332: iload 5
    //   1334: aload 6
    //   1336: iload 7
    //   1338: iload 8
    //   1340: aload 57
    //   1342: invokestatic 119	org/netlib/lapack/Dlascl:dlascl	(Ljava/lang/String;IIDDII[DIILorg/netlib/util/intW;)V
    //   1345: ldc 105
    //   1347: iload 5
    //   1349: iload 5
    //   1351: aload 9
    //   1353: iload 10
    //   1355: iload 11
    //   1357: aload 29
    //   1359: iload 30
    //   1361: invokestatic 111	org/netlib/lapack/Dlange:dlange	(Ljava/lang/String;II[DII[DI)D
    //   1364: dstore 79
    //   1366: iconst_0
    //   1367: istore 44
    //   1369: dload 79
    //   1371: dconst_0
    //   1372: dcmpl
    //   1373: ifgt +7 -> 1380
    //   1376: iconst_0
    //   1377: goto +4 -> 1381
    //   1380: iconst_1
    //   1381: ifeq +23 -> 1404
    //   1384: dload 79
    //   1386: dload 93
    //   1388: dcmpg
    //   1389: iflt +7 -> 1396
    //   1392: iconst_0
    //   1393: goto +4 -> 1397
    //   1396: iconst_1
    //   1397: ifeq +7 -> 1404
    //   1400: iconst_1
    //   1401: goto +4 -> 1405
    //   1404: iconst_0
    //   1405: ifeq +13 -> 1418
    //   1408: dload 93
    //   1410: dstore 81
    //   1412: iconst_1
    //   1413: istore 44
    //   1415: goto +29 -> 1444
    //   1418: dload 79
    //   1420: dload 77
    //   1422: dcmpl
    //   1423: ifgt +7 -> 1430
    //   1426: iconst_0
    //   1427: goto +4 -> 1431
    //   1430: iconst_1
    //   1431: ifeq +13 -> 1444
    //   1434: dload 77
    //   1436: dstore 81
    //   1438: iconst_1
    //   1439: istore 44
    //   1441: goto +3 -> 1444
    //   1444: iload 44
    //   1446: ifeq +26 -> 1472
    //   1449: ldc 113
    //   1451: iconst_0
    //   1452: iconst_0
    //   1453: dload 79
    //   1455: dload 81
    //   1457: iload 5
    //   1459: iload 5
    //   1461: aload 9
    //   1463: iload 10
    //   1465: iload 11
    //   1467: aload 57
    //   1469: invokestatic 119	org/netlib/lapack/Dlascl:dlascl	(Ljava/lang/String;IIDDII[DIILorg/netlib/util/intW;)V
    //   1472: iconst_1
    //   1473: istore 62
    //   1475: iload 5
    //   1477: iconst_1
    //   1478: iadd
    //   1479: istore 65
    //   1481: iload 65
    //   1483: iload 5
    //   1485: iadd
    //   1486: istore 68
    //   1488: ldc 84
    //   1490: iload 5
    //   1492: aload 6
    //   1494: iload 7
    //   1496: iload 8
    //   1498: aload 9
    //   1500: iload 10
    //   1502: iload 11
    //   1504: aload 63
    //   1506: aload 58
    //   1508: aload 29
    //   1510: iload 62
    //   1512: iconst_1
    //   1513: isub
    //   1514: iload 30
    //   1516: iadd
    //   1517: aload 29
    //   1519: iload 65
    //   1521: iconst_1
    //   1522: isub
    //   1523: iload 30
    //   1525: iadd
    //   1526: aload 29
    //   1528: iload 68
    //   1530: iconst_1
    //   1531: isub
    //   1532: iload 30
    //   1534: iadd
    //   1535: aload 57
    //   1537: invokestatic 125	org/netlib/lapack/Dggbal:dggbal	(Ljava/lang/String;I[DII[DIILorg/netlib/util/intW;Lorg/netlib/util/intW;[DI[DI[DILorg/netlib/util/intW;)V
    //   1540: aload 58
    //   1542: getfield 54	org/netlib/util/intW:val	I
    //   1545: iconst_1
    //   1546: iadd
    //   1547: aload 63
    //   1549: getfield 54	org/netlib/util/intW:val	I
    //   1552: isub
    //   1553: istore 66
    //   1555: iload 5
    //   1557: iconst_1
    //   1558: iadd
    //   1559: aload 63
    //   1561: getfield 54	org/netlib/util/intW:val	I
    //   1564: isub
    //   1565: istore 56
    //   1567: iload 68
    //   1569: istore 67
    //   1571: iload 67
    //   1573: iload 66
    //   1575: iadd
    //   1576: istore 68
    //   1578: iload 66
    //   1580: iload 56
    //   1582: aload 9
    //   1584: aload 63
    //   1586: getfield 54	org/netlib/util/intW:val	I
    //   1589: iconst_1
    //   1590: isub
    //   1591: aload 63
    //   1593: getfield 54	org/netlib/util/intW:val	I
    //   1596: iconst_1
    //   1597: isub
    //   1598: iload 11
    //   1600: imul
    //   1601: iadd
    //   1602: iload 10
    //   1604: iadd
    //   1605: iload 11
    //   1607: aload 29
    //   1609: iload 67
    //   1611: iconst_1
    //   1612: isub
    //   1613: iload 30
    //   1615: iadd
    //   1616: aload 29
    //   1618: iload 68
    //   1620: iconst_1
    //   1621: isub
    //   1622: iload 30
    //   1624: iadd
    //   1625: iload 31
    //   1627: iconst_1
    //   1628: iadd
    //   1629: iload 68
    //   1631: isub
    //   1632: aload 57
    //   1634: invokestatic 131	org/netlib/lapack/Dgeqrf:dgeqrf	(II[DII[DI[DIILorg/netlib/util/intW;)V
    //   1637: ldc -123
    //   1639: ldc -121
    //   1641: iload 66
    //   1643: iload 56
    //   1645: iload 66
    //   1647: aload 9
    //   1649: aload 63
    //   1651: getfield 54	org/netlib/util/intW:val	I
    //   1654: iconst_1
    //   1655: isub
    //   1656: aload 63
    //   1658: getfield 54	org/netlib/util/intW:val	I
    //   1661: iconst_1
    //   1662: isub
    //   1663: iload 11
    //   1665: imul
    //   1666: iadd
    //   1667: iload 10
    //   1669: iadd
    //   1670: iload 11
    //   1672: aload 29
    //   1674: iload 67
    //   1676: iconst_1
    //   1677: isub
    //   1678: iload 30
    //   1680: iadd
    //   1681: aload 6
    //   1683: aload 63
    //   1685: getfield 54	org/netlib/util/intW:val	I
    //   1688: iconst_1
    //   1689: isub
    //   1690: aload 63
    //   1692: getfield 54	org/netlib/util/intW:val	I
    //   1695: iconst_1
    //   1696: isub
    //   1697: iload 8
    //   1699: imul
    //   1700: iadd
    //   1701: iload 7
    //   1703: iadd
    //   1704: iload 8
    //   1706: aload 29
    //   1708: iload 68
    //   1710: iconst_1
    //   1711: isub
    //   1712: iload 30
    //   1714: iadd
    //   1715: iload 31
    //   1717: iconst_1
    //   1718: iadd
    //   1719: iload 68
    //   1721: isub
    //   1722: aload 57
    //   1724: invokestatic 141	org/netlib/lapack/Dormqr:dormqr	(Ljava/lang/String;Ljava/lang/String;III[DII[DI[DII[DIILorg/netlib/util/intW;)V
    //   1727: iload 45
    //   1729: ifeq +162 -> 1891
    //   1732: ldc -113
    //   1734: iload 5
    //   1736: iload 5
    //   1738: dconst_0
    //   1739: dconst_1
    //   1740: aload 19
    //   1742: iload 20
    //   1744: iload 21
    //   1746: invokestatic 149	org/netlib/lapack/Dlaset:dlaset	(Ljava/lang/String;IIDD[DII)V
    //   1749: iload 66
    //   1751: iconst_1
    //   1752: if_icmpgt +7 -> 1759
    //   1755: iconst_0
    //   1756: goto +4 -> 1760
    //   1759: iconst_1
    //   1760: ifeq +70 -> 1830
    //   1763: ldc -123
    //   1765: iload 66
    //   1767: iconst_1
    //   1768: isub
    //   1769: iload 66
    //   1771: iconst_1
    //   1772: isub
    //   1773: aload 9
    //   1775: aload 63
    //   1777: getfield 54	org/netlib/util/intW:val	I
    //   1780: iconst_1
    //   1781: iadd
    //   1782: iconst_1
    //   1783: isub
    //   1784: aload 63
    //   1786: getfield 54	org/netlib/util/intW:val	I
    //   1789: iconst_1
    //   1790: isub
    //   1791: iload 11
    //   1793: imul
    //   1794: iadd
    //   1795: iload 10
    //   1797: iadd
    //   1798: iload 11
    //   1800: aload 19
    //   1802: aload 63
    //   1804: getfield 54	org/netlib/util/intW:val	I
    //   1807: iconst_1
    //   1808: iadd
    //   1809: iconst_1
    //   1810: isub
    //   1811: aload 63
    //   1813: getfield 54	org/netlib/util/intW:val	I
    //   1816: iconst_1
    //   1817: isub
    //   1818: iload 21
    //   1820: imul
    //   1821: iadd
    //   1822: iload 20
    //   1824: iadd
    //   1825: iload 21
    //   1827: invokestatic 155	org/netlib/lapack/Dlacpy:dlacpy	(Ljava/lang/String;II[DII[DII)V
    //   1830: iload 66
    //   1832: iload 66
    //   1834: iload 66
    //   1836: aload 19
    //   1838: aload 63
    //   1840: getfield 54	org/netlib/util/intW:val	I
    //   1843: iconst_1
    //   1844: isub
    //   1845: aload 63
    //   1847: getfield 54	org/netlib/util/intW:val	I
    //   1850: iconst_1
    //   1851: isub
    //   1852: iload 21
    //   1854: imul
    //   1855: iadd
    //   1856: iload 20
    //   1858: iadd
    //   1859: iload 21
    //   1861: aload 29
    //   1863: iload 67
    //   1865: iconst_1
    //   1866: isub
    //   1867: iload 30
    //   1869: iadd
    //   1870: aload 29
    //   1872: iload 68
    //   1874: iconst_1
    //   1875: isub
    //   1876: iload 30
    //   1878: iadd
    //   1879: iload 31
    //   1881: iconst_1
    //   1882: iadd
    //   1883: iload 68
    //   1885: isub
    //   1886: aload 57
    //   1888: invokestatic 161	org/netlib/lapack/Dorgqr:dorgqr	(III[DII[DI[DIILorg/netlib/util/intW;)V
    //   1891: iload 46
    //   1893: ifeq +20 -> 1913
    //   1896: ldc -113
    //   1898: iload 5
    //   1900: iload 5
    //   1902: dconst_0
    //   1903: dconst_1
    //   1904: aload 22
    //   1906: iload 23
    //   1908: iload 24
    //   1910: invokestatic 149	org/netlib/lapack/Dlaset:dlaset	(Ljava/lang/String;IIDD[DII)V
    //   1913: aload_0
    //   1914: aload_1
    //   1915: iload 5
    //   1917: aload 63
    //   1919: getfield 54	org/netlib/util/intW:val	I
    //   1922: aload 58
    //   1924: getfield 54	org/netlib/util/intW:val	I
    //   1927: aload 6
    //   1929: iload 7
    //   1931: iload 8
    //   1933: aload 9
    //   1935: iload 10
    //   1937: iload 11
    //   1939: aload 19
    //   1941: iload 20
    //   1943: iload 21
    //   1945: aload 22
    //   1947: iload 23
    //   1949: iload 24
    //   1951: aload 57
    //   1953: invokestatic 167	org/netlib/lapack/Dgghrd:dgghrd	(Ljava/lang/String;Ljava/lang/String;III[DII[DII[DII[DIILorg/netlib/util/intW;)V
    //   1956: aload 12
    //   1958: iconst_0
    //   1959: putfield 54	org/netlib/util/intW:val	I
    //   1962: iload 67
    //   1964: istore 68
    //   1966: ldc 46
    //   1968: aload_0
    //   1969: aload_1
    //   1970: iload 5
    //   1972: aload 63
    //   1974: getfield 54	org/netlib/util/intW:val	I
    //   1977: aload 58
    //   1979: getfield 54	org/netlib/util/intW:val	I
    //   1982: aload 6
    //   1984: iload 7
    //   1986: iload 8
    //   1988: aload 9
    //   1990: iload 10
    //   1992: iload 11
    //   1994: aload 13
    //   1996: iload 14
    //   1998: aload 15
    //   2000: iload 16
    //   2002: aload 17
    //   2004: iload 18
    //   2006: aload 19
    //   2008: iload 20
    //   2010: iload 21
    //   2012: aload 22
    //   2014: iload 23
    //   2016: iload 24
    //   2018: aload 29
    //   2020: iload 68
    //   2022: iconst_1
    //   2023: isub
    //   2024: iload 30
    //   2026: iadd
    //   2027: iload 31
    //   2029: iconst_1
    //   2030: iadd
    //   2031: iload 68
    //   2033: isub
    //   2034: aload 57
    //   2036: invokestatic 173	org/netlib/lapack/Dhgeqz:dhgeqz	(Ljava/lang/String;Ljava/lang/String;Ljava/lang/String;III[DII[DII[DI[DI[DI[DII[DII[DIILorg/netlib/util/intW;)V
    //   2039: aload 57
    //   2041: getfield 54	org/netlib/util/intW:val	I
    //   2044: iconst_0
    //   2045: if_icmpne +7 -> 2052
    //   2048: iconst_0
    //   2049: goto +4 -> 2053
    //   2052: iconst_1
    //   2053: ifeq +133 -> 2186
    //   2056: aload 57
    //   2058: getfield 54	org/netlib/util/intW:val	I
    //   2061: iconst_0
    //   2062: if_icmpgt +7 -> 2069
    //   2065: iconst_0
    //   2066: goto +4 -> 2070
    //   2069: iconst_1
    //   2070: ifeq +25 -> 2095
    //   2073: aload 57
    //   2075: getfield 54	org/netlib/util/intW:val	I
    //   2078: iload 5
    //   2080: if_icmple +7 -> 2087
    //   2083: iconst_0
    //   2084: goto +4 -> 2088
    //   2087: iconst_1
    //   2088: ifeq +7 -> 2095
    //   2091: iconst_1
    //   2092: goto +4 -> 2096
    //   2095: iconst_0
    //   2096: ifeq +16 -> 2112
    //   2099: aload 37
    //   2101: aload 57
    //   2103: getfield 54	org/netlib/util/intW:val	I
    //   2106: putfield 54	org/netlib/util/intW:val	I
    //   2109: goto +74 -> 2183
    //   2112: aload 57
    //   2114: getfield 54	org/netlib/util/intW:val	I
    //   2117: iload 5
    //   2119: if_icmpgt +7 -> 2126
    //   2122: iconst_0
    //   2123: goto +4 -> 2127
    //   2126: iconst_1
    //   2127: ifeq +27 -> 2154
    //   2130: aload 57
    //   2132: getfield 54	org/netlib/util/intW:val	I
    //   2135: iconst_2
    //   2136: iload 5
    //   2138: imul
    //   2139: if_icmple +7 -> 2146
    //   2142: iconst_0
    //   2143: goto +4 -> 2147
    //   2146: iconst_1
    //   2147: ifeq +7 -> 2154
    //   2150: iconst_1
    //   2151: goto +4 -> 2155
    //   2154: iconst_0
    //   2155: ifeq +19 -> 2174
    //   2158: aload 37
    //   2160: aload 57
    //   2162: getfield 54	org/netlib/util/intW:val	I
    //   2165: iload 5
    //   2167: isub
    //   2168: putfield 54	org/netlib/util/intW:val	I
    //   2171: goto +12 -> 2183
    //   2174: aload 37
    //   2176: iload 5
    //   2178: iconst_1
    //   2179: iadd
    //   2180: putfield 54	org/netlib/util/intW:val	I
    //   2183: goto +1675 -> 3858
    //   2186: iload 53
    //   2188: ifeq +454 -> 2642
    //   2191: iload 43
    //   2193: ifeq +47 -> 2240
    //   2196: ldc 113
    //   2198: iconst_0
    //   2199: iconst_0
    //   2200: dload 75
    //   2202: dload 73
    //   2204: iload 5
    //   2206: iconst_1
    //   2207: aload 13
    //   2209: iload 14
    //   2211: iload 5
    //   2213: aload 57
    //   2215: invokestatic 119	org/netlib/lapack/Dlascl:dlascl	(Ljava/lang/String;IIDDII[DIILorg/netlib/util/intW;)V
    //   2218: ldc 113
    //   2220: iconst_0
    //   2221: iconst_0
    //   2222: dload 75
    //   2224: dload 73
    //   2226: iload 5
    //   2228: iconst_1
    //   2229: aload 15
    //   2231: iload 16
    //   2233: iload 5
    //   2235: aload 57
    //   2237: invokestatic 119	org/netlib/lapack/Dlascl:dlascl	(Ljava/lang/String;IIDDII[DIILorg/netlib/util/intW;)V
    //   2240: iload 44
    //   2242: ifeq +25 -> 2267
    //   2245: ldc 113
    //   2247: iconst_0
    //   2248: iconst_0
    //   2249: dload 81
    //   2251: dload 79
    //   2253: iload 5
    //   2255: iconst_1
    //   2256: aload 17
    //   2258: iload 18
    //   2260: iload 5
    //   2262: aload 57
    //   2264: invokestatic 119	org/netlib/lapack/Dlascl:dlascl	(Ljava/lang/String;IIDDII[DIILorg/netlib/util/intW;)V
    //   2267: iconst_1
    //   2268: istore 55
    //   2270: iload 5
    //   2272: iconst_1
    //   2273: isub
    //   2274: iconst_1
    //   2275: iadd
    //   2276: istore 98
    //   2278: goto +54 -> 2332
    //   2281: aload 35
    //   2283: iload 55
    //   2285: iconst_1
    //   2286: isub
    //   2287: iload 36
    //   2289: iadd
    //   2290: aload 97
    //   2292: aload 13
    //   2294: iload 55
    //   2296: iconst_1
    //   2297: isub
    //   2298: iload 14
    //   2300: iadd
    //   2301: aload 15
    //   2303: iload 55
    //   2305: iconst_1
    //   2306: isub
    //   2307: iload 16
    //   2309: iadd
    //   2310: aload 17
    //   2312: iload 55
    //   2314: iconst_1
    //   2315: isub
    //   2316: iload 18
    //   2318: iadd
    //   2319: invokestatic 177	org/netlib/lapack/Dggesx:selctg_methcall	(Ljava/lang/reflect/Method;[DI[DI[DI)Z
    //   2322: bastore
    //   2323: iload 55
    //   2325: iconst_1
    //   2326: iadd
    //   2327: istore 55
    //   2329: iinc 98 -1
    //   2332: iload 98
    //   2334: ifgt -53 -> 2281
    //   2337: iload 59
    //   2339: iload 45
    //   2341: iload 46
    //   2343: aload 35
    //   2345: iload 36
    //   2347: iload 5
    //   2349: aload 6
    //   2351: iload 7
    //   2353: iload 8
    //   2355: aload 9
    //   2357: iload 10
    //   2359: iload 11
    //   2361: aload 13
    //   2363: iload 14
    //   2365: aload 15
    //   2367: iload 16
    //   2369: aload 17
    //   2371: iload 18
    //   2373: aload 19
    //   2375: iload 20
    //   2377: iload 21
    //   2379: aload 22
    //   2381: iload 23
    //   2383: iload 24
    //   2385: aload 12
    //   2387: aload 85
    //   2389: aload 87
    //   2391: aload 95
    //   2393: iconst_0
    //   2394: aload 29
    //   2396: iload 68
    //   2398: iconst_1
    //   2399: isub
    //   2400: iload 30
    //   2402: iadd
    //   2403: iload 31
    //   2405: iload 68
    //   2407: isub
    //   2408: iconst_1
    //   2409: iadd
    //   2410: aload 32
    //   2412: iload 33
    //   2414: iload 34
    //   2416: aload 57
    //   2418: invokestatic 183	org/netlib/lapack/Dtgsen:dtgsen	(IZZ[ZII[DII[DII[DI[DI[DI[DII[DIILorg/netlib/util/intW;Lorg/netlib/util/doubleW;Lorg/netlib/util/doubleW;[DI[DII[IIILorg/netlib/util/intW;)V
    //   2421: iload 59
    //   2423: iconst_1
    //   2424: if_icmpge +7 -> 2431
    //   2427: iconst_0
    //   2428: goto +4 -> 2432
    //   2431: iconst_1
    //   2432: ifeq +26 -> 2458
    //   2435: iload 71
    //   2437: iconst_2
    //   2438: aload 12
    //   2440: getfield 54	org/netlib/util/intW:val	I
    //   2443: imul
    //   2444: iload 5
    //   2446: aload 12
    //   2448: getfield 54	org/netlib/util/intW:val	I
    //   2451: isub
    //   2452: imul
    //   2453: invokestatic 60	java/lang/Math:max	(II)I
    //   2456: istore 71
    //   2458: aload 57
    //   2460: getfield 54	org/netlib/util/intW:val	I
    //   2463: bipush -22
    //   2465: if_icmpeq +7 -> 2472
    //   2468: iconst_0
    //   2469: goto +4 -> 2473
    //   2472: iconst_1
    //   2473: ifeq +13 -> 2486
    //   2476: aload 37
    //   2478: bipush -22
    //   2480: putfield 54	org/netlib/util/intW:val	I
    //   2483: goto +159 -> 2642
    //   2486: iload 59
    //   2488: iconst_1
    //   2489: if_icmpeq +7 -> 2496
    //   2492: iconst_0
    //   2493: goto +4 -> 2497
    //   2496: iconst_1
    //   2497: ifne +21 -> 2518
    //   2500: iload 59
    //   2502: iconst_4
    //   2503: if_icmpeq +7 -> 2510
    //   2506: iconst_0
    //   2507: goto +4 -> 2511
    //   2510: iconst_1
    //   2511: ifne +7 -> 2518
    //   2514: iconst_0
    //   2515: goto +4 -> 2519
    //   2518: iconst_1
    //   2519: ifeq +31 -> 2550
    //   2522: aload 25
    //   2524: iconst_1
    //   2525: iconst_1
    //   2526: isub
    //   2527: iload 26
    //   2529: iadd
    //   2530: aload 85
    //   2532: getfield 93	org/netlib/util/doubleW:val	D
    //   2535: dastore
    //   2536: aload 25
    //   2538: iconst_2
    //   2539: iconst_1
    //   2540: isub
    //   2541: iload 26
    //   2543: iadd
    //   2544: aload 87
    //   2546: getfield 93	org/netlib/util/doubleW:val	D
    //   2549: dastore
    //   2550: iload 59
    //   2552: iconst_2
    //   2553: if_icmpeq +7 -> 2560
    //   2556: iconst_0
    //   2557: goto +4 -> 2561
    //   2560: iconst_1
    //   2561: ifne +21 -> 2582
    //   2564: iload 59
    //   2566: iconst_4
    //   2567: if_icmpeq +7 -> 2574
    //   2570: iconst_0
    //   2571: goto +4 -> 2575
    //   2574: iconst_1
    //   2575: ifne +7 -> 2582
    //   2578: iconst_0
    //   2579: goto +4 -> 2583
    //   2582: iconst_1
    //   2583: ifeq +33 -> 2616
    //   2586: aload 27
    //   2588: iconst_1
    //   2589: iconst_1
    //   2590: isub
    //   2591: iload 28
    //   2593: iadd
    //   2594: aload 95
    //   2596: iconst_1
    //   2597: iconst_1
    //   2598: isub
    //   2599: daload
    //   2600: dastore
    //   2601: aload 27
    //   2603: iconst_2
    //   2604: iconst_1
    //   2605: isub
    //   2606: iload 28
    //   2608: iadd
    //   2609: aload 95
    //   2611: iconst_2
    //   2612: iconst_1
    //   2613: isub
    //   2614: daload
    //   2615: dastore
    //   2616: aload 57
    //   2618: getfield 54	org/netlib/util/intW:val	I
    //   2621: iconst_1
    //   2622: if_icmpeq +7 -> 2629
    //   2625: iconst_0
    //   2626: goto +4 -> 2630
    //   2629: iconst_1
    //   2630: ifeq +12 -> 2642
    //   2633: aload 37
    //   2635: iload 5
    //   2637: iconst_3
    //   2638: iadd
    //   2639: putfield 54	org/netlib/util/intW:val	I
    //   2642: iload 45
    //   2644: ifeq +50 -> 2694
    //   2647: ldc 84
    //   2649: ldc -123
    //   2651: iload 5
    //   2653: aload 63
    //   2655: getfield 54	org/netlib/util/intW:val	I
    //   2658: aload 58
    //   2660: getfield 54	org/netlib/util/intW:val	I
    //   2663: aload 29
    //   2665: iload 62
    //   2667: iconst_1
    //   2668: isub
    //   2669: iload 30
    //   2671: iadd
    //   2672: aload 29
    //   2674: iload 65
    //   2676: iconst_1
    //   2677: isub
    //   2678: iload 30
    //   2680: iadd
    //   2681: iload 5
    //   2683: aload 19
    //   2685: iload 20
    //   2687: iload 21
    //   2689: aload 57
    //   2691: invokestatic 189	org/netlib/lapack/Dggbak:dggbak	(Ljava/lang/String;Ljava/lang/String;III[DI[DII[DIILorg/netlib/util/intW;)V
    //   2694: iload 46
    //   2696: ifeq +50 -> 2746
    //   2699: ldc 84
    //   2701: ldc -65
    //   2703: iload 5
    //   2705: aload 63
    //   2707: getfield 54	org/netlib/util/intW:val	I
    //   2710: aload 58
    //   2712: getfield 54	org/netlib/util/intW:val	I
    //   2715: aload 29
    //   2717: iload 62
    //   2719: iconst_1
    //   2720: isub
    //   2721: iload 30
    //   2723: iadd
    //   2724: aload 29
    //   2726: iload 65
    //   2728: iconst_1
    //   2729: isub
    //   2730: iload 30
    //   2732: iadd
    //   2733: iload 5
    //   2735: aload 22
    //   2737: iload 23
    //   2739: iload 24
    //   2741: aload 57
    //   2743: invokestatic 189	org/netlib/lapack/Dggbak:dggbak	(Ljava/lang/String;Ljava/lang/String;III[DI[DII[DIILorg/netlib/util/intW;)V
    //   2746: iload 43
    //   2748: ifeq +472 -> 3220
    //   2751: iconst_1
    //   2752: istore 55
    //   2754: iload 5
    //   2756: iconst_1
    //   2757: isub
    //   2758: iconst_1
    //   2759: iadd
    //   2760: istore 98
    //   2762: goto +453 -> 3215
    //   2765: aload 15
    //   2767: iload 55
    //   2769: iconst_1
    //   2770: isub
    //   2771: iload 16
    //   2773: iadd
    //   2774: daload
    //   2775: dconst_0
    //   2776: dcmpl
    //   2777: ifne +7 -> 2784
    //   2780: iconst_0
    //   2781: goto +4 -> 2785
    //   2784: iconst_1
    //   2785: ifeq +421 -> 3206
    //   2788: aload 13
    //   2790: iload 55
    //   2792: iconst_1
    //   2793: isub
    //   2794: iload 14
    //   2796: iadd
    //   2797: daload
    //   2798: aload 89
    //   2800: getfield 93	org/netlib/util/doubleW:val	D
    //   2803: ddiv
    //   2804: dload 75
    //   2806: dload 73
    //   2808: ddiv
    //   2809: dcmpl
    //   2810: ifgt +7 -> 2817
    //   2813: iconst_0
    //   2814: goto +4 -> 2818
    //   2817: iconst_1
    //   2818: ifne +40 -> 2858
    //   2821: aload 91
    //   2823: getfield 93	org/netlib/util/doubleW:val	D
    //   2826: aload 13
    //   2828: iload 55
    //   2830: iconst_1
    //   2831: isub
    //   2832: iload 14
    //   2834: iadd
    //   2835: daload
    //   2836: ddiv
    //   2837: dload 73
    //   2839: dload 75
    //   2841: ddiv
    //   2842: dcmpl
    //   2843: ifgt +7 -> 2850
    //   2846: iconst_0
    //   2847: goto +4 -> 2851
    //   2850: iconst_1
    //   2851: ifne +7 -> 2858
    //   2854: iconst_0
    //   2855: goto +4 -> 2859
    //   2858: iconst_1
    //   2859: ifeq +137 -> 2996
    //   2862: aload 29
    //   2864: iconst_1
    //   2865: iconst_1
    //   2866: isub
    //   2867: iload 30
    //   2869: iadd
    //   2870: aload 6
    //   2872: iload 55
    //   2874: iconst_1
    //   2875: isub
    //   2876: iload 55
    //   2878: iconst_1
    //   2879: isub
    //   2880: iload 8
    //   2882: imul
    //   2883: iadd
    //   2884: iload 7
    //   2886: iadd
    //   2887: daload
    //   2888: aload 13
    //   2890: iload 55
    //   2892: iconst_1
    //   2893: isub
    //   2894: iload 14
    //   2896: iadd
    //   2897: daload
    //   2898: ddiv
    //   2899: invokestatic 194	java/lang/Math:abs	(D)D
    //   2902: dastore
    //   2903: aload 17
    //   2905: iload 55
    //   2907: iconst_1
    //   2908: isub
    //   2909: iload 18
    //   2911: iadd
    //   2912: aload 17
    //   2914: iload 55
    //   2916: iconst_1
    //   2917: isub
    //   2918: iload 18
    //   2920: iadd
    //   2921: daload
    //   2922: aload 29
    //   2924: iconst_1
    //   2925: iconst_1
    //   2926: isub
    //   2927: iload 30
    //   2929: iadd
    //   2930: daload
    //   2931: dmul
    //   2932: dastore
    //   2933: aload 13
    //   2935: iload 55
    //   2937: iconst_1
    //   2938: isub
    //   2939: iload 14
    //   2941: iadd
    //   2942: aload 13
    //   2944: iload 55
    //   2946: iconst_1
    //   2947: isub
    //   2948: iload 14
    //   2950: iadd
    //   2951: daload
    //   2952: aload 29
    //   2954: iconst_1
    //   2955: iconst_1
    //   2956: isub
    //   2957: iload 30
    //   2959: iadd
    //   2960: daload
    //   2961: dmul
    //   2962: dastore
    //   2963: aload 15
    //   2965: iload 55
    //   2967: iconst_1
    //   2968: isub
    //   2969: iload 16
    //   2971: iadd
    //   2972: aload 15
    //   2974: iload 55
    //   2976: iconst_1
    //   2977: isub
    //   2978: iload 16
    //   2980: iadd
    //   2981: daload
    //   2982: aload 29
    //   2984: iconst_1
    //   2985: iconst_1
    //   2986: isub
    //   2987: iload 30
    //   2989: iadd
    //   2990: daload
    //   2991: dmul
    //   2992: dastore
    //   2993: goto +213 -> 3206
    //   2996: aload 15
    //   2998: iload 55
    //   3000: iconst_1
    //   3001: isub
    //   3002: iload 16
    //   3004: iadd
    //   3005: daload
    //   3006: aload 89
    //   3008: getfield 93	org/netlib/util/doubleW:val	D
    //   3011: ddiv
    //   3012: dload 75
    //   3014: dload 73
    //   3016: ddiv
    //   3017: dcmpl
    //   3018: ifgt +7 -> 3025
    //   3021: iconst_0
    //   3022: goto +4 -> 3026
    //   3025: iconst_1
    //   3026: ifne +40 -> 3066
    //   3029: aload 91
    //   3031: getfield 93	org/netlib/util/doubleW:val	D
    //   3034: aload 15
    //   3036: iload 55
    //   3038: iconst_1
    //   3039: isub
    //   3040: iload 16
    //   3042: iadd
    //   3043: daload
    //   3044: ddiv
    //   3045: dload 73
    //   3047: dload 75
    //   3049: ddiv
    //   3050: dcmpl
    //   3051: ifgt +7 -> 3058
    //   3054: iconst_0
    //   3055: goto +4 -> 3059
    //   3058: iconst_1
    //   3059: ifne +7 -> 3066
    //   3062: iconst_0
    //   3063: goto +4 -> 3067
    //   3066: iconst_1
    //   3067: ifeq +139 -> 3206
    //   3070: aload 29
    //   3072: iconst_1
    //   3073: iconst_1
    //   3074: isub
    //   3075: iload 30
    //   3077: iadd
    //   3078: aload 6
    //   3080: iload 55
    //   3082: iconst_1
    //   3083: isub
    //   3084: iload 55
    //   3086: iconst_1
    //   3087: iadd
    //   3088: iconst_1
    //   3089: isub
    //   3090: iload 8
    //   3092: imul
    //   3093: iadd
    //   3094: iload 7
    //   3096: iadd
    //   3097: daload
    //   3098: aload 15
    //   3100: iload 55
    //   3102: iconst_1
    //   3103: isub
    //   3104: iload 16
    //   3106: iadd
    //   3107: daload
    //   3108: ddiv
    //   3109: invokestatic 194	java/lang/Math:abs	(D)D
    //   3112: dastore
    //   3113: aload 17
    //   3115: iload 55
    //   3117: iconst_1
    //   3118: isub
    //   3119: iload 18
    //   3121: iadd
    //   3122: aload 17
    //   3124: iload 55
    //   3126: iconst_1
    //   3127: isub
    //   3128: iload 18
    //   3130: iadd
    //   3131: daload
    //   3132: aload 29
    //   3134: iconst_1
    //   3135: iconst_1
    //   3136: isub
    //   3137: iload 30
    //   3139: iadd
    //   3140: daload
    //   3141: dmul
    //   3142: dastore
    //   3143: aload 13
    //   3145: iload 55
    //   3147: iconst_1
    //   3148: isub
    //   3149: iload 14
    //   3151: iadd
    //   3152: aload 13
    //   3154: iload 55
    //   3156: iconst_1
    //   3157: isub
    //   3158: iload 14
    //   3160: iadd
    //   3161: daload
    //   3162: aload 29
    //   3164: iconst_1
    //   3165: iconst_1
    //   3166: isub
    //   3167: iload 30
    //   3169: iadd
    //   3170: daload
    //   3171: dmul
    //   3172: dastore
    //   3173: aload 15
    //   3175: iload 55
    //   3177: iconst_1
    //   3178: isub
    //   3179: iload 16
    //   3181: iadd
    //   3182: aload 15
    //   3184: iload 55
    //   3186: iconst_1
    //   3187: isub
    //   3188: iload 16
    //   3190: iadd
    //   3191: daload
    //   3192: aload 29
    //   3194: iconst_1
    //   3195: iconst_1
    //   3196: isub
    //   3197: iload 30
    //   3199: iadd
    //   3200: daload
    //   3201: dmul
    //   3202: dastore
    //   3203: goto +3 -> 3206
    //   3206: iload 55
    //   3208: iconst_1
    //   3209: iadd
    //   3210: istore 55
    //   3212: iinc 98 -1
    //   3215: iload 98
    //   3217: ifgt -452 -> 2765
    //   3220: iload 44
    //   3222: ifeq +259 -> 3481
    //   3225: iconst_1
    //   3226: istore 55
    //   3228: iload 5
    //   3230: iconst_1
    //   3231: isub
    //   3232: iconst_1
    //   3233: iadd
    //   3234: istore 98
    //   3236: goto +240 -> 3476
    //   3239: aload 15
    //   3241: iload 55
    //   3243: iconst_1
    //   3244: isub
    //   3245: iload 16
    //   3247: iadd
    //   3248: daload
    //   3249: dconst_0
    //   3250: dcmpl
    //   3251: ifne +7 -> 3258
    //   3254: iconst_0
    //   3255: goto +4 -> 3259
    //   3258: iconst_1
    //   3259: ifeq +208 -> 3467
    //   3262: aload 17
    //   3264: iload 55
    //   3266: iconst_1
    //   3267: isub
    //   3268: iload 18
    //   3270: iadd
    //   3271: daload
    //   3272: aload 89
    //   3274: getfield 93	org/netlib/util/doubleW:val	D
    //   3277: ddiv
    //   3278: dload 81
    //   3280: dload 79
    //   3282: ddiv
    //   3283: dcmpl
    //   3284: ifgt +7 -> 3291
    //   3287: iconst_0
    //   3288: goto +4 -> 3292
    //   3291: iconst_1
    //   3292: ifne +40 -> 3332
    //   3295: aload 91
    //   3297: getfield 93	org/netlib/util/doubleW:val	D
    //   3300: aload 17
    //   3302: iload 55
    //   3304: iconst_1
    //   3305: isub
    //   3306: iload 18
    //   3308: iadd
    //   3309: daload
    //   3310: ddiv
    //   3311: dload 79
    //   3313: dload 81
    //   3315: ddiv
    //   3316: dcmpl
    //   3317: ifgt +7 -> 3324
    //   3320: iconst_0
    //   3321: goto +4 -> 3325
    //   3324: iconst_1
    //   3325: ifne +7 -> 3332
    //   3328: iconst_0
    //   3329: goto +4 -> 3333
    //   3332: iconst_1
    //   3333: ifeq +134 -> 3467
    //   3336: aload 29
    //   3338: iconst_1
    //   3339: iconst_1
    //   3340: isub
    //   3341: iload 30
    //   3343: iadd
    //   3344: aload 9
    //   3346: iload 55
    //   3348: iconst_1
    //   3349: isub
    //   3350: iload 55
    //   3352: iconst_1
    //   3353: isub
    //   3354: iload 11
    //   3356: imul
    //   3357: iadd
    //   3358: iload 10
    //   3360: iadd
    //   3361: daload
    //   3362: aload 17
    //   3364: iload 55
    //   3366: iconst_1
    //   3367: isub
    //   3368: iload 18
    //   3370: iadd
    //   3371: daload
    //   3372: ddiv
    //   3373: invokestatic 194	java/lang/Math:abs	(D)D
    //   3376: dastore
    //   3377: aload 17
    //   3379: iload 55
    //   3381: iconst_1
    //   3382: isub
    //   3383: iload 18
    //   3385: iadd
    //   3386: aload 17
    //   3388: iload 55
    //   3390: iconst_1
    //   3391: isub
    //   3392: iload 18
    //   3394: iadd
    //   3395: daload
    //   3396: aload 29
    //   3398: iconst_1
    //   3399: iconst_1
    //   3400: isub
    //   3401: iload 30
    //   3403: iadd
    //   3404: daload
    //   3405: dmul
    //   3406: dastore
    //   3407: aload 13
    //   3409: iload 55
    //   3411: iconst_1
    //   3412: isub
    //   3413: iload 14
    //   3415: iadd
    //   3416: aload 13
    //   3418: iload 55
    //   3420: iconst_1
    //   3421: isub
    //   3422: iload 14
    //   3424: iadd
    //   3425: daload
    //   3426: aload 29
    //   3428: iconst_1
    //   3429: iconst_1
    //   3430: isub
    //   3431: iload 30
    //   3433: iadd
    //   3434: daload
    //   3435: dmul
    //   3436: dastore
    //   3437: aload 15
    //   3439: iload 55
    //   3441: iconst_1
    //   3442: isub
    //   3443: iload 16
    //   3445: iadd
    //   3446: aload 15
    //   3448: iload 55
    //   3450: iconst_1
    //   3451: isub
    //   3452: iload 16
    //   3454: iadd
    //   3455: daload
    //   3456: aload 29
    //   3458: iconst_1
    //   3459: iconst_1
    //   3460: isub
    //   3461: iload 30
    //   3463: iadd
    //   3464: daload
    //   3465: dmul
    //   3466: dastore
    //   3467: iload 55
    //   3469: iconst_1
    //   3470: iadd
    //   3471: istore 55
    //   3473: iinc 98 -1
    //   3476: iload 98
    //   3478: ifgt -239 -> 3239
    //   3481: iload 43
    //   3483: ifeq +70 -> 3553
    //   3486: ldc -60
    //   3488: iconst_0
    //   3489: iconst_0
    //   3490: dload 75
    //   3492: dload 73
    //   3494: iload 5
    //   3496: iload 5
    //   3498: aload 6
    //   3500: iload 7
    //   3502: iload 8
    //   3504: aload 57
    //   3506: invokestatic 119	org/netlib/lapack/Dlascl:dlascl	(Ljava/lang/String;IIDDII[DIILorg/netlib/util/intW;)V
    //   3509: ldc 113
    //   3511: iconst_0
    //   3512: iconst_0
    //   3513: dload 75
    //   3515: dload 73
    //   3517: iload 5
    //   3519: iconst_1
    //   3520: aload 13
    //   3522: iload 14
    //   3524: iload 5
    //   3526: aload 57
    //   3528: invokestatic 119	org/netlib/lapack/Dlascl:dlascl	(Ljava/lang/String;IIDDII[DIILorg/netlib/util/intW;)V
    //   3531: ldc 113
    //   3533: iconst_0
    //   3534: iconst_0
    //   3535: dload 75
    //   3537: dload 73
    //   3539: iload 5
    //   3541: iconst_1
    //   3542: aload 15
    //   3544: iload 16
    //   3546: iload 5
    //   3548: aload 57
    //   3550: invokestatic 119	org/netlib/lapack/Dlascl:dlascl	(Ljava/lang/String;IIDDII[DIILorg/netlib/util/intW;)V
    //   3553: iload 44
    //   3555: ifeq +48 -> 3603
    //   3558: ldc -58
    //   3560: iconst_0
    //   3561: iconst_0
    //   3562: dload 81
    //   3564: dload 79
    //   3566: iload 5
    //   3568: iload 5
    //   3570: aload 9
    //   3572: iload 10
    //   3574: iload 11
    //   3576: aload 57
    //   3578: invokestatic 119	org/netlib/lapack/Dlascl:dlascl	(Ljava/lang/String;IIDDII[DIILorg/netlib/util/intW;)V
    //   3581: ldc 113
    //   3583: iconst_0
    //   3584: iconst_0
    //   3585: dload 81
    //   3587: dload 79
    //   3589: iload 5
    //   3591: iconst_1
    //   3592: aload 17
    //   3594: iload 18
    //   3596: iload 5
    //   3598: aload 57
    //   3600: invokestatic 119	org/netlib/lapack/Dlascl:dlascl	(Ljava/lang/String;IIDDII[DIILorg/netlib/util/intW;)V
    //   3603: iload 53
    //   3605: ifeq +253 -> 3858
    //   3608: iconst_1
    //   3609: istore 47
    //   3611: iconst_1
    //   3612: istore 49
    //   3614: aload 12
    //   3616: iconst_0
    //   3617: putfield 54	org/netlib/util/intW:val	I
    //   3620: iconst_0
    //   3621: istore 64
    //   3623: iconst_1
    //   3624: istore 55
    //   3626: iload 5
    //   3628: iconst_1
    //   3629: isub
    //   3630: iconst_1
    //   3631: iadd
    //   3632: istore 98
    //   3634: goto +219 -> 3853
    //   3637: aload 97
    //   3639: aload 13
    //   3641: iload 55
    //   3643: iconst_1
    //   3644: isub
    //   3645: iload 14
    //   3647: iadd
    //   3648: aload 15
    //   3650: iload 55
    //   3652: iconst_1
    //   3653: isub
    //   3654: iload 16
    //   3656: iadd
    //   3657: aload 17
    //   3659: iload 55
    //   3661: iconst_1
    //   3662: isub
    //   3663: iload 18
    //   3665: iadd
    //   3666: invokestatic 177	org/netlib/lapack/Dggesx:selctg_methcall	(Ljava/lang/reflect/Method;[DI[DI[DI)Z
    //   3669: istore 42
    //   3671: aload 15
    //   3673: iload 55
    //   3675: iconst_1
    //   3676: isub
    //   3677: iload 16
    //   3679: iadd
    //   3680: daload
    //   3681: dconst_0
    //   3682: dcmpl
    //   3683: ifeq +7 -> 3690
    //   3686: iconst_0
    //   3687: goto +4 -> 3691
    //   3690: iconst_1
    //   3691: ifeq +55 -> 3746
    //   3694: iload 42
    //   3696: ifeq +15 -> 3711
    //   3699: aload 12
    //   3701: aload 12
    //   3703: getfield 54	org/netlib/util/intW:val	I
    //   3706: iconst_1
    //   3707: iadd
    //   3708: putfield 54	org/netlib/util/intW:val	I
    //   3711: iconst_0
    //   3712: istore 64
    //   3714: iload 42
    //   3716: ifeq +14 -> 3730
    //   3719: iload 47
    //   3721: iconst_1
    //   3722: ixor
    //   3723: ifeq +7 -> 3730
    //   3726: iconst_1
    //   3727: goto +4 -> 3731
    //   3730: iconst_0
    //   3731: ifeq +12 -> 3743
    //   3734: aload 37
    //   3736: iload 5
    //   3738: iconst_2
    //   3739: iadd
    //   3740: putfield 54	org/netlib/util/intW:val	I
    //   3743: goto +93 -> 3836
    //   3746: iload 64
    //   3748: iconst_1
    //   3749: if_icmpeq +7 -> 3756
    //   3752: iconst_0
    //   3753: goto +4 -> 3757
    //   3756: iconst_1
    //   3757: ifeq +76 -> 3833
    //   3760: iload 42
    //   3762: ifne +12 -> 3774
    //   3765: iload 47
    //   3767: ifne +7 -> 3774
    //   3770: iconst_0
    //   3771: goto +4 -> 3775
    //   3774: iconst_1
    //   3775: istore 42
    //   3777: iload 42
    //   3779: istore 47
    //   3781: iload 42
    //   3783: ifeq +15 -> 3798
    //   3786: aload 12
    //   3788: aload 12
    //   3790: getfield 54	org/netlib/util/intW:val	I
    //   3793: iconst_2
    //   3794: iadd
    //   3795: putfield 54	org/netlib/util/intW:val	I
    //   3798: iconst_m1
    //   3799: istore 64
    //   3801: iload 42
    //   3803: ifeq +14 -> 3817
    //   3806: iload 49
    //   3808: iconst_1
    //   3809: ixor
    //   3810: ifeq +7 -> 3817
    //   3813: iconst_1
    //   3814: goto +4 -> 3818
    //   3817: iconst_0
    //   3818: ifeq +12 -> 3830
    //   3821: aload 37
    //   3823: iload 5
    //   3825: iconst_2
    //   3826: iadd
    //   3827: putfield 54	org/netlib/util/intW:val	I
    //   3830: goto +6 -> 3836
    //   3833: iconst_1
    //   3834: istore 64
    //   3836: iload 47
    //   3838: istore 49
    //   3840: iload 42
    //   3842: istore 47
    //   3844: iload 55
    //   3846: iconst_1
    //   3847: iadd
    //   3848: istore 55
    //   3850: iinc 98 -1
    //   3853: iload 98
    //   3855: ifgt -218 -> 3637
    //   3858: aload 29
    //   3860: iconst_1
    //   3861: iconst_1
    //   3862: isub
    //   3863: iload 30
    //   3865: iadd
    //   3866: iload 71
    //   3868: i2d
    //   3869: dastore
    //   3870: aload 32
    //   3872: iconst_1
    //   3873: iconst_1
    //   3874: isub
    //   3875: iload 33
    //   3877: iadd
    //   3878: iload 69
    //   3880: iastore
    //   3881: return
    //   3882: goto +0 -> 3882
    //   3885: astore 98
    //   3887: getstatic 204	java/lang/System:err	Ljava/io/PrintStream;
    //   3890: new 206	java/lang/StringBuffer
    //   3893: dup
    //   3894: ldc -48
    //   3896: invokespecial 211	java/lang/StringBuffer:<init>	(Ljava/lang/String;)V
    //   3899: aload 98
    //   3901: invokevirtual 217	java/lang/Throwable:getMessage	()Ljava/lang/String;
    //   3904: invokevirtual 221	java/lang/StringBuffer:append	(Ljava/lang/String;)Ljava/lang/StringBuffer;
    //   3907: invokevirtual 224	java/lang/StringBuffer:toString	()Ljava/lang/String;
    //   3910: invokevirtual 229	java/io/PrintStream:println	(Ljava/lang/String;)V
    //   3913: goto +31 -> 3944
    //   3916: astore 98
    //   3918: getstatic 204	java/lang/System:err	Ljava/io/PrintStream;
    //   3921: new 206	java/lang/StringBuffer
    //   3924: dup
    //   3925: ldc -48
    //   3927: invokespecial 211	java/lang/StringBuffer:<init>	(Ljava/lang/String;)V
    //   3930: aload 98
    //   3932: invokevirtual 217	java/lang/Throwable:getMessage	()Ljava/lang/String;
    //   3935: invokevirtual 221	java/lang/StringBuffer:append	(Ljava/lang/String;)Ljava/lang/StringBuffer;
    //   3938: invokevirtual 224	java/lang/StringBuffer:toString	()Ljava/lang/String;
    //   3941: invokevirtual 229	java/io/PrintStream:println	(Ljava/lang/String;)V
    //   3944: return
    // Local variable table:
    //   start	length	slot	name	signature
    //   0	3945	0	paramString1	String
    //   0	3945	1	paramString2	String
    //   0	3945	2	paramString3	String
    //   0	3945	3	paramObject	Object
    //   0	3945	4	paramString4	String
    //   0	3945	5	paramInt1	int
    //   0	3945	6	paramArrayOfDouble1	double[]
    //   0	3945	7	paramInt2	int
    //   0	3945	8	paramInt3	int
    //   0	3945	9	paramArrayOfDouble2	double[]
    //   0	3945	10	paramInt4	int
    //   0	3945	11	paramInt5	int
    //   0	3945	12	paramintW1	org.netlib.util.intW
    //   0	3945	13	paramArrayOfDouble3	double[]
    //   0	3945	14	paramInt6	int
    //   0	3945	15	paramArrayOfDouble4	double[]
    //   0	3945	16	paramInt7	int
    //   0	3945	17	paramArrayOfDouble5	double[]
    //   0	3945	18	paramInt8	int
    //   0	3945	19	paramArrayOfDouble6	double[]
    //   0	3945	20	paramInt9	int
    //   0	3945	21	paramInt10	int
    //   0	3945	22	paramArrayOfDouble7	double[]
    //   0	3945	23	paramInt11	int
    //   0	3945	24	paramInt12	int
    //   0	3945	25	paramArrayOfDouble8	double[]
    //   0	3945	26	paramInt13	int
    //   0	3945	27	paramArrayOfDouble9	double[]
    //   0	3945	28	paramInt14	int
    //   0	3945	29	paramArrayOfDouble10	double[]
    //   0	3945	30	paramInt15	int
    //   0	3945	31	paramInt16	int
    //   0	3945	32	paramArrayOfInt	int[]
    //   0	3945	33	paramInt17	int
    //   0	3945	34	paramInt18	int
    //   0	3945	35	paramArrayOfBoolean	boolean[]
    //   0	3945	36	paramInt19	int
    //   0	3945	37	paramintW2	org.netlib.util.intW
    //   1	3840	42	bool1	boolean
    //   4	3478	43	i	int
    //   7	3547	44	j	int
    //   10	2633	45	bool2	boolean
    //   13	2682	46	bool3	boolean
    //   16	3827	47	k	int
    //   19	1115	48	m	int
    //   22	3817	49	n	int
    //   25	494	50	bool4	boolean
    //   28	465	51	bool5	boolean
    //   31	940	52	bool6	boolean
    //   34	3570	53	bool7	boolean
    //   37	469	54	bool8	boolean
    //   40	3809	55	i1	int
    //   43	1601	56	i2	int
    //   53	3546	57	localintW1	org.netlib.util.intW
    //   63	2648	58	localintW2	org.netlib.util.intW
    //   66	2502	59	i3	int
    //   69	339	60	i4	int
    //   72	359	61	i5	int
    //   75	2646	62	i6	int
    //   85	2621	63	localintW3	org.netlib.util.intW
    //   88	3747	64	i7	int
    //   91	2639	65	i8	int
    //   94	1741	66	i9	int
    //   97	1866	67	i10	int
    //   100	2308	68	i11	int
    //   103	3776	69	i12	int
    //   106	861	70	i13	int
    //   109	3758	71	i14	int
    //   112	914	72	i15	int
    //   115	3423	73	d1	double
    //   118	3418	75	d2	double
    //   121	1314	77	d3	double
    //   124	3464	79	d4	double
    //   127	3459	81	d5	double
    //   130	1078	83	d6	double
    //   140	2391	85	localdoubleW1	org.netlib.util.doubleW
    //   150	2395	87	localdoubleW2	org.netlib.util.doubleW
    //   160	3113	89	localdoubleW3	org.netlib.util.doubleW
    //   170	3126	91	localdoubleW4	org.netlib.util.doubleW
    //   173	1236	93	d7	double
    //   178	2432	95	arrayOfDouble	double[]
    //   189	3449	97	localMethod	Method
    //   2276	1578	98	i16	int
    //   3885	15	98	localInvocationTargetException	InvocationTargetException
    //   3916	15	98	localIllegalAccessException	IllegalAccessException
    // Exception table:
    //   from	to	target	type
    //   191	3882	3885	java/lang/reflect/InvocationTargetException
    //   191	3882	3916	java/lang/IllegalAccessException
  }
  
  private static boolean selctg_methcall(Method paramMethod, double[] paramArrayOfDouble1, int paramInt1, double[] paramArrayOfDouble2, int paramInt2, double[] paramArrayOfDouble3, int paramInt3)
    throws InvocationTargetException, IllegalAccessException
  {
    Object[] arrayOfObject = new Object[3];
    arrayOfObject[0] = new Double(paramArrayOfDouble1[paramInt1]);
    arrayOfObject[1] = new Double(paramArrayOfDouble2[paramInt2]);
    arrayOfObject[2] = new Double(paramArrayOfDouble3[paramInt3]);
    return ((Boolean)paramMethod.invoke(null, arrayOfObject)).booleanValue();
  }
}


/* Location:              /Users/assaad/Downloads/arpack_combined_all/!/org/netlib/lapack/Dggesx.class
 * Java compiler version: 1 (45.3)
 * JD-Core Version:       0.7.1
 */