package org.netlib.lapack;

public final class Dtrevc
{
  /* Error */
  public static void dtrevc(String paramString1, String paramString2, boolean[] paramArrayOfBoolean, int paramInt1, int paramInt2, double[] paramArrayOfDouble1, int paramInt3, int paramInt4, double[] paramArrayOfDouble2, int paramInt5, int paramInt6, double[] paramArrayOfDouble3, int paramInt7, int paramInt8, int paramInt9, org.netlib.util.intW paramintW1, double[] paramArrayOfDouble4, int paramInt10, org.netlib.util.intW paramintW2)
  {
    // Byte code:
    //   0: iconst_0
    //   1: istore 23
    //   3: iconst_0
    //   4: istore 24
    //   6: iconst_0
    //   7: istore 25
    //   9: iconst_0
    //   10: istore 26
    //   12: iconst_0
    //   13: istore 27
    //   15: iconst_0
    //   16: istore 28
    //   18: iconst_0
    //   19: istore 29
    //   21: iconst_0
    //   22: istore 30
    //   24: new 16	org/netlib/util/intW
    //   27: dup
    //   28: iconst_0
    //   29: invokespecial 19	org/netlib/util/intW:<init>	(I)V
    //   32: astore 31
    //   34: iconst_0
    //   35: istore 32
    //   37: iconst_0
    //   38: istore 33
    //   40: iconst_0
    //   41: istore 34
    //   43: iconst_0
    //   44: istore 35
    //   46: iconst_0
    //   47: istore 36
    //   49: iconst_0
    //   50: istore 37
    //   52: iconst_0
    //   53: istore 38
    //   55: iconst_0
    //   56: istore 39
    //   58: iconst_0
    //   59: istore 40
    //   61: iconst_0
    //   62: istore 41
    //   64: dconst_0
    //   65: dstore 42
    //   67: dconst_0
    //   68: dstore 44
    //   70: dconst_0
    //   71: dstore 46
    //   73: new 21	org/netlib/util/doubleW
    //   76: dup
    //   77: dconst_0
    //   78: invokespecial 24	org/netlib/util/doubleW:<init>	(D)V
    //   81: astore 48
    //   83: dconst_0
    //   84: dstore 50
    //   86: dconst_0
    //   87: dstore 52
    //   89: new 21	org/netlib/util/doubleW
    //   92: dup
    //   93: dconst_0
    //   94: invokespecial 24	org/netlib/util/doubleW:<init>	(D)V
    //   97: astore 54
    //   99: dconst_0
    //   100: dstore 56
    //   102: dconst_0
    //   103: dstore 58
    //   105: dconst_0
    //   106: dstore 60
    //   108: new 21	org/netlib/util/doubleW
    //   111: dup
    //   112: dconst_0
    //   113: invokespecial 24	org/netlib/util/doubleW:<init>	(D)V
    //   116: astore 62
    //   118: dconst_0
    //   119: dstore 64
    //   121: dconst_0
    //   122: dstore 66
    //   124: dconst_0
    //   125: dstore 68
    //   127: dconst_0
    //   128: dstore 70
    //   130: new 21	org/netlib/util/doubleW
    //   133: dup
    //   134: dconst_0
    //   135: invokespecial 24	org/netlib/util/doubleW:<init>	(D)V
    //   138: astore 72
    //   140: iconst_2
    //   141: iconst_2
    //   142: imul
    //   143: newarray <illegal type>
    //   145: astore 74
    //   147: aload_0
    //   148: ldc 26
    //   150: invokestatic 32	org/netlib/lapack/Lsame:lsame	(Ljava/lang/String;Ljava/lang/String;)Z
    //   153: istore 24
    //   155: aload_0
    //   156: ldc 34
    //   158: invokestatic 32	org/netlib/lapack/Lsame:lsame	(Ljava/lang/String;Ljava/lang/String;)Z
    //   161: ifne +12 -> 173
    //   164: iload 24
    //   166: ifne +7 -> 173
    //   169: iconst_0
    //   170: goto +4 -> 174
    //   173: iconst_1
    //   174: istore 28
    //   176: aload_0
    //   177: ldc 36
    //   179: invokestatic 32	org/netlib/lapack/Lsame:lsame	(Ljava/lang/String;Ljava/lang/String;)Z
    //   182: ifne +12 -> 194
    //   185: iload 24
    //   187: ifne +7 -> 194
    //   190: iconst_0
    //   191: goto +4 -> 195
    //   194: iconst_1
    //   195: istore 25
    //   197: aload_1
    //   198: ldc 38
    //   200: invokestatic 32	org/netlib/lapack/Lsame:lsame	(Ljava/lang/String;Ljava/lang/String;)Z
    //   203: istore 23
    //   205: aload_1
    //   206: ldc 26
    //   208: invokestatic 32	org/netlib/lapack/Lsame:lsame	(Ljava/lang/String;Ljava/lang/String;)Z
    //   211: istore 26
    //   213: aload_1
    //   214: ldc 40
    //   216: invokestatic 32	org/netlib/lapack/Lsame:lsame	(Ljava/lang/String;Ljava/lang/String;)Z
    //   219: istore 29
    //   221: aload 18
    //   223: iconst_0
    //   224: putfield 44	org/netlib/util/intW:val	I
    //   227: iload 28
    //   229: iconst_1
    //   230: ixor
    //   231: ifeq +14 -> 245
    //   234: iload 25
    //   236: iconst_1
    //   237: ixor
    //   238: ifeq +7 -> 245
    //   241: iconst_1
    //   242: goto +4 -> 246
    //   245: iconst_0
    //   246: ifeq +12 -> 258
    //   249: aload 18
    //   251: iconst_m1
    //   252: putfield 44	org/netlib/util/intW:val	I
    //   255: goto +476 -> 731
    //   258: iload 23
    //   260: iconst_1
    //   261: ixor
    //   262: ifeq +14 -> 276
    //   265: iload 26
    //   267: iconst_1
    //   268: ixor
    //   269: ifeq +7 -> 276
    //   272: iconst_1
    //   273: goto +4 -> 277
    //   276: iconst_0
    //   277: ifeq +14 -> 291
    //   280: iload 29
    //   282: iconst_1
    //   283: ixor
    //   284: ifeq +7 -> 291
    //   287: iconst_1
    //   288: goto +4 -> 292
    //   291: iconst_0
    //   292: ifeq +13 -> 305
    //   295: aload 18
    //   297: bipush -2
    //   299: putfield 44	org/netlib/util/intW:val	I
    //   302: goto +429 -> 731
    //   305: iload 4
    //   307: iconst_0
    //   308: if_icmplt +7 -> 315
    //   311: iconst_0
    //   312: goto +4 -> 316
    //   315: iconst_1
    //   316: ifeq +13 -> 329
    //   319: aload 18
    //   321: bipush -4
    //   323: putfield 44	org/netlib/util/intW:val	I
    //   326: goto +405 -> 731
    //   329: iload 7
    //   331: iconst_1
    //   332: iload 4
    //   334: invokestatic 50	java/lang/Math:max	(II)I
    //   337: if_icmplt +7 -> 344
    //   340: iconst_0
    //   341: goto +4 -> 345
    //   344: iconst_1
    //   345: ifeq +13 -> 358
    //   348: aload 18
    //   350: bipush -6
    //   352: putfield 44	org/netlib/util/intW:val	I
    //   355: goto +376 -> 731
    //   358: iload 10
    //   360: iconst_1
    //   361: if_icmplt +7 -> 368
    //   364: iconst_0
    //   365: goto +4 -> 369
    //   368: iconst_1
    //   369: ifne +35 -> 404
    //   372: iload 25
    //   374: ifeq +22 -> 396
    //   377: iload 10
    //   379: iload 4
    //   381: if_icmplt +7 -> 388
    //   384: iconst_0
    //   385: goto +4 -> 389
    //   388: iconst_1
    //   389: ifeq +7 -> 396
    //   392: iconst_1
    //   393: goto +4 -> 397
    //   396: iconst_0
    //   397: ifne +7 -> 404
    //   400: iconst_0
    //   401: goto +4 -> 405
    //   404: iconst_1
    //   405: ifeq +13 -> 418
    //   408: aload 18
    //   410: bipush -8
    //   412: putfield 44	org/netlib/util/intW:val	I
    //   415: goto +316 -> 731
    //   418: iload 13
    //   420: iconst_1
    //   421: if_icmplt +7 -> 428
    //   424: iconst_0
    //   425: goto +4 -> 429
    //   428: iconst_1
    //   429: ifne +35 -> 464
    //   432: iload 28
    //   434: ifeq +22 -> 456
    //   437: iload 13
    //   439: iload 4
    //   441: if_icmplt +7 -> 448
    //   444: iconst_0
    //   445: goto +4 -> 449
    //   448: iconst_1
    //   449: ifeq +7 -> 456
    //   452: iconst_1
    //   453: goto +4 -> 457
    //   456: iconst_0
    //   457: ifne +7 -> 464
    //   460: iconst_0
    //   461: goto +4 -> 465
    //   464: iconst_1
    //   465: ifeq +13 -> 478
    //   468: aload 18
    //   470: bipush -10
    //   472: putfield 44	org/netlib/util/intW:val	I
    //   475: goto +256 -> 731
    //   478: iload 29
    //   480: ifeq +219 -> 699
    //   483: aload 15
    //   485: iconst_0
    //   486: putfield 44	org/netlib/util/intW:val	I
    //   489: iconst_0
    //   490: istore 27
    //   492: iconst_1
    //   493: istore 35
    //   495: iload 4
    //   497: iconst_1
    //   498: isub
    //   499: iconst_1
    //   500: iadd
    //   501: istore 76
    //   503: goto +188 -> 691
    //   506: iload 27
    //   508: ifeq +18 -> 526
    //   511: iconst_0
    //   512: istore 27
    //   514: aload_2
    //   515: iload 35
    //   517: iconst_1
    //   518: isub
    //   519: iload_3
    //   520: iadd
    //   521: iconst_0
    //   522: bastore
    //   523: goto +159 -> 682
    //   526: iload 35
    //   528: iload 4
    //   530: if_icmplt +7 -> 537
    //   533: iconst_0
    //   534: goto +4 -> 538
    //   537: iconst_1
    //   538: ifeq +121 -> 659
    //   541: aload 5
    //   543: iload 35
    //   545: iconst_1
    //   546: iadd
    //   547: iconst_1
    //   548: isub
    //   549: iload 35
    //   551: iconst_1
    //   552: isub
    //   553: iload 7
    //   555: imul
    //   556: iadd
    //   557: iload 6
    //   559: iadd
    //   560: daload
    //   561: dconst_0
    //   562: dcmpl
    //   563: ifeq +7 -> 570
    //   566: iconst_0
    //   567: goto +4 -> 571
    //   570: iconst_1
    //   571: ifeq +29 -> 600
    //   574: aload_2
    //   575: iload 35
    //   577: iconst_1
    //   578: isub
    //   579: iload_3
    //   580: iadd
    //   581: baload
    //   582: ifeq +15 -> 597
    //   585: aload 15
    //   587: aload 15
    //   589: getfield 44	org/netlib/util/intW:val	I
    //   592: iconst_1
    //   593: iadd
    //   594: putfield 44	org/netlib/util/intW:val	I
    //   597: goto +59 -> 656
    //   600: iconst_1
    //   601: istore 27
    //   603: aload_2
    //   604: iload 35
    //   606: iconst_1
    //   607: isub
    //   608: iload_3
    //   609: iadd
    //   610: baload
    //   611: ifne +20 -> 631
    //   614: aload_2
    //   615: iload 35
    //   617: iconst_1
    //   618: iadd
    //   619: iconst_1
    //   620: isub
    //   621: iload_3
    //   622: iadd
    //   623: baload
    //   624: ifne +7 -> 631
    //   627: iconst_0
    //   628: goto +4 -> 632
    //   631: iconst_1
    //   632: ifeq +24 -> 656
    //   635: aload_2
    //   636: iload 35
    //   638: iconst_1
    //   639: isub
    //   640: iload_3
    //   641: iadd
    //   642: iconst_1
    //   643: bastore
    //   644: aload 15
    //   646: aload 15
    //   648: getfield 44	org/netlib/util/intW:val	I
    //   651: iconst_2
    //   652: iadd
    //   653: putfield 44	org/netlib/util/intW:val	I
    //   656: goto +26 -> 682
    //   659: aload_2
    //   660: iload 4
    //   662: iconst_1
    //   663: isub
    //   664: iload_3
    //   665: iadd
    //   666: baload
    //   667: ifeq +15 -> 682
    //   670: aload 15
    //   672: aload 15
    //   674: getfield 44	org/netlib/util/intW:val	I
    //   677: iconst_1
    //   678: iadd
    //   679: putfield 44	org/netlib/util/intW:val	I
    //   682: iload 35
    //   684: iconst_1
    //   685: iadd
    //   686: istore 35
    //   688: iinc 76 -1
    //   691: iload 76
    //   693: ifgt -187 -> 506
    //   696: goto +10 -> 706
    //   699: aload 15
    //   701: iload 4
    //   703: putfield 44	org/netlib/util/intW:val	I
    //   706: iload 14
    //   708: aload 15
    //   710: getfield 44	org/netlib/util/intW:val	I
    //   713: if_icmplt +7 -> 720
    //   716: iconst_0
    //   717: goto +4 -> 721
    //   720: iconst_1
    //   721: ifeq +10 -> 731
    //   724: aload 18
    //   726: bipush -11
    //   728: putfield 44	org/netlib/util/intW:val	I
    //   731: aload 18
    //   733: getfield 44	org/netlib/util/intW:val	I
    //   736: iconst_0
    //   737: if_icmpne +7 -> 744
    //   740: iconst_0
    //   741: goto +4 -> 745
    //   744: iconst_1
    //   745: ifeq +15 -> 760
    //   748: ldc 52
    //   750: aload 18
    //   752: getfield 44	org/netlib/util/intW:val	I
    //   755: ineg
    //   756: invokestatic 58	org/netlib/err/Xerbla:xerbla	(Ljava/lang/String;I)V
    //   759: return
    //   760: iload 4
    //   762: iconst_0
    //   763: if_icmpeq +7 -> 770
    //   766: iconst_0
    //   767: goto +4 -> 771
    //   770: iconst_1
    //   771: ifeq +4 -> 775
    //   774: return
    //   775: aload 62
    //   777: ldc 60
    //   779: invokestatic 66	org/netlib/lapack/Dlamch:dlamch	(Ljava/lang/String;)D
    //   782: putfield 69	org/netlib/util/doubleW:val	D
    //   785: aload 48
    //   787: dconst_1
    //   788: aload 62
    //   790: getfield 69	org/netlib/util/doubleW:val	D
    //   793: ddiv
    //   794: putfield 69	org/netlib/util/doubleW:val	D
    //   797: aload 62
    //   799: aload 48
    //   801: invokestatic 75	org/netlib/lapack/Dlabad:dlabad	(Lorg/netlib/util/doubleW;Lorg/netlib/util/doubleW;)V
    //   804: ldc 77
    //   806: invokestatic 66	org/netlib/lapack/Dlamch:dlamch	(Ljava/lang/String;)D
    //   809: dstore 60
    //   811: aload 62
    //   813: getfield 69	org/netlib/util/doubleW:val	D
    //   816: iload 4
    //   818: i2d
    //   819: dload 60
    //   821: ddiv
    //   822: dmul
    //   823: dstore 58
    //   825: dconst_1
    //   826: dload 60
    //   828: dsub
    //   829: dload 58
    //   831: ddiv
    //   832: dstore 44
    //   834: aload 16
    //   836: iconst_1
    //   837: iconst_1
    //   838: isub
    //   839: iload 17
    //   841: iadd
    //   842: dconst_0
    //   843: dastore
    //   844: iconst_2
    //   845: istore 35
    //   847: iload 4
    //   849: iconst_2
    //   850: isub
    //   851: iconst_1
    //   852: iadd
    //   853: istore 76
    //   855: goto +95 -> 950
    //   858: aload 16
    //   860: iload 35
    //   862: iconst_1
    //   863: isub
    //   864: iload 17
    //   866: iadd
    //   867: dconst_0
    //   868: dastore
    //   869: iconst_1
    //   870: istore 30
    //   872: iload 35
    //   874: iconst_1
    //   875: isub
    //   876: iconst_1
    //   877: isub
    //   878: iconst_1
    //   879: iadd
    //   880: istore 77
    //   882: goto +54 -> 936
    //   885: aload 16
    //   887: iload 35
    //   889: iconst_1
    //   890: isub
    //   891: iload 17
    //   893: iadd
    //   894: aload 16
    //   896: iload 35
    //   898: iconst_1
    //   899: isub
    //   900: iload 17
    //   902: iadd
    //   903: daload
    //   904: aload 5
    //   906: iload 30
    //   908: iconst_1
    //   909: isub
    //   910: iload 35
    //   912: iconst_1
    //   913: isub
    //   914: iload 7
    //   916: imul
    //   917: iadd
    //   918: iload 6
    //   920: iadd
    //   921: daload
    //   922: invokestatic 81	java/lang/Math:abs	(D)D
    //   925: dadd
    //   926: dastore
    //   927: iload 30
    //   929: iconst_1
    //   930: iadd
    //   931: istore 30
    //   933: iinc 77 -1
    //   936: iload 77
    //   938: ifgt -53 -> 885
    //   941: iload 35
    //   943: iconst_1
    //   944: iadd
    //   945: istore 35
    //   947: iinc 76 -1
    //   950: iload 76
    //   952: ifgt -94 -> 858
    //   955: iconst_2
    //   956: iload 4
    //   958: imul
    //   959: istore 41
    //   961: iload 28
    //   963: ifeq +3707 -> 4670
    //   966: iconst_0
    //   967: istore 33
    //   969: aload 15
    //   971: getfield 44	org/netlib/util/intW:val	I
    //   974: istore 34
    //   976: iload 4
    //   978: istore 40
    //   980: iconst_1
    //   981: iload 4
    //   983: isub
    //   984: iconst_m1
    //   985: iadd
    //   986: iconst_m1
    //   987: idiv
    //   988: istore 76
    //   990: goto +3675 -> 4665
    //   993: iload 33
    //   995: iconst_1
    //   996: if_icmpeq +7 -> 1003
    //   999: iconst_0
    //   1000: goto +4 -> 1004
    //   1003: iconst_1
    //   1004: ifeq +6 -> 1010
    //   1007: goto +3615 -> 4622
    //   1010: iload 40
    //   1012: iconst_1
    //   1013: if_icmpeq +7 -> 1020
    //   1016: iconst_0
    //   1017: goto +4 -> 1021
    //   1020: iconst_1
    //   1021: ifeq +6 -> 1027
    //   1024: goto +42 -> 1066
    //   1027: aload 5
    //   1029: iload 40
    //   1031: iconst_1
    //   1032: isub
    //   1033: iload 40
    //   1035: iconst_1
    //   1036: isub
    //   1037: iconst_1
    //   1038: isub
    //   1039: iload 7
    //   1041: imul
    //   1042: iadd
    //   1043: iload 6
    //   1045: iadd
    //   1046: daload
    //   1047: dconst_0
    //   1048: dcmpl
    //   1049: ifeq +7 -> 1056
    //   1052: iconst_0
    //   1053: goto +4 -> 1057
    //   1056: iconst_1
    //   1057: ifeq +6 -> 1063
    //   1060: goto +6 -> 1066
    //   1063: iconst_m1
    //   1064: istore 33
    //   1066: iload 29
    //   1068: ifeq +54 -> 1122
    //   1071: iload 33
    //   1073: iconst_0
    //   1074: if_icmpeq +7 -> 1081
    //   1077: iconst_0
    //   1078: goto +4 -> 1082
    //   1081: iconst_1
    //   1082: ifeq +22 -> 1104
    //   1085: aload_2
    //   1086: iload 40
    //   1088: iconst_1
    //   1089: isub
    //   1090: iload_3
    //   1091: iadd
    //   1092: baload
    //   1093: iconst_1
    //   1094: ixor
    //   1095: ifeq +6 -> 1101
    //   1098: goto +3524 -> 4622
    //   1101: goto +21 -> 1122
    //   1104: aload_2
    //   1105: iload 40
    //   1107: iconst_1
    //   1108: isub
    //   1109: iconst_1
    //   1110: isub
    //   1111: iload_3
    //   1112: iadd
    //   1113: baload
    //   1114: iconst_1
    //   1115: ixor
    //   1116: ifeq +6 -> 1122
    //   1119: goto +3503 -> 4622
    //   1122: aload 5
    //   1124: iload 40
    //   1126: iconst_1
    //   1127: isub
    //   1128: iload 40
    //   1130: iconst_1
    //   1131: isub
    //   1132: iload 7
    //   1134: imul
    //   1135: iadd
    //   1136: iload 6
    //   1138: iadd
    //   1139: daload
    //   1140: dstore 70
    //   1142: dconst_0
    //   1143: dstore 68
    //   1145: iload 33
    //   1147: iconst_0
    //   1148: if_icmpne +7 -> 1155
    //   1151: iconst_0
    //   1152: goto +4 -> 1156
    //   1155: iconst_1
    //   1156: ifeq +58 -> 1214
    //   1159: aload 5
    //   1161: iload 40
    //   1163: iconst_1
    //   1164: isub
    //   1165: iload 40
    //   1167: iconst_1
    //   1168: isub
    //   1169: iconst_1
    //   1170: isub
    //   1171: iload 7
    //   1173: imul
    //   1174: iadd
    //   1175: iload 6
    //   1177: iadd
    //   1178: daload
    //   1179: invokestatic 81	java/lang/Math:abs	(D)D
    //   1182: invokestatic 84	java/lang/Math:sqrt	(D)D
    //   1185: aload 5
    //   1187: iload 40
    //   1189: iconst_1
    //   1190: isub
    //   1191: iconst_1
    //   1192: isub
    //   1193: iload 40
    //   1195: iconst_1
    //   1196: isub
    //   1197: iload 7
    //   1199: imul
    //   1200: iadd
    //   1201: iload 6
    //   1203: iadd
    //   1204: daload
    //   1205: invokestatic 81	java/lang/Math:abs	(D)D
    //   1208: invokestatic 84	java/lang/Math:sqrt	(D)D
    //   1211: dmul
    //   1212: dstore 68
    //   1214: dload 60
    //   1216: dload 70
    //   1218: invokestatic 81	java/lang/Math:abs	(D)D
    //   1221: dload 68
    //   1223: invokestatic 81	java/lang/Math:abs	(D)D
    //   1226: dadd
    //   1227: dmul
    //   1228: dload 58
    //   1230: invokestatic 87	java/lang/Math:max	(DD)D
    //   1233: dstore 56
    //   1235: iload 33
    //   1237: iconst_0
    //   1238: if_icmpeq +7 -> 1245
    //   1241: iconst_0
    //   1242: goto +4 -> 1246
    //   1245: iconst_1
    //   1246: ifeq +1212 -> 2458
    //   1249: aload 16
    //   1251: iload 40
    //   1253: iload 4
    //   1255: iadd
    //   1256: iconst_1
    //   1257: isub
    //   1258: iload 17
    //   1260: iadd
    //   1261: dconst_1
    //   1262: dastore
    //   1263: iconst_1
    //   1264: istore 39
    //   1266: iload 40
    //   1268: iconst_1
    //   1269: isub
    //   1270: iconst_1
    //   1271: isub
    //   1272: iconst_1
    //   1273: iadd
    //   1274: istore 77
    //   1276: goto +44 -> 1320
    //   1279: aload 16
    //   1281: iload 39
    //   1283: iload 4
    //   1285: iadd
    //   1286: iconst_1
    //   1287: isub
    //   1288: iload 17
    //   1290: iadd
    //   1291: aload 5
    //   1293: iload 39
    //   1295: iconst_1
    //   1296: isub
    //   1297: iload 40
    //   1299: iconst_1
    //   1300: isub
    //   1301: iload 7
    //   1303: imul
    //   1304: iadd
    //   1305: iload 6
    //   1307: iadd
    //   1308: daload
    //   1309: dneg
    //   1310: dastore
    //   1311: iload 39
    //   1313: iconst_1
    //   1314: iadd
    //   1315: istore 39
    //   1317: iinc 77 -1
    //   1320: iload 77
    //   1322: ifgt -43 -> 1279
    //   1325: iload 40
    //   1327: iconst_1
    //   1328: isub
    //   1329: istore 38
    //   1331: iload 40
    //   1333: iconst_1
    //   1334: isub
    //   1335: istore 35
    //   1337: iconst_1
    //   1338: iload 40
    //   1340: iconst_1
    //   1341: isub
    //   1342: isub
    //   1343: iconst_m1
    //   1344: iadd
    //   1345: iconst_m1
    //   1346: idiv
    //   1347: istore 77
    //   1349: goto +784 -> 2133
    //   1352: iload 35
    //   1354: iload 38
    //   1356: if_icmpgt +7 -> 1363
    //   1359: iconst_0
    //   1360: goto +4 -> 1364
    //   1363: iconst_1
    //   1364: ifeq +6 -> 1370
    //   1367: goto +757 -> 2124
    //   1370: iload 35
    //   1372: istore 36
    //   1374: iload 35
    //   1376: istore 37
    //   1378: iload 35
    //   1380: iconst_1
    //   1381: isub
    //   1382: istore 38
    //   1384: iload 35
    //   1386: iconst_1
    //   1387: if_icmpgt +7 -> 1394
    //   1390: iconst_0
    //   1391: goto +4 -> 1395
    //   1394: iconst_1
    //   1395: ifeq +48 -> 1443
    //   1398: aload 5
    //   1400: iload 35
    //   1402: iconst_1
    //   1403: isub
    //   1404: iload 35
    //   1406: iconst_1
    //   1407: isub
    //   1408: iconst_1
    //   1409: isub
    //   1410: iload 7
    //   1412: imul
    //   1413: iadd
    //   1414: iload 6
    //   1416: iadd
    //   1417: daload
    //   1418: dconst_0
    //   1419: dcmpl
    //   1420: ifne +7 -> 1427
    //   1423: iconst_0
    //   1424: goto +4 -> 1428
    //   1427: iconst_1
    //   1428: ifeq +15 -> 1443
    //   1431: iload 35
    //   1433: iconst_1
    //   1434: isub
    //   1435: istore 36
    //   1437: iload 35
    //   1439: iconst_2
    //   1440: isub
    //   1441: istore 38
    //   1443: iload 36
    //   1445: iload 37
    //   1447: if_icmpeq +7 -> 1454
    //   1450: iconst_0
    //   1451: goto +4 -> 1455
    //   1454: iconst_1
    //   1455: ifeq +271 -> 1726
    //   1458: iconst_0
    //   1459: iconst_1
    //   1460: iconst_1
    //   1461: dload 56
    //   1463: dconst_1
    //   1464: aload 5
    //   1466: iload 35
    //   1468: iconst_1
    //   1469: isub
    //   1470: iload 35
    //   1472: iconst_1
    //   1473: isub
    //   1474: iload 7
    //   1476: imul
    //   1477: iadd
    //   1478: iload 6
    //   1480: iadd
    //   1481: iload 7
    //   1483: dconst_1
    //   1484: dconst_1
    //   1485: aload 16
    //   1487: iload 35
    //   1489: iload 4
    //   1491: iadd
    //   1492: iconst_1
    //   1493: isub
    //   1494: iload 17
    //   1496: iadd
    //   1497: iload 4
    //   1499: dload 70
    //   1501: dconst_0
    //   1502: aload 74
    //   1504: iconst_0
    //   1505: iconst_2
    //   1506: aload 54
    //   1508: aload 72
    //   1510: aload 31
    //   1512: invokestatic 93	org/netlib/lapack/Dlaln2:dlaln2	(ZIIDD[DIIDD[DIIDD[DIILorg/netlib/util/doubleW;Lorg/netlib/util/doubleW;Lorg/netlib/util/intW;)V
    //   1515: aload 72
    //   1517: getfield 69	org/netlib/util/doubleW:val	D
    //   1520: dconst_1
    //   1521: dcmpl
    //   1522: ifgt +7 -> 1529
    //   1525: iconst_0
    //   1526: goto +4 -> 1530
    //   1529: iconst_1
    //   1530: ifeq +79 -> 1609
    //   1533: aload 16
    //   1535: iload 35
    //   1537: iconst_1
    //   1538: isub
    //   1539: iload 17
    //   1541: iadd
    //   1542: daload
    //   1543: dload 44
    //   1545: aload 72
    //   1547: getfield 69	org/netlib/util/doubleW:val	D
    //   1550: ddiv
    //   1551: dcmpl
    //   1552: ifgt +7 -> 1559
    //   1555: iconst_0
    //   1556: goto +4 -> 1560
    //   1559: iconst_1
    //   1560: ifeq +49 -> 1609
    //   1563: aload 74
    //   1565: iconst_1
    //   1566: iconst_1
    //   1567: isub
    //   1568: iconst_1
    //   1569: iconst_1
    //   1570: isub
    //   1571: iconst_2
    //   1572: imul
    //   1573: iadd
    //   1574: aload 74
    //   1576: iconst_1
    //   1577: iconst_1
    //   1578: isub
    //   1579: iconst_1
    //   1580: iconst_1
    //   1581: isub
    //   1582: iconst_2
    //   1583: imul
    //   1584: iadd
    //   1585: daload
    //   1586: aload 72
    //   1588: getfield 69	org/netlib/util/doubleW:val	D
    //   1591: ddiv
    //   1592: dastore
    //   1593: aload 54
    //   1595: aload 54
    //   1597: getfield 69	org/netlib/util/doubleW:val	D
    //   1600: aload 72
    //   1602: getfield 69	org/netlib/util/doubleW:val	D
    //   1605: ddiv
    //   1606: putfield 69	org/netlib/util/doubleW:val	D
    //   1609: aload 54
    //   1611: getfield 69	org/netlib/util/doubleW:val	D
    //   1614: dconst_1
    //   1615: dcmpl
    //   1616: ifne +7 -> 1623
    //   1619: iconst_0
    //   1620: goto +4 -> 1624
    //   1623: iconst_1
    //   1624: ifeq +25 -> 1649
    //   1627: iload 40
    //   1629: aload 54
    //   1631: getfield 69	org/netlib/util/doubleW:val	D
    //   1634: aload 16
    //   1636: iconst_1
    //   1637: iload 4
    //   1639: iadd
    //   1640: iconst_1
    //   1641: isub
    //   1642: iload 17
    //   1644: iadd
    //   1645: iconst_1
    //   1646: invokestatic 99	org/netlib/blas/Dscal:dscal	(ID[DII)V
    //   1649: aload 16
    //   1651: iload 35
    //   1653: iload 4
    //   1655: iadd
    //   1656: iconst_1
    //   1657: isub
    //   1658: iload 17
    //   1660: iadd
    //   1661: aload 74
    //   1663: iconst_1
    //   1664: iconst_1
    //   1665: isub
    //   1666: iconst_1
    //   1667: iconst_1
    //   1668: isub
    //   1669: iconst_2
    //   1670: imul
    //   1671: iadd
    //   1672: daload
    //   1673: dastore
    //   1674: iload 35
    //   1676: iconst_1
    //   1677: isub
    //   1678: aload 74
    //   1680: iconst_1
    //   1681: iconst_1
    //   1682: isub
    //   1683: iconst_1
    //   1684: iconst_1
    //   1685: isub
    //   1686: iconst_2
    //   1687: imul
    //   1688: iadd
    //   1689: daload
    //   1690: dneg
    //   1691: aload 5
    //   1693: iconst_1
    //   1694: iconst_1
    //   1695: isub
    //   1696: iload 35
    //   1698: iconst_1
    //   1699: isub
    //   1700: iload 7
    //   1702: imul
    //   1703: iadd
    //   1704: iload 6
    //   1706: iadd
    //   1707: iconst_1
    //   1708: aload 16
    //   1710: iconst_1
    //   1711: iload 4
    //   1713: iadd
    //   1714: iconst_1
    //   1715: isub
    //   1716: iload 17
    //   1718: iadd
    //   1719: iconst_1
    //   1720: invokestatic 105	org/netlib/blas/Daxpy:daxpy	(ID[DII[DII)V
    //   1723: goto +401 -> 2124
    //   1726: iconst_0
    //   1727: iconst_2
    //   1728: iconst_1
    //   1729: dload 56
    //   1731: dconst_1
    //   1732: aload 5
    //   1734: iload 35
    //   1736: iconst_1
    //   1737: isub
    //   1738: iconst_1
    //   1739: isub
    //   1740: iload 35
    //   1742: iconst_1
    //   1743: isub
    //   1744: iconst_1
    //   1745: isub
    //   1746: iload 7
    //   1748: imul
    //   1749: iadd
    //   1750: iload 6
    //   1752: iadd
    //   1753: iload 7
    //   1755: dconst_1
    //   1756: dconst_1
    //   1757: aload 16
    //   1759: iload 35
    //   1761: iconst_1
    //   1762: isub
    //   1763: iload 4
    //   1765: iadd
    //   1766: iconst_1
    //   1767: isub
    //   1768: iload 17
    //   1770: iadd
    //   1771: iload 4
    //   1773: dload 70
    //   1775: dconst_0
    //   1776: aload 74
    //   1778: iconst_0
    //   1779: iconst_2
    //   1780: aload 54
    //   1782: aload 72
    //   1784: aload 31
    //   1786: invokestatic 93	org/netlib/lapack/Dlaln2:dlaln2	(ZIIDD[DIIDD[DIIDD[DIILorg/netlib/util/doubleW;Lorg/netlib/util/doubleW;Lorg/netlib/util/intW;)V
    //   1789: aload 72
    //   1791: getfield 69	org/netlib/util/doubleW:val	D
    //   1794: dconst_1
    //   1795: dcmpl
    //   1796: ifgt +7 -> 1803
    //   1799: iconst_0
    //   1800: goto +4 -> 1804
    //   1803: iconst_1
    //   1804: ifeq +128 -> 1932
    //   1807: aload 16
    //   1809: iload 35
    //   1811: iconst_1
    //   1812: isub
    //   1813: iconst_1
    //   1814: isub
    //   1815: iload 17
    //   1817: iadd
    //   1818: daload
    //   1819: aload 16
    //   1821: iload 35
    //   1823: iconst_1
    //   1824: isub
    //   1825: iload 17
    //   1827: iadd
    //   1828: daload
    //   1829: invokestatic 87	java/lang/Math:max	(DD)D
    //   1832: dstore 42
    //   1834: dload 42
    //   1836: dload 44
    //   1838: aload 72
    //   1840: getfield 69	org/netlib/util/doubleW:val	D
    //   1843: ddiv
    //   1844: dcmpl
    //   1845: ifgt +7 -> 1852
    //   1848: iconst_0
    //   1849: goto +4 -> 1853
    //   1852: iconst_1
    //   1853: ifeq +79 -> 1932
    //   1856: aload 74
    //   1858: iconst_1
    //   1859: iconst_1
    //   1860: isub
    //   1861: iconst_1
    //   1862: iconst_1
    //   1863: isub
    //   1864: iconst_2
    //   1865: imul
    //   1866: iadd
    //   1867: aload 74
    //   1869: iconst_1
    //   1870: iconst_1
    //   1871: isub
    //   1872: iconst_1
    //   1873: iconst_1
    //   1874: isub
    //   1875: iconst_2
    //   1876: imul
    //   1877: iadd
    //   1878: daload
    //   1879: aload 72
    //   1881: getfield 69	org/netlib/util/doubleW:val	D
    //   1884: ddiv
    //   1885: dastore
    //   1886: aload 74
    //   1888: iconst_2
    //   1889: iconst_1
    //   1890: isub
    //   1891: iconst_1
    //   1892: iconst_1
    //   1893: isub
    //   1894: iconst_2
    //   1895: imul
    //   1896: iadd
    //   1897: aload 74
    //   1899: iconst_2
    //   1900: iconst_1
    //   1901: isub
    //   1902: iconst_1
    //   1903: iconst_1
    //   1904: isub
    //   1905: iconst_2
    //   1906: imul
    //   1907: iadd
    //   1908: daload
    //   1909: aload 72
    //   1911: getfield 69	org/netlib/util/doubleW:val	D
    //   1914: ddiv
    //   1915: dastore
    //   1916: aload 54
    //   1918: aload 54
    //   1920: getfield 69	org/netlib/util/doubleW:val	D
    //   1923: aload 72
    //   1925: getfield 69	org/netlib/util/doubleW:val	D
    //   1928: ddiv
    //   1929: putfield 69	org/netlib/util/doubleW:val	D
    //   1932: aload 54
    //   1934: getfield 69	org/netlib/util/doubleW:val	D
    //   1937: dconst_1
    //   1938: dcmpl
    //   1939: ifne +7 -> 1946
    //   1942: iconst_0
    //   1943: goto +4 -> 1947
    //   1946: iconst_1
    //   1947: ifeq +25 -> 1972
    //   1950: iload 40
    //   1952: aload 54
    //   1954: getfield 69	org/netlib/util/doubleW:val	D
    //   1957: aload 16
    //   1959: iconst_1
    //   1960: iload 4
    //   1962: iadd
    //   1963: iconst_1
    //   1964: isub
    //   1965: iload 17
    //   1967: iadd
    //   1968: iconst_1
    //   1969: invokestatic 99	org/netlib/blas/Dscal:dscal	(ID[DII)V
    //   1972: aload 16
    //   1974: iload 35
    //   1976: iconst_1
    //   1977: isub
    //   1978: iload 4
    //   1980: iadd
    //   1981: iconst_1
    //   1982: isub
    //   1983: iload 17
    //   1985: iadd
    //   1986: aload 74
    //   1988: iconst_1
    //   1989: iconst_1
    //   1990: isub
    //   1991: iconst_1
    //   1992: iconst_1
    //   1993: isub
    //   1994: iconst_2
    //   1995: imul
    //   1996: iadd
    //   1997: daload
    //   1998: dastore
    //   1999: aload 16
    //   2001: iload 35
    //   2003: iload 4
    //   2005: iadd
    //   2006: iconst_1
    //   2007: isub
    //   2008: iload 17
    //   2010: iadd
    //   2011: aload 74
    //   2013: iconst_2
    //   2014: iconst_1
    //   2015: isub
    //   2016: iconst_1
    //   2017: iconst_1
    //   2018: isub
    //   2019: iconst_2
    //   2020: imul
    //   2021: iadd
    //   2022: daload
    //   2023: dastore
    //   2024: iload 35
    //   2026: iconst_2
    //   2027: isub
    //   2028: aload 74
    //   2030: iconst_1
    //   2031: iconst_1
    //   2032: isub
    //   2033: iconst_1
    //   2034: iconst_1
    //   2035: isub
    //   2036: iconst_2
    //   2037: imul
    //   2038: iadd
    //   2039: daload
    //   2040: dneg
    //   2041: aload 5
    //   2043: iconst_1
    //   2044: iconst_1
    //   2045: isub
    //   2046: iload 35
    //   2048: iconst_1
    //   2049: isub
    //   2050: iconst_1
    //   2051: isub
    //   2052: iload 7
    //   2054: imul
    //   2055: iadd
    //   2056: iload 6
    //   2058: iadd
    //   2059: iconst_1
    //   2060: aload 16
    //   2062: iconst_1
    //   2063: iload 4
    //   2065: iadd
    //   2066: iconst_1
    //   2067: isub
    //   2068: iload 17
    //   2070: iadd
    //   2071: iconst_1
    //   2072: invokestatic 105	org/netlib/blas/Daxpy:daxpy	(ID[DII[DII)V
    //   2075: iload 35
    //   2077: iconst_2
    //   2078: isub
    //   2079: aload 74
    //   2081: iconst_2
    //   2082: iconst_1
    //   2083: isub
    //   2084: iconst_1
    //   2085: iconst_1
    //   2086: isub
    //   2087: iconst_2
    //   2088: imul
    //   2089: iadd
    //   2090: daload
    //   2091: dneg
    //   2092: aload 5
    //   2094: iconst_1
    //   2095: iconst_1
    //   2096: isub
    //   2097: iload 35
    //   2099: iconst_1
    //   2100: isub
    //   2101: iload 7
    //   2103: imul
    //   2104: iadd
    //   2105: iload 6
    //   2107: iadd
    //   2108: iconst_1
    //   2109: aload 16
    //   2111: iconst_1
    //   2112: iload 4
    //   2114: iadd
    //   2115: iconst_1
    //   2116: isub
    //   2117: iload 17
    //   2119: iadd
    //   2120: iconst_1
    //   2121: invokestatic 105	org/netlib/blas/Daxpy:daxpy	(ID[DII[DII)V
    //   2124: iload 35
    //   2126: iconst_m1
    //   2127: iadd
    //   2128: istore 35
    //   2130: iinc 77 -1
    //   2133: iload 77
    //   2135: ifgt -783 -> 1352
    //   2138: iload 26
    //   2140: iconst_1
    //   2141: ixor
    //   2142: ifeq +166 -> 2308
    //   2145: iload 40
    //   2147: aload 16
    //   2149: iconst_1
    //   2150: iload 4
    //   2152: iadd
    //   2153: iconst_1
    //   2154: isub
    //   2155: iload 17
    //   2157: iadd
    //   2158: iconst_1
    //   2159: aload 11
    //   2161: iconst_1
    //   2162: iconst_1
    //   2163: isub
    //   2164: iload 34
    //   2166: iconst_1
    //   2167: isub
    //   2168: iload 13
    //   2170: imul
    //   2171: iadd
    //   2172: iload 12
    //   2174: iadd
    //   2175: iconst_1
    //   2176: invokestatic 111	org/netlib/blas/Dcopy:dcopy	(I[DII[DII)V
    //   2179: iload 40
    //   2181: aload 11
    //   2183: iconst_1
    //   2184: iconst_1
    //   2185: isub
    //   2186: iload 34
    //   2188: iconst_1
    //   2189: isub
    //   2190: iload 13
    //   2192: imul
    //   2193: iadd
    //   2194: iload 12
    //   2196: iadd
    //   2197: iconst_1
    //   2198: invokestatic 117	org/netlib/blas/Idamax:idamax	(I[DII)I
    //   2201: istore 32
    //   2203: dconst_1
    //   2204: aload 11
    //   2206: iload 32
    //   2208: iconst_1
    //   2209: isub
    //   2210: iload 34
    //   2212: iconst_1
    //   2213: isub
    //   2214: iload 13
    //   2216: imul
    //   2217: iadd
    //   2218: iload 12
    //   2220: iadd
    //   2221: daload
    //   2222: invokestatic 81	java/lang/Math:abs	(D)D
    //   2225: ddiv
    //   2226: dstore 52
    //   2228: iload 40
    //   2230: dload 52
    //   2232: aload 11
    //   2234: iconst_1
    //   2235: iconst_1
    //   2236: isub
    //   2237: iload 34
    //   2239: iconst_1
    //   2240: isub
    //   2241: iload 13
    //   2243: imul
    //   2244: iadd
    //   2245: iload 12
    //   2247: iadd
    //   2248: iconst_1
    //   2249: invokestatic 99	org/netlib/blas/Dscal:dscal	(ID[DII)V
    //   2252: iload 40
    //   2254: iconst_1
    //   2255: iadd
    //   2256: istore 39
    //   2258: iload 4
    //   2260: iload 40
    //   2262: iconst_1
    //   2263: iadd
    //   2264: isub
    //   2265: iconst_1
    //   2266: iadd
    //   2267: istore 77
    //   2269: goto +31 -> 2300
    //   2272: aload 11
    //   2274: iload 39
    //   2276: iconst_1
    //   2277: isub
    //   2278: iload 34
    //   2280: iconst_1
    //   2281: isub
    //   2282: iload 13
    //   2284: imul
    //   2285: iadd
    //   2286: iload 12
    //   2288: iadd
    //   2289: dconst_0
    //   2290: dastore
    //   2291: iload 39
    //   2293: iconst_1
    //   2294: iadd
    //   2295: istore 39
    //   2297: iinc 77 -1
    //   2300: iload 77
    //   2302: ifgt -30 -> 2272
    //   2305: goto +150 -> 2455
    //   2308: iload 40
    //   2310: iconst_1
    //   2311: if_icmpgt +7 -> 2318
    //   2314: iconst_0
    //   2315: goto +4 -> 2319
    //   2318: iconst_1
    //   2319: ifeq +63 -> 2382
    //   2322: ldc 119
    //   2324: iload 4
    //   2326: iload 40
    //   2328: iconst_1
    //   2329: isub
    //   2330: dconst_1
    //   2331: aload 11
    //   2333: iload 12
    //   2335: iload 13
    //   2337: aload 16
    //   2339: iconst_1
    //   2340: iload 4
    //   2342: iadd
    //   2343: iconst_1
    //   2344: isub
    //   2345: iload 17
    //   2347: iadd
    //   2348: iconst_1
    //   2349: aload 16
    //   2351: iload 40
    //   2353: iload 4
    //   2355: iadd
    //   2356: iconst_1
    //   2357: isub
    //   2358: iload 17
    //   2360: iadd
    //   2361: daload
    //   2362: aload 11
    //   2364: iconst_1
    //   2365: iconst_1
    //   2366: isub
    //   2367: iload 40
    //   2369: iconst_1
    //   2370: isub
    //   2371: iload 13
    //   2373: imul
    //   2374: iadd
    //   2375: iload 12
    //   2377: iadd
    //   2378: iconst_1
    //   2379: invokestatic 125	org/netlib/blas/Dgemv:dgemv	(Ljava/lang/String;IID[DII[DIID[DII)V
    //   2382: iload 4
    //   2384: aload 11
    //   2386: iconst_1
    //   2387: iconst_1
    //   2388: isub
    //   2389: iload 40
    //   2391: iconst_1
    //   2392: isub
    //   2393: iload 13
    //   2395: imul
    //   2396: iadd
    //   2397: iload 12
    //   2399: iadd
    //   2400: iconst_1
    //   2401: invokestatic 117	org/netlib/blas/Idamax:idamax	(I[DII)I
    //   2404: istore 32
    //   2406: dconst_1
    //   2407: aload 11
    //   2409: iload 32
    //   2411: iconst_1
    //   2412: isub
    //   2413: iload 40
    //   2415: iconst_1
    //   2416: isub
    //   2417: iload 13
    //   2419: imul
    //   2420: iadd
    //   2421: iload 12
    //   2423: iadd
    //   2424: daload
    //   2425: invokestatic 81	java/lang/Math:abs	(D)D
    //   2428: ddiv
    //   2429: dstore 52
    //   2431: iload 4
    //   2433: dload 52
    //   2435: aload 11
    //   2437: iconst_1
    //   2438: iconst_1
    //   2439: isub
    //   2440: iload 40
    //   2442: iconst_1
    //   2443: isub
    //   2444: iload 13
    //   2446: imul
    //   2447: iadd
    //   2448: iload 12
    //   2450: iadd
    //   2451: iconst_1
    //   2452: invokestatic 99	org/netlib/blas/Dscal:dscal	(ID[DII)V
    //   2455: goto +2141 -> 4596
    //   2458: aload 5
    //   2460: iload 40
    //   2462: iconst_1
    //   2463: isub
    //   2464: iconst_1
    //   2465: isub
    //   2466: iload 40
    //   2468: iconst_1
    //   2469: isub
    //   2470: iload 7
    //   2472: imul
    //   2473: iadd
    //   2474: iload 6
    //   2476: iadd
    //   2477: daload
    //   2478: invokestatic 81	java/lang/Math:abs	(D)D
    //   2481: aload 5
    //   2483: iload 40
    //   2485: iconst_1
    //   2486: isub
    //   2487: iload 40
    //   2489: iconst_1
    //   2490: isub
    //   2491: iconst_1
    //   2492: isub
    //   2493: iload 7
    //   2495: imul
    //   2496: iadd
    //   2497: iload 6
    //   2499: iadd
    //   2500: daload
    //   2501: invokestatic 81	java/lang/Math:abs	(D)D
    //   2504: dcmpl
    //   2505: ifge +7 -> 2512
    //   2508: iconst_0
    //   2509: goto +4 -> 2513
    //   2512: iconst_1
    //   2513: ifeq +58 -> 2571
    //   2516: aload 16
    //   2518: iload 40
    //   2520: iconst_1
    //   2521: isub
    //   2522: iload 4
    //   2524: iadd
    //   2525: iconst_1
    //   2526: isub
    //   2527: iload 17
    //   2529: iadd
    //   2530: dconst_1
    //   2531: dastore
    //   2532: aload 16
    //   2534: iload 40
    //   2536: iload 41
    //   2538: iadd
    //   2539: iconst_1
    //   2540: isub
    //   2541: iload 17
    //   2543: iadd
    //   2544: dload 68
    //   2546: aload 5
    //   2548: iload 40
    //   2550: iconst_1
    //   2551: isub
    //   2552: iconst_1
    //   2553: isub
    //   2554: iload 40
    //   2556: iconst_1
    //   2557: isub
    //   2558: iload 7
    //   2560: imul
    //   2561: iadd
    //   2562: iload 6
    //   2564: iadd
    //   2565: daload
    //   2566: ddiv
    //   2567: dastore
    //   2568: goto +56 -> 2624
    //   2571: aload 16
    //   2573: iload 40
    //   2575: iconst_1
    //   2576: isub
    //   2577: iload 4
    //   2579: iadd
    //   2580: iconst_1
    //   2581: isub
    //   2582: iload 17
    //   2584: iadd
    //   2585: dload 68
    //   2587: aload 5
    //   2589: iload 40
    //   2591: iconst_1
    //   2592: isub
    //   2593: iload 40
    //   2595: iconst_1
    //   2596: isub
    //   2597: iconst_1
    //   2598: isub
    //   2599: iload 7
    //   2601: imul
    //   2602: iadd
    //   2603: iload 6
    //   2605: iadd
    //   2606: daload
    //   2607: ddiv
    //   2608: dneg
    //   2609: dastore
    //   2610: aload 16
    //   2612: iload 40
    //   2614: iload 41
    //   2616: iadd
    //   2617: iconst_1
    //   2618: isub
    //   2619: iload 17
    //   2621: iadd
    //   2622: dconst_1
    //   2623: dastore
    //   2624: aload 16
    //   2626: iload 40
    //   2628: iload 4
    //   2630: iadd
    //   2631: iconst_1
    //   2632: isub
    //   2633: iload 17
    //   2635: iadd
    //   2636: dconst_0
    //   2637: dastore
    //   2638: aload 16
    //   2640: iload 40
    //   2642: iconst_1
    //   2643: isub
    //   2644: iload 41
    //   2646: iadd
    //   2647: iconst_1
    //   2648: isub
    //   2649: iload 17
    //   2651: iadd
    //   2652: dconst_0
    //   2653: dastore
    //   2654: iconst_1
    //   2655: istore 39
    //   2657: iload 40
    //   2659: iconst_2
    //   2660: isub
    //   2661: iconst_1
    //   2662: isub
    //   2663: iconst_1
    //   2664: iadd
    //   2665: istore 77
    //   2667: goto +108 -> 2775
    //   2670: aload 16
    //   2672: iload 39
    //   2674: iload 4
    //   2676: iadd
    //   2677: iconst_1
    //   2678: isub
    //   2679: iload 17
    //   2681: iadd
    //   2682: aload 16
    //   2684: iload 40
    //   2686: iconst_1
    //   2687: isub
    //   2688: iload 4
    //   2690: iadd
    //   2691: iconst_1
    //   2692: isub
    //   2693: iload 17
    //   2695: iadd
    //   2696: daload
    //   2697: aload 5
    //   2699: iload 39
    //   2701: iconst_1
    //   2702: isub
    //   2703: iload 40
    //   2705: iconst_1
    //   2706: isub
    //   2707: iconst_1
    //   2708: isub
    //   2709: iload 7
    //   2711: imul
    //   2712: iadd
    //   2713: iload 6
    //   2715: iadd
    //   2716: daload
    //   2717: dmul
    //   2718: dneg
    //   2719: dastore
    //   2720: aload 16
    //   2722: iload 39
    //   2724: iload 41
    //   2726: iadd
    //   2727: iconst_1
    //   2728: isub
    //   2729: iload 17
    //   2731: iadd
    //   2732: aload 16
    //   2734: iload 40
    //   2736: iload 41
    //   2738: iadd
    //   2739: iconst_1
    //   2740: isub
    //   2741: iload 17
    //   2743: iadd
    //   2744: daload
    //   2745: aload 5
    //   2747: iload 39
    //   2749: iconst_1
    //   2750: isub
    //   2751: iload 40
    //   2753: iconst_1
    //   2754: isub
    //   2755: iload 7
    //   2757: imul
    //   2758: iadd
    //   2759: iload 6
    //   2761: iadd
    //   2762: daload
    //   2763: dmul
    //   2764: dneg
    //   2765: dastore
    //   2766: iload 39
    //   2768: iconst_1
    //   2769: iadd
    //   2770: istore 39
    //   2772: iinc 77 -1
    //   2775: iload 77
    //   2777: ifgt -107 -> 2670
    //   2780: iload 40
    //   2782: iconst_2
    //   2783: isub
    //   2784: istore 38
    //   2786: iload 40
    //   2788: iconst_2
    //   2789: isub
    //   2790: istore 35
    //   2792: iconst_1
    //   2793: iload 40
    //   2795: iconst_2
    //   2796: isub
    //   2797: isub
    //   2798: iconst_m1
    //   2799: iadd
    //   2800: iconst_m1
    //   2801: idiv
    //   2802: istore 77
    //   2804: goto +1140 -> 3944
    //   2807: iload 35
    //   2809: iload 38
    //   2811: if_icmpgt +7 -> 2818
    //   2814: iconst_0
    //   2815: goto +4 -> 2819
    //   2818: iconst_1
    //   2819: ifeq +6 -> 2825
    //   2822: goto +1113 -> 3935
    //   2825: iload 35
    //   2827: istore 36
    //   2829: iload 35
    //   2831: istore 37
    //   2833: iload 35
    //   2835: iconst_1
    //   2836: isub
    //   2837: istore 38
    //   2839: iload 35
    //   2841: iconst_1
    //   2842: if_icmpgt +7 -> 2849
    //   2845: iconst_0
    //   2846: goto +4 -> 2850
    //   2849: iconst_1
    //   2850: ifeq +48 -> 2898
    //   2853: aload 5
    //   2855: iload 35
    //   2857: iconst_1
    //   2858: isub
    //   2859: iload 35
    //   2861: iconst_1
    //   2862: isub
    //   2863: iconst_1
    //   2864: isub
    //   2865: iload 7
    //   2867: imul
    //   2868: iadd
    //   2869: iload 6
    //   2871: iadd
    //   2872: daload
    //   2873: dconst_0
    //   2874: dcmpl
    //   2875: ifne +7 -> 2882
    //   2878: iconst_0
    //   2879: goto +4 -> 2883
    //   2882: iconst_1
    //   2883: ifeq +15 -> 2898
    //   2886: iload 35
    //   2888: iconst_1
    //   2889: isub
    //   2890: istore 36
    //   2892: iload 35
    //   2894: iconst_2
    //   2895: isub
    //   2896: istore 38
    //   2898: iload 36
    //   2900: iload 37
    //   2902: if_icmpeq +7 -> 2909
    //   2905: iconst_0
    //   2906: goto +4 -> 2910
    //   2909: iconst_1
    //   2910: ifeq +398 -> 3308
    //   2913: iconst_0
    //   2914: iconst_1
    //   2915: iconst_2
    //   2916: dload 56
    //   2918: dconst_1
    //   2919: aload 5
    //   2921: iload 35
    //   2923: iconst_1
    //   2924: isub
    //   2925: iload 35
    //   2927: iconst_1
    //   2928: isub
    //   2929: iload 7
    //   2931: imul
    //   2932: iadd
    //   2933: iload 6
    //   2935: iadd
    //   2936: iload 7
    //   2938: dconst_1
    //   2939: dconst_1
    //   2940: aload 16
    //   2942: iload 35
    //   2944: iload 4
    //   2946: iadd
    //   2947: iconst_1
    //   2948: isub
    //   2949: iload 17
    //   2951: iadd
    //   2952: iload 4
    //   2954: dload 70
    //   2956: dload 68
    //   2958: aload 74
    //   2960: iconst_0
    //   2961: iconst_2
    //   2962: aload 54
    //   2964: aload 72
    //   2966: aload 31
    //   2968: invokestatic 93	org/netlib/lapack/Dlaln2:dlaln2	(ZIIDD[DIIDD[DIIDD[DIILorg/netlib/util/doubleW;Lorg/netlib/util/doubleW;Lorg/netlib/util/intW;)V
    //   2971: aload 72
    //   2973: getfield 69	org/netlib/util/doubleW:val	D
    //   2976: dconst_1
    //   2977: dcmpl
    //   2978: ifgt +7 -> 2985
    //   2981: iconst_0
    //   2982: goto +4 -> 2986
    //   2985: iconst_1
    //   2986: ifeq +109 -> 3095
    //   2989: aload 16
    //   2991: iload 35
    //   2993: iconst_1
    //   2994: isub
    //   2995: iload 17
    //   2997: iadd
    //   2998: daload
    //   2999: dload 44
    //   3001: aload 72
    //   3003: getfield 69	org/netlib/util/doubleW:val	D
    //   3006: ddiv
    //   3007: dcmpl
    //   3008: ifgt +7 -> 3015
    //   3011: iconst_0
    //   3012: goto +4 -> 3016
    //   3015: iconst_1
    //   3016: ifeq +79 -> 3095
    //   3019: aload 74
    //   3021: iconst_1
    //   3022: iconst_1
    //   3023: isub
    //   3024: iconst_1
    //   3025: iconst_1
    //   3026: isub
    //   3027: iconst_2
    //   3028: imul
    //   3029: iadd
    //   3030: aload 74
    //   3032: iconst_1
    //   3033: iconst_1
    //   3034: isub
    //   3035: iconst_1
    //   3036: iconst_1
    //   3037: isub
    //   3038: iconst_2
    //   3039: imul
    //   3040: iadd
    //   3041: daload
    //   3042: aload 72
    //   3044: getfield 69	org/netlib/util/doubleW:val	D
    //   3047: ddiv
    //   3048: dastore
    //   3049: aload 74
    //   3051: iconst_1
    //   3052: iconst_1
    //   3053: isub
    //   3054: iconst_2
    //   3055: iconst_1
    //   3056: isub
    //   3057: iconst_2
    //   3058: imul
    //   3059: iadd
    //   3060: aload 74
    //   3062: iconst_1
    //   3063: iconst_1
    //   3064: isub
    //   3065: iconst_2
    //   3066: iconst_1
    //   3067: isub
    //   3068: iconst_2
    //   3069: imul
    //   3070: iadd
    //   3071: daload
    //   3072: aload 72
    //   3074: getfield 69	org/netlib/util/doubleW:val	D
    //   3077: ddiv
    //   3078: dastore
    //   3079: aload 54
    //   3081: aload 54
    //   3083: getfield 69	org/netlib/util/doubleW:val	D
    //   3086: aload 72
    //   3088: getfield 69	org/netlib/util/doubleW:val	D
    //   3091: ddiv
    //   3092: putfield 69	org/netlib/util/doubleW:val	D
    //   3095: aload 54
    //   3097: getfield 69	org/netlib/util/doubleW:val	D
    //   3100: dconst_1
    //   3101: dcmpl
    //   3102: ifne +7 -> 3109
    //   3105: iconst_0
    //   3106: goto +4 -> 3110
    //   3109: iconst_1
    //   3110: ifeq +47 -> 3157
    //   3113: iload 40
    //   3115: aload 54
    //   3117: getfield 69	org/netlib/util/doubleW:val	D
    //   3120: aload 16
    //   3122: iconst_1
    //   3123: iload 4
    //   3125: iadd
    //   3126: iconst_1
    //   3127: isub
    //   3128: iload 17
    //   3130: iadd
    //   3131: iconst_1
    //   3132: invokestatic 99	org/netlib/blas/Dscal:dscal	(ID[DII)V
    //   3135: iload 40
    //   3137: aload 54
    //   3139: getfield 69	org/netlib/util/doubleW:val	D
    //   3142: aload 16
    //   3144: iconst_1
    //   3145: iload 41
    //   3147: iadd
    //   3148: iconst_1
    //   3149: isub
    //   3150: iload 17
    //   3152: iadd
    //   3153: iconst_1
    //   3154: invokestatic 99	org/netlib/blas/Dscal:dscal	(ID[DII)V
    //   3157: aload 16
    //   3159: iload 35
    //   3161: iload 4
    //   3163: iadd
    //   3164: iconst_1
    //   3165: isub
    //   3166: iload 17
    //   3168: iadd
    //   3169: aload 74
    //   3171: iconst_1
    //   3172: iconst_1
    //   3173: isub
    //   3174: iconst_1
    //   3175: iconst_1
    //   3176: isub
    //   3177: iconst_2
    //   3178: imul
    //   3179: iadd
    //   3180: daload
    //   3181: dastore
    //   3182: aload 16
    //   3184: iload 35
    //   3186: iload 41
    //   3188: iadd
    //   3189: iconst_1
    //   3190: isub
    //   3191: iload 17
    //   3193: iadd
    //   3194: aload 74
    //   3196: iconst_1
    //   3197: iconst_1
    //   3198: isub
    //   3199: iconst_2
    //   3200: iconst_1
    //   3201: isub
    //   3202: iconst_2
    //   3203: imul
    //   3204: iadd
    //   3205: daload
    //   3206: dastore
    //   3207: iload 35
    //   3209: iconst_1
    //   3210: isub
    //   3211: aload 74
    //   3213: iconst_1
    //   3214: iconst_1
    //   3215: isub
    //   3216: iconst_1
    //   3217: iconst_1
    //   3218: isub
    //   3219: iconst_2
    //   3220: imul
    //   3221: iadd
    //   3222: daload
    //   3223: dneg
    //   3224: aload 5
    //   3226: iconst_1
    //   3227: iconst_1
    //   3228: isub
    //   3229: iload 35
    //   3231: iconst_1
    //   3232: isub
    //   3233: iload 7
    //   3235: imul
    //   3236: iadd
    //   3237: iload 6
    //   3239: iadd
    //   3240: iconst_1
    //   3241: aload 16
    //   3243: iconst_1
    //   3244: iload 4
    //   3246: iadd
    //   3247: iconst_1
    //   3248: isub
    //   3249: iload 17
    //   3251: iadd
    //   3252: iconst_1
    //   3253: invokestatic 105	org/netlib/blas/Daxpy:daxpy	(ID[DII[DII)V
    //   3256: iload 35
    //   3258: iconst_1
    //   3259: isub
    //   3260: aload 74
    //   3262: iconst_1
    //   3263: iconst_1
    //   3264: isub
    //   3265: iconst_2
    //   3266: iconst_1
    //   3267: isub
    //   3268: iconst_2
    //   3269: imul
    //   3270: iadd
    //   3271: daload
    //   3272: dneg
    //   3273: aload 5
    //   3275: iconst_1
    //   3276: iconst_1
    //   3277: isub
    //   3278: iload 35
    //   3280: iconst_1
    //   3281: isub
    //   3282: iload 7
    //   3284: imul
    //   3285: iadd
    //   3286: iload 6
    //   3288: iadd
    //   3289: iconst_1
    //   3290: aload 16
    //   3292: iconst_1
    //   3293: iload 41
    //   3295: iadd
    //   3296: iconst_1
    //   3297: isub
    //   3298: iload 17
    //   3300: iadd
    //   3301: iconst_1
    //   3302: invokestatic 105	org/netlib/blas/Daxpy:daxpy	(ID[DII[DII)V
    //   3305: goto +630 -> 3935
    //   3308: iconst_0
    //   3309: iconst_2
    //   3310: iconst_2
    //   3311: dload 56
    //   3313: dconst_1
    //   3314: aload 5
    //   3316: iload 35
    //   3318: iconst_1
    //   3319: isub
    //   3320: iconst_1
    //   3321: isub
    //   3322: iload 35
    //   3324: iconst_1
    //   3325: isub
    //   3326: iconst_1
    //   3327: isub
    //   3328: iload 7
    //   3330: imul
    //   3331: iadd
    //   3332: iload 6
    //   3334: iadd
    //   3335: iload 7
    //   3337: dconst_1
    //   3338: dconst_1
    //   3339: aload 16
    //   3341: iload 35
    //   3343: iconst_1
    //   3344: isub
    //   3345: iload 4
    //   3347: iadd
    //   3348: iconst_1
    //   3349: isub
    //   3350: iload 17
    //   3352: iadd
    //   3353: iload 4
    //   3355: dload 70
    //   3357: dload 68
    //   3359: aload 74
    //   3361: iconst_0
    //   3362: iconst_2
    //   3363: aload 54
    //   3365: aload 72
    //   3367: aload 31
    //   3369: invokestatic 93	org/netlib/lapack/Dlaln2:dlaln2	(ZIIDD[DIIDD[DIIDD[DIILorg/netlib/util/doubleW;Lorg/netlib/util/doubleW;Lorg/netlib/util/intW;)V
    //   3372: aload 72
    //   3374: getfield 69	org/netlib/util/doubleW:val	D
    //   3377: dconst_1
    //   3378: dcmpl
    //   3379: ifgt +7 -> 3386
    //   3382: iconst_0
    //   3383: goto +4 -> 3387
    //   3386: iconst_1
    //   3387: ifeq +182 -> 3569
    //   3390: aload 16
    //   3392: iload 35
    //   3394: iconst_1
    //   3395: isub
    //   3396: iconst_1
    //   3397: isub
    //   3398: iload 17
    //   3400: iadd
    //   3401: daload
    //   3402: aload 16
    //   3404: iload 35
    //   3406: iconst_1
    //   3407: isub
    //   3408: iload 17
    //   3410: iadd
    //   3411: daload
    //   3412: invokestatic 87	java/lang/Math:max	(DD)D
    //   3415: dstore 42
    //   3417: dload 42
    //   3419: dload 44
    //   3421: aload 72
    //   3423: getfield 69	org/netlib/util/doubleW:val	D
    //   3426: ddiv
    //   3427: dcmpl
    //   3428: ifgt +7 -> 3435
    //   3431: iconst_0
    //   3432: goto +4 -> 3436
    //   3435: iconst_1
    //   3436: ifeq +133 -> 3569
    //   3439: dconst_1
    //   3440: aload 72
    //   3442: getfield 69	org/netlib/util/doubleW:val	D
    //   3445: ddiv
    //   3446: dstore 50
    //   3448: aload 74
    //   3450: iconst_1
    //   3451: iconst_1
    //   3452: isub
    //   3453: iconst_1
    //   3454: iconst_1
    //   3455: isub
    //   3456: iconst_2
    //   3457: imul
    //   3458: iadd
    //   3459: aload 74
    //   3461: iconst_1
    //   3462: iconst_1
    //   3463: isub
    //   3464: iconst_1
    //   3465: iconst_1
    //   3466: isub
    //   3467: iconst_2
    //   3468: imul
    //   3469: iadd
    //   3470: daload
    //   3471: dload 50
    //   3473: dmul
    //   3474: dastore
    //   3475: aload 74
    //   3477: iconst_1
    //   3478: iconst_1
    //   3479: isub
    //   3480: iconst_2
    //   3481: iconst_1
    //   3482: isub
    //   3483: iconst_2
    //   3484: imul
    //   3485: iadd
    //   3486: aload 74
    //   3488: iconst_1
    //   3489: iconst_1
    //   3490: isub
    //   3491: iconst_2
    //   3492: iconst_1
    //   3493: isub
    //   3494: iconst_2
    //   3495: imul
    //   3496: iadd
    //   3497: daload
    //   3498: dload 50
    //   3500: dmul
    //   3501: dastore
    //   3502: aload 74
    //   3504: iconst_2
    //   3505: iconst_1
    //   3506: isub
    //   3507: iconst_1
    //   3508: iconst_1
    //   3509: isub
    //   3510: iconst_2
    //   3511: imul
    //   3512: iadd
    //   3513: aload 74
    //   3515: iconst_2
    //   3516: iconst_1
    //   3517: isub
    //   3518: iconst_1
    //   3519: iconst_1
    //   3520: isub
    //   3521: iconst_2
    //   3522: imul
    //   3523: iadd
    //   3524: daload
    //   3525: dload 50
    //   3527: dmul
    //   3528: dastore
    //   3529: aload 74
    //   3531: iconst_2
    //   3532: iconst_1
    //   3533: isub
    //   3534: iconst_2
    //   3535: iconst_1
    //   3536: isub
    //   3537: iconst_2
    //   3538: imul
    //   3539: iadd
    //   3540: aload 74
    //   3542: iconst_2
    //   3543: iconst_1
    //   3544: isub
    //   3545: iconst_2
    //   3546: iconst_1
    //   3547: isub
    //   3548: iconst_2
    //   3549: imul
    //   3550: iadd
    //   3551: daload
    //   3552: dload 50
    //   3554: dmul
    //   3555: dastore
    //   3556: aload 54
    //   3558: aload 54
    //   3560: getfield 69	org/netlib/util/doubleW:val	D
    //   3563: dload 50
    //   3565: dmul
    //   3566: putfield 69	org/netlib/util/doubleW:val	D
    //   3569: aload 54
    //   3571: getfield 69	org/netlib/util/doubleW:val	D
    //   3574: dconst_1
    //   3575: dcmpl
    //   3576: ifne +7 -> 3583
    //   3579: iconst_0
    //   3580: goto +4 -> 3584
    //   3583: iconst_1
    //   3584: ifeq +47 -> 3631
    //   3587: iload 40
    //   3589: aload 54
    //   3591: getfield 69	org/netlib/util/doubleW:val	D
    //   3594: aload 16
    //   3596: iconst_1
    //   3597: iload 4
    //   3599: iadd
    //   3600: iconst_1
    //   3601: isub
    //   3602: iload 17
    //   3604: iadd
    //   3605: iconst_1
    //   3606: invokestatic 99	org/netlib/blas/Dscal:dscal	(ID[DII)V
    //   3609: iload 40
    //   3611: aload 54
    //   3613: getfield 69	org/netlib/util/doubleW:val	D
    //   3616: aload 16
    //   3618: iconst_1
    //   3619: iload 41
    //   3621: iadd
    //   3622: iconst_1
    //   3623: isub
    //   3624: iload 17
    //   3626: iadd
    //   3627: iconst_1
    //   3628: invokestatic 99	org/netlib/blas/Dscal:dscal	(ID[DII)V
    //   3631: aload 16
    //   3633: iload 35
    //   3635: iconst_1
    //   3636: isub
    //   3637: iload 4
    //   3639: iadd
    //   3640: iconst_1
    //   3641: isub
    //   3642: iload 17
    //   3644: iadd
    //   3645: aload 74
    //   3647: iconst_1
    //   3648: iconst_1
    //   3649: isub
    //   3650: iconst_1
    //   3651: iconst_1
    //   3652: isub
    //   3653: iconst_2
    //   3654: imul
    //   3655: iadd
    //   3656: daload
    //   3657: dastore
    //   3658: aload 16
    //   3660: iload 35
    //   3662: iload 4
    //   3664: iadd
    //   3665: iconst_1
    //   3666: isub
    //   3667: iload 17
    //   3669: iadd
    //   3670: aload 74
    //   3672: iconst_2
    //   3673: iconst_1
    //   3674: isub
    //   3675: iconst_1
    //   3676: iconst_1
    //   3677: isub
    //   3678: iconst_2
    //   3679: imul
    //   3680: iadd
    //   3681: daload
    //   3682: dastore
    //   3683: aload 16
    //   3685: iload 35
    //   3687: iconst_1
    //   3688: isub
    //   3689: iload 41
    //   3691: iadd
    //   3692: iconst_1
    //   3693: isub
    //   3694: iload 17
    //   3696: iadd
    //   3697: aload 74
    //   3699: iconst_1
    //   3700: iconst_1
    //   3701: isub
    //   3702: iconst_2
    //   3703: iconst_1
    //   3704: isub
    //   3705: iconst_2
    //   3706: imul
    //   3707: iadd
    //   3708: daload
    //   3709: dastore
    //   3710: aload 16
    //   3712: iload 35
    //   3714: iload 41
    //   3716: iadd
    //   3717: iconst_1
    //   3718: isub
    //   3719: iload 17
    //   3721: iadd
    //   3722: aload 74
    //   3724: iconst_2
    //   3725: iconst_1
    //   3726: isub
    //   3727: iconst_2
    //   3728: iconst_1
    //   3729: isub
    //   3730: iconst_2
    //   3731: imul
    //   3732: iadd
    //   3733: daload
    //   3734: dastore
    //   3735: iload 35
    //   3737: iconst_2
    //   3738: isub
    //   3739: aload 74
    //   3741: iconst_1
    //   3742: iconst_1
    //   3743: isub
    //   3744: iconst_1
    //   3745: iconst_1
    //   3746: isub
    //   3747: iconst_2
    //   3748: imul
    //   3749: iadd
    //   3750: daload
    //   3751: dneg
    //   3752: aload 5
    //   3754: iconst_1
    //   3755: iconst_1
    //   3756: isub
    //   3757: iload 35
    //   3759: iconst_1
    //   3760: isub
    //   3761: iconst_1
    //   3762: isub
    //   3763: iload 7
    //   3765: imul
    //   3766: iadd
    //   3767: iload 6
    //   3769: iadd
    //   3770: iconst_1
    //   3771: aload 16
    //   3773: iconst_1
    //   3774: iload 4
    //   3776: iadd
    //   3777: iconst_1
    //   3778: isub
    //   3779: iload 17
    //   3781: iadd
    //   3782: iconst_1
    //   3783: invokestatic 105	org/netlib/blas/Daxpy:daxpy	(ID[DII[DII)V
    //   3786: iload 35
    //   3788: iconst_2
    //   3789: isub
    //   3790: aload 74
    //   3792: iconst_2
    //   3793: iconst_1
    //   3794: isub
    //   3795: iconst_1
    //   3796: iconst_1
    //   3797: isub
    //   3798: iconst_2
    //   3799: imul
    //   3800: iadd
    //   3801: daload
    //   3802: dneg
    //   3803: aload 5
    //   3805: iconst_1
    //   3806: iconst_1
    //   3807: isub
    //   3808: iload 35
    //   3810: iconst_1
    //   3811: isub
    //   3812: iload 7
    //   3814: imul
    //   3815: iadd
    //   3816: iload 6
    //   3818: iadd
    //   3819: iconst_1
    //   3820: aload 16
    //   3822: iconst_1
    //   3823: iload 4
    //   3825: iadd
    //   3826: iconst_1
    //   3827: isub
    //   3828: iload 17
    //   3830: iadd
    //   3831: iconst_1
    //   3832: invokestatic 105	org/netlib/blas/Daxpy:daxpy	(ID[DII[DII)V
    //   3835: iload 35
    //   3837: iconst_2
    //   3838: isub
    //   3839: aload 74
    //   3841: iconst_1
    //   3842: iconst_1
    //   3843: isub
    //   3844: iconst_2
    //   3845: iconst_1
    //   3846: isub
    //   3847: iconst_2
    //   3848: imul
    //   3849: iadd
    //   3850: daload
    //   3851: dneg
    //   3852: aload 5
    //   3854: iconst_1
    //   3855: iconst_1
    //   3856: isub
    //   3857: iload 35
    //   3859: iconst_1
    //   3860: isub
    //   3861: iconst_1
    //   3862: isub
    //   3863: iload 7
    //   3865: imul
    //   3866: iadd
    //   3867: iload 6
    //   3869: iadd
    //   3870: iconst_1
    //   3871: aload 16
    //   3873: iconst_1
    //   3874: iload 41
    //   3876: iadd
    //   3877: iconst_1
    //   3878: isub
    //   3879: iload 17
    //   3881: iadd
    //   3882: iconst_1
    //   3883: invokestatic 105	org/netlib/blas/Daxpy:daxpy	(ID[DII[DII)V
    //   3886: iload 35
    //   3888: iconst_2
    //   3889: isub
    //   3890: aload 74
    //   3892: iconst_2
    //   3893: iconst_1
    //   3894: isub
    //   3895: iconst_2
    //   3896: iconst_1
    //   3897: isub
    //   3898: iconst_2
    //   3899: imul
    //   3900: iadd
    //   3901: daload
    //   3902: dneg
    //   3903: aload 5
    //   3905: iconst_1
    //   3906: iconst_1
    //   3907: isub
    //   3908: iload 35
    //   3910: iconst_1
    //   3911: isub
    //   3912: iload 7
    //   3914: imul
    //   3915: iadd
    //   3916: iload 6
    //   3918: iadd
    //   3919: iconst_1
    //   3920: aload 16
    //   3922: iconst_1
    //   3923: iload 41
    //   3925: iadd
    //   3926: iconst_1
    //   3927: isub
    //   3928: iload 17
    //   3930: iadd
    //   3931: iconst_1
    //   3932: invokestatic 105	org/netlib/blas/Daxpy:daxpy	(ID[DII[DII)V
    //   3935: iload 35
    //   3937: iconst_m1
    //   3938: iadd
    //   3939: istore 35
    //   3941: iinc 77 -1
    //   3944: iload 77
    //   3946: ifgt -1139 -> 2807
    //   3949: iload 26
    //   3951: iconst_1
    //   3952: ixor
    //   3953: ifeq +289 -> 4242
    //   3956: iload 40
    //   3958: aload 16
    //   3960: iconst_1
    //   3961: iload 4
    //   3963: iadd
    //   3964: iconst_1
    //   3965: isub
    //   3966: iload 17
    //   3968: iadd
    //   3969: iconst_1
    //   3970: aload 11
    //   3972: iconst_1
    //   3973: iconst_1
    //   3974: isub
    //   3975: iload 34
    //   3977: iconst_1
    //   3978: isub
    //   3979: iconst_1
    //   3980: isub
    //   3981: iload 13
    //   3983: imul
    //   3984: iadd
    //   3985: iload 12
    //   3987: iadd
    //   3988: iconst_1
    //   3989: invokestatic 111	org/netlib/blas/Dcopy:dcopy	(I[DII[DII)V
    //   3992: iload 40
    //   3994: aload 16
    //   3996: iconst_1
    //   3997: iload 41
    //   3999: iadd
    //   4000: iconst_1
    //   4001: isub
    //   4002: iload 17
    //   4004: iadd
    //   4005: iconst_1
    //   4006: aload 11
    //   4008: iconst_1
    //   4009: iconst_1
    //   4010: isub
    //   4011: iload 34
    //   4013: iconst_1
    //   4014: isub
    //   4015: iload 13
    //   4017: imul
    //   4018: iadd
    //   4019: iload 12
    //   4021: iadd
    //   4022: iconst_1
    //   4023: invokestatic 111	org/netlib/blas/Dcopy:dcopy	(I[DII[DII)V
    //   4026: dconst_0
    //   4027: dstore 46
    //   4029: iconst_1
    //   4030: istore 39
    //   4032: iload 40
    //   4034: iconst_1
    //   4035: isub
    //   4036: iconst_1
    //   4037: iadd
    //   4038: istore 77
    //   4040: goto +64 -> 4104
    //   4043: dload 46
    //   4045: aload 11
    //   4047: iload 39
    //   4049: iconst_1
    //   4050: isub
    //   4051: iload 34
    //   4053: iconst_1
    //   4054: isub
    //   4055: iconst_1
    //   4056: isub
    //   4057: iload 13
    //   4059: imul
    //   4060: iadd
    //   4061: iload 12
    //   4063: iadd
    //   4064: daload
    //   4065: invokestatic 81	java/lang/Math:abs	(D)D
    //   4068: aload 11
    //   4070: iload 39
    //   4072: iconst_1
    //   4073: isub
    //   4074: iload 34
    //   4076: iconst_1
    //   4077: isub
    //   4078: iload 13
    //   4080: imul
    //   4081: iadd
    //   4082: iload 12
    //   4084: iadd
    //   4085: daload
    //   4086: invokestatic 81	java/lang/Math:abs	(D)D
    //   4089: dadd
    //   4090: invokestatic 87	java/lang/Math:max	(DD)D
    //   4093: dstore 46
    //   4095: iload 39
    //   4097: iconst_1
    //   4098: iadd
    //   4099: istore 39
    //   4101: iinc 77 -1
    //   4104: iload 77
    //   4106: ifgt -63 -> 4043
    //   4109: dconst_1
    //   4110: dload 46
    //   4112: ddiv
    //   4113: dstore 52
    //   4115: iload 40
    //   4117: dload 52
    //   4119: aload 11
    //   4121: iconst_1
    //   4122: iconst_1
    //   4123: isub
    //   4124: iload 34
    //   4126: iconst_1
    //   4127: isub
    //   4128: iconst_1
    //   4129: isub
    //   4130: iload 13
    //   4132: imul
    //   4133: iadd
    //   4134: iload 12
    //   4136: iadd
    //   4137: iconst_1
    //   4138: invokestatic 99	org/netlib/blas/Dscal:dscal	(ID[DII)V
    //   4141: iload 40
    //   4143: dload 52
    //   4145: aload 11
    //   4147: iconst_1
    //   4148: iconst_1
    //   4149: isub
    //   4150: iload 34
    //   4152: iconst_1
    //   4153: isub
    //   4154: iload 13
    //   4156: imul
    //   4157: iadd
    //   4158: iload 12
    //   4160: iadd
    //   4161: iconst_1
    //   4162: invokestatic 99	org/netlib/blas/Dscal:dscal	(ID[DII)V
    //   4165: iload 40
    //   4167: iconst_1
    //   4168: iadd
    //   4169: istore 39
    //   4171: iload 4
    //   4173: iload 40
    //   4175: iconst_1
    //   4176: iadd
    //   4177: isub
    //   4178: iconst_1
    //   4179: iadd
    //   4180: istore 77
    //   4182: goto +52 -> 4234
    //   4185: aload 11
    //   4187: iload 39
    //   4189: iconst_1
    //   4190: isub
    //   4191: iload 34
    //   4193: iconst_1
    //   4194: isub
    //   4195: iconst_1
    //   4196: isub
    //   4197: iload 13
    //   4199: imul
    //   4200: iadd
    //   4201: iload 12
    //   4203: iadd
    //   4204: dconst_0
    //   4205: dastore
    //   4206: aload 11
    //   4208: iload 39
    //   4210: iconst_1
    //   4211: isub
    //   4212: iload 34
    //   4214: iconst_1
    //   4215: isub
    //   4216: iload 13
    //   4218: imul
    //   4219: iadd
    //   4220: iload 12
    //   4222: iadd
    //   4223: dconst_0
    //   4224: dastore
    //   4225: iload 39
    //   4227: iconst_1
    //   4228: iadd
    //   4229: istore 39
    //   4231: iinc 77 -1
    //   4234: iload 77
    //   4236: ifgt -51 -> 4185
    //   4239: goto +357 -> 4596
    //   4242: iload 40
    //   4244: iconst_2
    //   4245: if_icmpgt +7 -> 4252
    //   4248: iconst_0
    //   4249: goto +4 -> 4253
    //   4252: iconst_1
    //   4253: ifeq +130 -> 4383
    //   4256: ldc 119
    //   4258: iload 4
    //   4260: iload 40
    //   4262: iconst_2
    //   4263: isub
    //   4264: dconst_1
    //   4265: aload 11
    //   4267: iload 12
    //   4269: iload 13
    //   4271: aload 16
    //   4273: iconst_1
    //   4274: iload 4
    //   4276: iadd
    //   4277: iconst_1
    //   4278: isub
    //   4279: iload 17
    //   4281: iadd
    //   4282: iconst_1
    //   4283: aload 16
    //   4285: iload 40
    //   4287: iconst_1
    //   4288: isub
    //   4289: iload 4
    //   4291: iadd
    //   4292: iconst_1
    //   4293: isub
    //   4294: iload 17
    //   4296: iadd
    //   4297: daload
    //   4298: aload 11
    //   4300: iconst_1
    //   4301: iconst_1
    //   4302: isub
    //   4303: iload 40
    //   4305: iconst_1
    //   4306: isub
    //   4307: iconst_1
    //   4308: isub
    //   4309: iload 13
    //   4311: imul
    //   4312: iadd
    //   4313: iload 12
    //   4315: iadd
    //   4316: iconst_1
    //   4317: invokestatic 125	org/netlib/blas/Dgemv:dgemv	(Ljava/lang/String;IID[DII[DIID[DII)V
    //   4320: ldc 119
    //   4322: iload 4
    //   4324: iload 40
    //   4326: iconst_2
    //   4327: isub
    //   4328: dconst_1
    //   4329: aload 11
    //   4331: iload 12
    //   4333: iload 13
    //   4335: aload 16
    //   4337: iconst_1
    //   4338: iload 41
    //   4340: iadd
    //   4341: iconst_1
    //   4342: isub
    //   4343: iload 17
    //   4345: iadd
    //   4346: iconst_1
    //   4347: aload 16
    //   4349: iload 40
    //   4351: iload 41
    //   4353: iadd
    //   4354: iconst_1
    //   4355: isub
    //   4356: iload 17
    //   4358: iadd
    //   4359: daload
    //   4360: aload 11
    //   4362: iconst_1
    //   4363: iconst_1
    //   4364: isub
    //   4365: iload 40
    //   4367: iconst_1
    //   4368: isub
    //   4369: iload 13
    //   4371: imul
    //   4372: iadd
    //   4373: iload 12
    //   4375: iadd
    //   4376: iconst_1
    //   4377: invokestatic 125	org/netlib/blas/Dgemv:dgemv	(Ljava/lang/String;IID[DII[DIID[DII)V
    //   4380: goto +77 -> 4457
    //   4383: iload 4
    //   4385: aload 16
    //   4387: iload 40
    //   4389: iconst_1
    //   4390: isub
    //   4391: iload 4
    //   4393: iadd
    //   4394: iconst_1
    //   4395: isub
    //   4396: iload 17
    //   4398: iadd
    //   4399: daload
    //   4400: aload 11
    //   4402: iconst_1
    //   4403: iconst_1
    //   4404: isub
    //   4405: iload 40
    //   4407: iconst_1
    //   4408: isub
    //   4409: iconst_1
    //   4410: isub
    //   4411: iload 13
    //   4413: imul
    //   4414: iadd
    //   4415: iload 12
    //   4417: iadd
    //   4418: iconst_1
    //   4419: invokestatic 99	org/netlib/blas/Dscal:dscal	(ID[DII)V
    //   4422: iload 4
    //   4424: aload 16
    //   4426: iload 40
    //   4428: iload 41
    //   4430: iadd
    //   4431: iconst_1
    //   4432: isub
    //   4433: iload 17
    //   4435: iadd
    //   4436: daload
    //   4437: aload 11
    //   4439: iconst_1
    //   4440: iconst_1
    //   4441: isub
    //   4442: iload 40
    //   4444: iconst_1
    //   4445: isub
    //   4446: iload 13
    //   4448: imul
    //   4449: iadd
    //   4450: iload 12
    //   4452: iadd
    //   4453: iconst_1
    //   4454: invokestatic 99	org/netlib/blas/Dscal:dscal	(ID[DII)V
    //   4457: dconst_0
    //   4458: dstore 46
    //   4460: iconst_1
    //   4461: istore 39
    //   4463: iload 4
    //   4465: iconst_1
    //   4466: isub
    //   4467: iconst_1
    //   4468: iadd
    //   4469: istore 77
    //   4471: goto +64 -> 4535
    //   4474: dload 46
    //   4476: aload 11
    //   4478: iload 39
    //   4480: iconst_1
    //   4481: isub
    //   4482: iload 40
    //   4484: iconst_1
    //   4485: isub
    //   4486: iconst_1
    //   4487: isub
    //   4488: iload 13
    //   4490: imul
    //   4491: iadd
    //   4492: iload 12
    //   4494: iadd
    //   4495: daload
    //   4496: invokestatic 81	java/lang/Math:abs	(D)D
    //   4499: aload 11
    //   4501: iload 39
    //   4503: iconst_1
    //   4504: isub
    //   4505: iload 40
    //   4507: iconst_1
    //   4508: isub
    //   4509: iload 13
    //   4511: imul
    //   4512: iadd
    //   4513: iload 12
    //   4515: iadd
    //   4516: daload
    //   4517: invokestatic 81	java/lang/Math:abs	(D)D
    //   4520: dadd
    //   4521: invokestatic 87	java/lang/Math:max	(DD)D
    //   4524: dstore 46
    //   4526: iload 39
    //   4528: iconst_1
    //   4529: iadd
    //   4530: istore 39
    //   4532: iinc 77 -1
    //   4535: iload 77
    //   4537: ifgt -63 -> 4474
    //   4540: dconst_1
    //   4541: dload 46
    //   4543: ddiv
    //   4544: dstore 52
    //   4546: iload 4
    //   4548: dload 52
    //   4550: aload 11
    //   4552: iconst_1
    //   4553: iconst_1
    //   4554: isub
    //   4555: iload 40
    //   4557: iconst_1
    //   4558: isub
    //   4559: iconst_1
    //   4560: isub
    //   4561: iload 13
    //   4563: imul
    //   4564: iadd
    //   4565: iload 12
    //   4567: iadd
    //   4568: iconst_1
    //   4569: invokestatic 99	org/netlib/blas/Dscal:dscal	(ID[DII)V
    //   4572: iload 4
    //   4574: dload 52
    //   4576: aload 11
    //   4578: iconst_1
    //   4579: iconst_1
    //   4580: isub
    //   4581: iload 40
    //   4583: iconst_1
    //   4584: isub
    //   4585: iload 13
    //   4587: imul
    //   4588: iadd
    //   4589: iload 12
    //   4591: iadd
    //   4592: iconst_1
    //   4593: invokestatic 99	org/netlib/blas/Dscal:dscal	(ID[DII)V
    //   4596: iload 34
    //   4598: iconst_1
    //   4599: isub
    //   4600: istore 34
    //   4602: iload 33
    //   4604: iconst_0
    //   4605: if_icmpne +7 -> 4612
    //   4608: iconst_0
    //   4609: goto +4 -> 4613
    //   4612: iconst_1
    //   4613: ifeq +9 -> 4622
    //   4616: iload 34
    //   4618: iconst_1
    //   4619: isub
    //   4620: istore 34
    //   4622: iload 33
    //   4624: iconst_1
    //   4625: if_icmpeq +7 -> 4632
    //   4628: iconst_0
    //   4629: goto +4 -> 4633
    //   4632: iconst_1
    //   4633: ifeq +6 -> 4639
    //   4636: iconst_0
    //   4637: istore 33
    //   4639: iload 33
    //   4641: iconst_m1
    //   4642: if_icmpeq +7 -> 4649
    //   4645: iconst_0
    //   4646: goto +4 -> 4650
    //   4649: iconst_1
    //   4650: ifeq +6 -> 4656
    //   4653: iconst_1
    //   4654: istore 33
    //   4656: iload 40
    //   4658: iconst_m1
    //   4659: iadd
    //   4660: istore 40
    //   4662: iinc 76 -1
    //   4665: iload 76
    //   4667: ifgt -3674 -> 993
    //   4670: iload 25
    //   4672: ifeq +4021 -> 8693
    //   4675: iconst_0
    //   4676: istore 33
    //   4678: iconst_1
    //   4679: istore 34
    //   4681: iconst_1
    //   4682: istore 40
    //   4684: iload 4
    //   4686: iconst_1
    //   4687: isub
    //   4688: iconst_1
    //   4689: iadd
    //   4690: istore 76
    //   4692: goto +3996 -> 8688
    //   4695: iload 33
    //   4697: iconst_m1
    //   4698: if_icmpeq +7 -> 4705
    //   4701: iconst_0
    //   4702: goto +4 -> 4706
    //   4705: iconst_1
    //   4706: ifeq +6 -> 4712
    //   4709: goto +3936 -> 8645
    //   4712: iload 40
    //   4714: iload 4
    //   4716: if_icmpeq +7 -> 4723
    //   4719: iconst_0
    //   4720: goto +4 -> 4724
    //   4723: iconst_1
    //   4724: ifeq +6 -> 4730
    //   4727: goto +42 -> 4769
    //   4730: aload 5
    //   4732: iload 40
    //   4734: iconst_1
    //   4735: iadd
    //   4736: iconst_1
    //   4737: isub
    //   4738: iload 40
    //   4740: iconst_1
    //   4741: isub
    //   4742: iload 7
    //   4744: imul
    //   4745: iadd
    //   4746: iload 6
    //   4748: iadd
    //   4749: daload
    //   4750: dconst_0
    //   4751: dcmpl
    //   4752: ifeq +7 -> 4759
    //   4755: iconst_0
    //   4756: goto +4 -> 4760
    //   4759: iconst_1
    //   4760: ifeq +6 -> 4766
    //   4763: goto +6 -> 4769
    //   4766: iconst_1
    //   4767: istore 33
    //   4769: iload 29
    //   4771: ifeq +19 -> 4790
    //   4774: aload_2
    //   4775: iload 40
    //   4777: iconst_1
    //   4778: isub
    //   4779: iload_3
    //   4780: iadd
    //   4781: baload
    //   4782: iconst_1
    //   4783: ixor
    //   4784: ifeq +6 -> 4790
    //   4787: goto +3858 -> 8645
    //   4790: aload 5
    //   4792: iload 40
    //   4794: iconst_1
    //   4795: isub
    //   4796: iload 40
    //   4798: iconst_1
    //   4799: isub
    //   4800: iload 7
    //   4802: imul
    //   4803: iadd
    //   4804: iload 6
    //   4806: iadd
    //   4807: daload
    //   4808: dstore 70
    //   4810: dconst_0
    //   4811: dstore 68
    //   4813: iload 33
    //   4815: iconst_0
    //   4816: if_icmpne +7 -> 4823
    //   4819: iconst_0
    //   4820: goto +4 -> 4824
    //   4823: iconst_1
    //   4824: ifeq +58 -> 4882
    //   4827: aload 5
    //   4829: iload 40
    //   4831: iconst_1
    //   4832: isub
    //   4833: iload 40
    //   4835: iconst_1
    //   4836: iadd
    //   4837: iconst_1
    //   4838: isub
    //   4839: iload 7
    //   4841: imul
    //   4842: iadd
    //   4843: iload 6
    //   4845: iadd
    //   4846: daload
    //   4847: invokestatic 81	java/lang/Math:abs	(D)D
    //   4850: invokestatic 84	java/lang/Math:sqrt	(D)D
    //   4853: aload 5
    //   4855: iload 40
    //   4857: iconst_1
    //   4858: iadd
    //   4859: iconst_1
    //   4860: isub
    //   4861: iload 40
    //   4863: iconst_1
    //   4864: isub
    //   4865: iload 7
    //   4867: imul
    //   4868: iadd
    //   4869: iload 6
    //   4871: iadd
    //   4872: daload
    //   4873: invokestatic 81	java/lang/Math:abs	(D)D
    //   4876: invokestatic 84	java/lang/Math:sqrt	(D)D
    //   4879: dmul
    //   4880: dstore 68
    //   4882: dload 60
    //   4884: dload 70
    //   4886: invokestatic 81	java/lang/Math:abs	(D)D
    //   4889: dload 68
    //   4891: invokestatic 81	java/lang/Math:abs	(D)D
    //   4894: dadd
    //   4895: dmul
    //   4896: dload 58
    //   4898: invokestatic 87	java/lang/Math:max	(DD)D
    //   4901: dstore 56
    //   4903: iload 33
    //   4905: iconst_0
    //   4906: if_icmpeq +7 -> 4913
    //   4909: iconst_0
    //   4910: goto +4 -> 4914
    //   4913: iconst_1
    //   4914: ifeq +1325 -> 6239
    //   4917: aload 16
    //   4919: iload 40
    //   4921: iload 4
    //   4923: iadd
    //   4924: iconst_1
    //   4925: isub
    //   4926: iload 17
    //   4928: iadd
    //   4929: dconst_1
    //   4930: dastore
    //   4931: iload 40
    //   4933: iconst_1
    //   4934: iadd
    //   4935: istore 39
    //   4937: iload 4
    //   4939: iload 40
    //   4941: iconst_1
    //   4942: iadd
    //   4943: isub
    //   4944: iconst_1
    //   4945: iadd
    //   4946: istore 77
    //   4948: goto +44 -> 4992
    //   4951: aload 16
    //   4953: iload 39
    //   4955: iload 4
    //   4957: iadd
    //   4958: iconst_1
    //   4959: isub
    //   4960: iload 17
    //   4962: iadd
    //   4963: aload 5
    //   4965: iload 40
    //   4967: iconst_1
    //   4968: isub
    //   4969: iload 39
    //   4971: iconst_1
    //   4972: isub
    //   4973: iload 7
    //   4975: imul
    //   4976: iadd
    //   4977: iload 6
    //   4979: iadd
    //   4980: daload
    //   4981: dneg
    //   4982: dastore
    //   4983: iload 39
    //   4985: iconst_1
    //   4986: iadd
    //   4987: istore 39
    //   4989: iinc 77 -1
    //   4992: iload 77
    //   4994: ifgt -43 -> 4951
    //   4997: dconst_1
    //   4998: dstore 66
    //   5000: dload 44
    //   5002: dstore 64
    //   5004: iload 40
    //   5006: iconst_1
    //   5007: iadd
    //   5008: istore 38
    //   5010: iload 40
    //   5012: iconst_1
    //   5013: iadd
    //   5014: istore 35
    //   5016: iload 4
    //   5018: iload 40
    //   5020: iconst_1
    //   5021: iadd
    //   5022: isub
    //   5023: iconst_1
    //   5024: iadd
    //   5025: istore 77
    //   5027: goto +848 -> 5875
    //   5030: iload 35
    //   5032: iload 38
    //   5034: if_icmplt +7 -> 5041
    //   5037: iconst_0
    //   5038: goto +4 -> 5042
    //   5041: iconst_1
    //   5042: ifeq +6 -> 5048
    //   5045: goto +821 -> 5866
    //   5048: iload 35
    //   5050: istore 36
    //   5052: iload 35
    //   5054: istore 37
    //   5056: iload 35
    //   5058: iconst_1
    //   5059: iadd
    //   5060: istore 38
    //   5062: iload 35
    //   5064: iload 4
    //   5066: if_icmplt +7 -> 5073
    //   5069: iconst_0
    //   5070: goto +4 -> 5074
    //   5073: iconst_1
    //   5074: ifeq +48 -> 5122
    //   5077: aload 5
    //   5079: iload 35
    //   5081: iconst_1
    //   5082: iadd
    //   5083: iconst_1
    //   5084: isub
    //   5085: iload 35
    //   5087: iconst_1
    //   5088: isub
    //   5089: iload 7
    //   5091: imul
    //   5092: iadd
    //   5093: iload 6
    //   5095: iadd
    //   5096: daload
    //   5097: dconst_0
    //   5098: dcmpl
    //   5099: ifne +7 -> 5106
    //   5102: iconst_0
    //   5103: goto +4 -> 5107
    //   5106: iconst_1
    //   5107: ifeq +15 -> 5122
    //   5110: iload 35
    //   5112: iconst_1
    //   5113: iadd
    //   5114: istore 37
    //   5116: iload 35
    //   5118: iconst_2
    //   5119: iadd
    //   5120: istore 38
    //   5122: iload 36
    //   5124: iload 37
    //   5126: if_icmpeq +7 -> 5133
    //   5129: iconst_0
    //   5130: goto +4 -> 5134
    //   5133: iconst_1
    //   5134: ifeq +298 -> 5432
    //   5137: aload 16
    //   5139: iload 35
    //   5141: iconst_1
    //   5142: isub
    //   5143: iload 17
    //   5145: iadd
    //   5146: daload
    //   5147: dload 64
    //   5149: dcmpl
    //   5150: ifgt +7 -> 5157
    //   5153: iconst_0
    //   5154: goto +4 -> 5158
    //   5157: iconst_1
    //   5158: ifeq +41 -> 5199
    //   5161: dconst_1
    //   5162: dload 66
    //   5164: ddiv
    //   5165: dstore 50
    //   5167: iload 4
    //   5169: iload 40
    //   5171: isub
    //   5172: iconst_1
    //   5173: iadd
    //   5174: dload 50
    //   5176: aload 16
    //   5178: iload 40
    //   5180: iload 4
    //   5182: iadd
    //   5183: iconst_1
    //   5184: isub
    //   5185: iload 17
    //   5187: iadd
    //   5188: iconst_1
    //   5189: invokestatic 99	org/netlib/blas/Dscal:dscal	(ID[DII)V
    //   5192: dconst_1
    //   5193: dstore 66
    //   5195: dload 44
    //   5197: dstore 64
    //   5199: aload 16
    //   5201: iload 35
    //   5203: iload 4
    //   5205: iadd
    //   5206: iconst_1
    //   5207: isub
    //   5208: iload 17
    //   5210: iadd
    //   5211: aload 16
    //   5213: iload 35
    //   5215: iload 4
    //   5217: iadd
    //   5218: iconst_1
    //   5219: isub
    //   5220: iload 17
    //   5222: iadd
    //   5223: daload
    //   5224: iload 35
    //   5226: iload 40
    //   5228: isub
    //   5229: iconst_1
    //   5230: isub
    //   5231: aload 5
    //   5233: iload 40
    //   5235: iconst_1
    //   5236: iadd
    //   5237: iconst_1
    //   5238: isub
    //   5239: iload 35
    //   5241: iconst_1
    //   5242: isub
    //   5243: iload 7
    //   5245: imul
    //   5246: iadd
    //   5247: iload 6
    //   5249: iadd
    //   5250: iconst_1
    //   5251: aload 16
    //   5253: iload 40
    //   5255: iconst_1
    //   5256: iadd
    //   5257: iload 4
    //   5259: iadd
    //   5260: iconst_1
    //   5261: isub
    //   5262: iload 17
    //   5264: iadd
    //   5265: iconst_1
    //   5266: invokestatic 131	org/netlib/blas/Ddot:ddot	(I[DII[DII)D
    //   5269: dsub
    //   5270: dastore
    //   5271: iconst_0
    //   5272: iconst_1
    //   5273: iconst_1
    //   5274: dload 56
    //   5276: dconst_1
    //   5277: aload 5
    //   5279: iload 35
    //   5281: iconst_1
    //   5282: isub
    //   5283: iload 35
    //   5285: iconst_1
    //   5286: isub
    //   5287: iload 7
    //   5289: imul
    //   5290: iadd
    //   5291: iload 6
    //   5293: iadd
    //   5294: iload 7
    //   5296: dconst_1
    //   5297: dconst_1
    //   5298: aload 16
    //   5300: iload 35
    //   5302: iload 4
    //   5304: iadd
    //   5305: iconst_1
    //   5306: isub
    //   5307: iload 17
    //   5309: iadd
    //   5310: iload 4
    //   5312: dload 70
    //   5314: dconst_0
    //   5315: aload 74
    //   5317: iconst_0
    //   5318: iconst_2
    //   5319: aload 54
    //   5321: aload 72
    //   5323: aload 31
    //   5325: invokestatic 93	org/netlib/lapack/Dlaln2:dlaln2	(ZIIDD[DIIDD[DIIDD[DIILorg/netlib/util/doubleW;Lorg/netlib/util/doubleW;Lorg/netlib/util/intW;)V
    //   5328: aload 54
    //   5330: getfield 69	org/netlib/util/doubleW:val	D
    //   5333: dconst_1
    //   5334: dcmpl
    //   5335: ifne +7 -> 5342
    //   5338: iconst_0
    //   5339: goto +4 -> 5343
    //   5342: iconst_1
    //   5343: ifeq +31 -> 5374
    //   5346: iload 4
    //   5348: iload 40
    //   5350: isub
    //   5351: iconst_1
    //   5352: iadd
    //   5353: aload 54
    //   5355: getfield 69	org/netlib/util/doubleW:val	D
    //   5358: aload 16
    //   5360: iload 40
    //   5362: iload 4
    //   5364: iadd
    //   5365: iconst_1
    //   5366: isub
    //   5367: iload 17
    //   5369: iadd
    //   5370: iconst_1
    //   5371: invokestatic 99	org/netlib/blas/Dscal:dscal	(ID[DII)V
    //   5374: aload 16
    //   5376: iload 35
    //   5378: iload 4
    //   5380: iadd
    //   5381: iconst_1
    //   5382: isub
    //   5383: iload 17
    //   5385: iadd
    //   5386: aload 74
    //   5388: iconst_1
    //   5389: iconst_1
    //   5390: isub
    //   5391: iconst_1
    //   5392: iconst_1
    //   5393: isub
    //   5394: iconst_2
    //   5395: imul
    //   5396: iadd
    //   5397: daload
    //   5398: dastore
    //   5399: aload 16
    //   5401: iload 35
    //   5403: iload 4
    //   5405: iadd
    //   5406: iconst_1
    //   5407: isub
    //   5408: iload 17
    //   5410: iadd
    //   5411: daload
    //   5412: invokestatic 81	java/lang/Math:abs	(D)D
    //   5415: dload 66
    //   5417: invokestatic 87	java/lang/Math:max	(DD)D
    //   5420: dstore 66
    //   5422: dload 44
    //   5424: dload 66
    //   5426: ddiv
    //   5427: dstore 64
    //   5429: goto +437 -> 5866
    //   5432: aload 16
    //   5434: iload 35
    //   5436: iconst_1
    //   5437: isub
    //   5438: iload 17
    //   5440: iadd
    //   5441: daload
    //   5442: aload 16
    //   5444: iload 35
    //   5446: iconst_1
    //   5447: iadd
    //   5448: iconst_1
    //   5449: isub
    //   5450: iload 17
    //   5452: iadd
    //   5453: daload
    //   5454: invokestatic 87	java/lang/Math:max	(DD)D
    //   5457: dstore 42
    //   5459: dload 42
    //   5461: dload 64
    //   5463: dcmpl
    //   5464: ifgt +7 -> 5471
    //   5467: iconst_0
    //   5468: goto +4 -> 5472
    //   5471: iconst_1
    //   5472: ifeq +41 -> 5513
    //   5475: dconst_1
    //   5476: dload 66
    //   5478: ddiv
    //   5479: dstore 50
    //   5481: iload 4
    //   5483: iload 40
    //   5485: isub
    //   5486: iconst_1
    //   5487: iadd
    //   5488: dload 50
    //   5490: aload 16
    //   5492: iload 40
    //   5494: iload 4
    //   5496: iadd
    //   5497: iconst_1
    //   5498: isub
    //   5499: iload 17
    //   5501: iadd
    //   5502: iconst_1
    //   5503: invokestatic 99	org/netlib/blas/Dscal:dscal	(ID[DII)V
    //   5506: dconst_1
    //   5507: dstore 66
    //   5509: dload 44
    //   5511: dstore 64
    //   5513: aload 16
    //   5515: iload 35
    //   5517: iload 4
    //   5519: iadd
    //   5520: iconst_1
    //   5521: isub
    //   5522: iload 17
    //   5524: iadd
    //   5525: aload 16
    //   5527: iload 35
    //   5529: iload 4
    //   5531: iadd
    //   5532: iconst_1
    //   5533: isub
    //   5534: iload 17
    //   5536: iadd
    //   5537: daload
    //   5538: iload 35
    //   5540: iload 40
    //   5542: isub
    //   5543: iconst_1
    //   5544: isub
    //   5545: aload 5
    //   5547: iload 40
    //   5549: iconst_1
    //   5550: iadd
    //   5551: iconst_1
    //   5552: isub
    //   5553: iload 35
    //   5555: iconst_1
    //   5556: isub
    //   5557: iload 7
    //   5559: imul
    //   5560: iadd
    //   5561: iload 6
    //   5563: iadd
    //   5564: iconst_1
    //   5565: aload 16
    //   5567: iload 40
    //   5569: iconst_1
    //   5570: iadd
    //   5571: iload 4
    //   5573: iadd
    //   5574: iconst_1
    //   5575: isub
    //   5576: iload 17
    //   5578: iadd
    //   5579: iconst_1
    //   5580: invokestatic 131	org/netlib/blas/Ddot:ddot	(I[DII[DII)D
    //   5583: dsub
    //   5584: dastore
    //   5585: aload 16
    //   5587: iload 35
    //   5589: iconst_1
    //   5590: iadd
    //   5591: iload 4
    //   5593: iadd
    //   5594: iconst_1
    //   5595: isub
    //   5596: iload 17
    //   5598: iadd
    //   5599: aload 16
    //   5601: iload 35
    //   5603: iconst_1
    //   5604: iadd
    //   5605: iload 4
    //   5607: iadd
    //   5608: iconst_1
    //   5609: isub
    //   5610: iload 17
    //   5612: iadd
    //   5613: daload
    //   5614: iload 35
    //   5616: iload 40
    //   5618: isub
    //   5619: iconst_1
    //   5620: isub
    //   5621: aload 5
    //   5623: iload 40
    //   5625: iconst_1
    //   5626: iadd
    //   5627: iconst_1
    //   5628: isub
    //   5629: iload 35
    //   5631: iconst_1
    //   5632: iadd
    //   5633: iconst_1
    //   5634: isub
    //   5635: iload 7
    //   5637: imul
    //   5638: iadd
    //   5639: iload 6
    //   5641: iadd
    //   5642: iconst_1
    //   5643: aload 16
    //   5645: iload 40
    //   5647: iconst_1
    //   5648: iadd
    //   5649: iload 4
    //   5651: iadd
    //   5652: iconst_1
    //   5653: isub
    //   5654: iload 17
    //   5656: iadd
    //   5657: iconst_1
    //   5658: invokestatic 131	org/netlib/blas/Ddot:ddot	(I[DII[DII)D
    //   5661: dsub
    //   5662: dastore
    //   5663: iconst_1
    //   5664: iconst_2
    //   5665: iconst_1
    //   5666: dload 56
    //   5668: dconst_1
    //   5669: aload 5
    //   5671: iload 35
    //   5673: iconst_1
    //   5674: isub
    //   5675: iload 35
    //   5677: iconst_1
    //   5678: isub
    //   5679: iload 7
    //   5681: imul
    //   5682: iadd
    //   5683: iload 6
    //   5685: iadd
    //   5686: iload 7
    //   5688: dconst_1
    //   5689: dconst_1
    //   5690: aload 16
    //   5692: iload 35
    //   5694: iload 4
    //   5696: iadd
    //   5697: iconst_1
    //   5698: isub
    //   5699: iload 17
    //   5701: iadd
    //   5702: iload 4
    //   5704: dload 70
    //   5706: dconst_0
    //   5707: aload 74
    //   5709: iconst_0
    //   5710: iconst_2
    //   5711: aload 54
    //   5713: aload 72
    //   5715: aload 31
    //   5717: invokestatic 93	org/netlib/lapack/Dlaln2:dlaln2	(ZIIDD[DIIDD[DIIDD[DIILorg/netlib/util/doubleW;Lorg/netlib/util/doubleW;Lorg/netlib/util/intW;)V
    //   5720: aload 54
    //   5722: getfield 69	org/netlib/util/doubleW:val	D
    //   5725: dconst_1
    //   5726: dcmpl
    //   5727: ifne +7 -> 5734
    //   5730: iconst_0
    //   5731: goto +4 -> 5735
    //   5734: iconst_1
    //   5735: ifeq +31 -> 5766
    //   5738: iload 4
    //   5740: iload 40
    //   5742: isub
    //   5743: iconst_1
    //   5744: iadd
    //   5745: aload 54
    //   5747: getfield 69	org/netlib/util/doubleW:val	D
    //   5750: aload 16
    //   5752: iload 40
    //   5754: iload 4
    //   5756: iadd
    //   5757: iconst_1
    //   5758: isub
    //   5759: iload 17
    //   5761: iadd
    //   5762: iconst_1
    //   5763: invokestatic 99	org/netlib/blas/Dscal:dscal	(ID[DII)V
    //   5766: aload 16
    //   5768: iload 35
    //   5770: iload 4
    //   5772: iadd
    //   5773: iconst_1
    //   5774: isub
    //   5775: iload 17
    //   5777: iadd
    //   5778: aload 74
    //   5780: iconst_1
    //   5781: iconst_1
    //   5782: isub
    //   5783: iconst_1
    //   5784: iconst_1
    //   5785: isub
    //   5786: iconst_2
    //   5787: imul
    //   5788: iadd
    //   5789: daload
    //   5790: dastore
    //   5791: aload 16
    //   5793: iload 35
    //   5795: iconst_1
    //   5796: iadd
    //   5797: iload 4
    //   5799: iadd
    //   5800: iconst_1
    //   5801: isub
    //   5802: iload 17
    //   5804: iadd
    //   5805: aload 74
    //   5807: iconst_2
    //   5808: iconst_1
    //   5809: isub
    //   5810: iconst_1
    //   5811: iconst_1
    //   5812: isub
    //   5813: iconst_2
    //   5814: imul
    //   5815: iadd
    //   5816: daload
    //   5817: dastore
    //   5818: aload 16
    //   5820: iload 35
    //   5822: iload 4
    //   5824: iadd
    //   5825: iconst_1
    //   5826: isub
    //   5827: iload 17
    //   5829: iadd
    //   5830: daload
    //   5831: invokestatic 81	java/lang/Math:abs	(D)D
    //   5834: aload 16
    //   5836: iload 35
    //   5838: iconst_1
    //   5839: iadd
    //   5840: iload 4
    //   5842: iadd
    //   5843: iconst_1
    //   5844: isub
    //   5845: iload 17
    //   5847: iadd
    //   5848: daload
    //   5849: invokestatic 81	java/lang/Math:abs	(D)D
    //   5852: dload 66
    //   5854: invokestatic 136	org/netlib/util/Util:max	(DDD)D
    //   5857: dstore 66
    //   5859: dload 44
    //   5861: dload 66
    //   5863: ddiv
    //   5864: dstore 64
    //   5866: iload 35
    //   5868: iconst_1
    //   5869: iadd
    //   5870: istore 35
    //   5872: iinc 77 -1
    //   5875: iload 77
    //   5877: ifgt -847 -> 5030
    //   5880: iload 26
    //   5882: iconst_1
    //   5883: ixor
    //   5884: ifeq +186 -> 6070
    //   5887: iload 4
    //   5889: iload 40
    //   5891: isub
    //   5892: iconst_1
    //   5893: iadd
    //   5894: aload 16
    //   5896: iload 40
    //   5898: iload 4
    //   5900: iadd
    //   5901: iconst_1
    //   5902: isub
    //   5903: iload 17
    //   5905: iadd
    //   5906: iconst_1
    //   5907: aload 8
    //   5909: iload 40
    //   5911: iconst_1
    //   5912: isub
    //   5913: iload 34
    //   5915: iconst_1
    //   5916: isub
    //   5917: iload 10
    //   5919: imul
    //   5920: iadd
    //   5921: iload 9
    //   5923: iadd
    //   5924: iconst_1
    //   5925: invokestatic 111	org/netlib/blas/Dcopy:dcopy	(I[DII[DII)V
    //   5928: iload 4
    //   5930: iload 40
    //   5932: isub
    //   5933: iconst_1
    //   5934: iadd
    //   5935: aload 8
    //   5937: iload 40
    //   5939: iconst_1
    //   5940: isub
    //   5941: iload 34
    //   5943: iconst_1
    //   5944: isub
    //   5945: iload 10
    //   5947: imul
    //   5948: iadd
    //   5949: iload 9
    //   5951: iadd
    //   5952: iconst_1
    //   5953: invokestatic 117	org/netlib/blas/Idamax:idamax	(I[DII)I
    //   5956: iload 40
    //   5958: iadd
    //   5959: iconst_1
    //   5960: isub
    //   5961: istore 32
    //   5963: dconst_1
    //   5964: aload 8
    //   5966: iload 32
    //   5968: iconst_1
    //   5969: isub
    //   5970: iload 34
    //   5972: iconst_1
    //   5973: isub
    //   5974: iload 10
    //   5976: imul
    //   5977: iadd
    //   5978: iload 9
    //   5980: iadd
    //   5981: daload
    //   5982: invokestatic 81	java/lang/Math:abs	(D)D
    //   5985: ddiv
    //   5986: dstore 52
    //   5988: iload 4
    //   5990: iload 40
    //   5992: isub
    //   5993: iconst_1
    //   5994: iadd
    //   5995: dload 52
    //   5997: aload 8
    //   5999: iload 40
    //   6001: iconst_1
    //   6002: isub
    //   6003: iload 34
    //   6005: iconst_1
    //   6006: isub
    //   6007: iload 10
    //   6009: imul
    //   6010: iadd
    //   6011: iload 9
    //   6013: iadd
    //   6014: iconst_1
    //   6015: invokestatic 99	org/netlib/blas/Dscal:dscal	(ID[DII)V
    //   6018: iconst_1
    //   6019: istore 39
    //   6021: iload 40
    //   6023: iconst_1
    //   6024: isub
    //   6025: iconst_1
    //   6026: isub
    //   6027: iconst_1
    //   6028: iadd
    //   6029: istore 77
    //   6031: goto +31 -> 6062
    //   6034: aload 8
    //   6036: iload 39
    //   6038: iconst_1
    //   6039: isub
    //   6040: iload 34
    //   6042: iconst_1
    //   6043: isub
    //   6044: iload 10
    //   6046: imul
    //   6047: iadd
    //   6048: iload 9
    //   6050: iadd
    //   6051: dconst_0
    //   6052: dastore
    //   6053: iload 39
    //   6055: iconst_1
    //   6056: iadd
    //   6057: istore 39
    //   6059: iinc 77 -1
    //   6062: iload 77
    //   6064: ifgt -30 -> 6034
    //   6067: goto +169 -> 6236
    //   6070: iload 40
    //   6072: iload 4
    //   6074: if_icmplt +7 -> 6081
    //   6077: iconst_0
    //   6078: goto +4 -> 6082
    //   6081: iconst_1
    //   6082: ifeq +81 -> 6163
    //   6085: ldc 119
    //   6087: iload 4
    //   6089: iload 4
    //   6091: iload 40
    //   6093: isub
    //   6094: dconst_1
    //   6095: aload 8
    //   6097: iconst_1
    //   6098: iconst_1
    //   6099: isub
    //   6100: iload 40
    //   6102: iconst_1
    //   6103: iadd
    //   6104: iconst_1
    //   6105: isub
    //   6106: iload 10
    //   6108: imul
    //   6109: iadd
    //   6110: iload 9
    //   6112: iadd
    //   6113: iload 10
    //   6115: aload 16
    //   6117: iload 40
    //   6119: iconst_1
    //   6120: iadd
    //   6121: iload 4
    //   6123: iadd
    //   6124: iconst_1
    //   6125: isub
    //   6126: iload 17
    //   6128: iadd
    //   6129: iconst_1
    //   6130: aload 16
    //   6132: iload 40
    //   6134: iload 4
    //   6136: iadd
    //   6137: iconst_1
    //   6138: isub
    //   6139: iload 17
    //   6141: iadd
    //   6142: daload
    //   6143: aload 8
    //   6145: iconst_1
    //   6146: iconst_1
    //   6147: isub
    //   6148: iload 40
    //   6150: iconst_1
    //   6151: isub
    //   6152: iload 10
    //   6154: imul
    //   6155: iadd
    //   6156: iload 9
    //   6158: iadd
    //   6159: iconst_1
    //   6160: invokestatic 125	org/netlib/blas/Dgemv:dgemv	(Ljava/lang/String;IID[DII[DIID[DII)V
    //   6163: iload 4
    //   6165: aload 8
    //   6167: iconst_1
    //   6168: iconst_1
    //   6169: isub
    //   6170: iload 40
    //   6172: iconst_1
    //   6173: isub
    //   6174: iload 10
    //   6176: imul
    //   6177: iadd
    //   6178: iload 9
    //   6180: iadd
    //   6181: iconst_1
    //   6182: invokestatic 117	org/netlib/blas/Idamax:idamax	(I[DII)I
    //   6185: istore 32
    //   6187: dconst_1
    //   6188: aload 8
    //   6190: iload 32
    //   6192: iconst_1
    //   6193: isub
    //   6194: iload 40
    //   6196: iconst_1
    //   6197: isub
    //   6198: iload 10
    //   6200: imul
    //   6201: iadd
    //   6202: iload 9
    //   6204: iadd
    //   6205: daload
    //   6206: invokestatic 81	java/lang/Math:abs	(D)D
    //   6209: ddiv
    //   6210: dstore 52
    //   6212: iload 4
    //   6214: dload 52
    //   6216: aload 8
    //   6218: iconst_1
    //   6219: iconst_1
    //   6220: isub
    //   6221: iload 40
    //   6223: iconst_1
    //   6224: isub
    //   6225: iload 10
    //   6227: imul
    //   6228: iadd
    //   6229: iload 9
    //   6231: iadd
    //   6232: iconst_1
    //   6233: invokestatic 99	org/netlib/blas/Dscal:dscal	(ID[DII)V
    //   6236: goto +2383 -> 8619
    //   6239: aload 5
    //   6241: iload 40
    //   6243: iconst_1
    //   6244: isub
    //   6245: iload 40
    //   6247: iconst_1
    //   6248: iadd
    //   6249: iconst_1
    //   6250: isub
    //   6251: iload 7
    //   6253: imul
    //   6254: iadd
    //   6255: iload 6
    //   6257: iadd
    //   6258: daload
    //   6259: invokestatic 81	java/lang/Math:abs	(D)D
    //   6262: aload 5
    //   6264: iload 40
    //   6266: iconst_1
    //   6267: iadd
    //   6268: iconst_1
    //   6269: isub
    //   6270: iload 40
    //   6272: iconst_1
    //   6273: isub
    //   6274: iload 7
    //   6276: imul
    //   6277: iadd
    //   6278: iload 6
    //   6280: iadd
    //   6281: daload
    //   6282: invokestatic 81	java/lang/Math:abs	(D)D
    //   6285: dcmpl
    //   6286: ifge +7 -> 6293
    //   6289: iconst_0
    //   6290: goto +4 -> 6294
    //   6293: iconst_1
    //   6294: ifeq +58 -> 6352
    //   6297: aload 16
    //   6299: iload 40
    //   6301: iload 4
    //   6303: iadd
    //   6304: iconst_1
    //   6305: isub
    //   6306: iload 17
    //   6308: iadd
    //   6309: dload 68
    //   6311: aload 5
    //   6313: iload 40
    //   6315: iconst_1
    //   6316: isub
    //   6317: iload 40
    //   6319: iconst_1
    //   6320: iadd
    //   6321: iconst_1
    //   6322: isub
    //   6323: iload 7
    //   6325: imul
    //   6326: iadd
    //   6327: iload 6
    //   6329: iadd
    //   6330: daload
    //   6331: ddiv
    //   6332: dastore
    //   6333: aload 16
    //   6335: iload 40
    //   6337: iconst_1
    //   6338: iadd
    //   6339: iload 41
    //   6341: iadd
    //   6342: iconst_1
    //   6343: isub
    //   6344: iload 17
    //   6346: iadd
    //   6347: dconst_1
    //   6348: dastore
    //   6349: goto +56 -> 6405
    //   6352: aload 16
    //   6354: iload 40
    //   6356: iload 4
    //   6358: iadd
    //   6359: iconst_1
    //   6360: isub
    //   6361: iload 17
    //   6363: iadd
    //   6364: dconst_1
    //   6365: dastore
    //   6366: aload 16
    //   6368: iload 40
    //   6370: iconst_1
    //   6371: iadd
    //   6372: iload 41
    //   6374: iadd
    //   6375: iconst_1
    //   6376: isub
    //   6377: iload 17
    //   6379: iadd
    //   6380: dload 68
    //   6382: aload 5
    //   6384: iload 40
    //   6386: iconst_1
    //   6387: iadd
    //   6388: iconst_1
    //   6389: isub
    //   6390: iload 40
    //   6392: iconst_1
    //   6393: isub
    //   6394: iload 7
    //   6396: imul
    //   6397: iadd
    //   6398: iload 6
    //   6400: iadd
    //   6401: daload
    //   6402: ddiv
    //   6403: dneg
    //   6404: dastore
    //   6405: aload 16
    //   6407: iload 40
    //   6409: iconst_1
    //   6410: iadd
    //   6411: iload 4
    //   6413: iadd
    //   6414: iconst_1
    //   6415: isub
    //   6416: iload 17
    //   6418: iadd
    //   6419: dconst_0
    //   6420: dastore
    //   6421: aload 16
    //   6423: iload 40
    //   6425: iload 41
    //   6427: iadd
    //   6428: iconst_1
    //   6429: isub
    //   6430: iload 17
    //   6432: iadd
    //   6433: dconst_0
    //   6434: dastore
    //   6435: iload 40
    //   6437: iconst_2
    //   6438: iadd
    //   6439: istore 39
    //   6441: iload 4
    //   6443: iload 40
    //   6445: iconst_2
    //   6446: iadd
    //   6447: isub
    //   6448: iconst_1
    //   6449: iadd
    //   6450: istore 77
    //   6452: goto +108 -> 6560
    //   6455: aload 16
    //   6457: iload 39
    //   6459: iload 4
    //   6461: iadd
    //   6462: iconst_1
    //   6463: isub
    //   6464: iload 17
    //   6466: iadd
    //   6467: aload 16
    //   6469: iload 40
    //   6471: iload 4
    //   6473: iadd
    //   6474: iconst_1
    //   6475: isub
    //   6476: iload 17
    //   6478: iadd
    //   6479: daload
    //   6480: aload 5
    //   6482: iload 40
    //   6484: iconst_1
    //   6485: isub
    //   6486: iload 39
    //   6488: iconst_1
    //   6489: isub
    //   6490: iload 7
    //   6492: imul
    //   6493: iadd
    //   6494: iload 6
    //   6496: iadd
    //   6497: daload
    //   6498: dmul
    //   6499: dneg
    //   6500: dastore
    //   6501: aload 16
    //   6503: iload 39
    //   6505: iload 41
    //   6507: iadd
    //   6508: iconst_1
    //   6509: isub
    //   6510: iload 17
    //   6512: iadd
    //   6513: aload 16
    //   6515: iload 40
    //   6517: iconst_1
    //   6518: iadd
    //   6519: iload 41
    //   6521: iadd
    //   6522: iconst_1
    //   6523: isub
    //   6524: iload 17
    //   6526: iadd
    //   6527: daload
    //   6528: aload 5
    //   6530: iload 40
    //   6532: iconst_1
    //   6533: iadd
    //   6534: iconst_1
    //   6535: isub
    //   6536: iload 39
    //   6538: iconst_1
    //   6539: isub
    //   6540: iload 7
    //   6542: imul
    //   6543: iadd
    //   6544: iload 6
    //   6546: iadd
    //   6547: daload
    //   6548: dmul
    //   6549: dneg
    //   6550: dastore
    //   6551: iload 39
    //   6553: iconst_1
    //   6554: iadd
    //   6555: istore 39
    //   6557: iinc 77 -1
    //   6560: iload 77
    //   6562: ifgt -107 -> 6455
    //   6565: dconst_1
    //   6566: dstore 66
    //   6568: dload 44
    //   6570: dstore 64
    //   6572: iload 40
    //   6574: iconst_2
    //   6575: iadd
    //   6576: istore 38
    //   6578: iload 40
    //   6580: iconst_2
    //   6581: iadd
    //   6582: istore 35
    //   6584: iload 4
    //   6586: iload 40
    //   6588: iconst_2
    //   6589: iadd
    //   6590: isub
    //   6591: iconst_1
    //   6592: iadd
    //   6593: istore 77
    //   6595: goto +1305 -> 7900
    //   6598: iload 35
    //   6600: iload 38
    //   6602: if_icmplt +7 -> 6609
    //   6605: iconst_0
    //   6606: goto +4 -> 6610
    //   6609: iconst_1
    //   6610: ifeq +6 -> 6616
    //   6613: goto +1278 -> 7891
    //   6616: iload 35
    //   6618: istore 36
    //   6620: iload 35
    //   6622: istore 37
    //   6624: iload 35
    //   6626: iconst_1
    //   6627: iadd
    //   6628: istore 38
    //   6630: iload 35
    //   6632: iload 4
    //   6634: if_icmplt +7 -> 6641
    //   6637: iconst_0
    //   6638: goto +4 -> 6642
    //   6641: iconst_1
    //   6642: ifeq +48 -> 6690
    //   6645: aload 5
    //   6647: iload 35
    //   6649: iconst_1
    //   6650: iadd
    //   6651: iconst_1
    //   6652: isub
    //   6653: iload 35
    //   6655: iconst_1
    //   6656: isub
    //   6657: iload 7
    //   6659: imul
    //   6660: iadd
    //   6661: iload 6
    //   6663: iadd
    //   6664: daload
    //   6665: dconst_0
    //   6666: dcmpl
    //   6667: ifne +7 -> 6674
    //   6670: iconst_0
    //   6671: goto +4 -> 6675
    //   6674: iconst_1
    //   6675: ifeq +15 -> 6690
    //   6678: iload 35
    //   6680: iconst_1
    //   6681: iadd
    //   6682: istore 37
    //   6684: iload 35
    //   6686: iconst_2
    //   6687: iadd
    //   6688: istore 38
    //   6690: iload 36
    //   6692: iload 37
    //   6694: if_icmpeq +7 -> 6701
    //   6697: iconst_0
    //   6698: goto +4 -> 6702
    //   6701: iconst_1
    //   6702: ifeq +466 -> 7168
    //   6705: aload 16
    //   6707: iload 35
    //   6709: iconst_1
    //   6710: isub
    //   6711: iload 17
    //   6713: iadd
    //   6714: daload
    //   6715: dload 64
    //   6717: dcmpl
    //   6718: ifgt +7 -> 6725
    //   6721: iconst_0
    //   6722: goto +4 -> 6726
    //   6725: iconst_1
    //   6726: ifeq +66 -> 6792
    //   6729: dconst_1
    //   6730: dload 66
    //   6732: ddiv
    //   6733: dstore 50
    //   6735: iload 4
    //   6737: iload 40
    //   6739: isub
    //   6740: iconst_1
    //   6741: iadd
    //   6742: dload 50
    //   6744: aload 16
    //   6746: iload 40
    //   6748: iload 4
    //   6750: iadd
    //   6751: iconst_1
    //   6752: isub
    //   6753: iload 17
    //   6755: iadd
    //   6756: iconst_1
    //   6757: invokestatic 99	org/netlib/blas/Dscal:dscal	(ID[DII)V
    //   6760: iload 4
    //   6762: iload 40
    //   6764: isub
    //   6765: iconst_1
    //   6766: iadd
    //   6767: dload 50
    //   6769: aload 16
    //   6771: iload 40
    //   6773: iload 41
    //   6775: iadd
    //   6776: iconst_1
    //   6777: isub
    //   6778: iload 17
    //   6780: iadd
    //   6781: iconst_1
    //   6782: invokestatic 99	org/netlib/blas/Dscal:dscal	(ID[DII)V
    //   6785: dconst_1
    //   6786: dstore 66
    //   6788: dload 44
    //   6790: dstore 64
    //   6792: aload 16
    //   6794: iload 35
    //   6796: iload 4
    //   6798: iadd
    //   6799: iconst_1
    //   6800: isub
    //   6801: iload 17
    //   6803: iadd
    //   6804: aload 16
    //   6806: iload 35
    //   6808: iload 4
    //   6810: iadd
    //   6811: iconst_1
    //   6812: isub
    //   6813: iload 17
    //   6815: iadd
    //   6816: daload
    //   6817: iload 35
    //   6819: iload 40
    //   6821: isub
    //   6822: iconst_2
    //   6823: isub
    //   6824: aload 5
    //   6826: iload 40
    //   6828: iconst_2
    //   6829: iadd
    //   6830: iconst_1
    //   6831: isub
    //   6832: iload 35
    //   6834: iconst_1
    //   6835: isub
    //   6836: iload 7
    //   6838: imul
    //   6839: iadd
    //   6840: iload 6
    //   6842: iadd
    //   6843: iconst_1
    //   6844: aload 16
    //   6846: iload 40
    //   6848: iconst_2
    //   6849: iadd
    //   6850: iload 4
    //   6852: iadd
    //   6853: iconst_1
    //   6854: isub
    //   6855: iload 17
    //   6857: iadd
    //   6858: iconst_1
    //   6859: invokestatic 131	org/netlib/blas/Ddot:ddot	(I[DII[DII)D
    //   6862: dsub
    //   6863: dastore
    //   6864: aload 16
    //   6866: iload 35
    //   6868: iload 41
    //   6870: iadd
    //   6871: iconst_1
    //   6872: isub
    //   6873: iload 17
    //   6875: iadd
    //   6876: aload 16
    //   6878: iload 35
    //   6880: iload 41
    //   6882: iadd
    //   6883: iconst_1
    //   6884: isub
    //   6885: iload 17
    //   6887: iadd
    //   6888: daload
    //   6889: iload 35
    //   6891: iload 40
    //   6893: isub
    //   6894: iconst_2
    //   6895: isub
    //   6896: aload 5
    //   6898: iload 40
    //   6900: iconst_2
    //   6901: iadd
    //   6902: iconst_1
    //   6903: isub
    //   6904: iload 35
    //   6906: iconst_1
    //   6907: isub
    //   6908: iload 7
    //   6910: imul
    //   6911: iadd
    //   6912: iload 6
    //   6914: iadd
    //   6915: iconst_1
    //   6916: aload 16
    //   6918: iload 40
    //   6920: iconst_2
    //   6921: iadd
    //   6922: iload 41
    //   6924: iadd
    //   6925: iconst_1
    //   6926: isub
    //   6927: iload 17
    //   6929: iadd
    //   6930: iconst_1
    //   6931: invokestatic 131	org/netlib/blas/Ddot:ddot	(I[DII[DII)D
    //   6934: dsub
    //   6935: dastore
    //   6936: iconst_0
    //   6937: iconst_1
    //   6938: iconst_2
    //   6939: dload 56
    //   6941: dconst_1
    //   6942: aload 5
    //   6944: iload 35
    //   6946: iconst_1
    //   6947: isub
    //   6948: iload 35
    //   6950: iconst_1
    //   6951: isub
    //   6952: iload 7
    //   6954: imul
    //   6955: iadd
    //   6956: iload 6
    //   6958: iadd
    //   6959: iload 7
    //   6961: dconst_1
    //   6962: dconst_1
    //   6963: aload 16
    //   6965: iload 35
    //   6967: iload 4
    //   6969: iadd
    //   6970: iconst_1
    //   6971: isub
    //   6972: iload 17
    //   6974: iadd
    //   6975: iload 4
    //   6977: dload 70
    //   6979: dload 68
    //   6981: dneg
    //   6982: aload 74
    //   6984: iconst_0
    //   6985: iconst_2
    //   6986: aload 54
    //   6988: aload 72
    //   6990: aload 31
    //   6992: invokestatic 93	org/netlib/lapack/Dlaln2:dlaln2	(ZIIDD[DIIDD[DIIDD[DIILorg/netlib/util/doubleW;Lorg/netlib/util/doubleW;Lorg/netlib/util/intW;)V
    //   6995: aload 54
    //   6997: getfield 69	org/netlib/util/doubleW:val	D
    //   7000: dconst_1
    //   7001: dcmpl
    //   7002: ifne +7 -> 7009
    //   7005: iconst_0
    //   7006: goto +4 -> 7010
    //   7009: iconst_1
    //   7010: ifeq +59 -> 7069
    //   7013: iload 4
    //   7015: iload 40
    //   7017: isub
    //   7018: iconst_1
    //   7019: iadd
    //   7020: aload 54
    //   7022: getfield 69	org/netlib/util/doubleW:val	D
    //   7025: aload 16
    //   7027: iload 40
    //   7029: iload 4
    //   7031: iadd
    //   7032: iconst_1
    //   7033: isub
    //   7034: iload 17
    //   7036: iadd
    //   7037: iconst_1
    //   7038: invokestatic 99	org/netlib/blas/Dscal:dscal	(ID[DII)V
    //   7041: iload 4
    //   7043: iload 40
    //   7045: isub
    //   7046: iconst_1
    //   7047: iadd
    //   7048: aload 54
    //   7050: getfield 69	org/netlib/util/doubleW:val	D
    //   7053: aload 16
    //   7055: iload 40
    //   7057: iload 41
    //   7059: iadd
    //   7060: iconst_1
    //   7061: isub
    //   7062: iload 17
    //   7064: iadd
    //   7065: iconst_1
    //   7066: invokestatic 99	org/netlib/blas/Dscal:dscal	(ID[DII)V
    //   7069: aload 16
    //   7071: iload 35
    //   7073: iload 4
    //   7075: iadd
    //   7076: iconst_1
    //   7077: isub
    //   7078: iload 17
    //   7080: iadd
    //   7081: aload 74
    //   7083: iconst_1
    //   7084: iconst_1
    //   7085: isub
    //   7086: iconst_1
    //   7087: iconst_1
    //   7088: isub
    //   7089: iconst_2
    //   7090: imul
    //   7091: iadd
    //   7092: daload
    //   7093: dastore
    //   7094: aload 16
    //   7096: iload 35
    //   7098: iload 41
    //   7100: iadd
    //   7101: iconst_1
    //   7102: isub
    //   7103: iload 17
    //   7105: iadd
    //   7106: aload 74
    //   7108: iconst_1
    //   7109: iconst_1
    //   7110: isub
    //   7111: iconst_2
    //   7112: iconst_1
    //   7113: isub
    //   7114: iconst_2
    //   7115: imul
    //   7116: iadd
    //   7117: daload
    //   7118: dastore
    //   7119: aload 16
    //   7121: iload 35
    //   7123: iload 4
    //   7125: iadd
    //   7126: iconst_1
    //   7127: isub
    //   7128: iload 17
    //   7130: iadd
    //   7131: daload
    //   7132: invokestatic 81	java/lang/Math:abs	(D)D
    //   7135: aload 16
    //   7137: iload 35
    //   7139: iload 41
    //   7141: iadd
    //   7142: iconst_1
    //   7143: isub
    //   7144: iload 17
    //   7146: iadd
    //   7147: daload
    //   7148: invokestatic 81	java/lang/Math:abs	(D)D
    //   7151: dload 66
    //   7153: invokestatic 136	org/netlib/util/Util:max	(DDD)D
    //   7156: dstore 66
    //   7158: dload 44
    //   7160: dload 66
    //   7162: ddiv
    //   7163: dstore 64
    //   7165: goto +726 -> 7891
    //   7168: aload 16
    //   7170: iload 35
    //   7172: iconst_1
    //   7173: isub
    //   7174: iload 17
    //   7176: iadd
    //   7177: daload
    //   7178: aload 16
    //   7180: iload 35
    //   7182: iconst_1
    //   7183: iadd
    //   7184: iconst_1
    //   7185: isub
    //   7186: iload 17
    //   7188: iadd
    //   7189: daload
    //   7190: invokestatic 87	java/lang/Math:max	(DD)D
    //   7193: dstore 42
    //   7195: dload 42
    //   7197: dload 64
    //   7199: dcmpl
    //   7200: ifgt +7 -> 7207
    //   7203: iconst_0
    //   7204: goto +4 -> 7208
    //   7207: iconst_1
    //   7208: ifeq +66 -> 7274
    //   7211: dconst_1
    //   7212: dload 66
    //   7214: ddiv
    //   7215: dstore 50
    //   7217: iload 4
    //   7219: iload 40
    //   7221: isub
    //   7222: iconst_1
    //   7223: iadd
    //   7224: dload 50
    //   7226: aload 16
    //   7228: iload 40
    //   7230: iload 4
    //   7232: iadd
    //   7233: iconst_1
    //   7234: isub
    //   7235: iload 17
    //   7237: iadd
    //   7238: iconst_1
    //   7239: invokestatic 99	org/netlib/blas/Dscal:dscal	(ID[DII)V
    //   7242: iload 4
    //   7244: iload 40
    //   7246: isub
    //   7247: iconst_1
    //   7248: iadd
    //   7249: dload 50
    //   7251: aload 16
    //   7253: iload 40
    //   7255: iload 41
    //   7257: iadd
    //   7258: iconst_1
    //   7259: isub
    //   7260: iload 17
    //   7262: iadd
    //   7263: iconst_1
    //   7264: invokestatic 99	org/netlib/blas/Dscal:dscal	(ID[DII)V
    //   7267: dconst_1
    //   7268: dstore 66
    //   7270: dload 44
    //   7272: dstore 64
    //   7274: aload 16
    //   7276: iload 35
    //   7278: iload 4
    //   7280: iadd
    //   7281: iconst_1
    //   7282: isub
    //   7283: iload 17
    //   7285: iadd
    //   7286: aload 16
    //   7288: iload 35
    //   7290: iload 4
    //   7292: iadd
    //   7293: iconst_1
    //   7294: isub
    //   7295: iload 17
    //   7297: iadd
    //   7298: daload
    //   7299: iload 35
    //   7301: iload 40
    //   7303: isub
    //   7304: iconst_2
    //   7305: isub
    //   7306: aload 5
    //   7308: iload 40
    //   7310: iconst_2
    //   7311: iadd
    //   7312: iconst_1
    //   7313: isub
    //   7314: iload 35
    //   7316: iconst_1
    //   7317: isub
    //   7318: iload 7
    //   7320: imul
    //   7321: iadd
    //   7322: iload 6
    //   7324: iadd
    //   7325: iconst_1
    //   7326: aload 16
    //   7328: iload 40
    //   7330: iconst_2
    //   7331: iadd
    //   7332: iload 4
    //   7334: iadd
    //   7335: iconst_1
    //   7336: isub
    //   7337: iload 17
    //   7339: iadd
    //   7340: iconst_1
    //   7341: invokestatic 131	org/netlib/blas/Ddot:ddot	(I[DII[DII)D
    //   7344: dsub
    //   7345: dastore
    //   7346: aload 16
    //   7348: iload 35
    //   7350: iload 41
    //   7352: iadd
    //   7353: iconst_1
    //   7354: isub
    //   7355: iload 17
    //   7357: iadd
    //   7358: aload 16
    //   7360: iload 35
    //   7362: iload 41
    //   7364: iadd
    //   7365: iconst_1
    //   7366: isub
    //   7367: iload 17
    //   7369: iadd
    //   7370: daload
    //   7371: iload 35
    //   7373: iload 40
    //   7375: isub
    //   7376: iconst_2
    //   7377: isub
    //   7378: aload 5
    //   7380: iload 40
    //   7382: iconst_2
    //   7383: iadd
    //   7384: iconst_1
    //   7385: isub
    //   7386: iload 35
    //   7388: iconst_1
    //   7389: isub
    //   7390: iload 7
    //   7392: imul
    //   7393: iadd
    //   7394: iload 6
    //   7396: iadd
    //   7397: iconst_1
    //   7398: aload 16
    //   7400: iload 40
    //   7402: iconst_2
    //   7403: iadd
    //   7404: iload 41
    //   7406: iadd
    //   7407: iconst_1
    //   7408: isub
    //   7409: iload 17
    //   7411: iadd
    //   7412: iconst_1
    //   7413: invokestatic 131	org/netlib/blas/Ddot:ddot	(I[DII[DII)D
    //   7416: dsub
    //   7417: dastore
    //   7418: aload 16
    //   7420: iload 35
    //   7422: iconst_1
    //   7423: iadd
    //   7424: iload 4
    //   7426: iadd
    //   7427: iconst_1
    //   7428: isub
    //   7429: iload 17
    //   7431: iadd
    //   7432: aload 16
    //   7434: iload 35
    //   7436: iconst_1
    //   7437: iadd
    //   7438: iload 4
    //   7440: iadd
    //   7441: iconst_1
    //   7442: isub
    //   7443: iload 17
    //   7445: iadd
    //   7446: daload
    //   7447: iload 35
    //   7449: iload 40
    //   7451: isub
    //   7452: iconst_2
    //   7453: isub
    //   7454: aload 5
    //   7456: iload 40
    //   7458: iconst_2
    //   7459: iadd
    //   7460: iconst_1
    //   7461: isub
    //   7462: iload 35
    //   7464: iconst_1
    //   7465: iadd
    //   7466: iconst_1
    //   7467: isub
    //   7468: iload 7
    //   7470: imul
    //   7471: iadd
    //   7472: iload 6
    //   7474: iadd
    //   7475: iconst_1
    //   7476: aload 16
    //   7478: iload 40
    //   7480: iconst_2
    //   7481: iadd
    //   7482: iload 4
    //   7484: iadd
    //   7485: iconst_1
    //   7486: isub
    //   7487: iload 17
    //   7489: iadd
    //   7490: iconst_1
    //   7491: invokestatic 131	org/netlib/blas/Ddot:ddot	(I[DII[DII)D
    //   7494: dsub
    //   7495: dastore
    //   7496: aload 16
    //   7498: iload 35
    //   7500: iconst_1
    //   7501: iadd
    //   7502: iload 41
    //   7504: iadd
    //   7505: iconst_1
    //   7506: isub
    //   7507: iload 17
    //   7509: iadd
    //   7510: aload 16
    //   7512: iload 35
    //   7514: iconst_1
    //   7515: iadd
    //   7516: iload 41
    //   7518: iadd
    //   7519: iconst_1
    //   7520: isub
    //   7521: iload 17
    //   7523: iadd
    //   7524: daload
    //   7525: iload 35
    //   7527: iload 40
    //   7529: isub
    //   7530: iconst_2
    //   7531: isub
    //   7532: aload 5
    //   7534: iload 40
    //   7536: iconst_2
    //   7537: iadd
    //   7538: iconst_1
    //   7539: isub
    //   7540: iload 35
    //   7542: iconst_1
    //   7543: iadd
    //   7544: iconst_1
    //   7545: isub
    //   7546: iload 7
    //   7548: imul
    //   7549: iadd
    //   7550: iload 6
    //   7552: iadd
    //   7553: iconst_1
    //   7554: aload 16
    //   7556: iload 40
    //   7558: iconst_2
    //   7559: iadd
    //   7560: iload 41
    //   7562: iadd
    //   7563: iconst_1
    //   7564: isub
    //   7565: iload 17
    //   7567: iadd
    //   7568: iconst_1
    //   7569: invokestatic 131	org/netlib/blas/Ddot:ddot	(I[DII[DII)D
    //   7572: dsub
    //   7573: dastore
    //   7574: iconst_1
    //   7575: iconst_2
    //   7576: iconst_2
    //   7577: dload 56
    //   7579: dconst_1
    //   7580: aload 5
    //   7582: iload 35
    //   7584: iconst_1
    //   7585: isub
    //   7586: iload 35
    //   7588: iconst_1
    //   7589: isub
    //   7590: iload 7
    //   7592: imul
    //   7593: iadd
    //   7594: iload 6
    //   7596: iadd
    //   7597: iload 7
    //   7599: dconst_1
    //   7600: dconst_1
    //   7601: aload 16
    //   7603: iload 35
    //   7605: iload 4
    //   7607: iadd
    //   7608: iconst_1
    //   7609: isub
    //   7610: iload 17
    //   7612: iadd
    //   7613: iload 4
    //   7615: dload 70
    //   7617: dload 68
    //   7619: dneg
    //   7620: aload 74
    //   7622: iconst_0
    //   7623: iconst_2
    //   7624: aload 54
    //   7626: aload 72
    //   7628: aload 31
    //   7630: invokestatic 93	org/netlib/lapack/Dlaln2:dlaln2	(ZIIDD[DIIDD[DIIDD[DIILorg/netlib/util/doubleW;Lorg/netlib/util/doubleW;Lorg/netlib/util/intW;)V
    //   7633: aload 54
    //   7635: getfield 69	org/netlib/util/doubleW:val	D
    //   7638: dconst_1
    //   7639: dcmpl
    //   7640: ifne +7 -> 7647
    //   7643: iconst_0
    //   7644: goto +4 -> 7648
    //   7647: iconst_1
    //   7648: ifeq +59 -> 7707
    //   7651: iload 4
    //   7653: iload 40
    //   7655: isub
    //   7656: iconst_1
    //   7657: iadd
    //   7658: aload 54
    //   7660: getfield 69	org/netlib/util/doubleW:val	D
    //   7663: aload 16
    //   7665: iload 40
    //   7667: iload 4
    //   7669: iadd
    //   7670: iconst_1
    //   7671: isub
    //   7672: iload 17
    //   7674: iadd
    //   7675: iconst_1
    //   7676: invokestatic 99	org/netlib/blas/Dscal:dscal	(ID[DII)V
    //   7679: iload 4
    //   7681: iload 40
    //   7683: isub
    //   7684: iconst_1
    //   7685: iadd
    //   7686: aload 54
    //   7688: getfield 69	org/netlib/util/doubleW:val	D
    //   7691: aload 16
    //   7693: iload 40
    //   7695: iload 41
    //   7697: iadd
    //   7698: iconst_1
    //   7699: isub
    //   7700: iload 17
    //   7702: iadd
    //   7703: iconst_1
    //   7704: invokestatic 99	org/netlib/blas/Dscal:dscal	(ID[DII)V
    //   7707: aload 16
    //   7709: iload 35
    //   7711: iload 4
    //   7713: iadd
    //   7714: iconst_1
    //   7715: isub
    //   7716: iload 17
    //   7718: iadd
    //   7719: aload 74
    //   7721: iconst_1
    //   7722: iconst_1
    //   7723: isub
    //   7724: iconst_1
    //   7725: iconst_1
    //   7726: isub
    //   7727: iconst_2
    //   7728: imul
    //   7729: iadd
    //   7730: daload
    //   7731: dastore
    //   7732: aload 16
    //   7734: iload 35
    //   7736: iload 41
    //   7738: iadd
    //   7739: iconst_1
    //   7740: isub
    //   7741: iload 17
    //   7743: iadd
    //   7744: aload 74
    //   7746: iconst_1
    //   7747: iconst_1
    //   7748: isub
    //   7749: iconst_2
    //   7750: iconst_1
    //   7751: isub
    //   7752: iconst_2
    //   7753: imul
    //   7754: iadd
    //   7755: daload
    //   7756: dastore
    //   7757: aload 16
    //   7759: iload 35
    //   7761: iconst_1
    //   7762: iadd
    //   7763: iload 4
    //   7765: iadd
    //   7766: iconst_1
    //   7767: isub
    //   7768: iload 17
    //   7770: iadd
    //   7771: aload 74
    //   7773: iconst_2
    //   7774: iconst_1
    //   7775: isub
    //   7776: iconst_1
    //   7777: iconst_1
    //   7778: isub
    //   7779: iconst_2
    //   7780: imul
    //   7781: iadd
    //   7782: daload
    //   7783: dastore
    //   7784: aload 16
    //   7786: iload 35
    //   7788: iconst_1
    //   7789: iadd
    //   7790: iload 41
    //   7792: iadd
    //   7793: iconst_1
    //   7794: isub
    //   7795: iload 17
    //   7797: iadd
    //   7798: aload 74
    //   7800: iconst_2
    //   7801: iconst_1
    //   7802: isub
    //   7803: iconst_2
    //   7804: iconst_1
    //   7805: isub
    //   7806: iconst_2
    //   7807: imul
    //   7808: iadd
    //   7809: daload
    //   7810: dastore
    //   7811: aload 74
    //   7813: iconst_1
    //   7814: iconst_1
    //   7815: isub
    //   7816: iconst_1
    //   7817: iconst_1
    //   7818: isub
    //   7819: iconst_2
    //   7820: imul
    //   7821: iadd
    //   7822: daload
    //   7823: invokestatic 81	java/lang/Math:abs	(D)D
    //   7826: aload 74
    //   7828: iconst_1
    //   7829: iconst_1
    //   7830: isub
    //   7831: iconst_2
    //   7832: iconst_1
    //   7833: isub
    //   7834: iconst_2
    //   7835: imul
    //   7836: iadd
    //   7837: daload
    //   7838: invokestatic 81	java/lang/Math:abs	(D)D
    //   7841: aload 74
    //   7843: iconst_2
    //   7844: iconst_1
    //   7845: isub
    //   7846: iconst_1
    //   7847: iconst_1
    //   7848: isub
    //   7849: iconst_2
    //   7850: imul
    //   7851: iadd
    //   7852: daload
    //   7853: invokestatic 81	java/lang/Math:abs	(D)D
    //   7856: invokestatic 136	org/netlib/util/Util:max	(DDD)D
    //   7859: aload 74
    //   7861: iconst_2
    //   7862: iconst_1
    //   7863: isub
    //   7864: iconst_2
    //   7865: iconst_1
    //   7866: isub
    //   7867: iconst_2
    //   7868: imul
    //   7869: iadd
    //   7870: daload
    //   7871: invokestatic 81	java/lang/Math:abs	(D)D
    //   7874: invokestatic 87	java/lang/Math:max	(DD)D
    //   7877: dload 66
    //   7879: invokestatic 87	java/lang/Math:max	(DD)D
    //   7882: dstore 66
    //   7884: dload 44
    //   7886: dload 66
    //   7888: ddiv
    //   7889: dstore 64
    //   7891: iload 35
    //   7893: iconst_1
    //   7894: iadd
    //   7895: istore 35
    //   7897: iinc 77 -1
    //   7900: iload 77
    //   7902: ifgt -1304 -> 6598
    //   7905: iload 26
    //   7907: iconst_1
    //   7908: ixor
    //   7909: ifeq +313 -> 8222
    //   7912: iload 4
    //   7914: iload 40
    //   7916: isub
    //   7917: iconst_1
    //   7918: iadd
    //   7919: aload 16
    //   7921: iload 40
    //   7923: iload 4
    //   7925: iadd
    //   7926: iconst_1
    //   7927: isub
    //   7928: iload 17
    //   7930: iadd
    //   7931: iconst_1
    //   7932: aload 8
    //   7934: iload 40
    //   7936: iconst_1
    //   7937: isub
    //   7938: iload 34
    //   7940: iconst_1
    //   7941: isub
    //   7942: iload 10
    //   7944: imul
    //   7945: iadd
    //   7946: iload 9
    //   7948: iadd
    //   7949: iconst_1
    //   7950: invokestatic 111	org/netlib/blas/Dcopy:dcopy	(I[DII[DII)V
    //   7953: iload 4
    //   7955: iload 40
    //   7957: isub
    //   7958: iconst_1
    //   7959: iadd
    //   7960: aload 16
    //   7962: iload 40
    //   7964: iload 41
    //   7966: iadd
    //   7967: iconst_1
    //   7968: isub
    //   7969: iload 17
    //   7971: iadd
    //   7972: iconst_1
    //   7973: aload 8
    //   7975: iload 40
    //   7977: iconst_1
    //   7978: isub
    //   7979: iload 34
    //   7981: iconst_1
    //   7982: iadd
    //   7983: iconst_1
    //   7984: isub
    //   7985: iload 10
    //   7987: imul
    //   7988: iadd
    //   7989: iload 9
    //   7991: iadd
    //   7992: iconst_1
    //   7993: invokestatic 111	org/netlib/blas/Dcopy:dcopy	(I[DII[DII)V
    //   7996: dconst_0
    //   7997: dstore 46
    //   7999: iload 40
    //   8001: istore 39
    //   8003: iload 4
    //   8005: iload 40
    //   8007: isub
    //   8008: iconst_1
    //   8009: iadd
    //   8010: istore 77
    //   8012: goto +64 -> 8076
    //   8015: dload 46
    //   8017: aload 8
    //   8019: iload 39
    //   8021: iconst_1
    //   8022: isub
    //   8023: iload 34
    //   8025: iconst_1
    //   8026: isub
    //   8027: iload 10
    //   8029: imul
    //   8030: iadd
    //   8031: iload 9
    //   8033: iadd
    //   8034: daload
    //   8035: invokestatic 81	java/lang/Math:abs	(D)D
    //   8038: aload 8
    //   8040: iload 39
    //   8042: iconst_1
    //   8043: isub
    //   8044: iload 34
    //   8046: iconst_1
    //   8047: iadd
    //   8048: iconst_1
    //   8049: isub
    //   8050: iload 10
    //   8052: imul
    //   8053: iadd
    //   8054: iload 9
    //   8056: iadd
    //   8057: daload
    //   8058: invokestatic 81	java/lang/Math:abs	(D)D
    //   8061: dadd
    //   8062: invokestatic 87	java/lang/Math:max	(DD)D
    //   8065: dstore 46
    //   8067: iload 39
    //   8069: iconst_1
    //   8070: iadd
    //   8071: istore 39
    //   8073: iinc 77 -1
    //   8076: iload 77
    //   8078: ifgt -63 -> 8015
    //   8081: dconst_1
    //   8082: dload 46
    //   8084: ddiv
    //   8085: dstore 52
    //   8087: iload 4
    //   8089: iload 40
    //   8091: isub
    //   8092: iconst_1
    //   8093: iadd
    //   8094: dload 52
    //   8096: aload 8
    //   8098: iload 40
    //   8100: iconst_1
    //   8101: isub
    //   8102: iload 34
    //   8104: iconst_1
    //   8105: isub
    //   8106: iload 10
    //   8108: imul
    //   8109: iadd
    //   8110: iload 9
    //   8112: iadd
    //   8113: iconst_1
    //   8114: invokestatic 99	org/netlib/blas/Dscal:dscal	(ID[DII)V
    //   8117: iload 4
    //   8119: iload 40
    //   8121: isub
    //   8122: iconst_1
    //   8123: iadd
    //   8124: dload 52
    //   8126: aload 8
    //   8128: iload 40
    //   8130: iconst_1
    //   8131: isub
    //   8132: iload 34
    //   8134: iconst_1
    //   8135: iadd
    //   8136: iconst_1
    //   8137: isub
    //   8138: iload 10
    //   8140: imul
    //   8141: iadd
    //   8142: iload 9
    //   8144: iadd
    //   8145: iconst_1
    //   8146: invokestatic 99	org/netlib/blas/Dscal:dscal	(ID[DII)V
    //   8149: iconst_1
    //   8150: istore 39
    //   8152: iload 40
    //   8154: iconst_1
    //   8155: isub
    //   8156: iconst_1
    //   8157: isub
    //   8158: iconst_1
    //   8159: iadd
    //   8160: istore 77
    //   8162: goto +52 -> 8214
    //   8165: aload 8
    //   8167: iload 39
    //   8169: iconst_1
    //   8170: isub
    //   8171: iload 34
    //   8173: iconst_1
    //   8174: isub
    //   8175: iload 10
    //   8177: imul
    //   8178: iadd
    //   8179: iload 9
    //   8181: iadd
    //   8182: dconst_0
    //   8183: dastore
    //   8184: aload 8
    //   8186: iload 39
    //   8188: iconst_1
    //   8189: isub
    //   8190: iload 34
    //   8192: iconst_1
    //   8193: iadd
    //   8194: iconst_1
    //   8195: isub
    //   8196: iload 10
    //   8198: imul
    //   8199: iadd
    //   8200: iload 9
    //   8202: iadd
    //   8203: dconst_0
    //   8204: dastore
    //   8205: iload 39
    //   8207: iconst_1
    //   8208: iadd
    //   8209: istore 39
    //   8211: iinc 77 -1
    //   8214: iload 77
    //   8216: ifgt -51 -> 8165
    //   8219: goto +400 -> 8619
    //   8222: iload 40
    //   8224: iload 4
    //   8226: iconst_1
    //   8227: isub
    //   8228: if_icmplt +7 -> 8235
    //   8231: iconst_0
    //   8232: goto +4 -> 8236
    //   8235: iconst_1
    //   8236: ifeq +170 -> 8406
    //   8239: ldc 119
    //   8241: iload 4
    //   8243: iload 4
    //   8245: iload 40
    //   8247: isub
    //   8248: iconst_1
    //   8249: isub
    //   8250: dconst_1
    //   8251: aload 8
    //   8253: iconst_1
    //   8254: iconst_1
    //   8255: isub
    //   8256: iload 40
    //   8258: iconst_2
    //   8259: iadd
    //   8260: iconst_1
    //   8261: isub
    //   8262: iload 10
    //   8264: imul
    //   8265: iadd
    //   8266: iload 9
    //   8268: iadd
    //   8269: iload 10
    //   8271: aload 16
    //   8273: iload 40
    //   8275: iconst_2
    //   8276: iadd
    //   8277: iload 4
    //   8279: iadd
    //   8280: iconst_1
    //   8281: isub
    //   8282: iload 17
    //   8284: iadd
    //   8285: iconst_1
    //   8286: aload 16
    //   8288: iload 40
    //   8290: iload 4
    //   8292: iadd
    //   8293: iconst_1
    //   8294: isub
    //   8295: iload 17
    //   8297: iadd
    //   8298: daload
    //   8299: aload 8
    //   8301: iconst_1
    //   8302: iconst_1
    //   8303: isub
    //   8304: iload 40
    //   8306: iconst_1
    //   8307: isub
    //   8308: iload 10
    //   8310: imul
    //   8311: iadd
    //   8312: iload 9
    //   8314: iadd
    //   8315: iconst_1
    //   8316: invokestatic 125	org/netlib/blas/Dgemv:dgemv	(Ljava/lang/String;IID[DII[DIID[DII)V
    //   8319: ldc 119
    //   8321: iload 4
    //   8323: iload 4
    //   8325: iload 40
    //   8327: isub
    //   8328: iconst_1
    //   8329: isub
    //   8330: dconst_1
    //   8331: aload 8
    //   8333: iconst_1
    //   8334: iconst_1
    //   8335: isub
    //   8336: iload 40
    //   8338: iconst_2
    //   8339: iadd
    //   8340: iconst_1
    //   8341: isub
    //   8342: iload 10
    //   8344: imul
    //   8345: iadd
    //   8346: iload 9
    //   8348: iadd
    //   8349: iload 10
    //   8351: aload 16
    //   8353: iload 40
    //   8355: iconst_2
    //   8356: iadd
    //   8357: iload 41
    //   8359: iadd
    //   8360: iconst_1
    //   8361: isub
    //   8362: iload 17
    //   8364: iadd
    //   8365: iconst_1
    //   8366: aload 16
    //   8368: iload 40
    //   8370: iconst_1
    //   8371: iadd
    //   8372: iload 41
    //   8374: iadd
    //   8375: iconst_1
    //   8376: isub
    //   8377: iload 17
    //   8379: iadd
    //   8380: daload
    //   8381: aload 8
    //   8383: iconst_1
    //   8384: iconst_1
    //   8385: isub
    //   8386: iload 40
    //   8388: iconst_1
    //   8389: iadd
    //   8390: iconst_1
    //   8391: isub
    //   8392: iload 10
    //   8394: imul
    //   8395: iadd
    //   8396: iload 9
    //   8398: iadd
    //   8399: iconst_1
    //   8400: invokestatic 125	org/netlib/blas/Dgemv:dgemv	(Ljava/lang/String;IID[DII[DIID[DII)V
    //   8403: goto +77 -> 8480
    //   8406: iload 4
    //   8408: aload 16
    //   8410: iload 40
    //   8412: iload 4
    //   8414: iadd
    //   8415: iconst_1
    //   8416: isub
    //   8417: iload 17
    //   8419: iadd
    //   8420: daload
    //   8421: aload 8
    //   8423: iconst_1
    //   8424: iconst_1
    //   8425: isub
    //   8426: iload 40
    //   8428: iconst_1
    //   8429: isub
    //   8430: iload 10
    //   8432: imul
    //   8433: iadd
    //   8434: iload 9
    //   8436: iadd
    //   8437: iconst_1
    //   8438: invokestatic 99	org/netlib/blas/Dscal:dscal	(ID[DII)V
    //   8441: iload 4
    //   8443: aload 16
    //   8445: iload 40
    //   8447: iconst_1
    //   8448: iadd
    //   8449: iload 41
    //   8451: iadd
    //   8452: iconst_1
    //   8453: isub
    //   8454: iload 17
    //   8456: iadd
    //   8457: daload
    //   8458: aload 8
    //   8460: iconst_1
    //   8461: iconst_1
    //   8462: isub
    //   8463: iload 40
    //   8465: iconst_1
    //   8466: iadd
    //   8467: iconst_1
    //   8468: isub
    //   8469: iload 10
    //   8471: imul
    //   8472: iadd
    //   8473: iload 9
    //   8475: iadd
    //   8476: iconst_1
    //   8477: invokestatic 99	org/netlib/blas/Dscal:dscal	(ID[DII)V
    //   8480: dconst_0
    //   8481: dstore 46
    //   8483: iconst_1
    //   8484: istore 39
    //   8486: iload 4
    //   8488: iconst_1
    //   8489: isub
    //   8490: iconst_1
    //   8491: iadd
    //   8492: istore 77
    //   8494: goto +64 -> 8558
    //   8497: dload 46
    //   8499: aload 8
    //   8501: iload 39
    //   8503: iconst_1
    //   8504: isub
    //   8505: iload 40
    //   8507: iconst_1
    //   8508: isub
    //   8509: iload 10
    //   8511: imul
    //   8512: iadd
    //   8513: iload 9
    //   8515: iadd
    //   8516: daload
    //   8517: invokestatic 81	java/lang/Math:abs	(D)D
    //   8520: aload 8
    //   8522: iload 39
    //   8524: iconst_1
    //   8525: isub
    //   8526: iload 40
    //   8528: iconst_1
    //   8529: iadd
    //   8530: iconst_1
    //   8531: isub
    //   8532: iload 10
    //   8534: imul
    //   8535: iadd
    //   8536: iload 9
    //   8538: iadd
    //   8539: daload
    //   8540: invokestatic 81	java/lang/Math:abs	(D)D
    //   8543: dadd
    //   8544: invokestatic 87	java/lang/Math:max	(DD)D
    //   8547: dstore 46
    //   8549: iload 39
    //   8551: iconst_1
    //   8552: iadd
    //   8553: istore 39
    //   8555: iinc 77 -1
    //   8558: iload 77
    //   8560: ifgt -63 -> 8497
    //   8563: dconst_1
    //   8564: dload 46
    //   8566: ddiv
    //   8567: dstore 52
    //   8569: iload 4
    //   8571: dload 52
    //   8573: aload 8
    //   8575: iconst_1
    //   8576: iconst_1
    //   8577: isub
    //   8578: iload 40
    //   8580: iconst_1
    //   8581: isub
    //   8582: iload 10
    //   8584: imul
    //   8585: iadd
    //   8586: iload 9
    //   8588: iadd
    //   8589: iconst_1
    //   8590: invokestatic 99	org/netlib/blas/Dscal:dscal	(ID[DII)V
    //   8593: iload 4
    //   8595: dload 52
    //   8597: aload 8
    //   8599: iconst_1
    //   8600: iconst_1
    //   8601: isub
    //   8602: iload 40
    //   8604: iconst_1
    //   8605: iadd
    //   8606: iconst_1
    //   8607: isub
    //   8608: iload 10
    //   8610: imul
    //   8611: iadd
    //   8612: iload 9
    //   8614: iadd
    //   8615: iconst_1
    //   8616: invokestatic 99	org/netlib/blas/Dscal:dscal	(ID[DII)V
    //   8619: iload 34
    //   8621: iconst_1
    //   8622: iadd
    //   8623: istore 34
    //   8625: iload 33
    //   8627: iconst_0
    //   8628: if_icmpne +7 -> 8635
    //   8631: iconst_0
    //   8632: goto +4 -> 8636
    //   8635: iconst_1
    //   8636: ifeq +9 -> 8645
    //   8639: iload 34
    //   8641: iconst_1
    //   8642: iadd
    //   8643: istore 34
    //   8645: iload 33
    //   8647: iconst_m1
    //   8648: if_icmpeq +7 -> 8655
    //   8651: iconst_0
    //   8652: goto +4 -> 8656
    //   8655: iconst_1
    //   8656: ifeq +6 -> 8662
    //   8659: iconst_0
    //   8660: istore 33
    //   8662: iload 33
    //   8664: iconst_1
    //   8665: if_icmpeq +7 -> 8672
    //   8668: iconst_0
    //   8669: goto +4 -> 8673
    //   8672: iconst_1
    //   8673: ifeq +6 -> 8679
    //   8676: iconst_m1
    //   8677: istore 33
    //   8679: iload 40
    //   8681: iconst_1
    //   8682: iadd
    //   8683: istore 40
    //   8685: iinc 76 -1
    //   8688: iload 76
    //   8690: ifgt -3995 -> 4695
    //   8693: return
    // Local variable table:
    //   start	length	slot	name	signature
    //   0	8694	0	paramString1	String
    //   0	8694	1	paramString2	String
    //   0	8694	2	paramArrayOfBoolean	boolean[]
    //   0	8694	3	paramInt1	int
    //   0	8694	4	paramInt2	int
    //   0	8694	5	paramArrayOfDouble1	double[]
    //   0	8694	6	paramInt3	int
    //   0	8694	7	paramInt4	int
    //   0	8694	8	paramArrayOfDouble2	double[]
    //   0	8694	9	paramInt5	int
    //   0	8694	10	paramInt6	int
    //   0	8694	11	paramArrayOfDouble3	double[]
    //   0	8694	12	paramInt7	int
    //   0	8694	13	paramInt8	int
    //   0	8694	14	paramInt9	int
    //   0	8694	15	paramintW1	org.netlib.util.intW
    //   0	8694	16	paramArrayOfDouble4	double[]
    //   0	8694	17	paramInt10	int
    //   0	8694	18	paramintW2	org.netlib.util.intW
    //   1	261	23	bool1	boolean
    //   4	182	24	bool2	boolean
    //   7	4664	25	i	int
    //   10	7899	26	bool3	boolean
    //   13	589	27	j	int
    //   16	946	28	k	int
    //   19	4751	29	bool4	boolean
    //   22	910	30	m	int
    //   32	7597	31	localintW	org.netlib.util.intW
    //   35	6159	32	n	int
    //   38	8640	33	i1	int
    //   41	8603	34	i2	int
    //   44	7852	35	i3	int
    //   47	6648	36	i4	int
    //   50	6645	37	i5	int
    //   53	6636	38	i6	int
    //   56	8498	39	i7	int
    //   59	8625	40	i8	int
    //   62	8390	41	i9	int
    //   65	7131	42	d1	double
    //   68	7817	44	d2	double
    //   71	8494	46	d3	double
    //   81	719	48	localdoubleW1	org.netlib.util.doubleW
    //   84	7166	50	d4	double
    //   87	8509	52	d5	double
    //   97	7590	54	localdoubleW2	org.netlib.util.doubleW
    //   100	7478	56	d6	double
    //   103	4794	58	d7	double
    //   106	4777	60	d8	double
    //   116	696	62	localdoubleW3	org.netlib.util.doubleW
    //   119	7771	64	d9	double
    //   122	7765	66	d10	double
    //   125	7493	68	d11	double
    //   128	7488	70	d12	double
    //   138	7489	72	localdoubleW4	org.netlib.util.doubleW
    //   145	7715	74	arrayOfDouble	double[]
    //   501	8188	76	i10	int
    //   880	7679	77	i11	int
  }
}


/* Location:              /Users/assaad/Downloads/arpack_combined_all/!/org/netlib/lapack/Dtrevc.class
 * Java compiler version: 1 (45.3)
 * JD-Core Version:       0.7.1
 */