package org.netlib.lapack;

import java.lang.reflect.InvocationTargetException;
import java.lang.reflect.Method;

public final class Sggesx
{
  /* Error */
  public static void sggesx(String paramString1, String paramString2, String paramString3, Object paramObject, String paramString4, int paramInt1, float[] paramArrayOfFloat1, int paramInt2, int paramInt3, float[] paramArrayOfFloat2, int paramInt4, int paramInt5, org.netlib.util.intW paramintW1, float[] paramArrayOfFloat3, int paramInt6, float[] paramArrayOfFloat4, int paramInt7, float[] paramArrayOfFloat5, int paramInt8, float[] paramArrayOfFloat6, int paramInt9, int paramInt10, float[] paramArrayOfFloat7, int paramInt11, int paramInt12, float[] paramArrayOfFloat8, int paramInt13, float[] paramArrayOfFloat9, int paramInt14, float[] paramArrayOfFloat10, int paramInt15, int paramInt16, int[] paramArrayOfInt, int paramInt17, int paramInt18, boolean[] paramArrayOfBoolean, int paramInt19, org.netlib.util.intW paramintW2)
  {
    // Byte code:
    //   0: iconst_0
    //   1: istore 40
    //   3: iconst_0
    //   4: istore 41
    //   6: iconst_0
    //   7: istore 42
    //   9: iconst_0
    //   10: istore 43
    //   12: iconst_0
    //   13: istore 44
    //   15: iconst_0
    //   16: istore 45
    //   18: iconst_0
    //   19: istore 46
    //   21: iconst_0
    //   22: istore 47
    //   24: iconst_0
    //   25: istore 48
    //   27: iconst_0
    //   28: istore 49
    //   30: iconst_0
    //   31: istore 50
    //   33: iconst_0
    //   34: istore 51
    //   36: iconst_0
    //   37: istore 52
    //   39: iconst_0
    //   40: istore 53
    //   42: iconst_0
    //   43: istore 54
    //   45: new 16	org/netlib/util/intW
    //   48: dup
    //   49: iconst_0
    //   50: invokespecial 19	org/netlib/util/intW:<init>	(I)V
    //   53: astore 55
    //   55: new 16	org/netlib/util/intW
    //   58: dup
    //   59: iconst_0
    //   60: invokespecial 19	org/netlib/util/intW:<init>	(I)V
    //   63: astore 56
    //   65: iconst_0
    //   66: istore 57
    //   68: iconst_0
    //   69: istore 58
    //   71: iconst_0
    //   72: istore 59
    //   74: iconst_0
    //   75: istore 60
    //   77: new 16	org/netlib/util/intW
    //   80: dup
    //   81: iconst_0
    //   82: invokespecial 19	org/netlib/util/intW:<init>	(I)V
    //   85: astore 61
    //   87: iconst_0
    //   88: istore 62
    //   90: iconst_0
    //   91: istore 63
    //   93: iconst_0
    //   94: istore 64
    //   96: iconst_0
    //   97: istore 65
    //   99: iconst_0
    //   100: istore 66
    //   102: iconst_0
    //   103: istore 67
    //   105: iconst_0
    //   106: istore 68
    //   108: iconst_0
    //   109: istore 69
    //   111: iconst_0
    //   112: istore 70
    //   114: fconst_0
    //   115: fstore 71
    //   117: fconst_0
    //   118: fstore 72
    //   120: fconst_0
    //   121: fstore 73
    //   123: fconst_0
    //   124: fstore 74
    //   126: fconst_0
    //   127: fstore 75
    //   129: fconst_0
    //   130: fstore 76
    //   132: new 21	org/netlib/util/floatW
    //   135: dup
    //   136: fconst_0
    //   137: invokespecial 24	org/netlib/util/floatW:<init>	(F)V
    //   140: astore 77
    //   142: new 21	org/netlib/util/floatW
    //   145: dup
    //   146: fconst_0
    //   147: invokespecial 24	org/netlib/util/floatW:<init>	(F)V
    //   150: astore 78
    //   152: new 21	org/netlib/util/floatW
    //   155: dup
    //   156: fconst_0
    //   157: invokespecial 24	org/netlib/util/floatW:<init>	(F)V
    //   160: astore 79
    //   162: new 21	org/netlib/util/floatW
    //   165: dup
    //   166: fconst_0
    //   167: invokespecial 24	org/netlib/util/floatW:<init>	(F)V
    //   170: astore 80
    //   172: fconst_0
    //   173: fstore 81
    //   175: iconst_2
    //   176: newarray <illegal type>
    //   178: astore 82
    //   180: aload_3
    //   181: invokevirtual 28	java/lang/Object:getClass	()Ljava/lang/Class;
    //   184: invokevirtual 34	java/lang/Class:getDeclaredMethods	()[Ljava/lang/reflect/Method;
    //   187: iconst_0
    //   188: aaload
    //   189: astore 83
    //   191: aload_0
    //   192: ldc 36
    //   194: invokestatic 42	org/netlib/lapack/Lsame:lsame	(Ljava/lang/String;Ljava/lang/String;)Z
    //   197: ifeq +12 -> 209
    //   200: iconst_1
    //   201: istore 58
    //   203: iconst_0
    //   204: istore 43
    //   206: goto +27 -> 233
    //   209: aload_0
    //   210: ldc 44
    //   212: invokestatic 42	org/netlib/lapack/Lsame:lsame	(Ljava/lang/String;Ljava/lang/String;)Z
    //   215: ifeq +12 -> 227
    //   218: iconst_2
    //   219: istore 58
    //   221: iconst_1
    //   222: istore 43
    //   224: goto +9 -> 233
    //   227: iconst_m1
    //   228: istore 58
    //   230: iconst_0
    //   231: istore 43
    //   233: aload_1
    //   234: ldc 36
    //   236: invokestatic 42	org/netlib/lapack/Lsame:lsame	(Ljava/lang/String;Ljava/lang/String;)Z
    //   239: ifeq +12 -> 251
    //   242: iconst_1
    //   243: istore 59
    //   245: iconst_0
    //   246: istore 44
    //   248: goto +27 -> 275
    //   251: aload_1
    //   252: ldc 44
    //   254: invokestatic 42	org/netlib/lapack/Lsame:lsame	(Ljava/lang/String;Ljava/lang/String;)Z
    //   257: ifeq +12 -> 269
    //   260: iconst_2
    //   261: istore 59
    //   263: iconst_1
    //   264: istore 44
    //   266: goto +9 -> 275
    //   269: iconst_m1
    //   270: istore 59
    //   272: iconst_0
    //   273: istore 44
    //   275: aload_2
    //   276: ldc 46
    //   278: invokestatic 42	org/netlib/lapack/Lsame:lsame	(Ljava/lang/String;Ljava/lang/String;)Z
    //   281: istore 51
    //   283: aload 4
    //   285: ldc 36
    //   287: invokestatic 42	org/netlib/lapack/Lsame:lsame	(Ljava/lang/String;Ljava/lang/String;)Z
    //   290: istore 50
    //   292: aload 4
    //   294: ldc 48
    //   296: invokestatic 42	org/netlib/lapack/Lsame:lsame	(Ljava/lang/String;Ljava/lang/String;)Z
    //   299: istore 49
    //   301: aload 4
    //   303: ldc 44
    //   305: invokestatic 42	org/netlib/lapack/Lsame:lsame	(Ljava/lang/String;Ljava/lang/String;)Z
    //   308: istore 52
    //   310: aload 4
    //   312: ldc 50
    //   314: invokestatic 42	org/netlib/lapack/Lsame:lsame	(Ljava/lang/String;Ljava/lang/String;)Z
    //   317: istore 48
    //   319: iload 31
    //   321: iconst_m1
    //   322: if_icmpeq +7 -> 329
    //   325: iconst_0
    //   326: goto +4 -> 330
    //   329: iconst_1
    //   330: ifne +21 -> 351
    //   333: iload 34
    //   335: iconst_m1
    //   336: if_icmpeq +7 -> 343
    //   339: iconst_0
    //   340: goto +4 -> 344
    //   343: iconst_1
    //   344: ifne +7 -> 351
    //   347: iconst_0
    //   348: goto +4 -> 352
    //   351: iconst_1
    //   352: istore 46
    //   354: iload 50
    //   356: ifeq +9 -> 365
    //   359: iconst_0
    //   360: istore 57
    //   362: goto +36 -> 398
    //   365: iload 49
    //   367: ifeq +9 -> 376
    //   370: iconst_1
    //   371: istore 57
    //   373: goto +25 -> 398
    //   376: iload 52
    //   378: ifeq +9 -> 387
    //   381: iconst_2
    //   382: istore 57
    //   384: goto +14 -> 398
    //   387: iload 48
    //   389: ifeq +9 -> 398
    //   392: iconst_4
    //   393: istore 57
    //   395: goto +3 -> 398
    //   398: aload 37
    //   400: iconst_0
    //   401: putfield 54	org/netlib/util/intW:val	I
    //   404: iload 58
    //   406: iconst_0
    //   407: if_icmple +7 -> 414
    //   410: iconst_0
    //   411: goto +4 -> 415
    //   414: iconst_1
    //   415: ifeq +12 -> 427
    //   418: aload 37
    //   420: iconst_m1
    //   421: putfield 54	org/netlib/util/intW:val	I
    //   424: goto +351 -> 775
    //   427: iload 59
    //   429: iconst_0
    //   430: if_icmple +7 -> 437
    //   433: iconst_0
    //   434: goto +4 -> 438
    //   437: iconst_1
    //   438: ifeq +13 -> 451
    //   441: aload 37
    //   443: bipush -2
    //   445: putfield 54	org/netlib/util/intW:val	I
    //   448: goto +327 -> 775
    //   451: iload 51
    //   453: iconst_1
    //   454: ixor
    //   455: ifeq +18 -> 473
    //   458: aload_2
    //   459: ldc 36
    //   461: invokestatic 42	org/netlib/lapack/Lsame:lsame	(Ljava/lang/String;Ljava/lang/String;)Z
    //   464: iconst_1
    //   465: ixor
    //   466: ifeq +7 -> 473
    //   469: iconst_1
    //   470: goto +4 -> 474
    //   473: iconst_0
    //   474: ifeq +13 -> 487
    //   477: aload 37
    //   479: bipush -3
    //   481: putfield 54	org/netlib/util/intW:val	I
    //   484: goto +291 -> 775
    //   487: iload 50
    //   489: ifne +12 -> 501
    //   492: iload 49
    //   494: ifne +7 -> 501
    //   497: iconst_0
    //   498: goto +4 -> 502
    //   501: iconst_1
    //   502: ifne +12 -> 514
    //   505: iload 52
    //   507: ifne +7 -> 514
    //   510: iconst_0
    //   511: goto +4 -> 515
    //   514: iconst_1
    //   515: ifne +12 -> 527
    //   518: iload 48
    //   520: ifne +7 -> 527
    //   523: iconst_0
    //   524: goto +4 -> 528
    //   527: iconst_1
    //   528: iconst_1
    //   529: ixor
    //   530: ifne +29 -> 559
    //   533: iload 51
    //   535: iconst_1
    //   536: ixor
    //   537: ifeq +14 -> 551
    //   540: iload 50
    //   542: iconst_1
    //   543: ixor
    //   544: ifeq +7 -> 551
    //   547: iconst_1
    //   548: goto +4 -> 552
    //   551: iconst_0
    //   552: ifne +7 -> 559
    //   555: iconst_0
    //   556: goto +4 -> 560
    //   559: iconst_1
    //   560: ifeq +13 -> 573
    //   563: aload 37
    //   565: bipush -5
    //   567: putfield 54	org/netlib/util/intW:val	I
    //   570: goto +205 -> 775
    //   573: iload 5
    //   575: iconst_0
    //   576: if_icmplt +7 -> 583
    //   579: iconst_0
    //   580: goto +4 -> 584
    //   583: iconst_1
    //   584: ifeq +13 -> 597
    //   587: aload 37
    //   589: bipush -6
    //   591: putfield 54	org/netlib/util/intW:val	I
    //   594: goto +181 -> 775
    //   597: iload 8
    //   599: iconst_1
    //   600: iload 5
    //   602: invokestatic 60	java/lang/Math:max	(II)I
    //   605: if_icmplt +7 -> 612
    //   608: iconst_0
    //   609: goto +4 -> 613
    //   612: iconst_1
    //   613: ifeq +13 -> 626
    //   616: aload 37
    //   618: bipush -8
    //   620: putfield 54	org/netlib/util/intW:val	I
    //   623: goto +152 -> 775
    //   626: iload 11
    //   628: iconst_1
    //   629: iload 5
    //   631: invokestatic 60	java/lang/Math:max	(II)I
    //   634: if_icmplt +7 -> 641
    //   637: iconst_0
    //   638: goto +4 -> 642
    //   641: iconst_1
    //   642: ifeq +13 -> 655
    //   645: aload 37
    //   647: bipush -10
    //   649: putfield 54	org/netlib/util/intW:val	I
    //   652: goto +123 -> 775
    //   655: iload 21
    //   657: iconst_1
    //   658: if_icmplt +7 -> 665
    //   661: iconst_0
    //   662: goto +4 -> 666
    //   665: iconst_1
    //   666: ifne +35 -> 701
    //   669: iload 43
    //   671: ifeq +22 -> 693
    //   674: iload 21
    //   676: iload 5
    //   678: if_icmplt +7 -> 685
    //   681: iconst_0
    //   682: goto +4 -> 686
    //   685: iconst_1
    //   686: ifeq +7 -> 693
    //   689: iconst_1
    //   690: goto +4 -> 694
    //   693: iconst_0
    //   694: ifne +7 -> 701
    //   697: iconst_0
    //   698: goto +4 -> 702
    //   701: iconst_1
    //   702: ifeq +13 -> 715
    //   705: aload 37
    //   707: bipush -16
    //   709: putfield 54	org/netlib/util/intW:val	I
    //   712: goto +63 -> 775
    //   715: iload 24
    //   717: iconst_1
    //   718: if_icmplt +7 -> 725
    //   721: iconst_0
    //   722: goto +4 -> 726
    //   725: iconst_1
    //   726: ifne +35 -> 761
    //   729: iload 44
    //   731: ifeq +22 -> 753
    //   734: iload 24
    //   736: iload 5
    //   738: if_icmplt +7 -> 745
    //   741: iconst_0
    //   742: goto +4 -> 746
    //   745: iconst_1
    //   746: ifeq +7 -> 753
    //   749: iconst_1
    //   750: goto +4 -> 754
    //   753: iconst_0
    //   754: ifne +7 -> 761
    //   757: iconst_0
    //   758: goto +4 -> 762
    //   761: iconst_1
    //   762: ifeq +13 -> 775
    //   765: aload 37
    //   767: bipush -18
    //   769: putfield 54	org/netlib/util/intW:val	I
    //   772: goto +3 -> 775
    //   775: aload 37
    //   777: getfield 54	org/netlib/util/intW:val	I
    //   780: iconst_0
    //   781: if_icmpeq +7 -> 788
    //   784: iconst_0
    //   785: goto +4 -> 789
    //   788: iconst_1
    //   789: ifeq +312 -> 1101
    //   792: iload 5
    //   794: iconst_0
    //   795: if_icmpgt +7 -> 802
    //   798: iconst_0
    //   799: goto +4 -> 803
    //   802: iconst_1
    //   803: ifeq +146 -> 949
    //   806: bipush 8
    //   808: iload 5
    //   810: imul
    //   811: bipush 6
    //   813: iload 5
    //   815: imul
    //   816: bipush 16
    //   818: iadd
    //   819: invokestatic 60	java/lang/Math:max	(II)I
    //   822: istore 70
    //   824: iload 70
    //   826: iload 5
    //   828: isub
    //   829: iload 5
    //   831: iconst_1
    //   832: ldc 62
    //   834: ldc 64
    //   836: iload 5
    //   838: iconst_1
    //   839: iload 5
    //   841: iconst_0
    //   842: invokestatic 70	org/netlib/lapack/Ilaenv:ilaenv	(ILjava/lang/String;Ljava/lang/String;IIII)I
    //   845: imul
    //   846: iadd
    //   847: istore 69
    //   849: iload 69
    //   851: iload 70
    //   853: iload 5
    //   855: isub
    //   856: iload 5
    //   858: iconst_1
    //   859: ldc 72
    //   861: ldc 64
    //   863: iload 5
    //   865: iconst_1
    //   866: iload 5
    //   868: iconst_m1
    //   869: invokestatic 70	org/netlib/lapack/Ilaenv:ilaenv	(ILjava/lang/String;Ljava/lang/String;IIII)I
    //   872: imul
    //   873: iadd
    //   874: invokestatic 60	java/lang/Math:max	(II)I
    //   877: istore 69
    //   879: iload 43
    //   881: ifeq +33 -> 914
    //   884: iload 69
    //   886: iload 70
    //   888: iload 5
    //   890: isub
    //   891: iload 5
    //   893: iconst_1
    //   894: ldc 74
    //   896: ldc 64
    //   898: iload 5
    //   900: iconst_1
    //   901: iload 5
    //   903: iconst_m1
    //   904: invokestatic 70	org/netlib/lapack/Ilaenv:ilaenv	(ILjava/lang/String;Ljava/lang/String;IIII)I
    //   907: imul
    //   908: iadd
    //   909: invokestatic 60	java/lang/Math:max	(II)I
    //   912: istore 69
    //   914: iload 69
    //   916: istore 68
    //   918: iload 57
    //   920: iconst_1
    //   921: if_icmpge +7 -> 928
    //   924: iconst_0
    //   925: goto +4 -> 929
    //   928: iconst_1
    //   929: ifeq +17 -> 946
    //   932: iload 68
    //   934: iload 5
    //   936: iload 5
    //   938: imul
    //   939: iconst_2
    //   940: idiv
    //   941: invokestatic 60	java/lang/Math:max	(II)I
    //   944: istore 68
    //   946: goto +12 -> 958
    //   949: iconst_1
    //   950: istore 70
    //   952: iconst_1
    //   953: istore 69
    //   955: iconst_1
    //   956: istore 68
    //   958: aload 29
    //   960: iconst_1
    //   961: iconst_1
    //   962: isub
    //   963: iload 30
    //   965: iadd
    //   966: iload 68
    //   968: i2f
    //   969: fastore
    //   970: iload 50
    //   972: ifne +21 -> 993
    //   975: iload 5
    //   977: iconst_0
    //   978: if_icmpeq +7 -> 985
    //   981: iconst_0
    //   982: goto +4 -> 986
    //   985: iconst_1
    //   986: ifne +7 -> 993
    //   989: iconst_0
    //   990: goto +4 -> 994
    //   993: iconst_1
    //   994: ifeq +9 -> 1003
    //   997: iconst_1
    //   998: istore 67
    //   1000: goto +10 -> 1010
    //   1003: iload 5
    //   1005: bipush 6
    //   1007: iadd
    //   1008: istore 67
    //   1010: aload 32
    //   1012: iconst_1
    //   1013: iconst_1
    //   1014: isub
    //   1015: iload 33
    //   1017: iadd
    //   1018: iload 67
    //   1020: iastore
    //   1021: iload 31
    //   1023: iload 70
    //   1025: if_icmplt +7 -> 1032
    //   1028: iconst_0
    //   1029: goto +4 -> 1033
    //   1032: iconst_1
    //   1033: ifeq +14 -> 1047
    //   1036: iload 46
    //   1038: iconst_1
    //   1039: ixor
    //   1040: ifeq +7 -> 1047
    //   1043: iconst_1
    //   1044: goto +4 -> 1048
    //   1047: iconst_0
    //   1048: ifeq +13 -> 1061
    //   1051: aload 37
    //   1053: bipush -22
    //   1055: putfield 54	org/netlib/util/intW:val	I
    //   1058: goto +43 -> 1101
    //   1061: iload 34
    //   1063: iload 67
    //   1065: if_icmplt +7 -> 1072
    //   1068: iconst_0
    //   1069: goto +4 -> 1073
    //   1072: iconst_1
    //   1073: ifeq +14 -> 1087
    //   1076: iload 46
    //   1078: iconst_1
    //   1079: ixor
    //   1080: ifeq +7 -> 1087
    //   1083: iconst_1
    //   1084: goto +4 -> 1088
    //   1087: iconst_0
    //   1088: ifeq +13 -> 1101
    //   1091: aload 37
    //   1093: bipush -24
    //   1095: putfield 54	org/netlib/util/intW:val	I
    //   1098: goto +3 -> 1101
    //   1101: aload 37
    //   1103: getfield 54	org/netlib/util/intW:val	I
    //   1106: iconst_0
    //   1107: if_icmpne +7 -> 1114
    //   1110: iconst_0
    //   1111: goto +4 -> 1115
    //   1114: iconst_1
    //   1115: ifeq +18 -> 1133
    //   1118: ldc 76
    //   1120: aload 37
    //   1122: getfield 54	org/netlib/util/intW:val	I
    //   1125: ineg
    //   1126: invokestatic 82	org/netlib/err/Xerbla:xerbla	(Ljava/lang/String;I)V
    //   1129: return
    //   1130: goto +0 -> 1130
    //   1133: iload 46
    //   1135: ifeq +7 -> 1142
    //   1138: return
    //   1139: goto +0 -> 1139
    //   1142: iload 5
    //   1144: iconst_0
    //   1145: if_icmpeq +7 -> 1152
    //   1148: iconst_0
    //   1149: goto +4 -> 1153
    //   1152: iconst_1
    //   1153: ifeq +10 -> 1163
    //   1156: aload 12
    //   1158: iconst_0
    //   1159: putfield 54	org/netlib/util/intW:val	I
    //   1162: return
    //   1163: ldc 84
    //   1165: invokestatic 90	org/netlib/lapack/Slamch:slamch	(Ljava/lang/String;)F
    //   1168: fstore 76
    //   1170: aload 80
    //   1172: ldc 46
    //   1174: invokestatic 90	org/netlib/lapack/Slamch:slamch	(Ljava/lang/String;)F
    //   1177: putfield 93	org/netlib/util/floatW:val	F
    //   1180: aload 79
    //   1182: fconst_1
    //   1183: aload 80
    //   1185: getfield 93	org/netlib/util/floatW:val	F
    //   1188: fdiv
    //   1189: putfield 93	org/netlib/util/floatW:val	F
    //   1192: aload 80
    //   1194: aload 79
    //   1196: invokestatic 99	org/netlib/lapack/Slabad:slabad	(Lorg/netlib/util/floatW;Lorg/netlib/util/floatW;)V
    //   1199: aload 80
    //   1201: getfield 93	org/netlib/util/floatW:val	F
    //   1204: f2d
    //   1205: invokestatic 103	java/lang/Math:sqrt	(D)D
    //   1208: d2f
    //   1209: fload 76
    //   1211: fdiv
    //   1212: fstore 81
    //   1214: fconst_1
    //   1215: fload 81
    //   1217: fdiv
    //   1218: fstore 73
    //   1220: ldc 105
    //   1222: iload 5
    //   1224: iload 5
    //   1226: aload 6
    //   1228: iload 7
    //   1230: iload 8
    //   1232: aload 29
    //   1234: iload 30
    //   1236: invokestatic 111	org/netlib/lapack/Slange:slange	(Ljava/lang/String;II[FII[FI)F
    //   1239: fstore 71
    //   1241: iconst_0
    //   1242: istore 41
    //   1244: fload 71
    //   1246: fconst_0
    //   1247: fcmpl
    //   1248: ifgt +7 -> 1255
    //   1251: iconst_0
    //   1252: goto +4 -> 1256
    //   1255: iconst_1
    //   1256: ifeq +23 -> 1279
    //   1259: fload 71
    //   1261: fload 81
    //   1263: fcmpg
    //   1264: iflt +7 -> 1271
    //   1267: iconst_0
    //   1268: goto +4 -> 1272
    //   1271: iconst_1
    //   1272: ifeq +7 -> 1279
    //   1275: iconst_1
    //   1276: goto +4 -> 1280
    //   1279: iconst_0
    //   1280: ifeq +13 -> 1293
    //   1283: fload 81
    //   1285: fstore 72
    //   1287: iconst_1
    //   1288: istore 41
    //   1290: goto +29 -> 1319
    //   1293: fload 71
    //   1295: fload 73
    //   1297: fcmpl
    //   1298: ifgt +7 -> 1305
    //   1301: iconst_0
    //   1302: goto +4 -> 1306
    //   1305: iconst_1
    //   1306: ifeq +13 -> 1319
    //   1309: fload 73
    //   1311: fstore 72
    //   1313: iconst_1
    //   1314: istore 41
    //   1316: goto +3 -> 1319
    //   1319: iload 41
    //   1321: ifeq +26 -> 1347
    //   1324: ldc 113
    //   1326: iconst_0
    //   1327: iconst_0
    //   1328: fload 71
    //   1330: fload 72
    //   1332: iload 5
    //   1334: iload 5
    //   1336: aload 6
    //   1338: iload 7
    //   1340: iload 8
    //   1342: aload 55
    //   1344: invokestatic 119	org/netlib/lapack/Slascl:slascl	(Ljava/lang/String;IIFFII[FIILorg/netlib/util/intW;)V
    //   1347: ldc 105
    //   1349: iload 5
    //   1351: iload 5
    //   1353: aload 9
    //   1355: iload 10
    //   1357: iload 11
    //   1359: aload 29
    //   1361: iload 30
    //   1363: invokestatic 111	org/netlib/lapack/Slange:slange	(Ljava/lang/String;II[FII[FI)F
    //   1366: fstore 74
    //   1368: iconst_0
    //   1369: istore 42
    //   1371: fload 74
    //   1373: fconst_0
    //   1374: fcmpl
    //   1375: ifgt +7 -> 1382
    //   1378: iconst_0
    //   1379: goto +4 -> 1383
    //   1382: iconst_1
    //   1383: ifeq +23 -> 1406
    //   1386: fload 74
    //   1388: fload 81
    //   1390: fcmpg
    //   1391: iflt +7 -> 1398
    //   1394: iconst_0
    //   1395: goto +4 -> 1399
    //   1398: iconst_1
    //   1399: ifeq +7 -> 1406
    //   1402: iconst_1
    //   1403: goto +4 -> 1407
    //   1406: iconst_0
    //   1407: ifeq +13 -> 1420
    //   1410: fload 81
    //   1412: fstore 75
    //   1414: iconst_1
    //   1415: istore 42
    //   1417: goto +29 -> 1446
    //   1420: fload 74
    //   1422: fload 73
    //   1424: fcmpl
    //   1425: ifgt +7 -> 1432
    //   1428: iconst_0
    //   1429: goto +4 -> 1433
    //   1432: iconst_1
    //   1433: ifeq +13 -> 1446
    //   1436: fload 73
    //   1438: fstore 75
    //   1440: iconst_1
    //   1441: istore 42
    //   1443: goto +3 -> 1446
    //   1446: iload 42
    //   1448: ifeq +26 -> 1474
    //   1451: ldc 113
    //   1453: iconst_0
    //   1454: iconst_0
    //   1455: fload 74
    //   1457: fload 75
    //   1459: iload 5
    //   1461: iload 5
    //   1463: aload 9
    //   1465: iload 10
    //   1467: iload 11
    //   1469: aload 55
    //   1471: invokestatic 119	org/netlib/lapack/Slascl:slascl	(Ljava/lang/String;IIFFII[FIILorg/netlib/util/intW;)V
    //   1474: iconst_1
    //   1475: istore 60
    //   1477: iload 5
    //   1479: iconst_1
    //   1480: iadd
    //   1481: istore 63
    //   1483: iload 63
    //   1485: iload 5
    //   1487: iadd
    //   1488: istore 66
    //   1490: ldc 84
    //   1492: iload 5
    //   1494: aload 6
    //   1496: iload 7
    //   1498: iload 8
    //   1500: aload 9
    //   1502: iload 10
    //   1504: iload 11
    //   1506: aload 61
    //   1508: aload 56
    //   1510: aload 29
    //   1512: iload 60
    //   1514: iconst_1
    //   1515: isub
    //   1516: iload 30
    //   1518: iadd
    //   1519: aload 29
    //   1521: iload 63
    //   1523: iconst_1
    //   1524: isub
    //   1525: iload 30
    //   1527: iadd
    //   1528: aload 29
    //   1530: iload 66
    //   1532: iconst_1
    //   1533: isub
    //   1534: iload 30
    //   1536: iadd
    //   1537: aload 55
    //   1539: invokestatic 125	org/netlib/lapack/Sggbal:sggbal	(Ljava/lang/String;I[FII[FIILorg/netlib/util/intW;Lorg/netlib/util/intW;[FI[FI[FILorg/netlib/util/intW;)V
    //   1542: aload 56
    //   1544: getfield 54	org/netlib/util/intW:val	I
    //   1547: iconst_1
    //   1548: iadd
    //   1549: aload 61
    //   1551: getfield 54	org/netlib/util/intW:val	I
    //   1554: isub
    //   1555: istore 64
    //   1557: iload 5
    //   1559: iconst_1
    //   1560: iadd
    //   1561: aload 61
    //   1563: getfield 54	org/netlib/util/intW:val	I
    //   1566: isub
    //   1567: istore 54
    //   1569: iload 66
    //   1571: istore 65
    //   1573: iload 65
    //   1575: iload 64
    //   1577: iadd
    //   1578: istore 66
    //   1580: iload 64
    //   1582: iload 54
    //   1584: aload 9
    //   1586: aload 61
    //   1588: getfield 54	org/netlib/util/intW:val	I
    //   1591: iconst_1
    //   1592: isub
    //   1593: aload 61
    //   1595: getfield 54	org/netlib/util/intW:val	I
    //   1598: iconst_1
    //   1599: isub
    //   1600: iload 11
    //   1602: imul
    //   1603: iadd
    //   1604: iload 10
    //   1606: iadd
    //   1607: iload 11
    //   1609: aload 29
    //   1611: iload 65
    //   1613: iconst_1
    //   1614: isub
    //   1615: iload 30
    //   1617: iadd
    //   1618: aload 29
    //   1620: iload 66
    //   1622: iconst_1
    //   1623: isub
    //   1624: iload 30
    //   1626: iadd
    //   1627: iload 31
    //   1629: iconst_1
    //   1630: iadd
    //   1631: iload 66
    //   1633: isub
    //   1634: aload 55
    //   1636: invokestatic 131	org/netlib/lapack/Sgeqrf:sgeqrf	(II[FII[FI[FIILorg/netlib/util/intW;)V
    //   1639: ldc -123
    //   1641: ldc -121
    //   1643: iload 64
    //   1645: iload 54
    //   1647: iload 64
    //   1649: aload 9
    //   1651: aload 61
    //   1653: getfield 54	org/netlib/util/intW:val	I
    //   1656: iconst_1
    //   1657: isub
    //   1658: aload 61
    //   1660: getfield 54	org/netlib/util/intW:val	I
    //   1663: iconst_1
    //   1664: isub
    //   1665: iload 11
    //   1667: imul
    //   1668: iadd
    //   1669: iload 10
    //   1671: iadd
    //   1672: iload 11
    //   1674: aload 29
    //   1676: iload 65
    //   1678: iconst_1
    //   1679: isub
    //   1680: iload 30
    //   1682: iadd
    //   1683: aload 6
    //   1685: aload 61
    //   1687: getfield 54	org/netlib/util/intW:val	I
    //   1690: iconst_1
    //   1691: isub
    //   1692: aload 61
    //   1694: getfield 54	org/netlib/util/intW:val	I
    //   1697: iconst_1
    //   1698: isub
    //   1699: iload 8
    //   1701: imul
    //   1702: iadd
    //   1703: iload 7
    //   1705: iadd
    //   1706: iload 8
    //   1708: aload 29
    //   1710: iload 66
    //   1712: iconst_1
    //   1713: isub
    //   1714: iload 30
    //   1716: iadd
    //   1717: iload 31
    //   1719: iconst_1
    //   1720: iadd
    //   1721: iload 66
    //   1723: isub
    //   1724: aload 55
    //   1726: invokestatic 141	org/netlib/lapack/Sormqr:sormqr	(Ljava/lang/String;Ljava/lang/String;III[FII[FI[FII[FIILorg/netlib/util/intW;)V
    //   1729: iload 43
    //   1731: ifeq +162 -> 1893
    //   1734: ldc -113
    //   1736: iload 5
    //   1738: iload 5
    //   1740: fconst_0
    //   1741: fconst_1
    //   1742: aload 19
    //   1744: iload 20
    //   1746: iload 21
    //   1748: invokestatic 149	org/netlib/lapack/Slaset:slaset	(Ljava/lang/String;IIFF[FII)V
    //   1751: iload 64
    //   1753: iconst_1
    //   1754: if_icmpgt +7 -> 1761
    //   1757: iconst_0
    //   1758: goto +4 -> 1762
    //   1761: iconst_1
    //   1762: ifeq +70 -> 1832
    //   1765: ldc -123
    //   1767: iload 64
    //   1769: iconst_1
    //   1770: isub
    //   1771: iload 64
    //   1773: iconst_1
    //   1774: isub
    //   1775: aload 9
    //   1777: aload 61
    //   1779: getfield 54	org/netlib/util/intW:val	I
    //   1782: iconst_1
    //   1783: iadd
    //   1784: iconst_1
    //   1785: isub
    //   1786: aload 61
    //   1788: getfield 54	org/netlib/util/intW:val	I
    //   1791: iconst_1
    //   1792: isub
    //   1793: iload 11
    //   1795: imul
    //   1796: iadd
    //   1797: iload 10
    //   1799: iadd
    //   1800: iload 11
    //   1802: aload 19
    //   1804: aload 61
    //   1806: getfield 54	org/netlib/util/intW:val	I
    //   1809: iconst_1
    //   1810: iadd
    //   1811: iconst_1
    //   1812: isub
    //   1813: aload 61
    //   1815: getfield 54	org/netlib/util/intW:val	I
    //   1818: iconst_1
    //   1819: isub
    //   1820: iload 21
    //   1822: imul
    //   1823: iadd
    //   1824: iload 20
    //   1826: iadd
    //   1827: iload 21
    //   1829: invokestatic 155	org/netlib/lapack/Slacpy:slacpy	(Ljava/lang/String;II[FII[FII)V
    //   1832: iload 64
    //   1834: iload 64
    //   1836: iload 64
    //   1838: aload 19
    //   1840: aload 61
    //   1842: getfield 54	org/netlib/util/intW:val	I
    //   1845: iconst_1
    //   1846: isub
    //   1847: aload 61
    //   1849: getfield 54	org/netlib/util/intW:val	I
    //   1852: iconst_1
    //   1853: isub
    //   1854: iload 21
    //   1856: imul
    //   1857: iadd
    //   1858: iload 20
    //   1860: iadd
    //   1861: iload 21
    //   1863: aload 29
    //   1865: iload 65
    //   1867: iconst_1
    //   1868: isub
    //   1869: iload 30
    //   1871: iadd
    //   1872: aload 29
    //   1874: iload 66
    //   1876: iconst_1
    //   1877: isub
    //   1878: iload 30
    //   1880: iadd
    //   1881: iload 31
    //   1883: iconst_1
    //   1884: iadd
    //   1885: iload 66
    //   1887: isub
    //   1888: aload 55
    //   1890: invokestatic 161	org/netlib/lapack/Sorgqr:sorgqr	(III[FII[FI[FIILorg/netlib/util/intW;)V
    //   1893: iload 44
    //   1895: ifeq +20 -> 1915
    //   1898: ldc -113
    //   1900: iload 5
    //   1902: iload 5
    //   1904: fconst_0
    //   1905: fconst_1
    //   1906: aload 22
    //   1908: iload 23
    //   1910: iload 24
    //   1912: invokestatic 149	org/netlib/lapack/Slaset:slaset	(Ljava/lang/String;IIFF[FII)V
    //   1915: aload_0
    //   1916: aload_1
    //   1917: iload 5
    //   1919: aload 61
    //   1921: getfield 54	org/netlib/util/intW:val	I
    //   1924: aload 56
    //   1926: getfield 54	org/netlib/util/intW:val	I
    //   1929: aload 6
    //   1931: iload 7
    //   1933: iload 8
    //   1935: aload 9
    //   1937: iload 10
    //   1939: iload 11
    //   1941: aload 19
    //   1943: iload 20
    //   1945: iload 21
    //   1947: aload 22
    //   1949: iload 23
    //   1951: iload 24
    //   1953: aload 55
    //   1955: invokestatic 167	org/netlib/lapack/Sgghrd:sgghrd	(Ljava/lang/String;Ljava/lang/String;III[FII[FII[FII[FIILorg/netlib/util/intW;)V
    //   1958: aload 12
    //   1960: iconst_0
    //   1961: putfield 54	org/netlib/util/intW:val	I
    //   1964: iload 65
    //   1966: istore 66
    //   1968: ldc 46
    //   1970: aload_0
    //   1971: aload_1
    //   1972: iload 5
    //   1974: aload 61
    //   1976: getfield 54	org/netlib/util/intW:val	I
    //   1979: aload 56
    //   1981: getfield 54	org/netlib/util/intW:val	I
    //   1984: aload 6
    //   1986: iload 7
    //   1988: iload 8
    //   1990: aload 9
    //   1992: iload 10
    //   1994: iload 11
    //   1996: aload 13
    //   1998: iload 14
    //   2000: aload 15
    //   2002: iload 16
    //   2004: aload 17
    //   2006: iload 18
    //   2008: aload 19
    //   2010: iload 20
    //   2012: iload 21
    //   2014: aload 22
    //   2016: iload 23
    //   2018: iload 24
    //   2020: aload 29
    //   2022: iload 66
    //   2024: iconst_1
    //   2025: isub
    //   2026: iload 30
    //   2028: iadd
    //   2029: iload 31
    //   2031: iconst_1
    //   2032: iadd
    //   2033: iload 66
    //   2035: isub
    //   2036: aload 55
    //   2038: invokestatic 173	org/netlib/lapack/Shgeqz:shgeqz	(Ljava/lang/String;Ljava/lang/String;Ljava/lang/String;III[FII[FII[FI[FI[FI[FII[FII[FIILorg/netlib/util/intW;)V
    //   2041: aload 55
    //   2043: getfield 54	org/netlib/util/intW:val	I
    //   2046: iconst_0
    //   2047: if_icmpne +7 -> 2054
    //   2050: iconst_0
    //   2051: goto +4 -> 2055
    //   2054: iconst_1
    //   2055: ifeq +133 -> 2188
    //   2058: aload 55
    //   2060: getfield 54	org/netlib/util/intW:val	I
    //   2063: iconst_0
    //   2064: if_icmpgt +7 -> 2071
    //   2067: iconst_0
    //   2068: goto +4 -> 2072
    //   2071: iconst_1
    //   2072: ifeq +25 -> 2097
    //   2075: aload 55
    //   2077: getfield 54	org/netlib/util/intW:val	I
    //   2080: iload 5
    //   2082: if_icmple +7 -> 2089
    //   2085: iconst_0
    //   2086: goto +4 -> 2090
    //   2089: iconst_1
    //   2090: ifeq +7 -> 2097
    //   2093: iconst_1
    //   2094: goto +4 -> 2098
    //   2097: iconst_0
    //   2098: ifeq +16 -> 2114
    //   2101: aload 37
    //   2103: aload 55
    //   2105: getfield 54	org/netlib/util/intW:val	I
    //   2108: putfield 54	org/netlib/util/intW:val	I
    //   2111: goto +74 -> 2185
    //   2114: aload 55
    //   2116: getfield 54	org/netlib/util/intW:val	I
    //   2119: iload 5
    //   2121: if_icmpgt +7 -> 2128
    //   2124: iconst_0
    //   2125: goto +4 -> 2129
    //   2128: iconst_1
    //   2129: ifeq +27 -> 2156
    //   2132: aload 55
    //   2134: getfield 54	org/netlib/util/intW:val	I
    //   2137: iconst_2
    //   2138: iload 5
    //   2140: imul
    //   2141: if_icmple +7 -> 2148
    //   2144: iconst_0
    //   2145: goto +4 -> 2149
    //   2148: iconst_1
    //   2149: ifeq +7 -> 2156
    //   2152: iconst_1
    //   2153: goto +4 -> 2157
    //   2156: iconst_0
    //   2157: ifeq +19 -> 2176
    //   2160: aload 37
    //   2162: aload 55
    //   2164: getfield 54	org/netlib/util/intW:val	I
    //   2167: iload 5
    //   2169: isub
    //   2170: putfield 54	org/netlib/util/intW:val	I
    //   2173: goto +12 -> 2185
    //   2176: aload 37
    //   2178: iload 5
    //   2180: iconst_1
    //   2181: iadd
    //   2182: putfield 54	org/netlib/util/intW:val	I
    //   2185: goto +1675 -> 3860
    //   2188: iload 51
    //   2190: ifeq +454 -> 2644
    //   2193: iload 41
    //   2195: ifeq +47 -> 2242
    //   2198: ldc 113
    //   2200: iconst_0
    //   2201: iconst_0
    //   2202: fload 72
    //   2204: fload 71
    //   2206: iload 5
    //   2208: iconst_1
    //   2209: aload 13
    //   2211: iload 14
    //   2213: iload 5
    //   2215: aload 55
    //   2217: invokestatic 119	org/netlib/lapack/Slascl:slascl	(Ljava/lang/String;IIFFII[FIILorg/netlib/util/intW;)V
    //   2220: ldc 113
    //   2222: iconst_0
    //   2223: iconst_0
    //   2224: fload 72
    //   2226: fload 71
    //   2228: iload 5
    //   2230: iconst_1
    //   2231: aload 15
    //   2233: iload 16
    //   2235: iload 5
    //   2237: aload 55
    //   2239: invokestatic 119	org/netlib/lapack/Slascl:slascl	(Ljava/lang/String;IIFFII[FIILorg/netlib/util/intW;)V
    //   2242: iload 42
    //   2244: ifeq +25 -> 2269
    //   2247: ldc 113
    //   2249: iconst_0
    //   2250: iconst_0
    //   2251: fload 75
    //   2253: fload 74
    //   2255: iload 5
    //   2257: iconst_1
    //   2258: aload 17
    //   2260: iload 18
    //   2262: iload 5
    //   2264: aload 55
    //   2266: invokestatic 119	org/netlib/lapack/Slascl:slascl	(Ljava/lang/String;IIFFII[FIILorg/netlib/util/intW;)V
    //   2269: iconst_1
    //   2270: istore 53
    //   2272: iload 5
    //   2274: iconst_1
    //   2275: isub
    //   2276: iconst_1
    //   2277: iadd
    //   2278: istore 84
    //   2280: goto +54 -> 2334
    //   2283: aload 35
    //   2285: iload 53
    //   2287: iconst_1
    //   2288: isub
    //   2289: iload 36
    //   2291: iadd
    //   2292: aload 83
    //   2294: aload 13
    //   2296: iload 53
    //   2298: iconst_1
    //   2299: isub
    //   2300: iload 14
    //   2302: iadd
    //   2303: aload 15
    //   2305: iload 53
    //   2307: iconst_1
    //   2308: isub
    //   2309: iload 16
    //   2311: iadd
    //   2312: aload 17
    //   2314: iload 53
    //   2316: iconst_1
    //   2317: isub
    //   2318: iload 18
    //   2320: iadd
    //   2321: invokestatic 177	org/netlib/lapack/Sggesx:selctg_methcall	(Ljava/lang/reflect/Method;[FI[FI[FI)Z
    //   2324: bastore
    //   2325: iload 53
    //   2327: iconst_1
    //   2328: iadd
    //   2329: istore 53
    //   2331: iinc 84 -1
    //   2334: iload 84
    //   2336: ifgt -53 -> 2283
    //   2339: iload 57
    //   2341: iload 43
    //   2343: iload 44
    //   2345: aload 35
    //   2347: iload 36
    //   2349: iload 5
    //   2351: aload 6
    //   2353: iload 7
    //   2355: iload 8
    //   2357: aload 9
    //   2359: iload 10
    //   2361: iload 11
    //   2363: aload 13
    //   2365: iload 14
    //   2367: aload 15
    //   2369: iload 16
    //   2371: aload 17
    //   2373: iload 18
    //   2375: aload 19
    //   2377: iload 20
    //   2379: iload 21
    //   2381: aload 22
    //   2383: iload 23
    //   2385: iload 24
    //   2387: aload 12
    //   2389: aload 77
    //   2391: aload 78
    //   2393: aload 82
    //   2395: iconst_0
    //   2396: aload 29
    //   2398: iload 66
    //   2400: iconst_1
    //   2401: isub
    //   2402: iload 30
    //   2404: iadd
    //   2405: iload 31
    //   2407: iload 66
    //   2409: isub
    //   2410: iconst_1
    //   2411: iadd
    //   2412: aload 32
    //   2414: iload 33
    //   2416: iload 34
    //   2418: aload 55
    //   2420: invokestatic 183	org/netlib/lapack/Stgsen:stgsen	(IZZ[ZII[FII[FII[FI[FI[FI[FII[FIILorg/netlib/util/intW;Lorg/netlib/util/floatW;Lorg/netlib/util/floatW;[FI[FII[IIILorg/netlib/util/intW;)V
    //   2423: iload 57
    //   2425: iconst_1
    //   2426: if_icmpge +7 -> 2433
    //   2429: iconst_0
    //   2430: goto +4 -> 2434
    //   2433: iconst_1
    //   2434: ifeq +26 -> 2460
    //   2437: iload 69
    //   2439: iconst_2
    //   2440: aload 12
    //   2442: getfield 54	org/netlib/util/intW:val	I
    //   2445: imul
    //   2446: iload 5
    //   2448: aload 12
    //   2450: getfield 54	org/netlib/util/intW:val	I
    //   2453: isub
    //   2454: imul
    //   2455: invokestatic 60	java/lang/Math:max	(II)I
    //   2458: istore 69
    //   2460: aload 55
    //   2462: getfield 54	org/netlib/util/intW:val	I
    //   2465: bipush -22
    //   2467: if_icmpeq +7 -> 2474
    //   2470: iconst_0
    //   2471: goto +4 -> 2475
    //   2474: iconst_1
    //   2475: ifeq +13 -> 2488
    //   2478: aload 37
    //   2480: bipush -22
    //   2482: putfield 54	org/netlib/util/intW:val	I
    //   2485: goto +159 -> 2644
    //   2488: iload 57
    //   2490: iconst_1
    //   2491: if_icmpeq +7 -> 2498
    //   2494: iconst_0
    //   2495: goto +4 -> 2499
    //   2498: iconst_1
    //   2499: ifne +21 -> 2520
    //   2502: iload 57
    //   2504: iconst_4
    //   2505: if_icmpeq +7 -> 2512
    //   2508: iconst_0
    //   2509: goto +4 -> 2513
    //   2512: iconst_1
    //   2513: ifne +7 -> 2520
    //   2516: iconst_0
    //   2517: goto +4 -> 2521
    //   2520: iconst_1
    //   2521: ifeq +31 -> 2552
    //   2524: aload 25
    //   2526: iconst_1
    //   2527: iconst_1
    //   2528: isub
    //   2529: iload 26
    //   2531: iadd
    //   2532: aload 77
    //   2534: getfield 93	org/netlib/util/floatW:val	F
    //   2537: fastore
    //   2538: aload 25
    //   2540: iconst_2
    //   2541: iconst_1
    //   2542: isub
    //   2543: iload 26
    //   2545: iadd
    //   2546: aload 78
    //   2548: getfield 93	org/netlib/util/floatW:val	F
    //   2551: fastore
    //   2552: iload 57
    //   2554: iconst_2
    //   2555: if_icmpeq +7 -> 2562
    //   2558: iconst_0
    //   2559: goto +4 -> 2563
    //   2562: iconst_1
    //   2563: ifne +21 -> 2584
    //   2566: iload 57
    //   2568: iconst_4
    //   2569: if_icmpeq +7 -> 2576
    //   2572: iconst_0
    //   2573: goto +4 -> 2577
    //   2576: iconst_1
    //   2577: ifne +7 -> 2584
    //   2580: iconst_0
    //   2581: goto +4 -> 2585
    //   2584: iconst_1
    //   2585: ifeq +33 -> 2618
    //   2588: aload 27
    //   2590: iconst_1
    //   2591: iconst_1
    //   2592: isub
    //   2593: iload 28
    //   2595: iadd
    //   2596: aload 82
    //   2598: iconst_1
    //   2599: iconst_1
    //   2600: isub
    //   2601: faload
    //   2602: fastore
    //   2603: aload 27
    //   2605: iconst_2
    //   2606: iconst_1
    //   2607: isub
    //   2608: iload 28
    //   2610: iadd
    //   2611: aload 82
    //   2613: iconst_2
    //   2614: iconst_1
    //   2615: isub
    //   2616: faload
    //   2617: fastore
    //   2618: aload 55
    //   2620: getfield 54	org/netlib/util/intW:val	I
    //   2623: iconst_1
    //   2624: if_icmpeq +7 -> 2631
    //   2627: iconst_0
    //   2628: goto +4 -> 2632
    //   2631: iconst_1
    //   2632: ifeq +12 -> 2644
    //   2635: aload 37
    //   2637: iload 5
    //   2639: iconst_3
    //   2640: iadd
    //   2641: putfield 54	org/netlib/util/intW:val	I
    //   2644: iload 43
    //   2646: ifeq +50 -> 2696
    //   2649: ldc 84
    //   2651: ldc -123
    //   2653: iload 5
    //   2655: aload 61
    //   2657: getfield 54	org/netlib/util/intW:val	I
    //   2660: aload 56
    //   2662: getfield 54	org/netlib/util/intW:val	I
    //   2665: aload 29
    //   2667: iload 60
    //   2669: iconst_1
    //   2670: isub
    //   2671: iload 30
    //   2673: iadd
    //   2674: aload 29
    //   2676: iload 63
    //   2678: iconst_1
    //   2679: isub
    //   2680: iload 30
    //   2682: iadd
    //   2683: iload 5
    //   2685: aload 19
    //   2687: iload 20
    //   2689: iload 21
    //   2691: aload 55
    //   2693: invokestatic 189	org/netlib/lapack/Sggbak:sggbak	(Ljava/lang/String;Ljava/lang/String;III[FI[FII[FIILorg/netlib/util/intW;)V
    //   2696: iload 44
    //   2698: ifeq +50 -> 2748
    //   2701: ldc 84
    //   2703: ldc -65
    //   2705: iload 5
    //   2707: aload 61
    //   2709: getfield 54	org/netlib/util/intW:val	I
    //   2712: aload 56
    //   2714: getfield 54	org/netlib/util/intW:val	I
    //   2717: aload 29
    //   2719: iload 60
    //   2721: iconst_1
    //   2722: isub
    //   2723: iload 30
    //   2725: iadd
    //   2726: aload 29
    //   2728: iload 63
    //   2730: iconst_1
    //   2731: isub
    //   2732: iload 30
    //   2734: iadd
    //   2735: iload 5
    //   2737: aload 22
    //   2739: iload 23
    //   2741: iload 24
    //   2743: aload 55
    //   2745: invokestatic 189	org/netlib/lapack/Sggbak:sggbak	(Ljava/lang/String;Ljava/lang/String;III[FI[FII[FIILorg/netlib/util/intW;)V
    //   2748: iload 41
    //   2750: ifeq +472 -> 3222
    //   2753: iconst_1
    //   2754: istore 53
    //   2756: iload 5
    //   2758: iconst_1
    //   2759: isub
    //   2760: iconst_1
    //   2761: iadd
    //   2762: istore 84
    //   2764: goto +453 -> 3217
    //   2767: aload 15
    //   2769: iload 53
    //   2771: iconst_1
    //   2772: isub
    //   2773: iload 16
    //   2775: iadd
    //   2776: faload
    //   2777: fconst_0
    //   2778: fcmpl
    //   2779: ifne +7 -> 2786
    //   2782: iconst_0
    //   2783: goto +4 -> 2787
    //   2786: iconst_1
    //   2787: ifeq +421 -> 3208
    //   2790: aload 13
    //   2792: iload 53
    //   2794: iconst_1
    //   2795: isub
    //   2796: iload 14
    //   2798: iadd
    //   2799: faload
    //   2800: aload 79
    //   2802: getfield 93	org/netlib/util/floatW:val	F
    //   2805: fdiv
    //   2806: fload 72
    //   2808: fload 71
    //   2810: fdiv
    //   2811: fcmpl
    //   2812: ifgt +7 -> 2819
    //   2815: iconst_0
    //   2816: goto +4 -> 2820
    //   2819: iconst_1
    //   2820: ifne +40 -> 2860
    //   2823: aload 80
    //   2825: getfield 93	org/netlib/util/floatW:val	F
    //   2828: aload 13
    //   2830: iload 53
    //   2832: iconst_1
    //   2833: isub
    //   2834: iload 14
    //   2836: iadd
    //   2837: faload
    //   2838: fdiv
    //   2839: fload 71
    //   2841: fload 72
    //   2843: fdiv
    //   2844: fcmpl
    //   2845: ifgt +7 -> 2852
    //   2848: iconst_0
    //   2849: goto +4 -> 2853
    //   2852: iconst_1
    //   2853: ifne +7 -> 2860
    //   2856: iconst_0
    //   2857: goto +4 -> 2861
    //   2860: iconst_1
    //   2861: ifeq +137 -> 2998
    //   2864: aload 29
    //   2866: iconst_1
    //   2867: iconst_1
    //   2868: isub
    //   2869: iload 30
    //   2871: iadd
    //   2872: aload 6
    //   2874: iload 53
    //   2876: iconst_1
    //   2877: isub
    //   2878: iload 53
    //   2880: iconst_1
    //   2881: isub
    //   2882: iload 8
    //   2884: imul
    //   2885: iadd
    //   2886: iload 7
    //   2888: iadd
    //   2889: faload
    //   2890: aload 13
    //   2892: iload 53
    //   2894: iconst_1
    //   2895: isub
    //   2896: iload 14
    //   2898: iadd
    //   2899: faload
    //   2900: fdiv
    //   2901: invokestatic 195	java/lang/Math:abs	(F)F
    //   2904: fastore
    //   2905: aload 17
    //   2907: iload 53
    //   2909: iconst_1
    //   2910: isub
    //   2911: iload 18
    //   2913: iadd
    //   2914: aload 17
    //   2916: iload 53
    //   2918: iconst_1
    //   2919: isub
    //   2920: iload 18
    //   2922: iadd
    //   2923: faload
    //   2924: aload 29
    //   2926: iconst_1
    //   2927: iconst_1
    //   2928: isub
    //   2929: iload 30
    //   2931: iadd
    //   2932: faload
    //   2933: fmul
    //   2934: fastore
    //   2935: aload 13
    //   2937: iload 53
    //   2939: iconst_1
    //   2940: isub
    //   2941: iload 14
    //   2943: iadd
    //   2944: aload 13
    //   2946: iload 53
    //   2948: iconst_1
    //   2949: isub
    //   2950: iload 14
    //   2952: iadd
    //   2953: faload
    //   2954: aload 29
    //   2956: iconst_1
    //   2957: iconst_1
    //   2958: isub
    //   2959: iload 30
    //   2961: iadd
    //   2962: faload
    //   2963: fmul
    //   2964: fastore
    //   2965: aload 15
    //   2967: iload 53
    //   2969: iconst_1
    //   2970: isub
    //   2971: iload 16
    //   2973: iadd
    //   2974: aload 15
    //   2976: iload 53
    //   2978: iconst_1
    //   2979: isub
    //   2980: iload 16
    //   2982: iadd
    //   2983: faload
    //   2984: aload 29
    //   2986: iconst_1
    //   2987: iconst_1
    //   2988: isub
    //   2989: iload 30
    //   2991: iadd
    //   2992: faload
    //   2993: fmul
    //   2994: fastore
    //   2995: goto +213 -> 3208
    //   2998: aload 15
    //   3000: iload 53
    //   3002: iconst_1
    //   3003: isub
    //   3004: iload 16
    //   3006: iadd
    //   3007: faload
    //   3008: aload 79
    //   3010: getfield 93	org/netlib/util/floatW:val	F
    //   3013: fdiv
    //   3014: fload 72
    //   3016: fload 71
    //   3018: fdiv
    //   3019: fcmpl
    //   3020: ifgt +7 -> 3027
    //   3023: iconst_0
    //   3024: goto +4 -> 3028
    //   3027: iconst_1
    //   3028: ifne +40 -> 3068
    //   3031: aload 80
    //   3033: getfield 93	org/netlib/util/floatW:val	F
    //   3036: aload 15
    //   3038: iload 53
    //   3040: iconst_1
    //   3041: isub
    //   3042: iload 16
    //   3044: iadd
    //   3045: faload
    //   3046: fdiv
    //   3047: fload 71
    //   3049: fload 72
    //   3051: fdiv
    //   3052: fcmpl
    //   3053: ifgt +7 -> 3060
    //   3056: iconst_0
    //   3057: goto +4 -> 3061
    //   3060: iconst_1
    //   3061: ifne +7 -> 3068
    //   3064: iconst_0
    //   3065: goto +4 -> 3069
    //   3068: iconst_1
    //   3069: ifeq +139 -> 3208
    //   3072: aload 29
    //   3074: iconst_1
    //   3075: iconst_1
    //   3076: isub
    //   3077: iload 30
    //   3079: iadd
    //   3080: aload 6
    //   3082: iload 53
    //   3084: iconst_1
    //   3085: isub
    //   3086: iload 53
    //   3088: iconst_1
    //   3089: iadd
    //   3090: iconst_1
    //   3091: isub
    //   3092: iload 8
    //   3094: imul
    //   3095: iadd
    //   3096: iload 7
    //   3098: iadd
    //   3099: faload
    //   3100: aload 15
    //   3102: iload 53
    //   3104: iconst_1
    //   3105: isub
    //   3106: iload 16
    //   3108: iadd
    //   3109: faload
    //   3110: fdiv
    //   3111: invokestatic 195	java/lang/Math:abs	(F)F
    //   3114: fastore
    //   3115: aload 17
    //   3117: iload 53
    //   3119: iconst_1
    //   3120: isub
    //   3121: iload 18
    //   3123: iadd
    //   3124: aload 17
    //   3126: iload 53
    //   3128: iconst_1
    //   3129: isub
    //   3130: iload 18
    //   3132: iadd
    //   3133: faload
    //   3134: aload 29
    //   3136: iconst_1
    //   3137: iconst_1
    //   3138: isub
    //   3139: iload 30
    //   3141: iadd
    //   3142: faload
    //   3143: fmul
    //   3144: fastore
    //   3145: aload 13
    //   3147: iload 53
    //   3149: iconst_1
    //   3150: isub
    //   3151: iload 14
    //   3153: iadd
    //   3154: aload 13
    //   3156: iload 53
    //   3158: iconst_1
    //   3159: isub
    //   3160: iload 14
    //   3162: iadd
    //   3163: faload
    //   3164: aload 29
    //   3166: iconst_1
    //   3167: iconst_1
    //   3168: isub
    //   3169: iload 30
    //   3171: iadd
    //   3172: faload
    //   3173: fmul
    //   3174: fastore
    //   3175: aload 15
    //   3177: iload 53
    //   3179: iconst_1
    //   3180: isub
    //   3181: iload 16
    //   3183: iadd
    //   3184: aload 15
    //   3186: iload 53
    //   3188: iconst_1
    //   3189: isub
    //   3190: iload 16
    //   3192: iadd
    //   3193: faload
    //   3194: aload 29
    //   3196: iconst_1
    //   3197: iconst_1
    //   3198: isub
    //   3199: iload 30
    //   3201: iadd
    //   3202: faload
    //   3203: fmul
    //   3204: fastore
    //   3205: goto +3 -> 3208
    //   3208: iload 53
    //   3210: iconst_1
    //   3211: iadd
    //   3212: istore 53
    //   3214: iinc 84 -1
    //   3217: iload 84
    //   3219: ifgt -452 -> 2767
    //   3222: iload 42
    //   3224: ifeq +259 -> 3483
    //   3227: iconst_1
    //   3228: istore 53
    //   3230: iload 5
    //   3232: iconst_1
    //   3233: isub
    //   3234: iconst_1
    //   3235: iadd
    //   3236: istore 84
    //   3238: goto +240 -> 3478
    //   3241: aload 15
    //   3243: iload 53
    //   3245: iconst_1
    //   3246: isub
    //   3247: iload 16
    //   3249: iadd
    //   3250: faload
    //   3251: fconst_0
    //   3252: fcmpl
    //   3253: ifne +7 -> 3260
    //   3256: iconst_0
    //   3257: goto +4 -> 3261
    //   3260: iconst_1
    //   3261: ifeq +208 -> 3469
    //   3264: aload 17
    //   3266: iload 53
    //   3268: iconst_1
    //   3269: isub
    //   3270: iload 18
    //   3272: iadd
    //   3273: faload
    //   3274: aload 79
    //   3276: getfield 93	org/netlib/util/floatW:val	F
    //   3279: fdiv
    //   3280: fload 75
    //   3282: fload 74
    //   3284: fdiv
    //   3285: fcmpl
    //   3286: ifgt +7 -> 3293
    //   3289: iconst_0
    //   3290: goto +4 -> 3294
    //   3293: iconst_1
    //   3294: ifne +40 -> 3334
    //   3297: aload 80
    //   3299: getfield 93	org/netlib/util/floatW:val	F
    //   3302: aload 17
    //   3304: iload 53
    //   3306: iconst_1
    //   3307: isub
    //   3308: iload 18
    //   3310: iadd
    //   3311: faload
    //   3312: fdiv
    //   3313: fload 74
    //   3315: fload 75
    //   3317: fdiv
    //   3318: fcmpl
    //   3319: ifgt +7 -> 3326
    //   3322: iconst_0
    //   3323: goto +4 -> 3327
    //   3326: iconst_1
    //   3327: ifne +7 -> 3334
    //   3330: iconst_0
    //   3331: goto +4 -> 3335
    //   3334: iconst_1
    //   3335: ifeq +134 -> 3469
    //   3338: aload 29
    //   3340: iconst_1
    //   3341: iconst_1
    //   3342: isub
    //   3343: iload 30
    //   3345: iadd
    //   3346: aload 9
    //   3348: iload 53
    //   3350: iconst_1
    //   3351: isub
    //   3352: iload 53
    //   3354: iconst_1
    //   3355: isub
    //   3356: iload 11
    //   3358: imul
    //   3359: iadd
    //   3360: iload 10
    //   3362: iadd
    //   3363: faload
    //   3364: aload 17
    //   3366: iload 53
    //   3368: iconst_1
    //   3369: isub
    //   3370: iload 18
    //   3372: iadd
    //   3373: faload
    //   3374: fdiv
    //   3375: invokestatic 195	java/lang/Math:abs	(F)F
    //   3378: fastore
    //   3379: aload 17
    //   3381: iload 53
    //   3383: iconst_1
    //   3384: isub
    //   3385: iload 18
    //   3387: iadd
    //   3388: aload 17
    //   3390: iload 53
    //   3392: iconst_1
    //   3393: isub
    //   3394: iload 18
    //   3396: iadd
    //   3397: faload
    //   3398: aload 29
    //   3400: iconst_1
    //   3401: iconst_1
    //   3402: isub
    //   3403: iload 30
    //   3405: iadd
    //   3406: faload
    //   3407: fmul
    //   3408: fastore
    //   3409: aload 13
    //   3411: iload 53
    //   3413: iconst_1
    //   3414: isub
    //   3415: iload 14
    //   3417: iadd
    //   3418: aload 13
    //   3420: iload 53
    //   3422: iconst_1
    //   3423: isub
    //   3424: iload 14
    //   3426: iadd
    //   3427: faload
    //   3428: aload 29
    //   3430: iconst_1
    //   3431: iconst_1
    //   3432: isub
    //   3433: iload 30
    //   3435: iadd
    //   3436: faload
    //   3437: fmul
    //   3438: fastore
    //   3439: aload 15
    //   3441: iload 53
    //   3443: iconst_1
    //   3444: isub
    //   3445: iload 16
    //   3447: iadd
    //   3448: aload 15
    //   3450: iload 53
    //   3452: iconst_1
    //   3453: isub
    //   3454: iload 16
    //   3456: iadd
    //   3457: faload
    //   3458: aload 29
    //   3460: iconst_1
    //   3461: iconst_1
    //   3462: isub
    //   3463: iload 30
    //   3465: iadd
    //   3466: faload
    //   3467: fmul
    //   3468: fastore
    //   3469: iload 53
    //   3471: iconst_1
    //   3472: iadd
    //   3473: istore 53
    //   3475: iinc 84 -1
    //   3478: iload 84
    //   3480: ifgt -239 -> 3241
    //   3483: iload 41
    //   3485: ifeq +70 -> 3555
    //   3488: ldc -59
    //   3490: iconst_0
    //   3491: iconst_0
    //   3492: fload 72
    //   3494: fload 71
    //   3496: iload 5
    //   3498: iload 5
    //   3500: aload 6
    //   3502: iload 7
    //   3504: iload 8
    //   3506: aload 55
    //   3508: invokestatic 119	org/netlib/lapack/Slascl:slascl	(Ljava/lang/String;IIFFII[FIILorg/netlib/util/intW;)V
    //   3511: ldc 113
    //   3513: iconst_0
    //   3514: iconst_0
    //   3515: fload 72
    //   3517: fload 71
    //   3519: iload 5
    //   3521: iconst_1
    //   3522: aload 13
    //   3524: iload 14
    //   3526: iload 5
    //   3528: aload 55
    //   3530: invokestatic 119	org/netlib/lapack/Slascl:slascl	(Ljava/lang/String;IIFFII[FIILorg/netlib/util/intW;)V
    //   3533: ldc 113
    //   3535: iconst_0
    //   3536: iconst_0
    //   3537: fload 72
    //   3539: fload 71
    //   3541: iload 5
    //   3543: iconst_1
    //   3544: aload 15
    //   3546: iload 16
    //   3548: iload 5
    //   3550: aload 55
    //   3552: invokestatic 119	org/netlib/lapack/Slascl:slascl	(Ljava/lang/String;IIFFII[FIILorg/netlib/util/intW;)V
    //   3555: iload 42
    //   3557: ifeq +48 -> 3605
    //   3560: ldc -57
    //   3562: iconst_0
    //   3563: iconst_0
    //   3564: fload 75
    //   3566: fload 74
    //   3568: iload 5
    //   3570: iload 5
    //   3572: aload 9
    //   3574: iload 10
    //   3576: iload 11
    //   3578: aload 55
    //   3580: invokestatic 119	org/netlib/lapack/Slascl:slascl	(Ljava/lang/String;IIFFII[FIILorg/netlib/util/intW;)V
    //   3583: ldc 113
    //   3585: iconst_0
    //   3586: iconst_0
    //   3587: fload 75
    //   3589: fload 74
    //   3591: iload 5
    //   3593: iconst_1
    //   3594: aload 17
    //   3596: iload 18
    //   3598: iload 5
    //   3600: aload 55
    //   3602: invokestatic 119	org/netlib/lapack/Slascl:slascl	(Ljava/lang/String;IIFFII[FIILorg/netlib/util/intW;)V
    //   3605: iload 51
    //   3607: ifeq +253 -> 3860
    //   3610: iconst_1
    //   3611: istore 45
    //   3613: iconst_1
    //   3614: istore 47
    //   3616: aload 12
    //   3618: iconst_0
    //   3619: putfield 54	org/netlib/util/intW:val	I
    //   3622: iconst_0
    //   3623: istore 62
    //   3625: iconst_1
    //   3626: istore 53
    //   3628: iload 5
    //   3630: iconst_1
    //   3631: isub
    //   3632: iconst_1
    //   3633: iadd
    //   3634: istore 84
    //   3636: goto +219 -> 3855
    //   3639: aload 83
    //   3641: aload 13
    //   3643: iload 53
    //   3645: iconst_1
    //   3646: isub
    //   3647: iload 14
    //   3649: iadd
    //   3650: aload 15
    //   3652: iload 53
    //   3654: iconst_1
    //   3655: isub
    //   3656: iload 16
    //   3658: iadd
    //   3659: aload 17
    //   3661: iload 53
    //   3663: iconst_1
    //   3664: isub
    //   3665: iload 18
    //   3667: iadd
    //   3668: invokestatic 177	org/netlib/lapack/Sggesx:selctg_methcall	(Ljava/lang/reflect/Method;[FI[FI[FI)Z
    //   3671: istore 40
    //   3673: aload 15
    //   3675: iload 53
    //   3677: iconst_1
    //   3678: isub
    //   3679: iload 16
    //   3681: iadd
    //   3682: faload
    //   3683: fconst_0
    //   3684: fcmpl
    //   3685: ifeq +7 -> 3692
    //   3688: iconst_0
    //   3689: goto +4 -> 3693
    //   3692: iconst_1
    //   3693: ifeq +55 -> 3748
    //   3696: iload 40
    //   3698: ifeq +15 -> 3713
    //   3701: aload 12
    //   3703: aload 12
    //   3705: getfield 54	org/netlib/util/intW:val	I
    //   3708: iconst_1
    //   3709: iadd
    //   3710: putfield 54	org/netlib/util/intW:val	I
    //   3713: iconst_0
    //   3714: istore 62
    //   3716: iload 40
    //   3718: ifeq +14 -> 3732
    //   3721: iload 45
    //   3723: iconst_1
    //   3724: ixor
    //   3725: ifeq +7 -> 3732
    //   3728: iconst_1
    //   3729: goto +4 -> 3733
    //   3732: iconst_0
    //   3733: ifeq +12 -> 3745
    //   3736: aload 37
    //   3738: iload 5
    //   3740: iconst_2
    //   3741: iadd
    //   3742: putfield 54	org/netlib/util/intW:val	I
    //   3745: goto +93 -> 3838
    //   3748: iload 62
    //   3750: iconst_1
    //   3751: if_icmpeq +7 -> 3758
    //   3754: iconst_0
    //   3755: goto +4 -> 3759
    //   3758: iconst_1
    //   3759: ifeq +76 -> 3835
    //   3762: iload 40
    //   3764: ifne +12 -> 3776
    //   3767: iload 45
    //   3769: ifne +7 -> 3776
    //   3772: iconst_0
    //   3773: goto +4 -> 3777
    //   3776: iconst_1
    //   3777: istore 40
    //   3779: iload 40
    //   3781: istore 45
    //   3783: iload 40
    //   3785: ifeq +15 -> 3800
    //   3788: aload 12
    //   3790: aload 12
    //   3792: getfield 54	org/netlib/util/intW:val	I
    //   3795: iconst_2
    //   3796: iadd
    //   3797: putfield 54	org/netlib/util/intW:val	I
    //   3800: iconst_m1
    //   3801: istore 62
    //   3803: iload 40
    //   3805: ifeq +14 -> 3819
    //   3808: iload 47
    //   3810: iconst_1
    //   3811: ixor
    //   3812: ifeq +7 -> 3819
    //   3815: iconst_1
    //   3816: goto +4 -> 3820
    //   3819: iconst_0
    //   3820: ifeq +12 -> 3832
    //   3823: aload 37
    //   3825: iload 5
    //   3827: iconst_2
    //   3828: iadd
    //   3829: putfield 54	org/netlib/util/intW:val	I
    //   3832: goto +6 -> 3838
    //   3835: iconst_1
    //   3836: istore 62
    //   3838: iload 45
    //   3840: istore 47
    //   3842: iload 40
    //   3844: istore 45
    //   3846: iload 53
    //   3848: iconst_1
    //   3849: iadd
    //   3850: istore 53
    //   3852: iinc 84 -1
    //   3855: iload 84
    //   3857: ifgt -218 -> 3639
    //   3860: aload 29
    //   3862: iconst_1
    //   3863: iconst_1
    //   3864: isub
    //   3865: iload 30
    //   3867: iadd
    //   3868: iload 69
    //   3870: i2f
    //   3871: fastore
    //   3872: aload 32
    //   3874: iconst_1
    //   3875: iconst_1
    //   3876: isub
    //   3877: iload 33
    //   3879: iadd
    //   3880: iload 67
    //   3882: iastore
    //   3883: return
    //   3884: goto +0 -> 3884
    //   3887: astore 84
    //   3889: getstatic 205	java/lang/System:err	Ljava/io/PrintStream;
    //   3892: new 207	java/lang/StringBuffer
    //   3895: dup
    //   3896: ldc -47
    //   3898: invokespecial 212	java/lang/StringBuffer:<init>	(Ljava/lang/String;)V
    //   3901: aload 84
    //   3903: invokevirtual 218	java/lang/Throwable:getMessage	()Ljava/lang/String;
    //   3906: invokevirtual 222	java/lang/StringBuffer:append	(Ljava/lang/String;)Ljava/lang/StringBuffer;
    //   3909: invokevirtual 225	java/lang/StringBuffer:toString	()Ljava/lang/String;
    //   3912: invokevirtual 230	java/io/PrintStream:println	(Ljava/lang/String;)V
    //   3915: goto +31 -> 3946
    //   3918: astore 84
    //   3920: getstatic 205	java/lang/System:err	Ljava/io/PrintStream;
    //   3923: new 207	java/lang/StringBuffer
    //   3926: dup
    //   3927: ldc -47
    //   3929: invokespecial 212	java/lang/StringBuffer:<init>	(Ljava/lang/String;)V
    //   3932: aload 84
    //   3934: invokevirtual 218	java/lang/Throwable:getMessage	()Ljava/lang/String;
    //   3937: invokevirtual 222	java/lang/StringBuffer:append	(Ljava/lang/String;)Ljava/lang/StringBuffer;
    //   3940: invokevirtual 225	java/lang/StringBuffer:toString	()Ljava/lang/String;
    //   3943: invokevirtual 230	java/io/PrintStream:println	(Ljava/lang/String;)V
    //   3946: return
    // Local variable table:
    //   start	length	slot	name	signature
    //   0	3947	0	paramString1	String
    //   0	3947	1	paramString2	String
    //   0	3947	2	paramString3	String
    //   0	3947	3	paramObject	Object
    //   0	3947	4	paramString4	String
    //   0	3947	5	paramInt1	int
    //   0	3947	6	paramArrayOfFloat1	float[]
    //   0	3947	7	paramInt2	int
    //   0	3947	8	paramInt3	int
    //   0	3947	9	paramArrayOfFloat2	float[]
    //   0	3947	10	paramInt4	int
    //   0	3947	11	paramInt5	int
    //   0	3947	12	paramintW1	org.netlib.util.intW
    //   0	3947	13	paramArrayOfFloat3	float[]
    //   0	3947	14	paramInt6	int
    //   0	3947	15	paramArrayOfFloat4	float[]
    //   0	3947	16	paramInt7	int
    //   0	3947	17	paramArrayOfFloat5	float[]
    //   0	3947	18	paramInt8	int
    //   0	3947	19	paramArrayOfFloat6	float[]
    //   0	3947	20	paramInt9	int
    //   0	3947	21	paramInt10	int
    //   0	3947	22	paramArrayOfFloat7	float[]
    //   0	3947	23	paramInt11	int
    //   0	3947	24	paramInt12	int
    //   0	3947	25	paramArrayOfFloat8	float[]
    //   0	3947	26	paramInt13	int
    //   0	3947	27	paramArrayOfFloat9	float[]
    //   0	3947	28	paramInt14	int
    //   0	3947	29	paramArrayOfFloat10	float[]
    //   0	3947	30	paramInt15	int
    //   0	3947	31	paramInt16	int
    //   0	3947	32	paramArrayOfInt	int[]
    //   0	3947	33	paramInt17	int
    //   0	3947	34	paramInt18	int
    //   0	3947	35	paramArrayOfBoolean	boolean[]
    //   0	3947	36	paramInt19	int
    //   0	3947	37	paramintW2	org.netlib.util.intW
    //   1	3842	40	bool1	boolean
    //   4	3480	41	i	int
    //   7	3549	42	j	int
    //   10	2635	43	bool2	boolean
    //   13	2684	44	bool3	boolean
    //   16	3829	45	k	int
    //   19	1115	46	m	int
    //   22	3819	47	n	int
    //   25	494	48	bool4	boolean
    //   28	465	49	bool5	boolean
    //   31	940	50	bool6	boolean
    //   34	3572	51	bool7	boolean
    //   37	469	52	bool8	boolean
    //   40	3811	53	i1	int
    //   43	1603	54	i2	int
    //   53	3548	55	localintW1	org.netlib.util.intW
    //   63	2650	56	localintW2	org.netlib.util.intW
    //   66	2504	57	i3	int
    //   69	339	58	i4	int
    //   72	359	59	i5	int
    //   75	2648	60	i6	int
    //   85	2623	61	localintW3	org.netlib.util.intW
    //   88	3749	62	i7	int
    //   91	2641	63	i8	int
    //   94	1743	64	i9	int
    //   97	1868	65	i10	int
    //   100	2310	66	i11	int
    //   103	3778	67	i12	int
    //   106	861	68	i13	int
    //   109	3760	69	i14	int
    //   112	914	70	i15	int
    //   115	3425	71	f1	float
    //   118	3420	72	f2	float
    //   121	1316	73	f3	float
    //   124	3466	74	f4	float
    //   127	3461	75	f5	float
    //   130	1080	76	f6	float
    //   140	2393	77	localfloatW1	org.netlib.util.floatW
    //   150	2397	78	localfloatW2	org.netlib.util.floatW
    //   160	3115	79	localfloatW3	org.netlib.util.floatW
    //   170	3128	80	localfloatW4	org.netlib.util.floatW
    //   173	1238	81	f7	float
    //   178	2434	82	arrayOfFloat	float[]
    //   189	3451	83	localMethod	Method
    //   2278	1578	84	i16	int
    //   3887	15	84	localInvocationTargetException	InvocationTargetException
    //   3918	15	84	localIllegalAccessException	IllegalAccessException
    // Exception table:
    //   from	to	target	type
    //   191	3884	3887	java/lang/reflect/InvocationTargetException
    //   191	3884	3918	java/lang/IllegalAccessException
  }
  
  private static boolean selctg_methcall(Method paramMethod, float[] paramArrayOfFloat1, int paramInt1, float[] paramArrayOfFloat2, int paramInt2, float[] paramArrayOfFloat3, int paramInt3)
    throws InvocationTargetException, IllegalAccessException
  {
    Object[] arrayOfObject = new Object[3];
    arrayOfObject[0] = new Float(paramArrayOfFloat1[paramInt1]);
    arrayOfObject[1] = new Float(paramArrayOfFloat2[paramInt2]);
    arrayOfObject[2] = new Float(paramArrayOfFloat3[paramInt3]);
    return ((Boolean)paramMethod.invoke(null, arrayOfObject)).booleanValue();
  }
}


/* Location:              /Users/assaad/Downloads/arpack_combined_all/!/org/netlib/lapack/Sggesx.class
 * Java compiler version: 1 (45.3)
 * JD-Core Version:       0.7.1
 */