package org.netlib.lapack;

public final class Strevc
{
  /* Error */
  public static void strevc(String paramString1, String paramString2, boolean[] paramArrayOfBoolean, int paramInt1, int paramInt2, float[] paramArrayOfFloat1, int paramInt3, int paramInt4, float[] paramArrayOfFloat2, int paramInt5, int paramInt6, float[] paramArrayOfFloat3, int paramInt7, int paramInt8, int paramInt9, org.netlib.util.intW paramintW1, float[] paramArrayOfFloat4, int paramInt10, org.netlib.util.intW paramintW2)
  {
    // Byte code:
    //   0: iconst_0
    //   1: istore 21
    //   3: iconst_0
    //   4: istore 22
    //   6: iconst_0
    //   7: istore 23
    //   9: iconst_0
    //   10: istore 24
    //   12: iconst_0
    //   13: istore 25
    //   15: iconst_0
    //   16: istore 26
    //   18: iconst_0
    //   19: istore 27
    //   21: iconst_0
    //   22: istore 28
    //   24: new 16	org/netlib/util/intW
    //   27: dup
    //   28: iconst_0
    //   29: invokespecial 19	org/netlib/util/intW:<init>	(I)V
    //   32: astore 29
    //   34: iconst_0
    //   35: istore 30
    //   37: iconst_0
    //   38: istore 31
    //   40: iconst_0
    //   41: istore 32
    //   43: iconst_0
    //   44: istore 33
    //   46: iconst_0
    //   47: istore 34
    //   49: iconst_0
    //   50: istore 35
    //   52: iconst_0
    //   53: istore 36
    //   55: iconst_0
    //   56: istore 37
    //   58: iconst_0
    //   59: istore 38
    //   61: iconst_0
    //   62: istore 39
    //   64: fconst_0
    //   65: fstore 40
    //   67: fconst_0
    //   68: fstore 41
    //   70: fconst_0
    //   71: fstore 42
    //   73: new 21	org/netlib/util/floatW
    //   76: dup
    //   77: fconst_0
    //   78: invokespecial 24	org/netlib/util/floatW:<init>	(F)V
    //   81: astore 43
    //   83: fconst_0
    //   84: fstore 44
    //   86: fconst_0
    //   87: fstore 45
    //   89: new 21	org/netlib/util/floatW
    //   92: dup
    //   93: fconst_0
    //   94: invokespecial 24	org/netlib/util/floatW:<init>	(F)V
    //   97: astore 46
    //   99: fconst_0
    //   100: fstore 47
    //   102: fconst_0
    //   103: fstore 48
    //   105: fconst_0
    //   106: fstore 49
    //   108: new 21	org/netlib/util/floatW
    //   111: dup
    //   112: fconst_0
    //   113: invokespecial 24	org/netlib/util/floatW:<init>	(F)V
    //   116: astore 50
    //   118: fconst_0
    //   119: fstore 51
    //   121: fconst_0
    //   122: fstore 52
    //   124: fconst_0
    //   125: fstore 53
    //   127: fconst_0
    //   128: fstore 54
    //   130: new 21	org/netlib/util/floatW
    //   133: dup
    //   134: fconst_0
    //   135: invokespecial 24	org/netlib/util/floatW:<init>	(F)V
    //   138: astore 55
    //   140: iconst_2
    //   141: iconst_2
    //   142: imul
    //   143: newarray <illegal type>
    //   145: astore 56
    //   147: aload_0
    //   148: ldc 26
    //   150: invokestatic 32	org/netlib/lapack/Lsame:lsame	(Ljava/lang/String;Ljava/lang/String;)Z
    //   153: istore 22
    //   155: aload_0
    //   156: ldc 34
    //   158: invokestatic 32	org/netlib/lapack/Lsame:lsame	(Ljava/lang/String;Ljava/lang/String;)Z
    //   161: ifne +12 -> 173
    //   164: iload 22
    //   166: ifne +7 -> 173
    //   169: iconst_0
    //   170: goto +4 -> 174
    //   173: iconst_1
    //   174: istore 26
    //   176: aload_0
    //   177: ldc 36
    //   179: invokestatic 32	org/netlib/lapack/Lsame:lsame	(Ljava/lang/String;Ljava/lang/String;)Z
    //   182: ifne +12 -> 194
    //   185: iload 22
    //   187: ifne +7 -> 194
    //   190: iconst_0
    //   191: goto +4 -> 195
    //   194: iconst_1
    //   195: istore 23
    //   197: aload_1
    //   198: ldc 38
    //   200: invokestatic 32	org/netlib/lapack/Lsame:lsame	(Ljava/lang/String;Ljava/lang/String;)Z
    //   203: istore 21
    //   205: aload_1
    //   206: ldc 26
    //   208: invokestatic 32	org/netlib/lapack/Lsame:lsame	(Ljava/lang/String;Ljava/lang/String;)Z
    //   211: istore 24
    //   213: aload_1
    //   214: ldc 40
    //   216: invokestatic 32	org/netlib/lapack/Lsame:lsame	(Ljava/lang/String;Ljava/lang/String;)Z
    //   219: istore 27
    //   221: aload 18
    //   223: iconst_0
    //   224: putfield 44	org/netlib/util/intW:val	I
    //   227: iload 26
    //   229: iconst_1
    //   230: ixor
    //   231: ifeq +14 -> 245
    //   234: iload 23
    //   236: iconst_1
    //   237: ixor
    //   238: ifeq +7 -> 245
    //   241: iconst_1
    //   242: goto +4 -> 246
    //   245: iconst_0
    //   246: ifeq +12 -> 258
    //   249: aload 18
    //   251: iconst_m1
    //   252: putfield 44	org/netlib/util/intW:val	I
    //   255: goto +476 -> 731
    //   258: iload 21
    //   260: iconst_1
    //   261: ixor
    //   262: ifeq +14 -> 276
    //   265: iload 24
    //   267: iconst_1
    //   268: ixor
    //   269: ifeq +7 -> 276
    //   272: iconst_1
    //   273: goto +4 -> 277
    //   276: iconst_0
    //   277: ifeq +14 -> 291
    //   280: iload 27
    //   282: iconst_1
    //   283: ixor
    //   284: ifeq +7 -> 291
    //   287: iconst_1
    //   288: goto +4 -> 292
    //   291: iconst_0
    //   292: ifeq +13 -> 305
    //   295: aload 18
    //   297: bipush -2
    //   299: putfield 44	org/netlib/util/intW:val	I
    //   302: goto +429 -> 731
    //   305: iload 4
    //   307: iconst_0
    //   308: if_icmplt +7 -> 315
    //   311: iconst_0
    //   312: goto +4 -> 316
    //   315: iconst_1
    //   316: ifeq +13 -> 329
    //   319: aload 18
    //   321: bipush -4
    //   323: putfield 44	org/netlib/util/intW:val	I
    //   326: goto +405 -> 731
    //   329: iload 7
    //   331: iconst_1
    //   332: iload 4
    //   334: invokestatic 50	java/lang/Math:max	(II)I
    //   337: if_icmplt +7 -> 344
    //   340: iconst_0
    //   341: goto +4 -> 345
    //   344: iconst_1
    //   345: ifeq +13 -> 358
    //   348: aload 18
    //   350: bipush -6
    //   352: putfield 44	org/netlib/util/intW:val	I
    //   355: goto +376 -> 731
    //   358: iload 10
    //   360: iconst_1
    //   361: if_icmplt +7 -> 368
    //   364: iconst_0
    //   365: goto +4 -> 369
    //   368: iconst_1
    //   369: ifne +35 -> 404
    //   372: iload 23
    //   374: ifeq +22 -> 396
    //   377: iload 10
    //   379: iload 4
    //   381: if_icmplt +7 -> 388
    //   384: iconst_0
    //   385: goto +4 -> 389
    //   388: iconst_1
    //   389: ifeq +7 -> 396
    //   392: iconst_1
    //   393: goto +4 -> 397
    //   396: iconst_0
    //   397: ifne +7 -> 404
    //   400: iconst_0
    //   401: goto +4 -> 405
    //   404: iconst_1
    //   405: ifeq +13 -> 418
    //   408: aload 18
    //   410: bipush -8
    //   412: putfield 44	org/netlib/util/intW:val	I
    //   415: goto +316 -> 731
    //   418: iload 13
    //   420: iconst_1
    //   421: if_icmplt +7 -> 428
    //   424: iconst_0
    //   425: goto +4 -> 429
    //   428: iconst_1
    //   429: ifne +35 -> 464
    //   432: iload 26
    //   434: ifeq +22 -> 456
    //   437: iload 13
    //   439: iload 4
    //   441: if_icmplt +7 -> 448
    //   444: iconst_0
    //   445: goto +4 -> 449
    //   448: iconst_1
    //   449: ifeq +7 -> 456
    //   452: iconst_1
    //   453: goto +4 -> 457
    //   456: iconst_0
    //   457: ifne +7 -> 464
    //   460: iconst_0
    //   461: goto +4 -> 465
    //   464: iconst_1
    //   465: ifeq +13 -> 478
    //   468: aload 18
    //   470: bipush -10
    //   472: putfield 44	org/netlib/util/intW:val	I
    //   475: goto +256 -> 731
    //   478: iload 27
    //   480: ifeq +219 -> 699
    //   483: aload 15
    //   485: iconst_0
    //   486: putfield 44	org/netlib/util/intW:val	I
    //   489: iconst_0
    //   490: istore 25
    //   492: iconst_1
    //   493: istore 33
    //   495: iload 4
    //   497: iconst_1
    //   498: isub
    //   499: iconst_1
    //   500: iadd
    //   501: istore 57
    //   503: goto +188 -> 691
    //   506: iload 25
    //   508: ifeq +18 -> 526
    //   511: iconst_0
    //   512: istore 25
    //   514: aload_2
    //   515: iload 33
    //   517: iconst_1
    //   518: isub
    //   519: iload_3
    //   520: iadd
    //   521: iconst_0
    //   522: bastore
    //   523: goto +159 -> 682
    //   526: iload 33
    //   528: iload 4
    //   530: if_icmplt +7 -> 537
    //   533: iconst_0
    //   534: goto +4 -> 538
    //   537: iconst_1
    //   538: ifeq +121 -> 659
    //   541: aload 5
    //   543: iload 33
    //   545: iconst_1
    //   546: iadd
    //   547: iconst_1
    //   548: isub
    //   549: iload 33
    //   551: iconst_1
    //   552: isub
    //   553: iload 7
    //   555: imul
    //   556: iadd
    //   557: iload 6
    //   559: iadd
    //   560: faload
    //   561: fconst_0
    //   562: fcmpl
    //   563: ifeq +7 -> 570
    //   566: iconst_0
    //   567: goto +4 -> 571
    //   570: iconst_1
    //   571: ifeq +29 -> 600
    //   574: aload_2
    //   575: iload 33
    //   577: iconst_1
    //   578: isub
    //   579: iload_3
    //   580: iadd
    //   581: baload
    //   582: ifeq +15 -> 597
    //   585: aload 15
    //   587: aload 15
    //   589: getfield 44	org/netlib/util/intW:val	I
    //   592: iconst_1
    //   593: iadd
    //   594: putfield 44	org/netlib/util/intW:val	I
    //   597: goto +59 -> 656
    //   600: iconst_1
    //   601: istore 25
    //   603: aload_2
    //   604: iload 33
    //   606: iconst_1
    //   607: isub
    //   608: iload_3
    //   609: iadd
    //   610: baload
    //   611: ifne +20 -> 631
    //   614: aload_2
    //   615: iload 33
    //   617: iconst_1
    //   618: iadd
    //   619: iconst_1
    //   620: isub
    //   621: iload_3
    //   622: iadd
    //   623: baload
    //   624: ifne +7 -> 631
    //   627: iconst_0
    //   628: goto +4 -> 632
    //   631: iconst_1
    //   632: ifeq +24 -> 656
    //   635: aload_2
    //   636: iload 33
    //   638: iconst_1
    //   639: isub
    //   640: iload_3
    //   641: iadd
    //   642: iconst_1
    //   643: bastore
    //   644: aload 15
    //   646: aload 15
    //   648: getfield 44	org/netlib/util/intW:val	I
    //   651: iconst_2
    //   652: iadd
    //   653: putfield 44	org/netlib/util/intW:val	I
    //   656: goto +26 -> 682
    //   659: aload_2
    //   660: iload 4
    //   662: iconst_1
    //   663: isub
    //   664: iload_3
    //   665: iadd
    //   666: baload
    //   667: ifeq +15 -> 682
    //   670: aload 15
    //   672: aload 15
    //   674: getfield 44	org/netlib/util/intW:val	I
    //   677: iconst_1
    //   678: iadd
    //   679: putfield 44	org/netlib/util/intW:val	I
    //   682: iload 33
    //   684: iconst_1
    //   685: iadd
    //   686: istore 33
    //   688: iinc 57 -1
    //   691: iload 57
    //   693: ifgt -187 -> 506
    //   696: goto +10 -> 706
    //   699: aload 15
    //   701: iload 4
    //   703: putfield 44	org/netlib/util/intW:val	I
    //   706: iload 14
    //   708: aload 15
    //   710: getfield 44	org/netlib/util/intW:val	I
    //   713: if_icmplt +7 -> 720
    //   716: iconst_0
    //   717: goto +4 -> 721
    //   720: iconst_1
    //   721: ifeq +10 -> 731
    //   724: aload 18
    //   726: bipush -11
    //   728: putfield 44	org/netlib/util/intW:val	I
    //   731: aload 18
    //   733: getfield 44	org/netlib/util/intW:val	I
    //   736: iconst_0
    //   737: if_icmpne +7 -> 744
    //   740: iconst_0
    //   741: goto +4 -> 745
    //   744: iconst_1
    //   745: ifeq +15 -> 760
    //   748: ldc 52
    //   750: aload 18
    //   752: getfield 44	org/netlib/util/intW:val	I
    //   755: ineg
    //   756: invokestatic 58	org/netlib/err/Xerbla:xerbla	(Ljava/lang/String;I)V
    //   759: return
    //   760: iload 4
    //   762: iconst_0
    //   763: if_icmpeq +7 -> 770
    //   766: iconst_0
    //   767: goto +4 -> 771
    //   770: iconst_1
    //   771: ifeq +4 -> 775
    //   774: return
    //   775: aload 50
    //   777: ldc 60
    //   779: invokestatic 66	org/netlib/lapack/Slamch:slamch	(Ljava/lang/String;)F
    //   782: putfield 69	org/netlib/util/floatW:val	F
    //   785: aload 43
    //   787: fconst_1
    //   788: aload 50
    //   790: getfield 69	org/netlib/util/floatW:val	F
    //   793: fdiv
    //   794: putfield 69	org/netlib/util/floatW:val	F
    //   797: aload 50
    //   799: aload 43
    //   801: invokestatic 75	org/netlib/lapack/Slabad:slabad	(Lorg/netlib/util/floatW;Lorg/netlib/util/floatW;)V
    //   804: ldc 77
    //   806: invokestatic 66	org/netlib/lapack/Slamch:slamch	(Ljava/lang/String;)F
    //   809: fstore 49
    //   811: aload 50
    //   813: getfield 69	org/netlib/util/floatW:val	F
    //   816: iload 4
    //   818: i2f
    //   819: fload 49
    //   821: fdiv
    //   822: fmul
    //   823: fstore 48
    //   825: fconst_1
    //   826: fload 49
    //   828: fsub
    //   829: fload 48
    //   831: fdiv
    //   832: fstore 41
    //   834: aload 16
    //   836: iconst_1
    //   837: iconst_1
    //   838: isub
    //   839: iload 17
    //   841: iadd
    //   842: fconst_0
    //   843: fastore
    //   844: iconst_2
    //   845: istore 33
    //   847: iload 4
    //   849: iconst_2
    //   850: isub
    //   851: iconst_1
    //   852: iadd
    //   853: istore 57
    //   855: goto +95 -> 950
    //   858: aload 16
    //   860: iload 33
    //   862: iconst_1
    //   863: isub
    //   864: iload 17
    //   866: iadd
    //   867: fconst_0
    //   868: fastore
    //   869: iconst_1
    //   870: istore 28
    //   872: iload 33
    //   874: iconst_1
    //   875: isub
    //   876: iconst_1
    //   877: isub
    //   878: iconst_1
    //   879: iadd
    //   880: istore 58
    //   882: goto +54 -> 936
    //   885: aload 16
    //   887: iload 33
    //   889: iconst_1
    //   890: isub
    //   891: iload 17
    //   893: iadd
    //   894: aload 16
    //   896: iload 33
    //   898: iconst_1
    //   899: isub
    //   900: iload 17
    //   902: iadd
    //   903: faload
    //   904: aload 5
    //   906: iload 28
    //   908: iconst_1
    //   909: isub
    //   910: iload 33
    //   912: iconst_1
    //   913: isub
    //   914: iload 7
    //   916: imul
    //   917: iadd
    //   918: iload 6
    //   920: iadd
    //   921: faload
    //   922: invokestatic 81	java/lang/Math:abs	(F)F
    //   925: fadd
    //   926: fastore
    //   927: iload 28
    //   929: iconst_1
    //   930: iadd
    //   931: istore 28
    //   933: iinc 58 -1
    //   936: iload 58
    //   938: ifgt -53 -> 885
    //   941: iload 33
    //   943: iconst_1
    //   944: iadd
    //   945: istore 33
    //   947: iinc 57 -1
    //   950: iload 57
    //   952: ifgt -94 -> 858
    //   955: iconst_2
    //   956: iload 4
    //   958: imul
    //   959: istore 39
    //   961: iload 26
    //   963: ifeq +3711 -> 4674
    //   966: iconst_0
    //   967: istore 31
    //   969: aload 15
    //   971: getfield 44	org/netlib/util/intW:val	I
    //   974: istore 32
    //   976: iload 4
    //   978: istore 38
    //   980: iconst_1
    //   981: iload 4
    //   983: isub
    //   984: iconst_m1
    //   985: iadd
    //   986: iconst_m1
    //   987: idiv
    //   988: istore 57
    //   990: goto +3679 -> 4669
    //   993: iload 31
    //   995: iconst_1
    //   996: if_icmpeq +7 -> 1003
    //   999: iconst_0
    //   1000: goto +4 -> 1004
    //   1003: iconst_1
    //   1004: ifeq +6 -> 1010
    //   1007: goto +3619 -> 4626
    //   1010: iload 38
    //   1012: iconst_1
    //   1013: if_icmpeq +7 -> 1020
    //   1016: iconst_0
    //   1017: goto +4 -> 1021
    //   1020: iconst_1
    //   1021: ifeq +6 -> 1027
    //   1024: goto +42 -> 1066
    //   1027: aload 5
    //   1029: iload 38
    //   1031: iconst_1
    //   1032: isub
    //   1033: iload 38
    //   1035: iconst_1
    //   1036: isub
    //   1037: iconst_1
    //   1038: isub
    //   1039: iload 7
    //   1041: imul
    //   1042: iadd
    //   1043: iload 6
    //   1045: iadd
    //   1046: faload
    //   1047: fconst_0
    //   1048: fcmpl
    //   1049: ifeq +7 -> 1056
    //   1052: iconst_0
    //   1053: goto +4 -> 1057
    //   1056: iconst_1
    //   1057: ifeq +6 -> 1063
    //   1060: goto +6 -> 1066
    //   1063: iconst_m1
    //   1064: istore 31
    //   1066: iload 27
    //   1068: ifeq +54 -> 1122
    //   1071: iload 31
    //   1073: iconst_0
    //   1074: if_icmpeq +7 -> 1081
    //   1077: iconst_0
    //   1078: goto +4 -> 1082
    //   1081: iconst_1
    //   1082: ifeq +22 -> 1104
    //   1085: aload_2
    //   1086: iload 38
    //   1088: iconst_1
    //   1089: isub
    //   1090: iload_3
    //   1091: iadd
    //   1092: baload
    //   1093: iconst_1
    //   1094: ixor
    //   1095: ifeq +6 -> 1101
    //   1098: goto +3528 -> 4626
    //   1101: goto +21 -> 1122
    //   1104: aload_2
    //   1105: iload 38
    //   1107: iconst_1
    //   1108: isub
    //   1109: iconst_1
    //   1110: isub
    //   1111: iload_3
    //   1112: iadd
    //   1113: baload
    //   1114: iconst_1
    //   1115: ixor
    //   1116: ifeq +6 -> 1122
    //   1119: goto +3507 -> 4626
    //   1122: aload 5
    //   1124: iload 38
    //   1126: iconst_1
    //   1127: isub
    //   1128: iload 38
    //   1130: iconst_1
    //   1131: isub
    //   1132: iload 7
    //   1134: imul
    //   1135: iadd
    //   1136: iload 6
    //   1138: iadd
    //   1139: faload
    //   1140: fstore 54
    //   1142: fconst_0
    //   1143: fstore 53
    //   1145: iload 31
    //   1147: iconst_0
    //   1148: if_icmpne +7 -> 1155
    //   1151: iconst_0
    //   1152: goto +4 -> 1156
    //   1155: iconst_1
    //   1156: ifeq +62 -> 1218
    //   1159: aload 5
    //   1161: iload 38
    //   1163: iconst_1
    //   1164: isub
    //   1165: iload 38
    //   1167: iconst_1
    //   1168: isub
    //   1169: iconst_1
    //   1170: isub
    //   1171: iload 7
    //   1173: imul
    //   1174: iadd
    //   1175: iload 6
    //   1177: iadd
    //   1178: faload
    //   1179: invokestatic 81	java/lang/Math:abs	(F)F
    //   1182: f2d
    //   1183: invokestatic 85	java/lang/Math:sqrt	(D)D
    //   1186: d2f
    //   1187: aload 5
    //   1189: iload 38
    //   1191: iconst_1
    //   1192: isub
    //   1193: iconst_1
    //   1194: isub
    //   1195: iload 38
    //   1197: iconst_1
    //   1198: isub
    //   1199: iload 7
    //   1201: imul
    //   1202: iadd
    //   1203: iload 6
    //   1205: iadd
    //   1206: faload
    //   1207: invokestatic 81	java/lang/Math:abs	(F)F
    //   1210: f2d
    //   1211: invokestatic 85	java/lang/Math:sqrt	(D)D
    //   1214: d2f
    //   1215: fmul
    //   1216: fstore 53
    //   1218: fload 49
    //   1220: fload 54
    //   1222: invokestatic 81	java/lang/Math:abs	(F)F
    //   1225: fload 53
    //   1227: invokestatic 81	java/lang/Math:abs	(F)F
    //   1230: fadd
    //   1231: fmul
    //   1232: fload 48
    //   1234: invokestatic 88	java/lang/Math:max	(FF)F
    //   1237: fstore 47
    //   1239: iload 31
    //   1241: iconst_0
    //   1242: if_icmpeq +7 -> 1249
    //   1245: iconst_0
    //   1246: goto +4 -> 1250
    //   1249: iconst_1
    //   1250: ifeq +1212 -> 2462
    //   1253: aload 16
    //   1255: iload 38
    //   1257: iload 4
    //   1259: iadd
    //   1260: iconst_1
    //   1261: isub
    //   1262: iload 17
    //   1264: iadd
    //   1265: fconst_1
    //   1266: fastore
    //   1267: iconst_1
    //   1268: istore 37
    //   1270: iload 38
    //   1272: iconst_1
    //   1273: isub
    //   1274: iconst_1
    //   1275: isub
    //   1276: iconst_1
    //   1277: iadd
    //   1278: istore 58
    //   1280: goto +44 -> 1324
    //   1283: aload 16
    //   1285: iload 37
    //   1287: iload 4
    //   1289: iadd
    //   1290: iconst_1
    //   1291: isub
    //   1292: iload 17
    //   1294: iadd
    //   1295: aload 5
    //   1297: iload 37
    //   1299: iconst_1
    //   1300: isub
    //   1301: iload 38
    //   1303: iconst_1
    //   1304: isub
    //   1305: iload 7
    //   1307: imul
    //   1308: iadd
    //   1309: iload 6
    //   1311: iadd
    //   1312: faload
    //   1313: fneg
    //   1314: fastore
    //   1315: iload 37
    //   1317: iconst_1
    //   1318: iadd
    //   1319: istore 37
    //   1321: iinc 58 -1
    //   1324: iload 58
    //   1326: ifgt -43 -> 1283
    //   1329: iload 38
    //   1331: iconst_1
    //   1332: isub
    //   1333: istore 36
    //   1335: iload 38
    //   1337: iconst_1
    //   1338: isub
    //   1339: istore 33
    //   1341: iconst_1
    //   1342: iload 38
    //   1344: iconst_1
    //   1345: isub
    //   1346: isub
    //   1347: iconst_m1
    //   1348: iadd
    //   1349: iconst_m1
    //   1350: idiv
    //   1351: istore 58
    //   1353: goto +784 -> 2137
    //   1356: iload 33
    //   1358: iload 36
    //   1360: if_icmpgt +7 -> 1367
    //   1363: iconst_0
    //   1364: goto +4 -> 1368
    //   1367: iconst_1
    //   1368: ifeq +6 -> 1374
    //   1371: goto +757 -> 2128
    //   1374: iload 33
    //   1376: istore 34
    //   1378: iload 33
    //   1380: istore 35
    //   1382: iload 33
    //   1384: iconst_1
    //   1385: isub
    //   1386: istore 36
    //   1388: iload 33
    //   1390: iconst_1
    //   1391: if_icmpgt +7 -> 1398
    //   1394: iconst_0
    //   1395: goto +4 -> 1399
    //   1398: iconst_1
    //   1399: ifeq +48 -> 1447
    //   1402: aload 5
    //   1404: iload 33
    //   1406: iconst_1
    //   1407: isub
    //   1408: iload 33
    //   1410: iconst_1
    //   1411: isub
    //   1412: iconst_1
    //   1413: isub
    //   1414: iload 7
    //   1416: imul
    //   1417: iadd
    //   1418: iload 6
    //   1420: iadd
    //   1421: faload
    //   1422: fconst_0
    //   1423: fcmpl
    //   1424: ifne +7 -> 1431
    //   1427: iconst_0
    //   1428: goto +4 -> 1432
    //   1431: iconst_1
    //   1432: ifeq +15 -> 1447
    //   1435: iload 33
    //   1437: iconst_1
    //   1438: isub
    //   1439: istore 34
    //   1441: iload 33
    //   1443: iconst_2
    //   1444: isub
    //   1445: istore 36
    //   1447: iload 34
    //   1449: iload 35
    //   1451: if_icmpeq +7 -> 1458
    //   1454: iconst_0
    //   1455: goto +4 -> 1459
    //   1458: iconst_1
    //   1459: ifeq +271 -> 1730
    //   1462: iconst_0
    //   1463: iconst_1
    //   1464: iconst_1
    //   1465: fload 47
    //   1467: fconst_1
    //   1468: aload 5
    //   1470: iload 33
    //   1472: iconst_1
    //   1473: isub
    //   1474: iload 33
    //   1476: iconst_1
    //   1477: isub
    //   1478: iload 7
    //   1480: imul
    //   1481: iadd
    //   1482: iload 6
    //   1484: iadd
    //   1485: iload 7
    //   1487: fconst_1
    //   1488: fconst_1
    //   1489: aload 16
    //   1491: iload 33
    //   1493: iload 4
    //   1495: iadd
    //   1496: iconst_1
    //   1497: isub
    //   1498: iload 17
    //   1500: iadd
    //   1501: iload 4
    //   1503: fload 54
    //   1505: fconst_0
    //   1506: aload 56
    //   1508: iconst_0
    //   1509: iconst_2
    //   1510: aload 46
    //   1512: aload 55
    //   1514: aload 29
    //   1516: invokestatic 94	org/netlib/lapack/Slaln2:slaln2	(ZIIFF[FIIFF[FIIFF[FIILorg/netlib/util/floatW;Lorg/netlib/util/floatW;Lorg/netlib/util/intW;)V
    //   1519: aload 55
    //   1521: getfield 69	org/netlib/util/floatW:val	F
    //   1524: fconst_1
    //   1525: fcmpl
    //   1526: ifgt +7 -> 1533
    //   1529: iconst_0
    //   1530: goto +4 -> 1534
    //   1533: iconst_1
    //   1534: ifeq +79 -> 1613
    //   1537: aload 16
    //   1539: iload 33
    //   1541: iconst_1
    //   1542: isub
    //   1543: iload 17
    //   1545: iadd
    //   1546: faload
    //   1547: fload 41
    //   1549: aload 55
    //   1551: getfield 69	org/netlib/util/floatW:val	F
    //   1554: fdiv
    //   1555: fcmpl
    //   1556: ifgt +7 -> 1563
    //   1559: iconst_0
    //   1560: goto +4 -> 1564
    //   1563: iconst_1
    //   1564: ifeq +49 -> 1613
    //   1567: aload 56
    //   1569: iconst_1
    //   1570: iconst_1
    //   1571: isub
    //   1572: iconst_1
    //   1573: iconst_1
    //   1574: isub
    //   1575: iconst_2
    //   1576: imul
    //   1577: iadd
    //   1578: aload 56
    //   1580: iconst_1
    //   1581: iconst_1
    //   1582: isub
    //   1583: iconst_1
    //   1584: iconst_1
    //   1585: isub
    //   1586: iconst_2
    //   1587: imul
    //   1588: iadd
    //   1589: faload
    //   1590: aload 55
    //   1592: getfield 69	org/netlib/util/floatW:val	F
    //   1595: fdiv
    //   1596: fastore
    //   1597: aload 46
    //   1599: aload 46
    //   1601: getfield 69	org/netlib/util/floatW:val	F
    //   1604: aload 55
    //   1606: getfield 69	org/netlib/util/floatW:val	F
    //   1609: fdiv
    //   1610: putfield 69	org/netlib/util/floatW:val	F
    //   1613: aload 46
    //   1615: getfield 69	org/netlib/util/floatW:val	F
    //   1618: fconst_1
    //   1619: fcmpl
    //   1620: ifne +7 -> 1627
    //   1623: iconst_0
    //   1624: goto +4 -> 1628
    //   1627: iconst_1
    //   1628: ifeq +25 -> 1653
    //   1631: iload 38
    //   1633: aload 46
    //   1635: getfield 69	org/netlib/util/floatW:val	F
    //   1638: aload 16
    //   1640: iconst_1
    //   1641: iload 4
    //   1643: iadd
    //   1644: iconst_1
    //   1645: isub
    //   1646: iload 17
    //   1648: iadd
    //   1649: iconst_1
    //   1650: invokestatic 100	org/netlib/blas/Sscal:sscal	(IF[FII)V
    //   1653: aload 16
    //   1655: iload 33
    //   1657: iload 4
    //   1659: iadd
    //   1660: iconst_1
    //   1661: isub
    //   1662: iload 17
    //   1664: iadd
    //   1665: aload 56
    //   1667: iconst_1
    //   1668: iconst_1
    //   1669: isub
    //   1670: iconst_1
    //   1671: iconst_1
    //   1672: isub
    //   1673: iconst_2
    //   1674: imul
    //   1675: iadd
    //   1676: faload
    //   1677: fastore
    //   1678: iload 33
    //   1680: iconst_1
    //   1681: isub
    //   1682: aload 56
    //   1684: iconst_1
    //   1685: iconst_1
    //   1686: isub
    //   1687: iconst_1
    //   1688: iconst_1
    //   1689: isub
    //   1690: iconst_2
    //   1691: imul
    //   1692: iadd
    //   1693: faload
    //   1694: fneg
    //   1695: aload 5
    //   1697: iconst_1
    //   1698: iconst_1
    //   1699: isub
    //   1700: iload 33
    //   1702: iconst_1
    //   1703: isub
    //   1704: iload 7
    //   1706: imul
    //   1707: iadd
    //   1708: iload 6
    //   1710: iadd
    //   1711: iconst_1
    //   1712: aload 16
    //   1714: iconst_1
    //   1715: iload 4
    //   1717: iadd
    //   1718: iconst_1
    //   1719: isub
    //   1720: iload 17
    //   1722: iadd
    //   1723: iconst_1
    //   1724: invokestatic 106	org/netlib/blas/Saxpy:saxpy	(IF[FII[FII)V
    //   1727: goto +401 -> 2128
    //   1730: iconst_0
    //   1731: iconst_2
    //   1732: iconst_1
    //   1733: fload 47
    //   1735: fconst_1
    //   1736: aload 5
    //   1738: iload 33
    //   1740: iconst_1
    //   1741: isub
    //   1742: iconst_1
    //   1743: isub
    //   1744: iload 33
    //   1746: iconst_1
    //   1747: isub
    //   1748: iconst_1
    //   1749: isub
    //   1750: iload 7
    //   1752: imul
    //   1753: iadd
    //   1754: iload 6
    //   1756: iadd
    //   1757: iload 7
    //   1759: fconst_1
    //   1760: fconst_1
    //   1761: aload 16
    //   1763: iload 33
    //   1765: iconst_1
    //   1766: isub
    //   1767: iload 4
    //   1769: iadd
    //   1770: iconst_1
    //   1771: isub
    //   1772: iload 17
    //   1774: iadd
    //   1775: iload 4
    //   1777: fload 54
    //   1779: fconst_0
    //   1780: aload 56
    //   1782: iconst_0
    //   1783: iconst_2
    //   1784: aload 46
    //   1786: aload 55
    //   1788: aload 29
    //   1790: invokestatic 94	org/netlib/lapack/Slaln2:slaln2	(ZIIFF[FIIFF[FIIFF[FIILorg/netlib/util/floatW;Lorg/netlib/util/floatW;Lorg/netlib/util/intW;)V
    //   1793: aload 55
    //   1795: getfield 69	org/netlib/util/floatW:val	F
    //   1798: fconst_1
    //   1799: fcmpl
    //   1800: ifgt +7 -> 1807
    //   1803: iconst_0
    //   1804: goto +4 -> 1808
    //   1807: iconst_1
    //   1808: ifeq +128 -> 1936
    //   1811: aload 16
    //   1813: iload 33
    //   1815: iconst_1
    //   1816: isub
    //   1817: iconst_1
    //   1818: isub
    //   1819: iload 17
    //   1821: iadd
    //   1822: faload
    //   1823: aload 16
    //   1825: iload 33
    //   1827: iconst_1
    //   1828: isub
    //   1829: iload 17
    //   1831: iadd
    //   1832: faload
    //   1833: invokestatic 88	java/lang/Math:max	(FF)F
    //   1836: fstore 40
    //   1838: fload 40
    //   1840: fload 41
    //   1842: aload 55
    //   1844: getfield 69	org/netlib/util/floatW:val	F
    //   1847: fdiv
    //   1848: fcmpl
    //   1849: ifgt +7 -> 1856
    //   1852: iconst_0
    //   1853: goto +4 -> 1857
    //   1856: iconst_1
    //   1857: ifeq +79 -> 1936
    //   1860: aload 56
    //   1862: iconst_1
    //   1863: iconst_1
    //   1864: isub
    //   1865: iconst_1
    //   1866: iconst_1
    //   1867: isub
    //   1868: iconst_2
    //   1869: imul
    //   1870: iadd
    //   1871: aload 56
    //   1873: iconst_1
    //   1874: iconst_1
    //   1875: isub
    //   1876: iconst_1
    //   1877: iconst_1
    //   1878: isub
    //   1879: iconst_2
    //   1880: imul
    //   1881: iadd
    //   1882: faload
    //   1883: aload 55
    //   1885: getfield 69	org/netlib/util/floatW:val	F
    //   1888: fdiv
    //   1889: fastore
    //   1890: aload 56
    //   1892: iconst_2
    //   1893: iconst_1
    //   1894: isub
    //   1895: iconst_1
    //   1896: iconst_1
    //   1897: isub
    //   1898: iconst_2
    //   1899: imul
    //   1900: iadd
    //   1901: aload 56
    //   1903: iconst_2
    //   1904: iconst_1
    //   1905: isub
    //   1906: iconst_1
    //   1907: iconst_1
    //   1908: isub
    //   1909: iconst_2
    //   1910: imul
    //   1911: iadd
    //   1912: faload
    //   1913: aload 55
    //   1915: getfield 69	org/netlib/util/floatW:val	F
    //   1918: fdiv
    //   1919: fastore
    //   1920: aload 46
    //   1922: aload 46
    //   1924: getfield 69	org/netlib/util/floatW:val	F
    //   1927: aload 55
    //   1929: getfield 69	org/netlib/util/floatW:val	F
    //   1932: fdiv
    //   1933: putfield 69	org/netlib/util/floatW:val	F
    //   1936: aload 46
    //   1938: getfield 69	org/netlib/util/floatW:val	F
    //   1941: fconst_1
    //   1942: fcmpl
    //   1943: ifne +7 -> 1950
    //   1946: iconst_0
    //   1947: goto +4 -> 1951
    //   1950: iconst_1
    //   1951: ifeq +25 -> 1976
    //   1954: iload 38
    //   1956: aload 46
    //   1958: getfield 69	org/netlib/util/floatW:val	F
    //   1961: aload 16
    //   1963: iconst_1
    //   1964: iload 4
    //   1966: iadd
    //   1967: iconst_1
    //   1968: isub
    //   1969: iload 17
    //   1971: iadd
    //   1972: iconst_1
    //   1973: invokestatic 100	org/netlib/blas/Sscal:sscal	(IF[FII)V
    //   1976: aload 16
    //   1978: iload 33
    //   1980: iconst_1
    //   1981: isub
    //   1982: iload 4
    //   1984: iadd
    //   1985: iconst_1
    //   1986: isub
    //   1987: iload 17
    //   1989: iadd
    //   1990: aload 56
    //   1992: iconst_1
    //   1993: iconst_1
    //   1994: isub
    //   1995: iconst_1
    //   1996: iconst_1
    //   1997: isub
    //   1998: iconst_2
    //   1999: imul
    //   2000: iadd
    //   2001: faload
    //   2002: fastore
    //   2003: aload 16
    //   2005: iload 33
    //   2007: iload 4
    //   2009: iadd
    //   2010: iconst_1
    //   2011: isub
    //   2012: iload 17
    //   2014: iadd
    //   2015: aload 56
    //   2017: iconst_2
    //   2018: iconst_1
    //   2019: isub
    //   2020: iconst_1
    //   2021: iconst_1
    //   2022: isub
    //   2023: iconst_2
    //   2024: imul
    //   2025: iadd
    //   2026: faload
    //   2027: fastore
    //   2028: iload 33
    //   2030: iconst_2
    //   2031: isub
    //   2032: aload 56
    //   2034: iconst_1
    //   2035: iconst_1
    //   2036: isub
    //   2037: iconst_1
    //   2038: iconst_1
    //   2039: isub
    //   2040: iconst_2
    //   2041: imul
    //   2042: iadd
    //   2043: faload
    //   2044: fneg
    //   2045: aload 5
    //   2047: iconst_1
    //   2048: iconst_1
    //   2049: isub
    //   2050: iload 33
    //   2052: iconst_1
    //   2053: isub
    //   2054: iconst_1
    //   2055: isub
    //   2056: iload 7
    //   2058: imul
    //   2059: iadd
    //   2060: iload 6
    //   2062: iadd
    //   2063: iconst_1
    //   2064: aload 16
    //   2066: iconst_1
    //   2067: iload 4
    //   2069: iadd
    //   2070: iconst_1
    //   2071: isub
    //   2072: iload 17
    //   2074: iadd
    //   2075: iconst_1
    //   2076: invokestatic 106	org/netlib/blas/Saxpy:saxpy	(IF[FII[FII)V
    //   2079: iload 33
    //   2081: iconst_2
    //   2082: isub
    //   2083: aload 56
    //   2085: iconst_2
    //   2086: iconst_1
    //   2087: isub
    //   2088: iconst_1
    //   2089: iconst_1
    //   2090: isub
    //   2091: iconst_2
    //   2092: imul
    //   2093: iadd
    //   2094: faload
    //   2095: fneg
    //   2096: aload 5
    //   2098: iconst_1
    //   2099: iconst_1
    //   2100: isub
    //   2101: iload 33
    //   2103: iconst_1
    //   2104: isub
    //   2105: iload 7
    //   2107: imul
    //   2108: iadd
    //   2109: iload 6
    //   2111: iadd
    //   2112: iconst_1
    //   2113: aload 16
    //   2115: iconst_1
    //   2116: iload 4
    //   2118: iadd
    //   2119: iconst_1
    //   2120: isub
    //   2121: iload 17
    //   2123: iadd
    //   2124: iconst_1
    //   2125: invokestatic 106	org/netlib/blas/Saxpy:saxpy	(IF[FII[FII)V
    //   2128: iload 33
    //   2130: iconst_m1
    //   2131: iadd
    //   2132: istore 33
    //   2134: iinc 58 -1
    //   2137: iload 58
    //   2139: ifgt -783 -> 1356
    //   2142: iload 24
    //   2144: iconst_1
    //   2145: ixor
    //   2146: ifeq +166 -> 2312
    //   2149: iload 38
    //   2151: aload 16
    //   2153: iconst_1
    //   2154: iload 4
    //   2156: iadd
    //   2157: iconst_1
    //   2158: isub
    //   2159: iload 17
    //   2161: iadd
    //   2162: iconst_1
    //   2163: aload 11
    //   2165: iconst_1
    //   2166: iconst_1
    //   2167: isub
    //   2168: iload 32
    //   2170: iconst_1
    //   2171: isub
    //   2172: iload 13
    //   2174: imul
    //   2175: iadd
    //   2176: iload 12
    //   2178: iadd
    //   2179: iconst_1
    //   2180: invokestatic 112	org/netlib/blas/Scopy:scopy	(I[FII[FII)V
    //   2183: iload 38
    //   2185: aload 11
    //   2187: iconst_1
    //   2188: iconst_1
    //   2189: isub
    //   2190: iload 32
    //   2192: iconst_1
    //   2193: isub
    //   2194: iload 13
    //   2196: imul
    //   2197: iadd
    //   2198: iload 12
    //   2200: iadd
    //   2201: iconst_1
    //   2202: invokestatic 118	org/netlib/blas/Isamax:isamax	(I[FII)I
    //   2205: istore 30
    //   2207: fconst_1
    //   2208: aload 11
    //   2210: iload 30
    //   2212: iconst_1
    //   2213: isub
    //   2214: iload 32
    //   2216: iconst_1
    //   2217: isub
    //   2218: iload 13
    //   2220: imul
    //   2221: iadd
    //   2222: iload 12
    //   2224: iadd
    //   2225: faload
    //   2226: invokestatic 81	java/lang/Math:abs	(F)F
    //   2229: fdiv
    //   2230: fstore 45
    //   2232: iload 38
    //   2234: fload 45
    //   2236: aload 11
    //   2238: iconst_1
    //   2239: iconst_1
    //   2240: isub
    //   2241: iload 32
    //   2243: iconst_1
    //   2244: isub
    //   2245: iload 13
    //   2247: imul
    //   2248: iadd
    //   2249: iload 12
    //   2251: iadd
    //   2252: iconst_1
    //   2253: invokestatic 100	org/netlib/blas/Sscal:sscal	(IF[FII)V
    //   2256: iload 38
    //   2258: iconst_1
    //   2259: iadd
    //   2260: istore 37
    //   2262: iload 4
    //   2264: iload 38
    //   2266: iconst_1
    //   2267: iadd
    //   2268: isub
    //   2269: iconst_1
    //   2270: iadd
    //   2271: istore 58
    //   2273: goto +31 -> 2304
    //   2276: aload 11
    //   2278: iload 37
    //   2280: iconst_1
    //   2281: isub
    //   2282: iload 32
    //   2284: iconst_1
    //   2285: isub
    //   2286: iload 13
    //   2288: imul
    //   2289: iadd
    //   2290: iload 12
    //   2292: iadd
    //   2293: fconst_0
    //   2294: fastore
    //   2295: iload 37
    //   2297: iconst_1
    //   2298: iadd
    //   2299: istore 37
    //   2301: iinc 58 -1
    //   2304: iload 58
    //   2306: ifgt -30 -> 2276
    //   2309: goto +150 -> 2459
    //   2312: iload 38
    //   2314: iconst_1
    //   2315: if_icmpgt +7 -> 2322
    //   2318: iconst_0
    //   2319: goto +4 -> 2323
    //   2322: iconst_1
    //   2323: ifeq +63 -> 2386
    //   2326: ldc 120
    //   2328: iload 4
    //   2330: iload 38
    //   2332: iconst_1
    //   2333: isub
    //   2334: fconst_1
    //   2335: aload 11
    //   2337: iload 12
    //   2339: iload 13
    //   2341: aload 16
    //   2343: iconst_1
    //   2344: iload 4
    //   2346: iadd
    //   2347: iconst_1
    //   2348: isub
    //   2349: iload 17
    //   2351: iadd
    //   2352: iconst_1
    //   2353: aload 16
    //   2355: iload 38
    //   2357: iload 4
    //   2359: iadd
    //   2360: iconst_1
    //   2361: isub
    //   2362: iload 17
    //   2364: iadd
    //   2365: faload
    //   2366: aload 11
    //   2368: iconst_1
    //   2369: iconst_1
    //   2370: isub
    //   2371: iload 38
    //   2373: iconst_1
    //   2374: isub
    //   2375: iload 13
    //   2377: imul
    //   2378: iadd
    //   2379: iload 12
    //   2381: iadd
    //   2382: iconst_1
    //   2383: invokestatic 126	org/netlib/blas/Sgemv:sgemv	(Ljava/lang/String;IIF[FII[FIIF[FII)V
    //   2386: iload 4
    //   2388: aload 11
    //   2390: iconst_1
    //   2391: iconst_1
    //   2392: isub
    //   2393: iload 38
    //   2395: iconst_1
    //   2396: isub
    //   2397: iload 13
    //   2399: imul
    //   2400: iadd
    //   2401: iload 12
    //   2403: iadd
    //   2404: iconst_1
    //   2405: invokestatic 118	org/netlib/blas/Isamax:isamax	(I[FII)I
    //   2408: istore 30
    //   2410: fconst_1
    //   2411: aload 11
    //   2413: iload 30
    //   2415: iconst_1
    //   2416: isub
    //   2417: iload 38
    //   2419: iconst_1
    //   2420: isub
    //   2421: iload 13
    //   2423: imul
    //   2424: iadd
    //   2425: iload 12
    //   2427: iadd
    //   2428: faload
    //   2429: invokestatic 81	java/lang/Math:abs	(F)F
    //   2432: fdiv
    //   2433: fstore 45
    //   2435: iload 4
    //   2437: fload 45
    //   2439: aload 11
    //   2441: iconst_1
    //   2442: iconst_1
    //   2443: isub
    //   2444: iload 38
    //   2446: iconst_1
    //   2447: isub
    //   2448: iload 13
    //   2450: imul
    //   2451: iadd
    //   2452: iload 12
    //   2454: iadd
    //   2455: iconst_1
    //   2456: invokestatic 100	org/netlib/blas/Sscal:sscal	(IF[FII)V
    //   2459: goto +2141 -> 4600
    //   2462: aload 5
    //   2464: iload 38
    //   2466: iconst_1
    //   2467: isub
    //   2468: iconst_1
    //   2469: isub
    //   2470: iload 38
    //   2472: iconst_1
    //   2473: isub
    //   2474: iload 7
    //   2476: imul
    //   2477: iadd
    //   2478: iload 6
    //   2480: iadd
    //   2481: faload
    //   2482: invokestatic 81	java/lang/Math:abs	(F)F
    //   2485: aload 5
    //   2487: iload 38
    //   2489: iconst_1
    //   2490: isub
    //   2491: iload 38
    //   2493: iconst_1
    //   2494: isub
    //   2495: iconst_1
    //   2496: isub
    //   2497: iload 7
    //   2499: imul
    //   2500: iadd
    //   2501: iload 6
    //   2503: iadd
    //   2504: faload
    //   2505: invokestatic 81	java/lang/Math:abs	(F)F
    //   2508: fcmpl
    //   2509: ifge +7 -> 2516
    //   2512: iconst_0
    //   2513: goto +4 -> 2517
    //   2516: iconst_1
    //   2517: ifeq +58 -> 2575
    //   2520: aload 16
    //   2522: iload 38
    //   2524: iconst_1
    //   2525: isub
    //   2526: iload 4
    //   2528: iadd
    //   2529: iconst_1
    //   2530: isub
    //   2531: iload 17
    //   2533: iadd
    //   2534: fconst_1
    //   2535: fastore
    //   2536: aload 16
    //   2538: iload 38
    //   2540: iload 39
    //   2542: iadd
    //   2543: iconst_1
    //   2544: isub
    //   2545: iload 17
    //   2547: iadd
    //   2548: fload 53
    //   2550: aload 5
    //   2552: iload 38
    //   2554: iconst_1
    //   2555: isub
    //   2556: iconst_1
    //   2557: isub
    //   2558: iload 38
    //   2560: iconst_1
    //   2561: isub
    //   2562: iload 7
    //   2564: imul
    //   2565: iadd
    //   2566: iload 6
    //   2568: iadd
    //   2569: faload
    //   2570: fdiv
    //   2571: fastore
    //   2572: goto +56 -> 2628
    //   2575: aload 16
    //   2577: iload 38
    //   2579: iconst_1
    //   2580: isub
    //   2581: iload 4
    //   2583: iadd
    //   2584: iconst_1
    //   2585: isub
    //   2586: iload 17
    //   2588: iadd
    //   2589: fload 53
    //   2591: aload 5
    //   2593: iload 38
    //   2595: iconst_1
    //   2596: isub
    //   2597: iload 38
    //   2599: iconst_1
    //   2600: isub
    //   2601: iconst_1
    //   2602: isub
    //   2603: iload 7
    //   2605: imul
    //   2606: iadd
    //   2607: iload 6
    //   2609: iadd
    //   2610: faload
    //   2611: fdiv
    //   2612: fneg
    //   2613: fastore
    //   2614: aload 16
    //   2616: iload 38
    //   2618: iload 39
    //   2620: iadd
    //   2621: iconst_1
    //   2622: isub
    //   2623: iload 17
    //   2625: iadd
    //   2626: fconst_1
    //   2627: fastore
    //   2628: aload 16
    //   2630: iload 38
    //   2632: iload 4
    //   2634: iadd
    //   2635: iconst_1
    //   2636: isub
    //   2637: iload 17
    //   2639: iadd
    //   2640: fconst_0
    //   2641: fastore
    //   2642: aload 16
    //   2644: iload 38
    //   2646: iconst_1
    //   2647: isub
    //   2648: iload 39
    //   2650: iadd
    //   2651: iconst_1
    //   2652: isub
    //   2653: iload 17
    //   2655: iadd
    //   2656: fconst_0
    //   2657: fastore
    //   2658: iconst_1
    //   2659: istore 37
    //   2661: iload 38
    //   2663: iconst_2
    //   2664: isub
    //   2665: iconst_1
    //   2666: isub
    //   2667: iconst_1
    //   2668: iadd
    //   2669: istore 58
    //   2671: goto +108 -> 2779
    //   2674: aload 16
    //   2676: iload 37
    //   2678: iload 4
    //   2680: iadd
    //   2681: iconst_1
    //   2682: isub
    //   2683: iload 17
    //   2685: iadd
    //   2686: aload 16
    //   2688: iload 38
    //   2690: iconst_1
    //   2691: isub
    //   2692: iload 4
    //   2694: iadd
    //   2695: iconst_1
    //   2696: isub
    //   2697: iload 17
    //   2699: iadd
    //   2700: faload
    //   2701: aload 5
    //   2703: iload 37
    //   2705: iconst_1
    //   2706: isub
    //   2707: iload 38
    //   2709: iconst_1
    //   2710: isub
    //   2711: iconst_1
    //   2712: isub
    //   2713: iload 7
    //   2715: imul
    //   2716: iadd
    //   2717: iload 6
    //   2719: iadd
    //   2720: faload
    //   2721: fmul
    //   2722: fneg
    //   2723: fastore
    //   2724: aload 16
    //   2726: iload 37
    //   2728: iload 39
    //   2730: iadd
    //   2731: iconst_1
    //   2732: isub
    //   2733: iload 17
    //   2735: iadd
    //   2736: aload 16
    //   2738: iload 38
    //   2740: iload 39
    //   2742: iadd
    //   2743: iconst_1
    //   2744: isub
    //   2745: iload 17
    //   2747: iadd
    //   2748: faload
    //   2749: aload 5
    //   2751: iload 37
    //   2753: iconst_1
    //   2754: isub
    //   2755: iload 38
    //   2757: iconst_1
    //   2758: isub
    //   2759: iload 7
    //   2761: imul
    //   2762: iadd
    //   2763: iload 6
    //   2765: iadd
    //   2766: faload
    //   2767: fmul
    //   2768: fneg
    //   2769: fastore
    //   2770: iload 37
    //   2772: iconst_1
    //   2773: iadd
    //   2774: istore 37
    //   2776: iinc 58 -1
    //   2779: iload 58
    //   2781: ifgt -107 -> 2674
    //   2784: iload 38
    //   2786: iconst_2
    //   2787: isub
    //   2788: istore 36
    //   2790: iload 38
    //   2792: iconst_2
    //   2793: isub
    //   2794: istore 33
    //   2796: iconst_1
    //   2797: iload 38
    //   2799: iconst_2
    //   2800: isub
    //   2801: isub
    //   2802: iconst_m1
    //   2803: iadd
    //   2804: iconst_m1
    //   2805: idiv
    //   2806: istore 58
    //   2808: goto +1140 -> 3948
    //   2811: iload 33
    //   2813: iload 36
    //   2815: if_icmpgt +7 -> 2822
    //   2818: iconst_0
    //   2819: goto +4 -> 2823
    //   2822: iconst_1
    //   2823: ifeq +6 -> 2829
    //   2826: goto +1113 -> 3939
    //   2829: iload 33
    //   2831: istore 34
    //   2833: iload 33
    //   2835: istore 35
    //   2837: iload 33
    //   2839: iconst_1
    //   2840: isub
    //   2841: istore 36
    //   2843: iload 33
    //   2845: iconst_1
    //   2846: if_icmpgt +7 -> 2853
    //   2849: iconst_0
    //   2850: goto +4 -> 2854
    //   2853: iconst_1
    //   2854: ifeq +48 -> 2902
    //   2857: aload 5
    //   2859: iload 33
    //   2861: iconst_1
    //   2862: isub
    //   2863: iload 33
    //   2865: iconst_1
    //   2866: isub
    //   2867: iconst_1
    //   2868: isub
    //   2869: iload 7
    //   2871: imul
    //   2872: iadd
    //   2873: iload 6
    //   2875: iadd
    //   2876: faload
    //   2877: fconst_0
    //   2878: fcmpl
    //   2879: ifne +7 -> 2886
    //   2882: iconst_0
    //   2883: goto +4 -> 2887
    //   2886: iconst_1
    //   2887: ifeq +15 -> 2902
    //   2890: iload 33
    //   2892: iconst_1
    //   2893: isub
    //   2894: istore 34
    //   2896: iload 33
    //   2898: iconst_2
    //   2899: isub
    //   2900: istore 36
    //   2902: iload 34
    //   2904: iload 35
    //   2906: if_icmpeq +7 -> 2913
    //   2909: iconst_0
    //   2910: goto +4 -> 2914
    //   2913: iconst_1
    //   2914: ifeq +398 -> 3312
    //   2917: iconst_0
    //   2918: iconst_1
    //   2919: iconst_2
    //   2920: fload 47
    //   2922: fconst_1
    //   2923: aload 5
    //   2925: iload 33
    //   2927: iconst_1
    //   2928: isub
    //   2929: iload 33
    //   2931: iconst_1
    //   2932: isub
    //   2933: iload 7
    //   2935: imul
    //   2936: iadd
    //   2937: iload 6
    //   2939: iadd
    //   2940: iload 7
    //   2942: fconst_1
    //   2943: fconst_1
    //   2944: aload 16
    //   2946: iload 33
    //   2948: iload 4
    //   2950: iadd
    //   2951: iconst_1
    //   2952: isub
    //   2953: iload 17
    //   2955: iadd
    //   2956: iload 4
    //   2958: fload 54
    //   2960: fload 53
    //   2962: aload 56
    //   2964: iconst_0
    //   2965: iconst_2
    //   2966: aload 46
    //   2968: aload 55
    //   2970: aload 29
    //   2972: invokestatic 94	org/netlib/lapack/Slaln2:slaln2	(ZIIFF[FIIFF[FIIFF[FIILorg/netlib/util/floatW;Lorg/netlib/util/floatW;Lorg/netlib/util/intW;)V
    //   2975: aload 55
    //   2977: getfield 69	org/netlib/util/floatW:val	F
    //   2980: fconst_1
    //   2981: fcmpl
    //   2982: ifgt +7 -> 2989
    //   2985: iconst_0
    //   2986: goto +4 -> 2990
    //   2989: iconst_1
    //   2990: ifeq +109 -> 3099
    //   2993: aload 16
    //   2995: iload 33
    //   2997: iconst_1
    //   2998: isub
    //   2999: iload 17
    //   3001: iadd
    //   3002: faload
    //   3003: fload 41
    //   3005: aload 55
    //   3007: getfield 69	org/netlib/util/floatW:val	F
    //   3010: fdiv
    //   3011: fcmpl
    //   3012: ifgt +7 -> 3019
    //   3015: iconst_0
    //   3016: goto +4 -> 3020
    //   3019: iconst_1
    //   3020: ifeq +79 -> 3099
    //   3023: aload 56
    //   3025: iconst_1
    //   3026: iconst_1
    //   3027: isub
    //   3028: iconst_1
    //   3029: iconst_1
    //   3030: isub
    //   3031: iconst_2
    //   3032: imul
    //   3033: iadd
    //   3034: aload 56
    //   3036: iconst_1
    //   3037: iconst_1
    //   3038: isub
    //   3039: iconst_1
    //   3040: iconst_1
    //   3041: isub
    //   3042: iconst_2
    //   3043: imul
    //   3044: iadd
    //   3045: faload
    //   3046: aload 55
    //   3048: getfield 69	org/netlib/util/floatW:val	F
    //   3051: fdiv
    //   3052: fastore
    //   3053: aload 56
    //   3055: iconst_1
    //   3056: iconst_1
    //   3057: isub
    //   3058: iconst_2
    //   3059: iconst_1
    //   3060: isub
    //   3061: iconst_2
    //   3062: imul
    //   3063: iadd
    //   3064: aload 56
    //   3066: iconst_1
    //   3067: iconst_1
    //   3068: isub
    //   3069: iconst_2
    //   3070: iconst_1
    //   3071: isub
    //   3072: iconst_2
    //   3073: imul
    //   3074: iadd
    //   3075: faload
    //   3076: aload 55
    //   3078: getfield 69	org/netlib/util/floatW:val	F
    //   3081: fdiv
    //   3082: fastore
    //   3083: aload 46
    //   3085: aload 46
    //   3087: getfield 69	org/netlib/util/floatW:val	F
    //   3090: aload 55
    //   3092: getfield 69	org/netlib/util/floatW:val	F
    //   3095: fdiv
    //   3096: putfield 69	org/netlib/util/floatW:val	F
    //   3099: aload 46
    //   3101: getfield 69	org/netlib/util/floatW:val	F
    //   3104: fconst_1
    //   3105: fcmpl
    //   3106: ifne +7 -> 3113
    //   3109: iconst_0
    //   3110: goto +4 -> 3114
    //   3113: iconst_1
    //   3114: ifeq +47 -> 3161
    //   3117: iload 38
    //   3119: aload 46
    //   3121: getfield 69	org/netlib/util/floatW:val	F
    //   3124: aload 16
    //   3126: iconst_1
    //   3127: iload 4
    //   3129: iadd
    //   3130: iconst_1
    //   3131: isub
    //   3132: iload 17
    //   3134: iadd
    //   3135: iconst_1
    //   3136: invokestatic 100	org/netlib/blas/Sscal:sscal	(IF[FII)V
    //   3139: iload 38
    //   3141: aload 46
    //   3143: getfield 69	org/netlib/util/floatW:val	F
    //   3146: aload 16
    //   3148: iconst_1
    //   3149: iload 39
    //   3151: iadd
    //   3152: iconst_1
    //   3153: isub
    //   3154: iload 17
    //   3156: iadd
    //   3157: iconst_1
    //   3158: invokestatic 100	org/netlib/blas/Sscal:sscal	(IF[FII)V
    //   3161: aload 16
    //   3163: iload 33
    //   3165: iload 4
    //   3167: iadd
    //   3168: iconst_1
    //   3169: isub
    //   3170: iload 17
    //   3172: iadd
    //   3173: aload 56
    //   3175: iconst_1
    //   3176: iconst_1
    //   3177: isub
    //   3178: iconst_1
    //   3179: iconst_1
    //   3180: isub
    //   3181: iconst_2
    //   3182: imul
    //   3183: iadd
    //   3184: faload
    //   3185: fastore
    //   3186: aload 16
    //   3188: iload 33
    //   3190: iload 39
    //   3192: iadd
    //   3193: iconst_1
    //   3194: isub
    //   3195: iload 17
    //   3197: iadd
    //   3198: aload 56
    //   3200: iconst_1
    //   3201: iconst_1
    //   3202: isub
    //   3203: iconst_2
    //   3204: iconst_1
    //   3205: isub
    //   3206: iconst_2
    //   3207: imul
    //   3208: iadd
    //   3209: faload
    //   3210: fastore
    //   3211: iload 33
    //   3213: iconst_1
    //   3214: isub
    //   3215: aload 56
    //   3217: iconst_1
    //   3218: iconst_1
    //   3219: isub
    //   3220: iconst_1
    //   3221: iconst_1
    //   3222: isub
    //   3223: iconst_2
    //   3224: imul
    //   3225: iadd
    //   3226: faload
    //   3227: fneg
    //   3228: aload 5
    //   3230: iconst_1
    //   3231: iconst_1
    //   3232: isub
    //   3233: iload 33
    //   3235: iconst_1
    //   3236: isub
    //   3237: iload 7
    //   3239: imul
    //   3240: iadd
    //   3241: iload 6
    //   3243: iadd
    //   3244: iconst_1
    //   3245: aload 16
    //   3247: iconst_1
    //   3248: iload 4
    //   3250: iadd
    //   3251: iconst_1
    //   3252: isub
    //   3253: iload 17
    //   3255: iadd
    //   3256: iconst_1
    //   3257: invokestatic 106	org/netlib/blas/Saxpy:saxpy	(IF[FII[FII)V
    //   3260: iload 33
    //   3262: iconst_1
    //   3263: isub
    //   3264: aload 56
    //   3266: iconst_1
    //   3267: iconst_1
    //   3268: isub
    //   3269: iconst_2
    //   3270: iconst_1
    //   3271: isub
    //   3272: iconst_2
    //   3273: imul
    //   3274: iadd
    //   3275: faload
    //   3276: fneg
    //   3277: aload 5
    //   3279: iconst_1
    //   3280: iconst_1
    //   3281: isub
    //   3282: iload 33
    //   3284: iconst_1
    //   3285: isub
    //   3286: iload 7
    //   3288: imul
    //   3289: iadd
    //   3290: iload 6
    //   3292: iadd
    //   3293: iconst_1
    //   3294: aload 16
    //   3296: iconst_1
    //   3297: iload 39
    //   3299: iadd
    //   3300: iconst_1
    //   3301: isub
    //   3302: iload 17
    //   3304: iadd
    //   3305: iconst_1
    //   3306: invokestatic 106	org/netlib/blas/Saxpy:saxpy	(IF[FII[FII)V
    //   3309: goto +630 -> 3939
    //   3312: iconst_0
    //   3313: iconst_2
    //   3314: iconst_2
    //   3315: fload 47
    //   3317: fconst_1
    //   3318: aload 5
    //   3320: iload 33
    //   3322: iconst_1
    //   3323: isub
    //   3324: iconst_1
    //   3325: isub
    //   3326: iload 33
    //   3328: iconst_1
    //   3329: isub
    //   3330: iconst_1
    //   3331: isub
    //   3332: iload 7
    //   3334: imul
    //   3335: iadd
    //   3336: iload 6
    //   3338: iadd
    //   3339: iload 7
    //   3341: fconst_1
    //   3342: fconst_1
    //   3343: aload 16
    //   3345: iload 33
    //   3347: iconst_1
    //   3348: isub
    //   3349: iload 4
    //   3351: iadd
    //   3352: iconst_1
    //   3353: isub
    //   3354: iload 17
    //   3356: iadd
    //   3357: iload 4
    //   3359: fload 54
    //   3361: fload 53
    //   3363: aload 56
    //   3365: iconst_0
    //   3366: iconst_2
    //   3367: aload 46
    //   3369: aload 55
    //   3371: aload 29
    //   3373: invokestatic 94	org/netlib/lapack/Slaln2:slaln2	(ZIIFF[FIIFF[FIIFF[FIILorg/netlib/util/floatW;Lorg/netlib/util/floatW;Lorg/netlib/util/intW;)V
    //   3376: aload 55
    //   3378: getfield 69	org/netlib/util/floatW:val	F
    //   3381: fconst_1
    //   3382: fcmpl
    //   3383: ifgt +7 -> 3390
    //   3386: iconst_0
    //   3387: goto +4 -> 3391
    //   3390: iconst_1
    //   3391: ifeq +182 -> 3573
    //   3394: aload 16
    //   3396: iload 33
    //   3398: iconst_1
    //   3399: isub
    //   3400: iconst_1
    //   3401: isub
    //   3402: iload 17
    //   3404: iadd
    //   3405: faload
    //   3406: aload 16
    //   3408: iload 33
    //   3410: iconst_1
    //   3411: isub
    //   3412: iload 17
    //   3414: iadd
    //   3415: faload
    //   3416: invokestatic 88	java/lang/Math:max	(FF)F
    //   3419: fstore 40
    //   3421: fload 40
    //   3423: fload 41
    //   3425: aload 55
    //   3427: getfield 69	org/netlib/util/floatW:val	F
    //   3430: fdiv
    //   3431: fcmpl
    //   3432: ifgt +7 -> 3439
    //   3435: iconst_0
    //   3436: goto +4 -> 3440
    //   3439: iconst_1
    //   3440: ifeq +133 -> 3573
    //   3443: fconst_1
    //   3444: aload 55
    //   3446: getfield 69	org/netlib/util/floatW:val	F
    //   3449: fdiv
    //   3450: fstore 44
    //   3452: aload 56
    //   3454: iconst_1
    //   3455: iconst_1
    //   3456: isub
    //   3457: iconst_1
    //   3458: iconst_1
    //   3459: isub
    //   3460: iconst_2
    //   3461: imul
    //   3462: iadd
    //   3463: aload 56
    //   3465: iconst_1
    //   3466: iconst_1
    //   3467: isub
    //   3468: iconst_1
    //   3469: iconst_1
    //   3470: isub
    //   3471: iconst_2
    //   3472: imul
    //   3473: iadd
    //   3474: faload
    //   3475: fload 44
    //   3477: fmul
    //   3478: fastore
    //   3479: aload 56
    //   3481: iconst_1
    //   3482: iconst_1
    //   3483: isub
    //   3484: iconst_2
    //   3485: iconst_1
    //   3486: isub
    //   3487: iconst_2
    //   3488: imul
    //   3489: iadd
    //   3490: aload 56
    //   3492: iconst_1
    //   3493: iconst_1
    //   3494: isub
    //   3495: iconst_2
    //   3496: iconst_1
    //   3497: isub
    //   3498: iconst_2
    //   3499: imul
    //   3500: iadd
    //   3501: faload
    //   3502: fload 44
    //   3504: fmul
    //   3505: fastore
    //   3506: aload 56
    //   3508: iconst_2
    //   3509: iconst_1
    //   3510: isub
    //   3511: iconst_1
    //   3512: iconst_1
    //   3513: isub
    //   3514: iconst_2
    //   3515: imul
    //   3516: iadd
    //   3517: aload 56
    //   3519: iconst_2
    //   3520: iconst_1
    //   3521: isub
    //   3522: iconst_1
    //   3523: iconst_1
    //   3524: isub
    //   3525: iconst_2
    //   3526: imul
    //   3527: iadd
    //   3528: faload
    //   3529: fload 44
    //   3531: fmul
    //   3532: fastore
    //   3533: aload 56
    //   3535: iconst_2
    //   3536: iconst_1
    //   3537: isub
    //   3538: iconst_2
    //   3539: iconst_1
    //   3540: isub
    //   3541: iconst_2
    //   3542: imul
    //   3543: iadd
    //   3544: aload 56
    //   3546: iconst_2
    //   3547: iconst_1
    //   3548: isub
    //   3549: iconst_2
    //   3550: iconst_1
    //   3551: isub
    //   3552: iconst_2
    //   3553: imul
    //   3554: iadd
    //   3555: faload
    //   3556: fload 44
    //   3558: fmul
    //   3559: fastore
    //   3560: aload 46
    //   3562: aload 46
    //   3564: getfield 69	org/netlib/util/floatW:val	F
    //   3567: fload 44
    //   3569: fmul
    //   3570: putfield 69	org/netlib/util/floatW:val	F
    //   3573: aload 46
    //   3575: getfield 69	org/netlib/util/floatW:val	F
    //   3578: fconst_1
    //   3579: fcmpl
    //   3580: ifne +7 -> 3587
    //   3583: iconst_0
    //   3584: goto +4 -> 3588
    //   3587: iconst_1
    //   3588: ifeq +47 -> 3635
    //   3591: iload 38
    //   3593: aload 46
    //   3595: getfield 69	org/netlib/util/floatW:val	F
    //   3598: aload 16
    //   3600: iconst_1
    //   3601: iload 4
    //   3603: iadd
    //   3604: iconst_1
    //   3605: isub
    //   3606: iload 17
    //   3608: iadd
    //   3609: iconst_1
    //   3610: invokestatic 100	org/netlib/blas/Sscal:sscal	(IF[FII)V
    //   3613: iload 38
    //   3615: aload 46
    //   3617: getfield 69	org/netlib/util/floatW:val	F
    //   3620: aload 16
    //   3622: iconst_1
    //   3623: iload 39
    //   3625: iadd
    //   3626: iconst_1
    //   3627: isub
    //   3628: iload 17
    //   3630: iadd
    //   3631: iconst_1
    //   3632: invokestatic 100	org/netlib/blas/Sscal:sscal	(IF[FII)V
    //   3635: aload 16
    //   3637: iload 33
    //   3639: iconst_1
    //   3640: isub
    //   3641: iload 4
    //   3643: iadd
    //   3644: iconst_1
    //   3645: isub
    //   3646: iload 17
    //   3648: iadd
    //   3649: aload 56
    //   3651: iconst_1
    //   3652: iconst_1
    //   3653: isub
    //   3654: iconst_1
    //   3655: iconst_1
    //   3656: isub
    //   3657: iconst_2
    //   3658: imul
    //   3659: iadd
    //   3660: faload
    //   3661: fastore
    //   3662: aload 16
    //   3664: iload 33
    //   3666: iload 4
    //   3668: iadd
    //   3669: iconst_1
    //   3670: isub
    //   3671: iload 17
    //   3673: iadd
    //   3674: aload 56
    //   3676: iconst_2
    //   3677: iconst_1
    //   3678: isub
    //   3679: iconst_1
    //   3680: iconst_1
    //   3681: isub
    //   3682: iconst_2
    //   3683: imul
    //   3684: iadd
    //   3685: faload
    //   3686: fastore
    //   3687: aload 16
    //   3689: iload 33
    //   3691: iconst_1
    //   3692: isub
    //   3693: iload 39
    //   3695: iadd
    //   3696: iconst_1
    //   3697: isub
    //   3698: iload 17
    //   3700: iadd
    //   3701: aload 56
    //   3703: iconst_1
    //   3704: iconst_1
    //   3705: isub
    //   3706: iconst_2
    //   3707: iconst_1
    //   3708: isub
    //   3709: iconst_2
    //   3710: imul
    //   3711: iadd
    //   3712: faload
    //   3713: fastore
    //   3714: aload 16
    //   3716: iload 33
    //   3718: iload 39
    //   3720: iadd
    //   3721: iconst_1
    //   3722: isub
    //   3723: iload 17
    //   3725: iadd
    //   3726: aload 56
    //   3728: iconst_2
    //   3729: iconst_1
    //   3730: isub
    //   3731: iconst_2
    //   3732: iconst_1
    //   3733: isub
    //   3734: iconst_2
    //   3735: imul
    //   3736: iadd
    //   3737: faload
    //   3738: fastore
    //   3739: iload 33
    //   3741: iconst_2
    //   3742: isub
    //   3743: aload 56
    //   3745: iconst_1
    //   3746: iconst_1
    //   3747: isub
    //   3748: iconst_1
    //   3749: iconst_1
    //   3750: isub
    //   3751: iconst_2
    //   3752: imul
    //   3753: iadd
    //   3754: faload
    //   3755: fneg
    //   3756: aload 5
    //   3758: iconst_1
    //   3759: iconst_1
    //   3760: isub
    //   3761: iload 33
    //   3763: iconst_1
    //   3764: isub
    //   3765: iconst_1
    //   3766: isub
    //   3767: iload 7
    //   3769: imul
    //   3770: iadd
    //   3771: iload 6
    //   3773: iadd
    //   3774: iconst_1
    //   3775: aload 16
    //   3777: iconst_1
    //   3778: iload 4
    //   3780: iadd
    //   3781: iconst_1
    //   3782: isub
    //   3783: iload 17
    //   3785: iadd
    //   3786: iconst_1
    //   3787: invokestatic 106	org/netlib/blas/Saxpy:saxpy	(IF[FII[FII)V
    //   3790: iload 33
    //   3792: iconst_2
    //   3793: isub
    //   3794: aload 56
    //   3796: iconst_2
    //   3797: iconst_1
    //   3798: isub
    //   3799: iconst_1
    //   3800: iconst_1
    //   3801: isub
    //   3802: iconst_2
    //   3803: imul
    //   3804: iadd
    //   3805: faload
    //   3806: fneg
    //   3807: aload 5
    //   3809: iconst_1
    //   3810: iconst_1
    //   3811: isub
    //   3812: iload 33
    //   3814: iconst_1
    //   3815: isub
    //   3816: iload 7
    //   3818: imul
    //   3819: iadd
    //   3820: iload 6
    //   3822: iadd
    //   3823: iconst_1
    //   3824: aload 16
    //   3826: iconst_1
    //   3827: iload 4
    //   3829: iadd
    //   3830: iconst_1
    //   3831: isub
    //   3832: iload 17
    //   3834: iadd
    //   3835: iconst_1
    //   3836: invokestatic 106	org/netlib/blas/Saxpy:saxpy	(IF[FII[FII)V
    //   3839: iload 33
    //   3841: iconst_2
    //   3842: isub
    //   3843: aload 56
    //   3845: iconst_1
    //   3846: iconst_1
    //   3847: isub
    //   3848: iconst_2
    //   3849: iconst_1
    //   3850: isub
    //   3851: iconst_2
    //   3852: imul
    //   3853: iadd
    //   3854: faload
    //   3855: fneg
    //   3856: aload 5
    //   3858: iconst_1
    //   3859: iconst_1
    //   3860: isub
    //   3861: iload 33
    //   3863: iconst_1
    //   3864: isub
    //   3865: iconst_1
    //   3866: isub
    //   3867: iload 7
    //   3869: imul
    //   3870: iadd
    //   3871: iload 6
    //   3873: iadd
    //   3874: iconst_1
    //   3875: aload 16
    //   3877: iconst_1
    //   3878: iload 39
    //   3880: iadd
    //   3881: iconst_1
    //   3882: isub
    //   3883: iload 17
    //   3885: iadd
    //   3886: iconst_1
    //   3887: invokestatic 106	org/netlib/blas/Saxpy:saxpy	(IF[FII[FII)V
    //   3890: iload 33
    //   3892: iconst_2
    //   3893: isub
    //   3894: aload 56
    //   3896: iconst_2
    //   3897: iconst_1
    //   3898: isub
    //   3899: iconst_2
    //   3900: iconst_1
    //   3901: isub
    //   3902: iconst_2
    //   3903: imul
    //   3904: iadd
    //   3905: faload
    //   3906: fneg
    //   3907: aload 5
    //   3909: iconst_1
    //   3910: iconst_1
    //   3911: isub
    //   3912: iload 33
    //   3914: iconst_1
    //   3915: isub
    //   3916: iload 7
    //   3918: imul
    //   3919: iadd
    //   3920: iload 6
    //   3922: iadd
    //   3923: iconst_1
    //   3924: aload 16
    //   3926: iconst_1
    //   3927: iload 39
    //   3929: iadd
    //   3930: iconst_1
    //   3931: isub
    //   3932: iload 17
    //   3934: iadd
    //   3935: iconst_1
    //   3936: invokestatic 106	org/netlib/blas/Saxpy:saxpy	(IF[FII[FII)V
    //   3939: iload 33
    //   3941: iconst_m1
    //   3942: iadd
    //   3943: istore 33
    //   3945: iinc 58 -1
    //   3948: iload 58
    //   3950: ifgt -1139 -> 2811
    //   3953: iload 24
    //   3955: iconst_1
    //   3956: ixor
    //   3957: ifeq +289 -> 4246
    //   3960: iload 38
    //   3962: aload 16
    //   3964: iconst_1
    //   3965: iload 4
    //   3967: iadd
    //   3968: iconst_1
    //   3969: isub
    //   3970: iload 17
    //   3972: iadd
    //   3973: iconst_1
    //   3974: aload 11
    //   3976: iconst_1
    //   3977: iconst_1
    //   3978: isub
    //   3979: iload 32
    //   3981: iconst_1
    //   3982: isub
    //   3983: iconst_1
    //   3984: isub
    //   3985: iload 13
    //   3987: imul
    //   3988: iadd
    //   3989: iload 12
    //   3991: iadd
    //   3992: iconst_1
    //   3993: invokestatic 112	org/netlib/blas/Scopy:scopy	(I[FII[FII)V
    //   3996: iload 38
    //   3998: aload 16
    //   4000: iconst_1
    //   4001: iload 39
    //   4003: iadd
    //   4004: iconst_1
    //   4005: isub
    //   4006: iload 17
    //   4008: iadd
    //   4009: iconst_1
    //   4010: aload 11
    //   4012: iconst_1
    //   4013: iconst_1
    //   4014: isub
    //   4015: iload 32
    //   4017: iconst_1
    //   4018: isub
    //   4019: iload 13
    //   4021: imul
    //   4022: iadd
    //   4023: iload 12
    //   4025: iadd
    //   4026: iconst_1
    //   4027: invokestatic 112	org/netlib/blas/Scopy:scopy	(I[FII[FII)V
    //   4030: fconst_0
    //   4031: fstore 42
    //   4033: iconst_1
    //   4034: istore 37
    //   4036: iload 38
    //   4038: iconst_1
    //   4039: isub
    //   4040: iconst_1
    //   4041: iadd
    //   4042: istore 58
    //   4044: goto +64 -> 4108
    //   4047: fload 42
    //   4049: aload 11
    //   4051: iload 37
    //   4053: iconst_1
    //   4054: isub
    //   4055: iload 32
    //   4057: iconst_1
    //   4058: isub
    //   4059: iconst_1
    //   4060: isub
    //   4061: iload 13
    //   4063: imul
    //   4064: iadd
    //   4065: iload 12
    //   4067: iadd
    //   4068: faload
    //   4069: invokestatic 81	java/lang/Math:abs	(F)F
    //   4072: aload 11
    //   4074: iload 37
    //   4076: iconst_1
    //   4077: isub
    //   4078: iload 32
    //   4080: iconst_1
    //   4081: isub
    //   4082: iload 13
    //   4084: imul
    //   4085: iadd
    //   4086: iload 12
    //   4088: iadd
    //   4089: faload
    //   4090: invokestatic 81	java/lang/Math:abs	(F)F
    //   4093: fadd
    //   4094: invokestatic 88	java/lang/Math:max	(FF)F
    //   4097: fstore 42
    //   4099: iload 37
    //   4101: iconst_1
    //   4102: iadd
    //   4103: istore 37
    //   4105: iinc 58 -1
    //   4108: iload 58
    //   4110: ifgt -63 -> 4047
    //   4113: fconst_1
    //   4114: fload 42
    //   4116: fdiv
    //   4117: fstore 45
    //   4119: iload 38
    //   4121: fload 45
    //   4123: aload 11
    //   4125: iconst_1
    //   4126: iconst_1
    //   4127: isub
    //   4128: iload 32
    //   4130: iconst_1
    //   4131: isub
    //   4132: iconst_1
    //   4133: isub
    //   4134: iload 13
    //   4136: imul
    //   4137: iadd
    //   4138: iload 12
    //   4140: iadd
    //   4141: iconst_1
    //   4142: invokestatic 100	org/netlib/blas/Sscal:sscal	(IF[FII)V
    //   4145: iload 38
    //   4147: fload 45
    //   4149: aload 11
    //   4151: iconst_1
    //   4152: iconst_1
    //   4153: isub
    //   4154: iload 32
    //   4156: iconst_1
    //   4157: isub
    //   4158: iload 13
    //   4160: imul
    //   4161: iadd
    //   4162: iload 12
    //   4164: iadd
    //   4165: iconst_1
    //   4166: invokestatic 100	org/netlib/blas/Sscal:sscal	(IF[FII)V
    //   4169: iload 38
    //   4171: iconst_1
    //   4172: iadd
    //   4173: istore 37
    //   4175: iload 4
    //   4177: iload 38
    //   4179: iconst_1
    //   4180: iadd
    //   4181: isub
    //   4182: iconst_1
    //   4183: iadd
    //   4184: istore 58
    //   4186: goto +52 -> 4238
    //   4189: aload 11
    //   4191: iload 37
    //   4193: iconst_1
    //   4194: isub
    //   4195: iload 32
    //   4197: iconst_1
    //   4198: isub
    //   4199: iconst_1
    //   4200: isub
    //   4201: iload 13
    //   4203: imul
    //   4204: iadd
    //   4205: iload 12
    //   4207: iadd
    //   4208: fconst_0
    //   4209: fastore
    //   4210: aload 11
    //   4212: iload 37
    //   4214: iconst_1
    //   4215: isub
    //   4216: iload 32
    //   4218: iconst_1
    //   4219: isub
    //   4220: iload 13
    //   4222: imul
    //   4223: iadd
    //   4224: iload 12
    //   4226: iadd
    //   4227: fconst_0
    //   4228: fastore
    //   4229: iload 37
    //   4231: iconst_1
    //   4232: iadd
    //   4233: istore 37
    //   4235: iinc 58 -1
    //   4238: iload 58
    //   4240: ifgt -51 -> 4189
    //   4243: goto +357 -> 4600
    //   4246: iload 38
    //   4248: iconst_2
    //   4249: if_icmpgt +7 -> 4256
    //   4252: iconst_0
    //   4253: goto +4 -> 4257
    //   4256: iconst_1
    //   4257: ifeq +130 -> 4387
    //   4260: ldc 120
    //   4262: iload 4
    //   4264: iload 38
    //   4266: iconst_2
    //   4267: isub
    //   4268: fconst_1
    //   4269: aload 11
    //   4271: iload 12
    //   4273: iload 13
    //   4275: aload 16
    //   4277: iconst_1
    //   4278: iload 4
    //   4280: iadd
    //   4281: iconst_1
    //   4282: isub
    //   4283: iload 17
    //   4285: iadd
    //   4286: iconst_1
    //   4287: aload 16
    //   4289: iload 38
    //   4291: iconst_1
    //   4292: isub
    //   4293: iload 4
    //   4295: iadd
    //   4296: iconst_1
    //   4297: isub
    //   4298: iload 17
    //   4300: iadd
    //   4301: faload
    //   4302: aload 11
    //   4304: iconst_1
    //   4305: iconst_1
    //   4306: isub
    //   4307: iload 38
    //   4309: iconst_1
    //   4310: isub
    //   4311: iconst_1
    //   4312: isub
    //   4313: iload 13
    //   4315: imul
    //   4316: iadd
    //   4317: iload 12
    //   4319: iadd
    //   4320: iconst_1
    //   4321: invokestatic 126	org/netlib/blas/Sgemv:sgemv	(Ljava/lang/String;IIF[FII[FIIF[FII)V
    //   4324: ldc 120
    //   4326: iload 4
    //   4328: iload 38
    //   4330: iconst_2
    //   4331: isub
    //   4332: fconst_1
    //   4333: aload 11
    //   4335: iload 12
    //   4337: iload 13
    //   4339: aload 16
    //   4341: iconst_1
    //   4342: iload 39
    //   4344: iadd
    //   4345: iconst_1
    //   4346: isub
    //   4347: iload 17
    //   4349: iadd
    //   4350: iconst_1
    //   4351: aload 16
    //   4353: iload 38
    //   4355: iload 39
    //   4357: iadd
    //   4358: iconst_1
    //   4359: isub
    //   4360: iload 17
    //   4362: iadd
    //   4363: faload
    //   4364: aload 11
    //   4366: iconst_1
    //   4367: iconst_1
    //   4368: isub
    //   4369: iload 38
    //   4371: iconst_1
    //   4372: isub
    //   4373: iload 13
    //   4375: imul
    //   4376: iadd
    //   4377: iload 12
    //   4379: iadd
    //   4380: iconst_1
    //   4381: invokestatic 126	org/netlib/blas/Sgemv:sgemv	(Ljava/lang/String;IIF[FII[FIIF[FII)V
    //   4384: goto +77 -> 4461
    //   4387: iload 4
    //   4389: aload 16
    //   4391: iload 38
    //   4393: iconst_1
    //   4394: isub
    //   4395: iload 4
    //   4397: iadd
    //   4398: iconst_1
    //   4399: isub
    //   4400: iload 17
    //   4402: iadd
    //   4403: faload
    //   4404: aload 11
    //   4406: iconst_1
    //   4407: iconst_1
    //   4408: isub
    //   4409: iload 38
    //   4411: iconst_1
    //   4412: isub
    //   4413: iconst_1
    //   4414: isub
    //   4415: iload 13
    //   4417: imul
    //   4418: iadd
    //   4419: iload 12
    //   4421: iadd
    //   4422: iconst_1
    //   4423: invokestatic 100	org/netlib/blas/Sscal:sscal	(IF[FII)V
    //   4426: iload 4
    //   4428: aload 16
    //   4430: iload 38
    //   4432: iload 39
    //   4434: iadd
    //   4435: iconst_1
    //   4436: isub
    //   4437: iload 17
    //   4439: iadd
    //   4440: faload
    //   4441: aload 11
    //   4443: iconst_1
    //   4444: iconst_1
    //   4445: isub
    //   4446: iload 38
    //   4448: iconst_1
    //   4449: isub
    //   4450: iload 13
    //   4452: imul
    //   4453: iadd
    //   4454: iload 12
    //   4456: iadd
    //   4457: iconst_1
    //   4458: invokestatic 100	org/netlib/blas/Sscal:sscal	(IF[FII)V
    //   4461: fconst_0
    //   4462: fstore 42
    //   4464: iconst_1
    //   4465: istore 37
    //   4467: iload 4
    //   4469: iconst_1
    //   4470: isub
    //   4471: iconst_1
    //   4472: iadd
    //   4473: istore 58
    //   4475: goto +64 -> 4539
    //   4478: fload 42
    //   4480: aload 11
    //   4482: iload 37
    //   4484: iconst_1
    //   4485: isub
    //   4486: iload 38
    //   4488: iconst_1
    //   4489: isub
    //   4490: iconst_1
    //   4491: isub
    //   4492: iload 13
    //   4494: imul
    //   4495: iadd
    //   4496: iload 12
    //   4498: iadd
    //   4499: faload
    //   4500: invokestatic 81	java/lang/Math:abs	(F)F
    //   4503: aload 11
    //   4505: iload 37
    //   4507: iconst_1
    //   4508: isub
    //   4509: iload 38
    //   4511: iconst_1
    //   4512: isub
    //   4513: iload 13
    //   4515: imul
    //   4516: iadd
    //   4517: iload 12
    //   4519: iadd
    //   4520: faload
    //   4521: invokestatic 81	java/lang/Math:abs	(F)F
    //   4524: fadd
    //   4525: invokestatic 88	java/lang/Math:max	(FF)F
    //   4528: fstore 42
    //   4530: iload 37
    //   4532: iconst_1
    //   4533: iadd
    //   4534: istore 37
    //   4536: iinc 58 -1
    //   4539: iload 58
    //   4541: ifgt -63 -> 4478
    //   4544: fconst_1
    //   4545: fload 42
    //   4547: fdiv
    //   4548: fstore 45
    //   4550: iload 4
    //   4552: fload 45
    //   4554: aload 11
    //   4556: iconst_1
    //   4557: iconst_1
    //   4558: isub
    //   4559: iload 38
    //   4561: iconst_1
    //   4562: isub
    //   4563: iconst_1
    //   4564: isub
    //   4565: iload 13
    //   4567: imul
    //   4568: iadd
    //   4569: iload 12
    //   4571: iadd
    //   4572: iconst_1
    //   4573: invokestatic 100	org/netlib/blas/Sscal:sscal	(IF[FII)V
    //   4576: iload 4
    //   4578: fload 45
    //   4580: aload 11
    //   4582: iconst_1
    //   4583: iconst_1
    //   4584: isub
    //   4585: iload 38
    //   4587: iconst_1
    //   4588: isub
    //   4589: iload 13
    //   4591: imul
    //   4592: iadd
    //   4593: iload 12
    //   4595: iadd
    //   4596: iconst_1
    //   4597: invokestatic 100	org/netlib/blas/Sscal:sscal	(IF[FII)V
    //   4600: iload 32
    //   4602: iconst_1
    //   4603: isub
    //   4604: istore 32
    //   4606: iload 31
    //   4608: iconst_0
    //   4609: if_icmpne +7 -> 4616
    //   4612: iconst_0
    //   4613: goto +4 -> 4617
    //   4616: iconst_1
    //   4617: ifeq +9 -> 4626
    //   4620: iload 32
    //   4622: iconst_1
    //   4623: isub
    //   4624: istore 32
    //   4626: iload 31
    //   4628: iconst_1
    //   4629: if_icmpeq +7 -> 4636
    //   4632: iconst_0
    //   4633: goto +4 -> 4637
    //   4636: iconst_1
    //   4637: ifeq +6 -> 4643
    //   4640: iconst_0
    //   4641: istore 31
    //   4643: iload 31
    //   4645: iconst_m1
    //   4646: if_icmpeq +7 -> 4653
    //   4649: iconst_0
    //   4650: goto +4 -> 4654
    //   4653: iconst_1
    //   4654: ifeq +6 -> 4660
    //   4657: iconst_1
    //   4658: istore 31
    //   4660: iload 38
    //   4662: iconst_m1
    //   4663: iadd
    //   4664: istore 38
    //   4666: iinc 57 -1
    //   4669: iload 57
    //   4671: ifgt -3678 -> 993
    //   4674: iload 23
    //   4676: ifeq +4025 -> 8701
    //   4679: iconst_0
    //   4680: istore 31
    //   4682: iconst_1
    //   4683: istore 32
    //   4685: iconst_1
    //   4686: istore 38
    //   4688: iload 4
    //   4690: iconst_1
    //   4691: isub
    //   4692: iconst_1
    //   4693: iadd
    //   4694: istore 57
    //   4696: goto +4000 -> 8696
    //   4699: iload 31
    //   4701: iconst_m1
    //   4702: if_icmpeq +7 -> 4709
    //   4705: iconst_0
    //   4706: goto +4 -> 4710
    //   4709: iconst_1
    //   4710: ifeq +6 -> 4716
    //   4713: goto +3940 -> 8653
    //   4716: iload 38
    //   4718: iload 4
    //   4720: if_icmpeq +7 -> 4727
    //   4723: iconst_0
    //   4724: goto +4 -> 4728
    //   4727: iconst_1
    //   4728: ifeq +6 -> 4734
    //   4731: goto +42 -> 4773
    //   4734: aload 5
    //   4736: iload 38
    //   4738: iconst_1
    //   4739: iadd
    //   4740: iconst_1
    //   4741: isub
    //   4742: iload 38
    //   4744: iconst_1
    //   4745: isub
    //   4746: iload 7
    //   4748: imul
    //   4749: iadd
    //   4750: iload 6
    //   4752: iadd
    //   4753: faload
    //   4754: fconst_0
    //   4755: fcmpl
    //   4756: ifeq +7 -> 4763
    //   4759: iconst_0
    //   4760: goto +4 -> 4764
    //   4763: iconst_1
    //   4764: ifeq +6 -> 4770
    //   4767: goto +6 -> 4773
    //   4770: iconst_1
    //   4771: istore 31
    //   4773: iload 27
    //   4775: ifeq +19 -> 4794
    //   4778: aload_2
    //   4779: iload 38
    //   4781: iconst_1
    //   4782: isub
    //   4783: iload_3
    //   4784: iadd
    //   4785: baload
    //   4786: iconst_1
    //   4787: ixor
    //   4788: ifeq +6 -> 4794
    //   4791: goto +3862 -> 8653
    //   4794: aload 5
    //   4796: iload 38
    //   4798: iconst_1
    //   4799: isub
    //   4800: iload 38
    //   4802: iconst_1
    //   4803: isub
    //   4804: iload 7
    //   4806: imul
    //   4807: iadd
    //   4808: iload 6
    //   4810: iadd
    //   4811: faload
    //   4812: fstore 54
    //   4814: fconst_0
    //   4815: fstore 53
    //   4817: iload 31
    //   4819: iconst_0
    //   4820: if_icmpne +7 -> 4827
    //   4823: iconst_0
    //   4824: goto +4 -> 4828
    //   4827: iconst_1
    //   4828: ifeq +62 -> 4890
    //   4831: aload 5
    //   4833: iload 38
    //   4835: iconst_1
    //   4836: isub
    //   4837: iload 38
    //   4839: iconst_1
    //   4840: iadd
    //   4841: iconst_1
    //   4842: isub
    //   4843: iload 7
    //   4845: imul
    //   4846: iadd
    //   4847: iload 6
    //   4849: iadd
    //   4850: faload
    //   4851: invokestatic 81	java/lang/Math:abs	(F)F
    //   4854: f2d
    //   4855: invokestatic 85	java/lang/Math:sqrt	(D)D
    //   4858: d2f
    //   4859: aload 5
    //   4861: iload 38
    //   4863: iconst_1
    //   4864: iadd
    //   4865: iconst_1
    //   4866: isub
    //   4867: iload 38
    //   4869: iconst_1
    //   4870: isub
    //   4871: iload 7
    //   4873: imul
    //   4874: iadd
    //   4875: iload 6
    //   4877: iadd
    //   4878: faload
    //   4879: invokestatic 81	java/lang/Math:abs	(F)F
    //   4882: f2d
    //   4883: invokestatic 85	java/lang/Math:sqrt	(D)D
    //   4886: d2f
    //   4887: fmul
    //   4888: fstore 53
    //   4890: fload 49
    //   4892: fload 54
    //   4894: invokestatic 81	java/lang/Math:abs	(F)F
    //   4897: fload 53
    //   4899: invokestatic 81	java/lang/Math:abs	(F)F
    //   4902: fadd
    //   4903: fmul
    //   4904: fload 48
    //   4906: invokestatic 88	java/lang/Math:max	(FF)F
    //   4909: fstore 47
    //   4911: iload 31
    //   4913: iconst_0
    //   4914: if_icmpeq +7 -> 4921
    //   4917: iconst_0
    //   4918: goto +4 -> 4922
    //   4921: iconst_1
    //   4922: ifeq +1325 -> 6247
    //   4925: aload 16
    //   4927: iload 38
    //   4929: iload 4
    //   4931: iadd
    //   4932: iconst_1
    //   4933: isub
    //   4934: iload 17
    //   4936: iadd
    //   4937: fconst_1
    //   4938: fastore
    //   4939: iload 38
    //   4941: iconst_1
    //   4942: iadd
    //   4943: istore 37
    //   4945: iload 4
    //   4947: iload 38
    //   4949: iconst_1
    //   4950: iadd
    //   4951: isub
    //   4952: iconst_1
    //   4953: iadd
    //   4954: istore 58
    //   4956: goto +44 -> 5000
    //   4959: aload 16
    //   4961: iload 37
    //   4963: iload 4
    //   4965: iadd
    //   4966: iconst_1
    //   4967: isub
    //   4968: iload 17
    //   4970: iadd
    //   4971: aload 5
    //   4973: iload 38
    //   4975: iconst_1
    //   4976: isub
    //   4977: iload 37
    //   4979: iconst_1
    //   4980: isub
    //   4981: iload 7
    //   4983: imul
    //   4984: iadd
    //   4985: iload 6
    //   4987: iadd
    //   4988: faload
    //   4989: fneg
    //   4990: fastore
    //   4991: iload 37
    //   4993: iconst_1
    //   4994: iadd
    //   4995: istore 37
    //   4997: iinc 58 -1
    //   5000: iload 58
    //   5002: ifgt -43 -> 4959
    //   5005: fconst_1
    //   5006: fstore 52
    //   5008: fload 41
    //   5010: fstore 51
    //   5012: iload 38
    //   5014: iconst_1
    //   5015: iadd
    //   5016: istore 36
    //   5018: iload 38
    //   5020: iconst_1
    //   5021: iadd
    //   5022: istore 33
    //   5024: iload 4
    //   5026: iload 38
    //   5028: iconst_1
    //   5029: iadd
    //   5030: isub
    //   5031: iconst_1
    //   5032: iadd
    //   5033: istore 58
    //   5035: goto +848 -> 5883
    //   5038: iload 33
    //   5040: iload 36
    //   5042: if_icmplt +7 -> 5049
    //   5045: iconst_0
    //   5046: goto +4 -> 5050
    //   5049: iconst_1
    //   5050: ifeq +6 -> 5056
    //   5053: goto +821 -> 5874
    //   5056: iload 33
    //   5058: istore 34
    //   5060: iload 33
    //   5062: istore 35
    //   5064: iload 33
    //   5066: iconst_1
    //   5067: iadd
    //   5068: istore 36
    //   5070: iload 33
    //   5072: iload 4
    //   5074: if_icmplt +7 -> 5081
    //   5077: iconst_0
    //   5078: goto +4 -> 5082
    //   5081: iconst_1
    //   5082: ifeq +48 -> 5130
    //   5085: aload 5
    //   5087: iload 33
    //   5089: iconst_1
    //   5090: iadd
    //   5091: iconst_1
    //   5092: isub
    //   5093: iload 33
    //   5095: iconst_1
    //   5096: isub
    //   5097: iload 7
    //   5099: imul
    //   5100: iadd
    //   5101: iload 6
    //   5103: iadd
    //   5104: faload
    //   5105: fconst_0
    //   5106: fcmpl
    //   5107: ifne +7 -> 5114
    //   5110: iconst_0
    //   5111: goto +4 -> 5115
    //   5114: iconst_1
    //   5115: ifeq +15 -> 5130
    //   5118: iload 33
    //   5120: iconst_1
    //   5121: iadd
    //   5122: istore 35
    //   5124: iload 33
    //   5126: iconst_2
    //   5127: iadd
    //   5128: istore 36
    //   5130: iload 34
    //   5132: iload 35
    //   5134: if_icmpeq +7 -> 5141
    //   5137: iconst_0
    //   5138: goto +4 -> 5142
    //   5141: iconst_1
    //   5142: ifeq +298 -> 5440
    //   5145: aload 16
    //   5147: iload 33
    //   5149: iconst_1
    //   5150: isub
    //   5151: iload 17
    //   5153: iadd
    //   5154: faload
    //   5155: fload 51
    //   5157: fcmpl
    //   5158: ifgt +7 -> 5165
    //   5161: iconst_0
    //   5162: goto +4 -> 5166
    //   5165: iconst_1
    //   5166: ifeq +41 -> 5207
    //   5169: fconst_1
    //   5170: fload 52
    //   5172: fdiv
    //   5173: fstore 44
    //   5175: iload 4
    //   5177: iload 38
    //   5179: isub
    //   5180: iconst_1
    //   5181: iadd
    //   5182: fload 44
    //   5184: aload 16
    //   5186: iload 38
    //   5188: iload 4
    //   5190: iadd
    //   5191: iconst_1
    //   5192: isub
    //   5193: iload 17
    //   5195: iadd
    //   5196: iconst_1
    //   5197: invokestatic 100	org/netlib/blas/Sscal:sscal	(IF[FII)V
    //   5200: fconst_1
    //   5201: fstore 52
    //   5203: fload 41
    //   5205: fstore 51
    //   5207: aload 16
    //   5209: iload 33
    //   5211: iload 4
    //   5213: iadd
    //   5214: iconst_1
    //   5215: isub
    //   5216: iload 17
    //   5218: iadd
    //   5219: aload 16
    //   5221: iload 33
    //   5223: iload 4
    //   5225: iadd
    //   5226: iconst_1
    //   5227: isub
    //   5228: iload 17
    //   5230: iadd
    //   5231: faload
    //   5232: iload 33
    //   5234: iload 38
    //   5236: isub
    //   5237: iconst_1
    //   5238: isub
    //   5239: aload 5
    //   5241: iload 38
    //   5243: iconst_1
    //   5244: iadd
    //   5245: iconst_1
    //   5246: isub
    //   5247: iload 33
    //   5249: iconst_1
    //   5250: isub
    //   5251: iload 7
    //   5253: imul
    //   5254: iadd
    //   5255: iload 6
    //   5257: iadd
    //   5258: iconst_1
    //   5259: aload 16
    //   5261: iload 38
    //   5263: iconst_1
    //   5264: iadd
    //   5265: iload 4
    //   5267: iadd
    //   5268: iconst_1
    //   5269: isub
    //   5270: iload 17
    //   5272: iadd
    //   5273: iconst_1
    //   5274: invokestatic 132	org/netlib/blas/Sdot:sdot	(I[FII[FII)F
    //   5277: fsub
    //   5278: fastore
    //   5279: iconst_0
    //   5280: iconst_1
    //   5281: iconst_1
    //   5282: fload 47
    //   5284: fconst_1
    //   5285: aload 5
    //   5287: iload 33
    //   5289: iconst_1
    //   5290: isub
    //   5291: iload 33
    //   5293: iconst_1
    //   5294: isub
    //   5295: iload 7
    //   5297: imul
    //   5298: iadd
    //   5299: iload 6
    //   5301: iadd
    //   5302: iload 7
    //   5304: fconst_1
    //   5305: fconst_1
    //   5306: aload 16
    //   5308: iload 33
    //   5310: iload 4
    //   5312: iadd
    //   5313: iconst_1
    //   5314: isub
    //   5315: iload 17
    //   5317: iadd
    //   5318: iload 4
    //   5320: fload 54
    //   5322: fconst_0
    //   5323: aload 56
    //   5325: iconst_0
    //   5326: iconst_2
    //   5327: aload 46
    //   5329: aload 55
    //   5331: aload 29
    //   5333: invokestatic 94	org/netlib/lapack/Slaln2:slaln2	(ZIIFF[FIIFF[FIIFF[FIILorg/netlib/util/floatW;Lorg/netlib/util/floatW;Lorg/netlib/util/intW;)V
    //   5336: aload 46
    //   5338: getfield 69	org/netlib/util/floatW:val	F
    //   5341: fconst_1
    //   5342: fcmpl
    //   5343: ifne +7 -> 5350
    //   5346: iconst_0
    //   5347: goto +4 -> 5351
    //   5350: iconst_1
    //   5351: ifeq +31 -> 5382
    //   5354: iload 4
    //   5356: iload 38
    //   5358: isub
    //   5359: iconst_1
    //   5360: iadd
    //   5361: aload 46
    //   5363: getfield 69	org/netlib/util/floatW:val	F
    //   5366: aload 16
    //   5368: iload 38
    //   5370: iload 4
    //   5372: iadd
    //   5373: iconst_1
    //   5374: isub
    //   5375: iload 17
    //   5377: iadd
    //   5378: iconst_1
    //   5379: invokestatic 100	org/netlib/blas/Sscal:sscal	(IF[FII)V
    //   5382: aload 16
    //   5384: iload 33
    //   5386: iload 4
    //   5388: iadd
    //   5389: iconst_1
    //   5390: isub
    //   5391: iload 17
    //   5393: iadd
    //   5394: aload 56
    //   5396: iconst_1
    //   5397: iconst_1
    //   5398: isub
    //   5399: iconst_1
    //   5400: iconst_1
    //   5401: isub
    //   5402: iconst_2
    //   5403: imul
    //   5404: iadd
    //   5405: faload
    //   5406: fastore
    //   5407: aload 16
    //   5409: iload 33
    //   5411: iload 4
    //   5413: iadd
    //   5414: iconst_1
    //   5415: isub
    //   5416: iload 17
    //   5418: iadd
    //   5419: faload
    //   5420: invokestatic 81	java/lang/Math:abs	(F)F
    //   5423: fload 52
    //   5425: invokestatic 88	java/lang/Math:max	(FF)F
    //   5428: fstore 52
    //   5430: fload 41
    //   5432: fload 52
    //   5434: fdiv
    //   5435: fstore 51
    //   5437: goto +437 -> 5874
    //   5440: aload 16
    //   5442: iload 33
    //   5444: iconst_1
    //   5445: isub
    //   5446: iload 17
    //   5448: iadd
    //   5449: faload
    //   5450: aload 16
    //   5452: iload 33
    //   5454: iconst_1
    //   5455: iadd
    //   5456: iconst_1
    //   5457: isub
    //   5458: iload 17
    //   5460: iadd
    //   5461: faload
    //   5462: invokestatic 88	java/lang/Math:max	(FF)F
    //   5465: fstore 40
    //   5467: fload 40
    //   5469: fload 51
    //   5471: fcmpl
    //   5472: ifgt +7 -> 5479
    //   5475: iconst_0
    //   5476: goto +4 -> 5480
    //   5479: iconst_1
    //   5480: ifeq +41 -> 5521
    //   5483: fconst_1
    //   5484: fload 52
    //   5486: fdiv
    //   5487: fstore 44
    //   5489: iload 4
    //   5491: iload 38
    //   5493: isub
    //   5494: iconst_1
    //   5495: iadd
    //   5496: fload 44
    //   5498: aload 16
    //   5500: iload 38
    //   5502: iload 4
    //   5504: iadd
    //   5505: iconst_1
    //   5506: isub
    //   5507: iload 17
    //   5509: iadd
    //   5510: iconst_1
    //   5511: invokestatic 100	org/netlib/blas/Sscal:sscal	(IF[FII)V
    //   5514: fconst_1
    //   5515: fstore 52
    //   5517: fload 41
    //   5519: fstore 51
    //   5521: aload 16
    //   5523: iload 33
    //   5525: iload 4
    //   5527: iadd
    //   5528: iconst_1
    //   5529: isub
    //   5530: iload 17
    //   5532: iadd
    //   5533: aload 16
    //   5535: iload 33
    //   5537: iload 4
    //   5539: iadd
    //   5540: iconst_1
    //   5541: isub
    //   5542: iload 17
    //   5544: iadd
    //   5545: faload
    //   5546: iload 33
    //   5548: iload 38
    //   5550: isub
    //   5551: iconst_1
    //   5552: isub
    //   5553: aload 5
    //   5555: iload 38
    //   5557: iconst_1
    //   5558: iadd
    //   5559: iconst_1
    //   5560: isub
    //   5561: iload 33
    //   5563: iconst_1
    //   5564: isub
    //   5565: iload 7
    //   5567: imul
    //   5568: iadd
    //   5569: iload 6
    //   5571: iadd
    //   5572: iconst_1
    //   5573: aload 16
    //   5575: iload 38
    //   5577: iconst_1
    //   5578: iadd
    //   5579: iload 4
    //   5581: iadd
    //   5582: iconst_1
    //   5583: isub
    //   5584: iload 17
    //   5586: iadd
    //   5587: iconst_1
    //   5588: invokestatic 132	org/netlib/blas/Sdot:sdot	(I[FII[FII)F
    //   5591: fsub
    //   5592: fastore
    //   5593: aload 16
    //   5595: iload 33
    //   5597: iconst_1
    //   5598: iadd
    //   5599: iload 4
    //   5601: iadd
    //   5602: iconst_1
    //   5603: isub
    //   5604: iload 17
    //   5606: iadd
    //   5607: aload 16
    //   5609: iload 33
    //   5611: iconst_1
    //   5612: iadd
    //   5613: iload 4
    //   5615: iadd
    //   5616: iconst_1
    //   5617: isub
    //   5618: iload 17
    //   5620: iadd
    //   5621: faload
    //   5622: iload 33
    //   5624: iload 38
    //   5626: isub
    //   5627: iconst_1
    //   5628: isub
    //   5629: aload 5
    //   5631: iload 38
    //   5633: iconst_1
    //   5634: iadd
    //   5635: iconst_1
    //   5636: isub
    //   5637: iload 33
    //   5639: iconst_1
    //   5640: iadd
    //   5641: iconst_1
    //   5642: isub
    //   5643: iload 7
    //   5645: imul
    //   5646: iadd
    //   5647: iload 6
    //   5649: iadd
    //   5650: iconst_1
    //   5651: aload 16
    //   5653: iload 38
    //   5655: iconst_1
    //   5656: iadd
    //   5657: iload 4
    //   5659: iadd
    //   5660: iconst_1
    //   5661: isub
    //   5662: iload 17
    //   5664: iadd
    //   5665: iconst_1
    //   5666: invokestatic 132	org/netlib/blas/Sdot:sdot	(I[FII[FII)F
    //   5669: fsub
    //   5670: fastore
    //   5671: iconst_1
    //   5672: iconst_2
    //   5673: iconst_1
    //   5674: fload 47
    //   5676: fconst_1
    //   5677: aload 5
    //   5679: iload 33
    //   5681: iconst_1
    //   5682: isub
    //   5683: iload 33
    //   5685: iconst_1
    //   5686: isub
    //   5687: iload 7
    //   5689: imul
    //   5690: iadd
    //   5691: iload 6
    //   5693: iadd
    //   5694: iload 7
    //   5696: fconst_1
    //   5697: fconst_1
    //   5698: aload 16
    //   5700: iload 33
    //   5702: iload 4
    //   5704: iadd
    //   5705: iconst_1
    //   5706: isub
    //   5707: iload 17
    //   5709: iadd
    //   5710: iload 4
    //   5712: fload 54
    //   5714: fconst_0
    //   5715: aload 56
    //   5717: iconst_0
    //   5718: iconst_2
    //   5719: aload 46
    //   5721: aload 55
    //   5723: aload 29
    //   5725: invokestatic 94	org/netlib/lapack/Slaln2:slaln2	(ZIIFF[FIIFF[FIIFF[FIILorg/netlib/util/floatW;Lorg/netlib/util/floatW;Lorg/netlib/util/intW;)V
    //   5728: aload 46
    //   5730: getfield 69	org/netlib/util/floatW:val	F
    //   5733: fconst_1
    //   5734: fcmpl
    //   5735: ifne +7 -> 5742
    //   5738: iconst_0
    //   5739: goto +4 -> 5743
    //   5742: iconst_1
    //   5743: ifeq +31 -> 5774
    //   5746: iload 4
    //   5748: iload 38
    //   5750: isub
    //   5751: iconst_1
    //   5752: iadd
    //   5753: aload 46
    //   5755: getfield 69	org/netlib/util/floatW:val	F
    //   5758: aload 16
    //   5760: iload 38
    //   5762: iload 4
    //   5764: iadd
    //   5765: iconst_1
    //   5766: isub
    //   5767: iload 17
    //   5769: iadd
    //   5770: iconst_1
    //   5771: invokestatic 100	org/netlib/blas/Sscal:sscal	(IF[FII)V
    //   5774: aload 16
    //   5776: iload 33
    //   5778: iload 4
    //   5780: iadd
    //   5781: iconst_1
    //   5782: isub
    //   5783: iload 17
    //   5785: iadd
    //   5786: aload 56
    //   5788: iconst_1
    //   5789: iconst_1
    //   5790: isub
    //   5791: iconst_1
    //   5792: iconst_1
    //   5793: isub
    //   5794: iconst_2
    //   5795: imul
    //   5796: iadd
    //   5797: faload
    //   5798: fastore
    //   5799: aload 16
    //   5801: iload 33
    //   5803: iconst_1
    //   5804: iadd
    //   5805: iload 4
    //   5807: iadd
    //   5808: iconst_1
    //   5809: isub
    //   5810: iload 17
    //   5812: iadd
    //   5813: aload 56
    //   5815: iconst_2
    //   5816: iconst_1
    //   5817: isub
    //   5818: iconst_1
    //   5819: iconst_1
    //   5820: isub
    //   5821: iconst_2
    //   5822: imul
    //   5823: iadd
    //   5824: faload
    //   5825: fastore
    //   5826: aload 16
    //   5828: iload 33
    //   5830: iload 4
    //   5832: iadd
    //   5833: iconst_1
    //   5834: isub
    //   5835: iload 17
    //   5837: iadd
    //   5838: faload
    //   5839: invokestatic 81	java/lang/Math:abs	(F)F
    //   5842: aload 16
    //   5844: iload 33
    //   5846: iconst_1
    //   5847: iadd
    //   5848: iload 4
    //   5850: iadd
    //   5851: iconst_1
    //   5852: isub
    //   5853: iload 17
    //   5855: iadd
    //   5856: faload
    //   5857: invokestatic 81	java/lang/Math:abs	(F)F
    //   5860: fload 52
    //   5862: invokestatic 137	org/netlib/util/Util:max	(FFF)F
    //   5865: fstore 52
    //   5867: fload 41
    //   5869: fload 52
    //   5871: fdiv
    //   5872: fstore 51
    //   5874: iload 33
    //   5876: iconst_1
    //   5877: iadd
    //   5878: istore 33
    //   5880: iinc 58 -1
    //   5883: iload 58
    //   5885: ifgt -847 -> 5038
    //   5888: iload 24
    //   5890: iconst_1
    //   5891: ixor
    //   5892: ifeq +186 -> 6078
    //   5895: iload 4
    //   5897: iload 38
    //   5899: isub
    //   5900: iconst_1
    //   5901: iadd
    //   5902: aload 16
    //   5904: iload 38
    //   5906: iload 4
    //   5908: iadd
    //   5909: iconst_1
    //   5910: isub
    //   5911: iload 17
    //   5913: iadd
    //   5914: iconst_1
    //   5915: aload 8
    //   5917: iload 38
    //   5919: iconst_1
    //   5920: isub
    //   5921: iload 32
    //   5923: iconst_1
    //   5924: isub
    //   5925: iload 10
    //   5927: imul
    //   5928: iadd
    //   5929: iload 9
    //   5931: iadd
    //   5932: iconst_1
    //   5933: invokestatic 112	org/netlib/blas/Scopy:scopy	(I[FII[FII)V
    //   5936: iload 4
    //   5938: iload 38
    //   5940: isub
    //   5941: iconst_1
    //   5942: iadd
    //   5943: aload 8
    //   5945: iload 38
    //   5947: iconst_1
    //   5948: isub
    //   5949: iload 32
    //   5951: iconst_1
    //   5952: isub
    //   5953: iload 10
    //   5955: imul
    //   5956: iadd
    //   5957: iload 9
    //   5959: iadd
    //   5960: iconst_1
    //   5961: invokestatic 118	org/netlib/blas/Isamax:isamax	(I[FII)I
    //   5964: iload 38
    //   5966: iadd
    //   5967: iconst_1
    //   5968: isub
    //   5969: istore 30
    //   5971: fconst_1
    //   5972: aload 8
    //   5974: iload 30
    //   5976: iconst_1
    //   5977: isub
    //   5978: iload 32
    //   5980: iconst_1
    //   5981: isub
    //   5982: iload 10
    //   5984: imul
    //   5985: iadd
    //   5986: iload 9
    //   5988: iadd
    //   5989: faload
    //   5990: invokestatic 81	java/lang/Math:abs	(F)F
    //   5993: fdiv
    //   5994: fstore 45
    //   5996: iload 4
    //   5998: iload 38
    //   6000: isub
    //   6001: iconst_1
    //   6002: iadd
    //   6003: fload 45
    //   6005: aload 8
    //   6007: iload 38
    //   6009: iconst_1
    //   6010: isub
    //   6011: iload 32
    //   6013: iconst_1
    //   6014: isub
    //   6015: iload 10
    //   6017: imul
    //   6018: iadd
    //   6019: iload 9
    //   6021: iadd
    //   6022: iconst_1
    //   6023: invokestatic 100	org/netlib/blas/Sscal:sscal	(IF[FII)V
    //   6026: iconst_1
    //   6027: istore 37
    //   6029: iload 38
    //   6031: iconst_1
    //   6032: isub
    //   6033: iconst_1
    //   6034: isub
    //   6035: iconst_1
    //   6036: iadd
    //   6037: istore 58
    //   6039: goto +31 -> 6070
    //   6042: aload 8
    //   6044: iload 37
    //   6046: iconst_1
    //   6047: isub
    //   6048: iload 32
    //   6050: iconst_1
    //   6051: isub
    //   6052: iload 10
    //   6054: imul
    //   6055: iadd
    //   6056: iload 9
    //   6058: iadd
    //   6059: fconst_0
    //   6060: fastore
    //   6061: iload 37
    //   6063: iconst_1
    //   6064: iadd
    //   6065: istore 37
    //   6067: iinc 58 -1
    //   6070: iload 58
    //   6072: ifgt -30 -> 6042
    //   6075: goto +169 -> 6244
    //   6078: iload 38
    //   6080: iload 4
    //   6082: if_icmplt +7 -> 6089
    //   6085: iconst_0
    //   6086: goto +4 -> 6090
    //   6089: iconst_1
    //   6090: ifeq +81 -> 6171
    //   6093: ldc 120
    //   6095: iload 4
    //   6097: iload 4
    //   6099: iload 38
    //   6101: isub
    //   6102: fconst_1
    //   6103: aload 8
    //   6105: iconst_1
    //   6106: iconst_1
    //   6107: isub
    //   6108: iload 38
    //   6110: iconst_1
    //   6111: iadd
    //   6112: iconst_1
    //   6113: isub
    //   6114: iload 10
    //   6116: imul
    //   6117: iadd
    //   6118: iload 9
    //   6120: iadd
    //   6121: iload 10
    //   6123: aload 16
    //   6125: iload 38
    //   6127: iconst_1
    //   6128: iadd
    //   6129: iload 4
    //   6131: iadd
    //   6132: iconst_1
    //   6133: isub
    //   6134: iload 17
    //   6136: iadd
    //   6137: iconst_1
    //   6138: aload 16
    //   6140: iload 38
    //   6142: iload 4
    //   6144: iadd
    //   6145: iconst_1
    //   6146: isub
    //   6147: iload 17
    //   6149: iadd
    //   6150: faload
    //   6151: aload 8
    //   6153: iconst_1
    //   6154: iconst_1
    //   6155: isub
    //   6156: iload 38
    //   6158: iconst_1
    //   6159: isub
    //   6160: iload 10
    //   6162: imul
    //   6163: iadd
    //   6164: iload 9
    //   6166: iadd
    //   6167: iconst_1
    //   6168: invokestatic 126	org/netlib/blas/Sgemv:sgemv	(Ljava/lang/String;IIF[FII[FIIF[FII)V
    //   6171: iload 4
    //   6173: aload 8
    //   6175: iconst_1
    //   6176: iconst_1
    //   6177: isub
    //   6178: iload 38
    //   6180: iconst_1
    //   6181: isub
    //   6182: iload 10
    //   6184: imul
    //   6185: iadd
    //   6186: iload 9
    //   6188: iadd
    //   6189: iconst_1
    //   6190: invokestatic 118	org/netlib/blas/Isamax:isamax	(I[FII)I
    //   6193: istore 30
    //   6195: fconst_1
    //   6196: aload 8
    //   6198: iload 30
    //   6200: iconst_1
    //   6201: isub
    //   6202: iload 38
    //   6204: iconst_1
    //   6205: isub
    //   6206: iload 10
    //   6208: imul
    //   6209: iadd
    //   6210: iload 9
    //   6212: iadd
    //   6213: faload
    //   6214: invokestatic 81	java/lang/Math:abs	(F)F
    //   6217: fdiv
    //   6218: fstore 45
    //   6220: iload 4
    //   6222: fload 45
    //   6224: aload 8
    //   6226: iconst_1
    //   6227: iconst_1
    //   6228: isub
    //   6229: iload 38
    //   6231: iconst_1
    //   6232: isub
    //   6233: iload 10
    //   6235: imul
    //   6236: iadd
    //   6237: iload 9
    //   6239: iadd
    //   6240: iconst_1
    //   6241: invokestatic 100	org/netlib/blas/Sscal:sscal	(IF[FII)V
    //   6244: goto +2383 -> 8627
    //   6247: aload 5
    //   6249: iload 38
    //   6251: iconst_1
    //   6252: isub
    //   6253: iload 38
    //   6255: iconst_1
    //   6256: iadd
    //   6257: iconst_1
    //   6258: isub
    //   6259: iload 7
    //   6261: imul
    //   6262: iadd
    //   6263: iload 6
    //   6265: iadd
    //   6266: faload
    //   6267: invokestatic 81	java/lang/Math:abs	(F)F
    //   6270: aload 5
    //   6272: iload 38
    //   6274: iconst_1
    //   6275: iadd
    //   6276: iconst_1
    //   6277: isub
    //   6278: iload 38
    //   6280: iconst_1
    //   6281: isub
    //   6282: iload 7
    //   6284: imul
    //   6285: iadd
    //   6286: iload 6
    //   6288: iadd
    //   6289: faload
    //   6290: invokestatic 81	java/lang/Math:abs	(F)F
    //   6293: fcmpl
    //   6294: ifge +7 -> 6301
    //   6297: iconst_0
    //   6298: goto +4 -> 6302
    //   6301: iconst_1
    //   6302: ifeq +58 -> 6360
    //   6305: aload 16
    //   6307: iload 38
    //   6309: iload 4
    //   6311: iadd
    //   6312: iconst_1
    //   6313: isub
    //   6314: iload 17
    //   6316: iadd
    //   6317: fload 53
    //   6319: aload 5
    //   6321: iload 38
    //   6323: iconst_1
    //   6324: isub
    //   6325: iload 38
    //   6327: iconst_1
    //   6328: iadd
    //   6329: iconst_1
    //   6330: isub
    //   6331: iload 7
    //   6333: imul
    //   6334: iadd
    //   6335: iload 6
    //   6337: iadd
    //   6338: faload
    //   6339: fdiv
    //   6340: fastore
    //   6341: aload 16
    //   6343: iload 38
    //   6345: iconst_1
    //   6346: iadd
    //   6347: iload 39
    //   6349: iadd
    //   6350: iconst_1
    //   6351: isub
    //   6352: iload 17
    //   6354: iadd
    //   6355: fconst_1
    //   6356: fastore
    //   6357: goto +56 -> 6413
    //   6360: aload 16
    //   6362: iload 38
    //   6364: iload 4
    //   6366: iadd
    //   6367: iconst_1
    //   6368: isub
    //   6369: iload 17
    //   6371: iadd
    //   6372: fconst_1
    //   6373: fastore
    //   6374: aload 16
    //   6376: iload 38
    //   6378: iconst_1
    //   6379: iadd
    //   6380: iload 39
    //   6382: iadd
    //   6383: iconst_1
    //   6384: isub
    //   6385: iload 17
    //   6387: iadd
    //   6388: fload 53
    //   6390: aload 5
    //   6392: iload 38
    //   6394: iconst_1
    //   6395: iadd
    //   6396: iconst_1
    //   6397: isub
    //   6398: iload 38
    //   6400: iconst_1
    //   6401: isub
    //   6402: iload 7
    //   6404: imul
    //   6405: iadd
    //   6406: iload 6
    //   6408: iadd
    //   6409: faload
    //   6410: fdiv
    //   6411: fneg
    //   6412: fastore
    //   6413: aload 16
    //   6415: iload 38
    //   6417: iconst_1
    //   6418: iadd
    //   6419: iload 4
    //   6421: iadd
    //   6422: iconst_1
    //   6423: isub
    //   6424: iload 17
    //   6426: iadd
    //   6427: fconst_0
    //   6428: fastore
    //   6429: aload 16
    //   6431: iload 38
    //   6433: iload 39
    //   6435: iadd
    //   6436: iconst_1
    //   6437: isub
    //   6438: iload 17
    //   6440: iadd
    //   6441: fconst_0
    //   6442: fastore
    //   6443: iload 38
    //   6445: iconst_2
    //   6446: iadd
    //   6447: istore 37
    //   6449: iload 4
    //   6451: iload 38
    //   6453: iconst_2
    //   6454: iadd
    //   6455: isub
    //   6456: iconst_1
    //   6457: iadd
    //   6458: istore 58
    //   6460: goto +108 -> 6568
    //   6463: aload 16
    //   6465: iload 37
    //   6467: iload 4
    //   6469: iadd
    //   6470: iconst_1
    //   6471: isub
    //   6472: iload 17
    //   6474: iadd
    //   6475: aload 16
    //   6477: iload 38
    //   6479: iload 4
    //   6481: iadd
    //   6482: iconst_1
    //   6483: isub
    //   6484: iload 17
    //   6486: iadd
    //   6487: faload
    //   6488: aload 5
    //   6490: iload 38
    //   6492: iconst_1
    //   6493: isub
    //   6494: iload 37
    //   6496: iconst_1
    //   6497: isub
    //   6498: iload 7
    //   6500: imul
    //   6501: iadd
    //   6502: iload 6
    //   6504: iadd
    //   6505: faload
    //   6506: fmul
    //   6507: fneg
    //   6508: fastore
    //   6509: aload 16
    //   6511: iload 37
    //   6513: iload 39
    //   6515: iadd
    //   6516: iconst_1
    //   6517: isub
    //   6518: iload 17
    //   6520: iadd
    //   6521: aload 16
    //   6523: iload 38
    //   6525: iconst_1
    //   6526: iadd
    //   6527: iload 39
    //   6529: iadd
    //   6530: iconst_1
    //   6531: isub
    //   6532: iload 17
    //   6534: iadd
    //   6535: faload
    //   6536: aload 5
    //   6538: iload 38
    //   6540: iconst_1
    //   6541: iadd
    //   6542: iconst_1
    //   6543: isub
    //   6544: iload 37
    //   6546: iconst_1
    //   6547: isub
    //   6548: iload 7
    //   6550: imul
    //   6551: iadd
    //   6552: iload 6
    //   6554: iadd
    //   6555: faload
    //   6556: fmul
    //   6557: fneg
    //   6558: fastore
    //   6559: iload 37
    //   6561: iconst_1
    //   6562: iadd
    //   6563: istore 37
    //   6565: iinc 58 -1
    //   6568: iload 58
    //   6570: ifgt -107 -> 6463
    //   6573: fconst_1
    //   6574: fstore 52
    //   6576: fload 41
    //   6578: fstore 51
    //   6580: iload 38
    //   6582: iconst_2
    //   6583: iadd
    //   6584: istore 36
    //   6586: iload 38
    //   6588: iconst_2
    //   6589: iadd
    //   6590: istore 33
    //   6592: iload 4
    //   6594: iload 38
    //   6596: iconst_2
    //   6597: iadd
    //   6598: isub
    //   6599: iconst_1
    //   6600: iadd
    //   6601: istore 58
    //   6603: goto +1305 -> 7908
    //   6606: iload 33
    //   6608: iload 36
    //   6610: if_icmplt +7 -> 6617
    //   6613: iconst_0
    //   6614: goto +4 -> 6618
    //   6617: iconst_1
    //   6618: ifeq +6 -> 6624
    //   6621: goto +1278 -> 7899
    //   6624: iload 33
    //   6626: istore 34
    //   6628: iload 33
    //   6630: istore 35
    //   6632: iload 33
    //   6634: iconst_1
    //   6635: iadd
    //   6636: istore 36
    //   6638: iload 33
    //   6640: iload 4
    //   6642: if_icmplt +7 -> 6649
    //   6645: iconst_0
    //   6646: goto +4 -> 6650
    //   6649: iconst_1
    //   6650: ifeq +48 -> 6698
    //   6653: aload 5
    //   6655: iload 33
    //   6657: iconst_1
    //   6658: iadd
    //   6659: iconst_1
    //   6660: isub
    //   6661: iload 33
    //   6663: iconst_1
    //   6664: isub
    //   6665: iload 7
    //   6667: imul
    //   6668: iadd
    //   6669: iload 6
    //   6671: iadd
    //   6672: faload
    //   6673: fconst_0
    //   6674: fcmpl
    //   6675: ifne +7 -> 6682
    //   6678: iconst_0
    //   6679: goto +4 -> 6683
    //   6682: iconst_1
    //   6683: ifeq +15 -> 6698
    //   6686: iload 33
    //   6688: iconst_1
    //   6689: iadd
    //   6690: istore 35
    //   6692: iload 33
    //   6694: iconst_2
    //   6695: iadd
    //   6696: istore 36
    //   6698: iload 34
    //   6700: iload 35
    //   6702: if_icmpeq +7 -> 6709
    //   6705: iconst_0
    //   6706: goto +4 -> 6710
    //   6709: iconst_1
    //   6710: ifeq +466 -> 7176
    //   6713: aload 16
    //   6715: iload 33
    //   6717: iconst_1
    //   6718: isub
    //   6719: iload 17
    //   6721: iadd
    //   6722: faload
    //   6723: fload 51
    //   6725: fcmpl
    //   6726: ifgt +7 -> 6733
    //   6729: iconst_0
    //   6730: goto +4 -> 6734
    //   6733: iconst_1
    //   6734: ifeq +66 -> 6800
    //   6737: fconst_1
    //   6738: fload 52
    //   6740: fdiv
    //   6741: fstore 44
    //   6743: iload 4
    //   6745: iload 38
    //   6747: isub
    //   6748: iconst_1
    //   6749: iadd
    //   6750: fload 44
    //   6752: aload 16
    //   6754: iload 38
    //   6756: iload 4
    //   6758: iadd
    //   6759: iconst_1
    //   6760: isub
    //   6761: iload 17
    //   6763: iadd
    //   6764: iconst_1
    //   6765: invokestatic 100	org/netlib/blas/Sscal:sscal	(IF[FII)V
    //   6768: iload 4
    //   6770: iload 38
    //   6772: isub
    //   6773: iconst_1
    //   6774: iadd
    //   6775: fload 44
    //   6777: aload 16
    //   6779: iload 38
    //   6781: iload 39
    //   6783: iadd
    //   6784: iconst_1
    //   6785: isub
    //   6786: iload 17
    //   6788: iadd
    //   6789: iconst_1
    //   6790: invokestatic 100	org/netlib/blas/Sscal:sscal	(IF[FII)V
    //   6793: fconst_1
    //   6794: fstore 52
    //   6796: fload 41
    //   6798: fstore 51
    //   6800: aload 16
    //   6802: iload 33
    //   6804: iload 4
    //   6806: iadd
    //   6807: iconst_1
    //   6808: isub
    //   6809: iload 17
    //   6811: iadd
    //   6812: aload 16
    //   6814: iload 33
    //   6816: iload 4
    //   6818: iadd
    //   6819: iconst_1
    //   6820: isub
    //   6821: iload 17
    //   6823: iadd
    //   6824: faload
    //   6825: iload 33
    //   6827: iload 38
    //   6829: isub
    //   6830: iconst_2
    //   6831: isub
    //   6832: aload 5
    //   6834: iload 38
    //   6836: iconst_2
    //   6837: iadd
    //   6838: iconst_1
    //   6839: isub
    //   6840: iload 33
    //   6842: iconst_1
    //   6843: isub
    //   6844: iload 7
    //   6846: imul
    //   6847: iadd
    //   6848: iload 6
    //   6850: iadd
    //   6851: iconst_1
    //   6852: aload 16
    //   6854: iload 38
    //   6856: iconst_2
    //   6857: iadd
    //   6858: iload 4
    //   6860: iadd
    //   6861: iconst_1
    //   6862: isub
    //   6863: iload 17
    //   6865: iadd
    //   6866: iconst_1
    //   6867: invokestatic 132	org/netlib/blas/Sdot:sdot	(I[FII[FII)F
    //   6870: fsub
    //   6871: fastore
    //   6872: aload 16
    //   6874: iload 33
    //   6876: iload 39
    //   6878: iadd
    //   6879: iconst_1
    //   6880: isub
    //   6881: iload 17
    //   6883: iadd
    //   6884: aload 16
    //   6886: iload 33
    //   6888: iload 39
    //   6890: iadd
    //   6891: iconst_1
    //   6892: isub
    //   6893: iload 17
    //   6895: iadd
    //   6896: faload
    //   6897: iload 33
    //   6899: iload 38
    //   6901: isub
    //   6902: iconst_2
    //   6903: isub
    //   6904: aload 5
    //   6906: iload 38
    //   6908: iconst_2
    //   6909: iadd
    //   6910: iconst_1
    //   6911: isub
    //   6912: iload 33
    //   6914: iconst_1
    //   6915: isub
    //   6916: iload 7
    //   6918: imul
    //   6919: iadd
    //   6920: iload 6
    //   6922: iadd
    //   6923: iconst_1
    //   6924: aload 16
    //   6926: iload 38
    //   6928: iconst_2
    //   6929: iadd
    //   6930: iload 39
    //   6932: iadd
    //   6933: iconst_1
    //   6934: isub
    //   6935: iload 17
    //   6937: iadd
    //   6938: iconst_1
    //   6939: invokestatic 132	org/netlib/blas/Sdot:sdot	(I[FII[FII)F
    //   6942: fsub
    //   6943: fastore
    //   6944: iconst_0
    //   6945: iconst_1
    //   6946: iconst_2
    //   6947: fload 47
    //   6949: fconst_1
    //   6950: aload 5
    //   6952: iload 33
    //   6954: iconst_1
    //   6955: isub
    //   6956: iload 33
    //   6958: iconst_1
    //   6959: isub
    //   6960: iload 7
    //   6962: imul
    //   6963: iadd
    //   6964: iload 6
    //   6966: iadd
    //   6967: iload 7
    //   6969: fconst_1
    //   6970: fconst_1
    //   6971: aload 16
    //   6973: iload 33
    //   6975: iload 4
    //   6977: iadd
    //   6978: iconst_1
    //   6979: isub
    //   6980: iload 17
    //   6982: iadd
    //   6983: iload 4
    //   6985: fload 54
    //   6987: fload 53
    //   6989: fneg
    //   6990: aload 56
    //   6992: iconst_0
    //   6993: iconst_2
    //   6994: aload 46
    //   6996: aload 55
    //   6998: aload 29
    //   7000: invokestatic 94	org/netlib/lapack/Slaln2:slaln2	(ZIIFF[FIIFF[FIIFF[FIILorg/netlib/util/floatW;Lorg/netlib/util/floatW;Lorg/netlib/util/intW;)V
    //   7003: aload 46
    //   7005: getfield 69	org/netlib/util/floatW:val	F
    //   7008: fconst_1
    //   7009: fcmpl
    //   7010: ifne +7 -> 7017
    //   7013: iconst_0
    //   7014: goto +4 -> 7018
    //   7017: iconst_1
    //   7018: ifeq +59 -> 7077
    //   7021: iload 4
    //   7023: iload 38
    //   7025: isub
    //   7026: iconst_1
    //   7027: iadd
    //   7028: aload 46
    //   7030: getfield 69	org/netlib/util/floatW:val	F
    //   7033: aload 16
    //   7035: iload 38
    //   7037: iload 4
    //   7039: iadd
    //   7040: iconst_1
    //   7041: isub
    //   7042: iload 17
    //   7044: iadd
    //   7045: iconst_1
    //   7046: invokestatic 100	org/netlib/blas/Sscal:sscal	(IF[FII)V
    //   7049: iload 4
    //   7051: iload 38
    //   7053: isub
    //   7054: iconst_1
    //   7055: iadd
    //   7056: aload 46
    //   7058: getfield 69	org/netlib/util/floatW:val	F
    //   7061: aload 16
    //   7063: iload 38
    //   7065: iload 39
    //   7067: iadd
    //   7068: iconst_1
    //   7069: isub
    //   7070: iload 17
    //   7072: iadd
    //   7073: iconst_1
    //   7074: invokestatic 100	org/netlib/blas/Sscal:sscal	(IF[FII)V
    //   7077: aload 16
    //   7079: iload 33
    //   7081: iload 4
    //   7083: iadd
    //   7084: iconst_1
    //   7085: isub
    //   7086: iload 17
    //   7088: iadd
    //   7089: aload 56
    //   7091: iconst_1
    //   7092: iconst_1
    //   7093: isub
    //   7094: iconst_1
    //   7095: iconst_1
    //   7096: isub
    //   7097: iconst_2
    //   7098: imul
    //   7099: iadd
    //   7100: faload
    //   7101: fastore
    //   7102: aload 16
    //   7104: iload 33
    //   7106: iload 39
    //   7108: iadd
    //   7109: iconst_1
    //   7110: isub
    //   7111: iload 17
    //   7113: iadd
    //   7114: aload 56
    //   7116: iconst_1
    //   7117: iconst_1
    //   7118: isub
    //   7119: iconst_2
    //   7120: iconst_1
    //   7121: isub
    //   7122: iconst_2
    //   7123: imul
    //   7124: iadd
    //   7125: faload
    //   7126: fastore
    //   7127: aload 16
    //   7129: iload 33
    //   7131: iload 4
    //   7133: iadd
    //   7134: iconst_1
    //   7135: isub
    //   7136: iload 17
    //   7138: iadd
    //   7139: faload
    //   7140: invokestatic 81	java/lang/Math:abs	(F)F
    //   7143: aload 16
    //   7145: iload 33
    //   7147: iload 39
    //   7149: iadd
    //   7150: iconst_1
    //   7151: isub
    //   7152: iload 17
    //   7154: iadd
    //   7155: faload
    //   7156: invokestatic 81	java/lang/Math:abs	(F)F
    //   7159: fload 52
    //   7161: invokestatic 137	org/netlib/util/Util:max	(FFF)F
    //   7164: fstore 52
    //   7166: fload 41
    //   7168: fload 52
    //   7170: fdiv
    //   7171: fstore 51
    //   7173: goto +726 -> 7899
    //   7176: aload 16
    //   7178: iload 33
    //   7180: iconst_1
    //   7181: isub
    //   7182: iload 17
    //   7184: iadd
    //   7185: faload
    //   7186: aload 16
    //   7188: iload 33
    //   7190: iconst_1
    //   7191: iadd
    //   7192: iconst_1
    //   7193: isub
    //   7194: iload 17
    //   7196: iadd
    //   7197: faload
    //   7198: invokestatic 88	java/lang/Math:max	(FF)F
    //   7201: fstore 40
    //   7203: fload 40
    //   7205: fload 51
    //   7207: fcmpl
    //   7208: ifgt +7 -> 7215
    //   7211: iconst_0
    //   7212: goto +4 -> 7216
    //   7215: iconst_1
    //   7216: ifeq +66 -> 7282
    //   7219: fconst_1
    //   7220: fload 52
    //   7222: fdiv
    //   7223: fstore 44
    //   7225: iload 4
    //   7227: iload 38
    //   7229: isub
    //   7230: iconst_1
    //   7231: iadd
    //   7232: fload 44
    //   7234: aload 16
    //   7236: iload 38
    //   7238: iload 4
    //   7240: iadd
    //   7241: iconst_1
    //   7242: isub
    //   7243: iload 17
    //   7245: iadd
    //   7246: iconst_1
    //   7247: invokestatic 100	org/netlib/blas/Sscal:sscal	(IF[FII)V
    //   7250: iload 4
    //   7252: iload 38
    //   7254: isub
    //   7255: iconst_1
    //   7256: iadd
    //   7257: fload 44
    //   7259: aload 16
    //   7261: iload 38
    //   7263: iload 39
    //   7265: iadd
    //   7266: iconst_1
    //   7267: isub
    //   7268: iload 17
    //   7270: iadd
    //   7271: iconst_1
    //   7272: invokestatic 100	org/netlib/blas/Sscal:sscal	(IF[FII)V
    //   7275: fconst_1
    //   7276: fstore 52
    //   7278: fload 41
    //   7280: fstore 51
    //   7282: aload 16
    //   7284: iload 33
    //   7286: iload 4
    //   7288: iadd
    //   7289: iconst_1
    //   7290: isub
    //   7291: iload 17
    //   7293: iadd
    //   7294: aload 16
    //   7296: iload 33
    //   7298: iload 4
    //   7300: iadd
    //   7301: iconst_1
    //   7302: isub
    //   7303: iload 17
    //   7305: iadd
    //   7306: faload
    //   7307: iload 33
    //   7309: iload 38
    //   7311: isub
    //   7312: iconst_2
    //   7313: isub
    //   7314: aload 5
    //   7316: iload 38
    //   7318: iconst_2
    //   7319: iadd
    //   7320: iconst_1
    //   7321: isub
    //   7322: iload 33
    //   7324: iconst_1
    //   7325: isub
    //   7326: iload 7
    //   7328: imul
    //   7329: iadd
    //   7330: iload 6
    //   7332: iadd
    //   7333: iconst_1
    //   7334: aload 16
    //   7336: iload 38
    //   7338: iconst_2
    //   7339: iadd
    //   7340: iload 4
    //   7342: iadd
    //   7343: iconst_1
    //   7344: isub
    //   7345: iload 17
    //   7347: iadd
    //   7348: iconst_1
    //   7349: invokestatic 132	org/netlib/blas/Sdot:sdot	(I[FII[FII)F
    //   7352: fsub
    //   7353: fastore
    //   7354: aload 16
    //   7356: iload 33
    //   7358: iload 39
    //   7360: iadd
    //   7361: iconst_1
    //   7362: isub
    //   7363: iload 17
    //   7365: iadd
    //   7366: aload 16
    //   7368: iload 33
    //   7370: iload 39
    //   7372: iadd
    //   7373: iconst_1
    //   7374: isub
    //   7375: iload 17
    //   7377: iadd
    //   7378: faload
    //   7379: iload 33
    //   7381: iload 38
    //   7383: isub
    //   7384: iconst_2
    //   7385: isub
    //   7386: aload 5
    //   7388: iload 38
    //   7390: iconst_2
    //   7391: iadd
    //   7392: iconst_1
    //   7393: isub
    //   7394: iload 33
    //   7396: iconst_1
    //   7397: isub
    //   7398: iload 7
    //   7400: imul
    //   7401: iadd
    //   7402: iload 6
    //   7404: iadd
    //   7405: iconst_1
    //   7406: aload 16
    //   7408: iload 38
    //   7410: iconst_2
    //   7411: iadd
    //   7412: iload 39
    //   7414: iadd
    //   7415: iconst_1
    //   7416: isub
    //   7417: iload 17
    //   7419: iadd
    //   7420: iconst_1
    //   7421: invokestatic 132	org/netlib/blas/Sdot:sdot	(I[FII[FII)F
    //   7424: fsub
    //   7425: fastore
    //   7426: aload 16
    //   7428: iload 33
    //   7430: iconst_1
    //   7431: iadd
    //   7432: iload 4
    //   7434: iadd
    //   7435: iconst_1
    //   7436: isub
    //   7437: iload 17
    //   7439: iadd
    //   7440: aload 16
    //   7442: iload 33
    //   7444: iconst_1
    //   7445: iadd
    //   7446: iload 4
    //   7448: iadd
    //   7449: iconst_1
    //   7450: isub
    //   7451: iload 17
    //   7453: iadd
    //   7454: faload
    //   7455: iload 33
    //   7457: iload 38
    //   7459: isub
    //   7460: iconst_2
    //   7461: isub
    //   7462: aload 5
    //   7464: iload 38
    //   7466: iconst_2
    //   7467: iadd
    //   7468: iconst_1
    //   7469: isub
    //   7470: iload 33
    //   7472: iconst_1
    //   7473: iadd
    //   7474: iconst_1
    //   7475: isub
    //   7476: iload 7
    //   7478: imul
    //   7479: iadd
    //   7480: iload 6
    //   7482: iadd
    //   7483: iconst_1
    //   7484: aload 16
    //   7486: iload 38
    //   7488: iconst_2
    //   7489: iadd
    //   7490: iload 4
    //   7492: iadd
    //   7493: iconst_1
    //   7494: isub
    //   7495: iload 17
    //   7497: iadd
    //   7498: iconst_1
    //   7499: invokestatic 132	org/netlib/blas/Sdot:sdot	(I[FII[FII)F
    //   7502: fsub
    //   7503: fastore
    //   7504: aload 16
    //   7506: iload 33
    //   7508: iconst_1
    //   7509: iadd
    //   7510: iload 39
    //   7512: iadd
    //   7513: iconst_1
    //   7514: isub
    //   7515: iload 17
    //   7517: iadd
    //   7518: aload 16
    //   7520: iload 33
    //   7522: iconst_1
    //   7523: iadd
    //   7524: iload 39
    //   7526: iadd
    //   7527: iconst_1
    //   7528: isub
    //   7529: iload 17
    //   7531: iadd
    //   7532: faload
    //   7533: iload 33
    //   7535: iload 38
    //   7537: isub
    //   7538: iconst_2
    //   7539: isub
    //   7540: aload 5
    //   7542: iload 38
    //   7544: iconst_2
    //   7545: iadd
    //   7546: iconst_1
    //   7547: isub
    //   7548: iload 33
    //   7550: iconst_1
    //   7551: iadd
    //   7552: iconst_1
    //   7553: isub
    //   7554: iload 7
    //   7556: imul
    //   7557: iadd
    //   7558: iload 6
    //   7560: iadd
    //   7561: iconst_1
    //   7562: aload 16
    //   7564: iload 38
    //   7566: iconst_2
    //   7567: iadd
    //   7568: iload 39
    //   7570: iadd
    //   7571: iconst_1
    //   7572: isub
    //   7573: iload 17
    //   7575: iadd
    //   7576: iconst_1
    //   7577: invokestatic 132	org/netlib/blas/Sdot:sdot	(I[FII[FII)F
    //   7580: fsub
    //   7581: fastore
    //   7582: iconst_1
    //   7583: iconst_2
    //   7584: iconst_2
    //   7585: fload 47
    //   7587: fconst_1
    //   7588: aload 5
    //   7590: iload 33
    //   7592: iconst_1
    //   7593: isub
    //   7594: iload 33
    //   7596: iconst_1
    //   7597: isub
    //   7598: iload 7
    //   7600: imul
    //   7601: iadd
    //   7602: iload 6
    //   7604: iadd
    //   7605: iload 7
    //   7607: fconst_1
    //   7608: fconst_1
    //   7609: aload 16
    //   7611: iload 33
    //   7613: iload 4
    //   7615: iadd
    //   7616: iconst_1
    //   7617: isub
    //   7618: iload 17
    //   7620: iadd
    //   7621: iload 4
    //   7623: fload 54
    //   7625: fload 53
    //   7627: fneg
    //   7628: aload 56
    //   7630: iconst_0
    //   7631: iconst_2
    //   7632: aload 46
    //   7634: aload 55
    //   7636: aload 29
    //   7638: invokestatic 94	org/netlib/lapack/Slaln2:slaln2	(ZIIFF[FIIFF[FIIFF[FIILorg/netlib/util/floatW;Lorg/netlib/util/floatW;Lorg/netlib/util/intW;)V
    //   7641: aload 46
    //   7643: getfield 69	org/netlib/util/floatW:val	F
    //   7646: fconst_1
    //   7647: fcmpl
    //   7648: ifne +7 -> 7655
    //   7651: iconst_0
    //   7652: goto +4 -> 7656
    //   7655: iconst_1
    //   7656: ifeq +59 -> 7715
    //   7659: iload 4
    //   7661: iload 38
    //   7663: isub
    //   7664: iconst_1
    //   7665: iadd
    //   7666: aload 46
    //   7668: getfield 69	org/netlib/util/floatW:val	F
    //   7671: aload 16
    //   7673: iload 38
    //   7675: iload 4
    //   7677: iadd
    //   7678: iconst_1
    //   7679: isub
    //   7680: iload 17
    //   7682: iadd
    //   7683: iconst_1
    //   7684: invokestatic 100	org/netlib/blas/Sscal:sscal	(IF[FII)V
    //   7687: iload 4
    //   7689: iload 38
    //   7691: isub
    //   7692: iconst_1
    //   7693: iadd
    //   7694: aload 46
    //   7696: getfield 69	org/netlib/util/floatW:val	F
    //   7699: aload 16
    //   7701: iload 38
    //   7703: iload 39
    //   7705: iadd
    //   7706: iconst_1
    //   7707: isub
    //   7708: iload 17
    //   7710: iadd
    //   7711: iconst_1
    //   7712: invokestatic 100	org/netlib/blas/Sscal:sscal	(IF[FII)V
    //   7715: aload 16
    //   7717: iload 33
    //   7719: iload 4
    //   7721: iadd
    //   7722: iconst_1
    //   7723: isub
    //   7724: iload 17
    //   7726: iadd
    //   7727: aload 56
    //   7729: iconst_1
    //   7730: iconst_1
    //   7731: isub
    //   7732: iconst_1
    //   7733: iconst_1
    //   7734: isub
    //   7735: iconst_2
    //   7736: imul
    //   7737: iadd
    //   7738: faload
    //   7739: fastore
    //   7740: aload 16
    //   7742: iload 33
    //   7744: iload 39
    //   7746: iadd
    //   7747: iconst_1
    //   7748: isub
    //   7749: iload 17
    //   7751: iadd
    //   7752: aload 56
    //   7754: iconst_1
    //   7755: iconst_1
    //   7756: isub
    //   7757: iconst_2
    //   7758: iconst_1
    //   7759: isub
    //   7760: iconst_2
    //   7761: imul
    //   7762: iadd
    //   7763: faload
    //   7764: fastore
    //   7765: aload 16
    //   7767: iload 33
    //   7769: iconst_1
    //   7770: iadd
    //   7771: iload 4
    //   7773: iadd
    //   7774: iconst_1
    //   7775: isub
    //   7776: iload 17
    //   7778: iadd
    //   7779: aload 56
    //   7781: iconst_2
    //   7782: iconst_1
    //   7783: isub
    //   7784: iconst_1
    //   7785: iconst_1
    //   7786: isub
    //   7787: iconst_2
    //   7788: imul
    //   7789: iadd
    //   7790: faload
    //   7791: fastore
    //   7792: aload 16
    //   7794: iload 33
    //   7796: iconst_1
    //   7797: iadd
    //   7798: iload 39
    //   7800: iadd
    //   7801: iconst_1
    //   7802: isub
    //   7803: iload 17
    //   7805: iadd
    //   7806: aload 56
    //   7808: iconst_2
    //   7809: iconst_1
    //   7810: isub
    //   7811: iconst_2
    //   7812: iconst_1
    //   7813: isub
    //   7814: iconst_2
    //   7815: imul
    //   7816: iadd
    //   7817: faload
    //   7818: fastore
    //   7819: aload 56
    //   7821: iconst_1
    //   7822: iconst_1
    //   7823: isub
    //   7824: iconst_1
    //   7825: iconst_1
    //   7826: isub
    //   7827: iconst_2
    //   7828: imul
    //   7829: iadd
    //   7830: faload
    //   7831: invokestatic 81	java/lang/Math:abs	(F)F
    //   7834: aload 56
    //   7836: iconst_1
    //   7837: iconst_1
    //   7838: isub
    //   7839: iconst_2
    //   7840: iconst_1
    //   7841: isub
    //   7842: iconst_2
    //   7843: imul
    //   7844: iadd
    //   7845: faload
    //   7846: invokestatic 81	java/lang/Math:abs	(F)F
    //   7849: aload 56
    //   7851: iconst_2
    //   7852: iconst_1
    //   7853: isub
    //   7854: iconst_1
    //   7855: iconst_1
    //   7856: isub
    //   7857: iconst_2
    //   7858: imul
    //   7859: iadd
    //   7860: faload
    //   7861: invokestatic 81	java/lang/Math:abs	(F)F
    //   7864: invokestatic 137	org/netlib/util/Util:max	(FFF)F
    //   7867: aload 56
    //   7869: iconst_2
    //   7870: iconst_1
    //   7871: isub
    //   7872: iconst_2
    //   7873: iconst_1
    //   7874: isub
    //   7875: iconst_2
    //   7876: imul
    //   7877: iadd
    //   7878: faload
    //   7879: invokestatic 81	java/lang/Math:abs	(F)F
    //   7882: invokestatic 88	java/lang/Math:max	(FF)F
    //   7885: fload 52
    //   7887: invokestatic 88	java/lang/Math:max	(FF)F
    //   7890: fstore 52
    //   7892: fload 41
    //   7894: fload 52
    //   7896: fdiv
    //   7897: fstore 51
    //   7899: iload 33
    //   7901: iconst_1
    //   7902: iadd
    //   7903: istore 33
    //   7905: iinc 58 -1
    //   7908: iload 58
    //   7910: ifgt -1304 -> 6606
    //   7913: iload 24
    //   7915: iconst_1
    //   7916: ixor
    //   7917: ifeq +313 -> 8230
    //   7920: iload 4
    //   7922: iload 38
    //   7924: isub
    //   7925: iconst_1
    //   7926: iadd
    //   7927: aload 16
    //   7929: iload 38
    //   7931: iload 4
    //   7933: iadd
    //   7934: iconst_1
    //   7935: isub
    //   7936: iload 17
    //   7938: iadd
    //   7939: iconst_1
    //   7940: aload 8
    //   7942: iload 38
    //   7944: iconst_1
    //   7945: isub
    //   7946: iload 32
    //   7948: iconst_1
    //   7949: isub
    //   7950: iload 10
    //   7952: imul
    //   7953: iadd
    //   7954: iload 9
    //   7956: iadd
    //   7957: iconst_1
    //   7958: invokestatic 112	org/netlib/blas/Scopy:scopy	(I[FII[FII)V
    //   7961: iload 4
    //   7963: iload 38
    //   7965: isub
    //   7966: iconst_1
    //   7967: iadd
    //   7968: aload 16
    //   7970: iload 38
    //   7972: iload 39
    //   7974: iadd
    //   7975: iconst_1
    //   7976: isub
    //   7977: iload 17
    //   7979: iadd
    //   7980: iconst_1
    //   7981: aload 8
    //   7983: iload 38
    //   7985: iconst_1
    //   7986: isub
    //   7987: iload 32
    //   7989: iconst_1
    //   7990: iadd
    //   7991: iconst_1
    //   7992: isub
    //   7993: iload 10
    //   7995: imul
    //   7996: iadd
    //   7997: iload 9
    //   7999: iadd
    //   8000: iconst_1
    //   8001: invokestatic 112	org/netlib/blas/Scopy:scopy	(I[FII[FII)V
    //   8004: fconst_0
    //   8005: fstore 42
    //   8007: iload 38
    //   8009: istore 37
    //   8011: iload 4
    //   8013: iload 38
    //   8015: isub
    //   8016: iconst_1
    //   8017: iadd
    //   8018: istore 58
    //   8020: goto +64 -> 8084
    //   8023: fload 42
    //   8025: aload 8
    //   8027: iload 37
    //   8029: iconst_1
    //   8030: isub
    //   8031: iload 32
    //   8033: iconst_1
    //   8034: isub
    //   8035: iload 10
    //   8037: imul
    //   8038: iadd
    //   8039: iload 9
    //   8041: iadd
    //   8042: faload
    //   8043: invokestatic 81	java/lang/Math:abs	(F)F
    //   8046: aload 8
    //   8048: iload 37
    //   8050: iconst_1
    //   8051: isub
    //   8052: iload 32
    //   8054: iconst_1
    //   8055: iadd
    //   8056: iconst_1
    //   8057: isub
    //   8058: iload 10
    //   8060: imul
    //   8061: iadd
    //   8062: iload 9
    //   8064: iadd
    //   8065: faload
    //   8066: invokestatic 81	java/lang/Math:abs	(F)F
    //   8069: fadd
    //   8070: invokestatic 88	java/lang/Math:max	(FF)F
    //   8073: fstore 42
    //   8075: iload 37
    //   8077: iconst_1
    //   8078: iadd
    //   8079: istore 37
    //   8081: iinc 58 -1
    //   8084: iload 58
    //   8086: ifgt -63 -> 8023
    //   8089: fconst_1
    //   8090: fload 42
    //   8092: fdiv
    //   8093: fstore 45
    //   8095: iload 4
    //   8097: iload 38
    //   8099: isub
    //   8100: iconst_1
    //   8101: iadd
    //   8102: fload 45
    //   8104: aload 8
    //   8106: iload 38
    //   8108: iconst_1
    //   8109: isub
    //   8110: iload 32
    //   8112: iconst_1
    //   8113: isub
    //   8114: iload 10
    //   8116: imul
    //   8117: iadd
    //   8118: iload 9
    //   8120: iadd
    //   8121: iconst_1
    //   8122: invokestatic 100	org/netlib/blas/Sscal:sscal	(IF[FII)V
    //   8125: iload 4
    //   8127: iload 38
    //   8129: isub
    //   8130: iconst_1
    //   8131: iadd
    //   8132: fload 45
    //   8134: aload 8
    //   8136: iload 38
    //   8138: iconst_1
    //   8139: isub
    //   8140: iload 32
    //   8142: iconst_1
    //   8143: iadd
    //   8144: iconst_1
    //   8145: isub
    //   8146: iload 10
    //   8148: imul
    //   8149: iadd
    //   8150: iload 9
    //   8152: iadd
    //   8153: iconst_1
    //   8154: invokestatic 100	org/netlib/blas/Sscal:sscal	(IF[FII)V
    //   8157: iconst_1
    //   8158: istore 37
    //   8160: iload 38
    //   8162: iconst_1
    //   8163: isub
    //   8164: iconst_1
    //   8165: isub
    //   8166: iconst_1
    //   8167: iadd
    //   8168: istore 58
    //   8170: goto +52 -> 8222
    //   8173: aload 8
    //   8175: iload 37
    //   8177: iconst_1
    //   8178: isub
    //   8179: iload 32
    //   8181: iconst_1
    //   8182: isub
    //   8183: iload 10
    //   8185: imul
    //   8186: iadd
    //   8187: iload 9
    //   8189: iadd
    //   8190: fconst_0
    //   8191: fastore
    //   8192: aload 8
    //   8194: iload 37
    //   8196: iconst_1
    //   8197: isub
    //   8198: iload 32
    //   8200: iconst_1
    //   8201: iadd
    //   8202: iconst_1
    //   8203: isub
    //   8204: iload 10
    //   8206: imul
    //   8207: iadd
    //   8208: iload 9
    //   8210: iadd
    //   8211: fconst_0
    //   8212: fastore
    //   8213: iload 37
    //   8215: iconst_1
    //   8216: iadd
    //   8217: istore 37
    //   8219: iinc 58 -1
    //   8222: iload 58
    //   8224: ifgt -51 -> 8173
    //   8227: goto +400 -> 8627
    //   8230: iload 38
    //   8232: iload 4
    //   8234: iconst_1
    //   8235: isub
    //   8236: if_icmplt +7 -> 8243
    //   8239: iconst_0
    //   8240: goto +4 -> 8244
    //   8243: iconst_1
    //   8244: ifeq +170 -> 8414
    //   8247: ldc 120
    //   8249: iload 4
    //   8251: iload 4
    //   8253: iload 38
    //   8255: isub
    //   8256: iconst_1
    //   8257: isub
    //   8258: fconst_1
    //   8259: aload 8
    //   8261: iconst_1
    //   8262: iconst_1
    //   8263: isub
    //   8264: iload 38
    //   8266: iconst_2
    //   8267: iadd
    //   8268: iconst_1
    //   8269: isub
    //   8270: iload 10
    //   8272: imul
    //   8273: iadd
    //   8274: iload 9
    //   8276: iadd
    //   8277: iload 10
    //   8279: aload 16
    //   8281: iload 38
    //   8283: iconst_2
    //   8284: iadd
    //   8285: iload 4
    //   8287: iadd
    //   8288: iconst_1
    //   8289: isub
    //   8290: iload 17
    //   8292: iadd
    //   8293: iconst_1
    //   8294: aload 16
    //   8296: iload 38
    //   8298: iload 4
    //   8300: iadd
    //   8301: iconst_1
    //   8302: isub
    //   8303: iload 17
    //   8305: iadd
    //   8306: faload
    //   8307: aload 8
    //   8309: iconst_1
    //   8310: iconst_1
    //   8311: isub
    //   8312: iload 38
    //   8314: iconst_1
    //   8315: isub
    //   8316: iload 10
    //   8318: imul
    //   8319: iadd
    //   8320: iload 9
    //   8322: iadd
    //   8323: iconst_1
    //   8324: invokestatic 126	org/netlib/blas/Sgemv:sgemv	(Ljava/lang/String;IIF[FII[FIIF[FII)V
    //   8327: ldc 120
    //   8329: iload 4
    //   8331: iload 4
    //   8333: iload 38
    //   8335: isub
    //   8336: iconst_1
    //   8337: isub
    //   8338: fconst_1
    //   8339: aload 8
    //   8341: iconst_1
    //   8342: iconst_1
    //   8343: isub
    //   8344: iload 38
    //   8346: iconst_2
    //   8347: iadd
    //   8348: iconst_1
    //   8349: isub
    //   8350: iload 10
    //   8352: imul
    //   8353: iadd
    //   8354: iload 9
    //   8356: iadd
    //   8357: iload 10
    //   8359: aload 16
    //   8361: iload 38
    //   8363: iconst_2
    //   8364: iadd
    //   8365: iload 39
    //   8367: iadd
    //   8368: iconst_1
    //   8369: isub
    //   8370: iload 17
    //   8372: iadd
    //   8373: iconst_1
    //   8374: aload 16
    //   8376: iload 38
    //   8378: iconst_1
    //   8379: iadd
    //   8380: iload 39
    //   8382: iadd
    //   8383: iconst_1
    //   8384: isub
    //   8385: iload 17
    //   8387: iadd
    //   8388: faload
    //   8389: aload 8
    //   8391: iconst_1
    //   8392: iconst_1
    //   8393: isub
    //   8394: iload 38
    //   8396: iconst_1
    //   8397: iadd
    //   8398: iconst_1
    //   8399: isub
    //   8400: iload 10
    //   8402: imul
    //   8403: iadd
    //   8404: iload 9
    //   8406: iadd
    //   8407: iconst_1
    //   8408: invokestatic 126	org/netlib/blas/Sgemv:sgemv	(Ljava/lang/String;IIF[FII[FIIF[FII)V
    //   8411: goto +77 -> 8488
    //   8414: iload 4
    //   8416: aload 16
    //   8418: iload 38
    //   8420: iload 4
    //   8422: iadd
    //   8423: iconst_1
    //   8424: isub
    //   8425: iload 17
    //   8427: iadd
    //   8428: faload
    //   8429: aload 8
    //   8431: iconst_1
    //   8432: iconst_1
    //   8433: isub
    //   8434: iload 38
    //   8436: iconst_1
    //   8437: isub
    //   8438: iload 10
    //   8440: imul
    //   8441: iadd
    //   8442: iload 9
    //   8444: iadd
    //   8445: iconst_1
    //   8446: invokestatic 100	org/netlib/blas/Sscal:sscal	(IF[FII)V
    //   8449: iload 4
    //   8451: aload 16
    //   8453: iload 38
    //   8455: iconst_1
    //   8456: iadd
    //   8457: iload 39
    //   8459: iadd
    //   8460: iconst_1
    //   8461: isub
    //   8462: iload 17
    //   8464: iadd
    //   8465: faload
    //   8466: aload 8
    //   8468: iconst_1
    //   8469: iconst_1
    //   8470: isub
    //   8471: iload 38
    //   8473: iconst_1
    //   8474: iadd
    //   8475: iconst_1
    //   8476: isub
    //   8477: iload 10
    //   8479: imul
    //   8480: iadd
    //   8481: iload 9
    //   8483: iadd
    //   8484: iconst_1
    //   8485: invokestatic 100	org/netlib/blas/Sscal:sscal	(IF[FII)V
    //   8488: fconst_0
    //   8489: fstore 42
    //   8491: iconst_1
    //   8492: istore 37
    //   8494: iload 4
    //   8496: iconst_1
    //   8497: isub
    //   8498: iconst_1
    //   8499: iadd
    //   8500: istore 58
    //   8502: goto +64 -> 8566
    //   8505: fload 42
    //   8507: aload 8
    //   8509: iload 37
    //   8511: iconst_1
    //   8512: isub
    //   8513: iload 38
    //   8515: iconst_1
    //   8516: isub
    //   8517: iload 10
    //   8519: imul
    //   8520: iadd
    //   8521: iload 9
    //   8523: iadd
    //   8524: faload
    //   8525: invokestatic 81	java/lang/Math:abs	(F)F
    //   8528: aload 8
    //   8530: iload 37
    //   8532: iconst_1
    //   8533: isub
    //   8534: iload 38
    //   8536: iconst_1
    //   8537: iadd
    //   8538: iconst_1
    //   8539: isub
    //   8540: iload 10
    //   8542: imul
    //   8543: iadd
    //   8544: iload 9
    //   8546: iadd
    //   8547: faload
    //   8548: invokestatic 81	java/lang/Math:abs	(F)F
    //   8551: fadd
    //   8552: invokestatic 88	java/lang/Math:max	(FF)F
    //   8555: fstore 42
    //   8557: iload 37
    //   8559: iconst_1
    //   8560: iadd
    //   8561: istore 37
    //   8563: iinc 58 -1
    //   8566: iload 58
    //   8568: ifgt -63 -> 8505
    //   8571: fconst_1
    //   8572: fload 42
    //   8574: fdiv
    //   8575: fstore 45
    //   8577: iload 4
    //   8579: fload 45
    //   8581: aload 8
    //   8583: iconst_1
    //   8584: iconst_1
    //   8585: isub
    //   8586: iload 38
    //   8588: iconst_1
    //   8589: isub
    //   8590: iload 10
    //   8592: imul
    //   8593: iadd
    //   8594: iload 9
    //   8596: iadd
    //   8597: iconst_1
    //   8598: invokestatic 100	org/netlib/blas/Sscal:sscal	(IF[FII)V
    //   8601: iload 4
    //   8603: fload 45
    //   8605: aload 8
    //   8607: iconst_1
    //   8608: iconst_1
    //   8609: isub
    //   8610: iload 38
    //   8612: iconst_1
    //   8613: iadd
    //   8614: iconst_1
    //   8615: isub
    //   8616: iload 10
    //   8618: imul
    //   8619: iadd
    //   8620: iload 9
    //   8622: iadd
    //   8623: iconst_1
    //   8624: invokestatic 100	org/netlib/blas/Sscal:sscal	(IF[FII)V
    //   8627: iload 32
    //   8629: iconst_1
    //   8630: iadd
    //   8631: istore 32
    //   8633: iload 31
    //   8635: iconst_0
    //   8636: if_icmpne +7 -> 8643
    //   8639: iconst_0
    //   8640: goto +4 -> 8644
    //   8643: iconst_1
    //   8644: ifeq +9 -> 8653
    //   8647: iload 32
    //   8649: iconst_1
    //   8650: iadd
    //   8651: istore 32
    //   8653: iload 31
    //   8655: iconst_m1
    //   8656: if_icmpeq +7 -> 8663
    //   8659: iconst_0
    //   8660: goto +4 -> 8664
    //   8663: iconst_1
    //   8664: ifeq +6 -> 8670
    //   8667: iconst_0
    //   8668: istore 31
    //   8670: iload 31
    //   8672: iconst_1
    //   8673: if_icmpeq +7 -> 8680
    //   8676: iconst_0
    //   8677: goto +4 -> 8681
    //   8680: iconst_1
    //   8681: ifeq +6 -> 8687
    //   8684: iconst_m1
    //   8685: istore 31
    //   8687: iload 38
    //   8689: iconst_1
    //   8690: iadd
    //   8691: istore 38
    //   8693: iinc 57 -1
    //   8696: iload 57
    //   8698: ifgt -3999 -> 4699
    //   8701: return
    // Local variable table:
    //   start	length	slot	name	signature
    //   0	8702	0	paramString1	String
    //   0	8702	1	paramString2	String
    //   0	8702	2	paramArrayOfBoolean	boolean[]
    //   0	8702	3	paramInt1	int
    //   0	8702	4	paramInt2	int
    //   0	8702	5	paramArrayOfFloat1	float[]
    //   0	8702	6	paramInt3	int
    //   0	8702	7	paramInt4	int
    //   0	8702	8	paramArrayOfFloat2	float[]
    //   0	8702	9	paramInt5	int
    //   0	8702	10	paramInt6	int
    //   0	8702	11	paramArrayOfFloat3	float[]
    //   0	8702	12	paramInt7	int
    //   0	8702	13	paramInt8	int
    //   0	8702	14	paramInt9	int
    //   0	8702	15	paramintW1	org.netlib.util.intW
    //   0	8702	16	paramArrayOfFloat4	float[]
    //   0	8702	17	paramInt10	int
    //   0	8702	18	paramintW2	org.netlib.util.intW
    //   1	261	21	bool1	boolean
    //   4	182	22	bool2	boolean
    //   7	4668	23	i	int
    //   10	7907	24	bool3	boolean
    //   13	589	25	j	int
    //   16	946	26	k	int
    //   19	4755	27	bool4	boolean
    //   22	910	28	m	int
    //   32	7605	29	localintW	org.netlib.util.intW
    //   35	6167	30	n	int
    //   38	8648	31	i1	int
    //   41	8611	32	i2	int
    //   44	7860	33	i3	int
    //   47	6656	34	i4	int
    //   50	6653	35	i5	int
    //   53	6644	36	i6	int
    //   56	8506	37	i7	int
    //   59	8633	38	i8	int
    //   62	8398	39	i9	int
    //   65	7139	40	f1	float
    //   68	7825	41	f2	float
    //   71	8502	42	f3	float
    //   81	719	43	localfloatW1	org.netlib.util.floatW
    //   84	7174	44	f4	float
    //   87	8517	45	f5	float
    //   97	7598	46	localfloatW2	org.netlib.util.floatW
    //   100	7486	47	f6	float
    //   103	4802	48	f7	float
    //   106	4785	49	f8	float
    //   116	696	50	localfloatW3	org.netlib.util.floatW
    //   119	7779	51	f9	float
    //   122	7773	52	f10	float
    //   125	7501	53	f11	float
    //   128	7496	54	f12	float
    //   138	7497	55	localfloatW4	org.netlib.util.floatW
    //   145	7723	56	arrayOfFloat	float[]
    //   501	8196	57	i10	int
    //   880	7687	58	i11	int
  }
}


/* Location:              /Users/assaad/Downloads/arpack_combined_all/!/org/netlib/lapack/Strevc.class
 * Java compiler version: 1 (45.3)
 * JD-Core Version:       0.7.1
 */